Workbook
Name area: #REF!
Name ds: 'IKARIA TECHO'!$Q$6
Name ETR: 'CALCULO CANTIDADES '!$P$6
Name KH: 'BASE DATOS EQUIPOS Y SUBCONTRAT'!$P$6
Name plazo: #REF!
Name tc: #REF!
Name area: 'IKARIA TECHO'!$E$8
Name tc: 'IKARIA TECHO'!$Q$6
Name area: [2]Presupuesto!$C$8
Name plazo: 'Gastos generales'!$F$6
Name tc: 'Gastos generales'!$C$5

Sheet IKARIA TECHO
D3: Desglose de Presupuesto
D4: Proyecto: | E4: IKARIA TECHO
D5: Cliente: | E5: ADELANTE DESARROLLOS | R5: Actualizacion
D6: Fecha: | E6: 44719 | P6: TC | Q6: 700 | R6: 44713
D7: Ubicación: | E7: Cartago
D8: Area: | E8: 90.84
B9: CODIGO | C9: CODIGO ACUMATICA | D9: N° | E9: Descripcion actividad | F9: Cantidad | G9: Unidad | H9: Unit mater | I9: Unit MO | J9: Unit Sub/ Equipos | K9: Total Mater | L9: Total MO | M9: Total Sub/Equipos | N9: Total Directo Colones | O9: Total Directo Dólares
E10: TOTAL PRESUPUESTO | K10: =K11+K123+K182+K214+K309+K422+K504+K528+K560+K638+K667+K738+K743+K834+K886+K905 | L10: =L11+L123+L182+L214+L309+L422+L504+L528+L560+L638+L667+L738+L743+L834+L886+L905 | M10: =M11+M123+M182+M214+M309+M422+M504+M528+M560+M638+M667+M738+M743+M834+M886+M905 | N10: =N11+N123+N182+N214+N309+N422+N504+N528+N560+N638+N667+N738+N743+N834+N886+N905 | O10: =O11+O123+O182+O214+O309+O422+O504+O528+O560+O638+O667+O738+O743+O834+O886+O905
B11: 01 | D11: 1 | E11: FUNDACIONES | K11: =K12+K21+K58+K69 | L11: =L12+L21+L58+L69 | M11: =M12+M21+M58+M69 | N11: =N12+N21+N58+N69 | O11: =O12+O21+O58+O69
B12: 01-01 | D12: 1.1 | E12: OBRAS PRELIMINARES Y RELLENOS | F12: 1 | G12: gb | K12: =SUM(K13:K20) | L12: =SUM(L13:L20) | M12: =SUM(M13:M20) | N12: =SUM(N13:N20) | O12: =SUM(O13:O20)
A13: MAT | C13: =_xlfn.XLOOKUP(D13,'INSUMOS MAT '!B:B,'INSUMOS MAT '!C:C,"ERROR",0) | D13: MAT03-0014 | E13: =_xlfn.XLOOKUP(D13,'BASE DATOS PRECIOS '!B:B,'BASE DATOS PRECIOS '!C:C) | F13: 12.5 | G13: =+_xlfn.XLOOKUP(D13,'BASE DATOS PRECIOS '!B:B,'BASE DATOS PRECIOS '!D:D) | H13: =+_xlfn.XLOOKUP(E13,'BASE DATOS PRECIOS '!C:C,'BASE DATOS PRECIOS '!F:F) | K13: =+F13*H13 | L13: =+F13*I13 | M13: =+F13*J13 | N13: =SUM(K13:M13) | O13: =SUM(K13:M13)/tc
A14: MAT | C14: =_xlfn.XLOOKUP(D14,'INSUMOS MAT '!B:B,'INSUMOS MAT '!C:C,"ERROR",0) | D14: MAT08-0017 | E14: =_xlfn.XLOOKUP(D14,'BASE DATOS PRECIOS '!B:B,'BASE DATOS PRECIOS '!C:C) | F14: 2 | G14: =+_xlfn.XLOOKUP(D14,'BASE DATOS PRECIOS '!B:B,'BASE DATOS PRECIOS '!D:D) | H14: =+_xlfn.XLOOKUP(E14,'BASE DATOS PRECIOS '!C:C,'BASE DATOS PRECIOS '!F:F) | K14: =+F14*H14 | L14: =+F14*I14 | M14: =+F14*J14 | N14: =SUM(K14:M14) | O14: =SUM(K14:M14)/tc
A15: MAT | C15: =_xlfn.XLOOKUP(D15,'INSUMOS MAT '!B:B,'INSUMOS MAT '!C:C,"ERROR",0) | D15: MAT08-0029 | E15: =_xlfn.XLOOKUP(D15,'BASE DATOS PRECIOS '!B:B,'BASE DATOS PRECIOS '!C:C) | F15: 6 | G15: =+_xlfn.XLOOKUP(D15,'BASE DATOS PRECIOS '!B:B,'BASE DATOS PRECIOS '!D:D) | H15: =+_xlfn.XLOOKUP(E15,'BASE DATOS PRECIOS '!C:C,'BASE DATOS PRECIOS '!F:F) | K15: =+F15*H15 | L15: =+F15*I15 | M15: =+F15*J15 | N15: =SUM(K15:M15) | O15: =SUM(K15:M15)/tc
A16: MAT | C16: =_xlfn.XLOOKUP(D16,'INSUMOS MAT '!B:B,'INSUMOS MAT '!C:C,"ERROR",0) | D16: MAT08-0031 | E16: =_xlfn.XLOOKUP(D16,'BASE DATOS PRECIOS '!B:B,'BASE DATOS PRECIOS '!C:C) | F16: 3 | G16: =+_xlfn.XLOOKUP(D16,'BASE DATOS PRECIOS '!B:B,'BASE DATOS PRECIOS '!D:D) | H16: =+_xlfn.XLOOKUP(E16,'BASE DATOS PRECIOS '!C:C,'BASE DATOS PRECIOS '!F:F) | K16: =+F16*H16 | L16: =+F16*I16 | M16: =+F16*J16 | N16: =SUM(K16:M16) | O16: =SUM(K16:M16)/tc
A17: EQUIP | D17: BACK HOE | E17: =+_xlfn.XLOOKUP(D17,'BASE DATOS EQUIPOS Y SUBCONTRAT'!A:A,'BASE DATOS EQUIPOS Y SUBCONTRAT'!B:B) | F17: 1 | G17: =+_xlfn.XLOOKUP(D17,'BASE DATOS EQUIPOS Y SUBCONTRAT'!A:A,'BASE DATOS EQUIPOS Y SUBCONTRAT'!C:C) | H17: 0 | J17: =+_xlfn.XLOOKUP(D17,'BASE DATOS EQUIPOS Y SUBCONTRAT'!A:A,'BASE DATOS EQUIPOS Y SUBCONTRAT'!E:E) | K17: =+F17*H17 | L17: =+F17*I17 | M17: =+F17*J17 | N17: =SUM(K17:M17) | O17: =SUM(K17:M17)/tc
A18: EQUIP | D18: COMPACTADOR | E18: =+_xlfn.XLOOKUP(D18,'BASE DATOS EQUIPOS Y SUBCONTRAT'!A:A,'BASE DATOS EQUIPOS Y SUBCONTRAT'!B:B) | F18: 3 | G18: =+_xlfn.XLOOKUP(D18,'BASE DATOS EQUIPOS Y SUBCONTRAT'!A:A,'BASE DATOS EQUIPOS Y SUBCONTRAT'!C:C) | H18: 0 | J18: =+_xlfn.XLOOKUP(D18,'BASE DATOS EQUIPOS Y SUBCONTRAT'!A:A,'BASE DATOS EQUIPOS Y SUBCONTRAT'!E:E) | K18: =+F18*H18 | L18: =+F18*I18 | M18: =+F18*J18 | N18: =SUM(K18:M18) | O18: =SUM(K18:M18)/tc
A19: MO | B19: 01-01-01 | D19: OPERARIO | E19: =+_xlfn.XLOOKUP(D19,'BASE DATOS MANO DE OBRA'!A:A,'BASE DATOS MANO DE OBRA'!B:B) | F19: 38.5 | G19: =+_xlfn.XLOOKUP(D19,'BASE DATOS MANO DE OBRA'!A:A,'BASE DATOS MANO DE OBRA'!C:C) | H19: 0 | I19: =+_xlfn.XLOOKUP(D19,'BASE DATOS MANO DE OBRA'!A:A,'BASE DATOS MANO DE OBRA'!E:E) | J19: 0 | K19: =+F19*H19 | L19: =+F19*I19 | M19: =+F19*J19 | N19: =SUM(K19:M19) | O19: =SUM(K19:M19)/tc
A20: MO | B20: 01-01-01 | D20: AYUDANTE | E20: =+_xlfn.XLOOKUP(D20,'BASE DATOS MANO DE OBRA'!A:A,'BASE DATOS MANO DE OBRA'!B:B) | F20: 38.5 | G20: =+_xlfn.XLOOKUP(D20,'BASE DATOS MANO DE OBRA'!A:A,'BASE DATOS MANO DE OBRA'!C:C) | H20: 0 | I20: =+_xlfn.XLOOKUP(D20,'BASE DATOS MANO DE OBRA'!A:A,'BASE DATOS MANO DE OBRA'!E:E) | J20: 0 | K20: =+F20*H20 | L20: =+F20*I20 | M20: =+F20*J20 | N20: =SUM(K20:M20) | O20: =SUM(K20:M20)/tc
B21: 01-02 | D21: 1.2 | E21: EXCAVACIÓN Y TUBERÍAS MECÁNICAS (INCLUYE ACOMETIDA) | F21: 1 | G21: gb | K21: =SUM(K23:K57) | L21: =SUM(L23:L57) | M21: =SUM(M23:M57) | N21: =SUM(N23:N57) | O21: =SUM(O23:O57)
E22: TUBERÍA MECÁNICA
A23: MAT | C23: =_xlfn.XLOOKUP(D23,'INSUMOS MAT '!B:B,'INSUMOS MAT '!C:C,"ERROR",0) | D23: MAT19-0100 | E23: =+_xlfn.XLOOKUP(D23,'BASE DATOS PRECIOS '!B:B,'BASE DATOS PRECIOS '!C:C) | F23: 3 | G23: =+_xlfn.XLOOKUP(D23,'BASE DATOS PRECIOS '!B:B,'BASE DATOS PRECIOS '!D:D) | H23: =+_xlfn.XLOOKUP(E23,'BASE DATOS PRECIOS '!C:C,'BASE DATOS PRECIOS '!F:F) | K23: =+F23*H23 | L23: =+F23*I23 | M23: =+F23*J23 | N23: =SUM(K23:M23) | O23: =SUM(K23:M23)/tc
A24: MAT | C24: =_xlfn.XLOOKUP(D24,'INSUMOS MAT '!B:B,'INSUMOS MAT '!C:C,"ERROR",0) | D24: MAT19-0095 | E24: =+_xlfn.XLOOKUP(D24,'BASE DATOS PRECIOS '!B:B,'BASE DATOS PRECIOS '!C:C) | F24: 1 | G24: =+_xlfn.XLOOKUP(D24,'BASE DATOS PRECIOS '!B:B,'BASE DATOS PRECIOS '!D:D) | H24: =+_xlfn.XLOOKUP(E24,'BASE DATOS PRECIOS '!C:C,'BASE DATOS PRECIOS '!F:F) | K24: =+F24*H24 | L24: =+F24*I24 | M24: =+F24*J24 | N24: =SUM(K24:M24) | O24: =SUM(K24:M24)/tc
A25: MAT | C25: =_xlfn.XLOOKUP(D25,'INSUMOS MAT '!B:B,'INSUMOS MAT '!C:C,"ERROR",0) | D25: MAT19-0094 | E25: =+_xlfn.XLOOKUP(D25,'BASE DATOS PRECIOS '!B:B,'BASE DATOS PRECIOS '!C:C) | F25: 1 | G25: =+_xlfn.XLOOKUP(D25,'BASE DATOS PRECIOS '!B:B,'BASE DATOS PRECIOS '!D:D) | H25: =+_xlfn.XLOOKUP(E25,'BASE DATOS PRECIOS '!C:C,'BASE DATOS PRECIOS '!F:F) | K25: =+F25*H25 | L25: =+F25*I25 | M25: =+F25*J25 | N25: =SUM(K25:M25) | O25: =SUM(K25:M25)/tc
A26: MAT | C26: =_xlfn.XLOOKUP(D26,'INSUMOS MAT '!B:B,'INSUMOS MAT '!C:C,"ERROR",0) | D26: MAT19-0081 | E26: =+_xlfn.XLOOKUP(D26,'BASE DATOS PRECIOS '!B:B,'BASE DATOS PRECIOS '!C:C) | F26: 2 | G26: =+_xlfn.XLOOKUP(D26,'BASE DATOS PRECIOS '!B:B,'BASE DATOS PRECIOS '!D:D) | H26: =+_xlfn.XLOOKUP(E26,'BASE DATOS PRECIOS '!C:C,'BASE DATOS PRECIOS '!F:F) | K26: =+F26*H26 | L26: =+F26*I26 | M26: =+F26*J26 | N26: =SUM(K26:M26) | O26: =SUM(K26:M26)/tc
A27: MAT | C27: =_xlfn.XLOOKUP(D27,'INSUMOS MAT '!B:B,'INSUMOS MAT '!C:C,"ERROR",0) | D27: MAT19-0044 | E27: =+_xlfn.XLOOKUP(D27,'BASE DATOS PRECIOS '!B:B,'BASE DATOS PRECIOS '!C:C) | F27: 4 | G27: =+_xlfn.XLOOKUP(D27,'BASE DATOS PRECIOS '!B:B,'BASE DATOS PRECIOS '!D:D) | H27: =+_xlfn.XLOOKUP(E27,'BASE DATOS PRECIOS '!C:C,'BASE DATOS PRECIOS '!F:F) | K27: =+F27*H27 | L27: =+F27*I27 | M27: =+F27*J27 | N27: =SUM(K27:M27) | O27: =SUM(K27:M27)/tc
A28: MAT | C28: =_xlfn.XLOOKUP(D28,'INSUMOS MAT '!B:B,'INSUMOS MAT '!C:C,"ERROR",0) | D28: MAT19-0118 | E28: =+_xlfn.XLOOKUP(D28,'BASE DATOS PRECIOS '!B:B,'BASE DATOS PRECIOS '!C:C) | F28: 5 | G28: =+_xlfn.XLOOKUP(D28,'BASE DATOS PRECIOS '!B:B,'BASE DATOS PRECIOS '!D:D) | H28: =+_xlfn.XLOOKUP(E28,'BASE DATOS PRECIOS '!C:C,'BASE DATOS PRECIOS '!F:F) | K28: =+F28*H28 | L28: =+F28*I28 | M28: =+F28*J28 | N28: =SUM(K28:M28) | O28: =SUM(K28:M28)/tc
A29: MAT | C29: =_xlfn.XLOOKUP(D29,'INSUMOS MAT '!B:B,'INSUMOS MAT '!C:C,"ERROR",0) | D29: MAT19-0024 | E29: =+_xlfn.XLOOKUP(D29,'BASE DATOS PRECIOS '!B:B,'BASE DATOS PRECIOS '!C:C) | F29: 2 | G29: =+_xlfn.XLOOKUP(D29,'BASE DATOS PRECIOS '!B:B,'BASE DATOS PRECIOS '!D:D) | H29: =+_xlfn.XLOOKUP(E29,'BASE DATOS PRECIOS '!C:C,'BASE DATOS PRECIOS '!F:F) | K29: =+F29*H29 | L29: =+F29*I29 | M29: =+F29*J29 | N29: =SUM(K29:M29) | O29: =SUM(K29:M29)/tc
A30: MAT | C30: =_xlfn.XLOOKUP(D30,'INSUMOS MAT '!B:B,'INSUMOS MAT '!C:C,"ERROR",0) | D30: MAT19-0049 | E30: =+_xlfn.XLOOKUP(D30,'BASE DATOS PRECIOS '!B:B,'BASE DATOS PRECIOS '!C:C) | F30: 2 | G30: =+_xlfn.XLOOKUP(D30,'BASE DATOS PRECIOS '!B:B,'BASE DATOS PRECIOS '!D:D) | H30: =+_xlfn.XLOOKUP(E30,'BASE DATOS PRECIOS '!C:C,'BASE DATOS PRECIOS '!F:F) | K30: =+F30*H30 | L30: =+F30*I30 | M30: =+F30*J30 | N30: =SUM(K30:M30) | O30: =SUM(K30:M30)/tc
A31: MAT | C31: =_xlfn.XLOOKUP(D31,'INSUMOS MAT '!B:B,'INSUMOS MAT '!C:C,"ERROR",0) | D31: MAT19-0055 | E31: =+_xlfn.XLOOKUP(D31,'BASE DATOS PRECIOS '!B:B,'BASE DATOS PRECIOS '!C:C) | F31: 2 | G31: =+_xlfn.XLOOKUP(D31,'BASE DATOS PRECIOS '!B:B,'BASE DATOS PRECIOS '!D:D) | H31: =+_xlfn.XLOOKUP(E31,'BASE DATOS PRECIOS '!C:C,'BASE DATOS PRECIOS '!F:F) | K31: =+F31*H31 | L31: =+F31*I31 | M31: =+F31*J31 | N31: =SUM(K31:M31) | O31: =SUM(K31:M31)/tc
A32: MAT | C32: =_xlfn.XLOOKUP(D32,'INSUMOS MAT '!B:B,'INSUMOS MAT '!C:C,"ERROR",0) | D32: MAT19-0112 | E32: =+_xlfn.XLOOKUP(D32,'BASE DATOS PRECIOS '!B:B,'BASE DATOS PRECIOS '!C:C) | F32: 6 | G32: =+_xlfn.XLOOKUP(D32,'BASE DATOS PRECIOS '!B:B,'BASE DATOS PRECIOS '!D:D) | H32: =+_xlfn.XLOOKUP(E32,'BASE DATOS PRECIOS '!C:C,'BASE DATOS PRECIOS '!F:F) | K32: =+F32*H32 | L32: =+F32*I32 | M32: =+F32*J32 | N32: =SUM(K32:M32) | O32: =SUM(K32:M32)/tc
A33: MAT | C33: =_xlfn.XLOOKUP(D33,'INSUMOS MAT '!B:B,'INSUMOS MAT '!C:C,"ERROR",0) | D33: MAT19-0126 | E33: =+_xlfn.XLOOKUP(D33,'BASE DATOS PRECIOS '!B:B,'BASE DATOS PRECIOS '!C:C) | F33: 2 | G33: =+_xlfn.XLOOKUP(D33,'BASE DATOS PRECIOS '!B:B,'BASE DATOS PRECIOS '!D:D) | H33: =+_xlfn.XLOOKUP(E33,'BASE DATOS PRECIOS '!C:C,'BASE DATOS PRECIOS '!F:F) | K33: =+F33*H33 | L33: =+F33*I33 | M33: =+F33*J33 | N33: =SUM(K33:M33) | O33: =SUM(K33:M33)/tc
A34: MAT | C34: =_xlfn.XLOOKUP(D34,'INSUMOS MAT '!B:B,'INSUMOS MAT '!C:C,"ERROR",0) | D34: MAT19-0063 | E34: =+_xlfn.XLOOKUP(D34,'BASE DATOS PRECIOS '!B:B,'BASE DATOS PRECIOS '!C:C) | F34: 4 | G34: =+_xlfn.XLOOKUP(D34,'BASE DATOS PRECIOS '!B:B,'BASE DATOS PRECIOS '!D:D) | H34: =+_xlfn.XLOOKUP(E34,'BASE DATOS PRECIOS '!C:C,'BASE DATOS PRECIOS '!F:F) | K34: =+F34*H34 | L34: =+F34*I34 | M34: =+F34*J34 | N34: =SUM(K34:M34) | O34: =SUM(K34:M34)/tc
A35: MAT | C35: =_xlfn.XLOOKUP(D35,'INSUMOS MAT '!B:B,'INSUMOS MAT '!C:C,"ERROR",0) | D35: MAT19-0124 | E35: =+_xlfn.XLOOKUP(D35,'BASE DATOS PRECIOS '!B:B,'BASE DATOS PRECIOS '!C:C) | F35: 2 | G35: =+_xlfn.XLOOKUP(D35,'BASE DATOS PRECIOS '!B:B,'BASE DATOS PRECIOS '!D:D) | H35: =+_xlfn.XLOOKUP(E35,'BASE DATOS PRECIOS '!C:C,'BASE DATOS PRECIOS '!F:F) | K35: =+F35*H35 | L35: =+F35*I35 | M35: =+F35*J35 | N35: =SUM(K35:M35) | O35: =SUM(K35:M35)/tc
A36: MAT | C36: =_xlfn.XLOOKUP(D36,'INSUMOS MAT '!B:B,'INSUMOS MAT '!C:C,"ERROR",0) | D36: MAT19-0041 | E36: =+_xlfn.XLOOKUP(D36,'BASE DATOS PRECIOS '!B:B,'BASE DATOS PRECIOS '!C:C) | F36: 1 | G36: =+_xlfn.XLOOKUP(D36,'BASE DATOS PRECIOS '!B:B,'BASE DATOS PRECIOS '!D:D) | H36: =+_xlfn.XLOOKUP(E36,'BASE DATOS PRECIOS '!C:C,'BASE DATOS PRECIOS '!F:F) | K36: =+F36*H36 | L36: 0 | M36: 0 | N36: =SUM(K36:M36) | O36: 1266.5567
A37: MAT | C37: =_xlfn.XLOOKUP(D37,'INSUMOS MAT '!B:B,'INSUMOS MAT '!C:C,"ERROR",0) | D37: MAT19-0017 | E37: =+_xlfn.XLOOKUP(D37,'BASE DATOS PRECIOS '!B:B,'BASE DATOS PRECIOS '!C:C) | F37: 1 | G37: =+_xlfn.XLOOKUP(D37,'BASE DATOS PRECIOS '!B:B,'BASE DATOS PRECIOS '!D:D) | H37: =+_xlfn.XLOOKUP(E37,'BASE DATOS PRECIOS '!C:C,'BASE DATOS PRECIOS '!F:F) | K37: =+F37*H37 | L37: =+F37*I37 | M37: =+F37*J37 | N37: =SUM(K37:M37) | O37: =SUM(K37:M37)/tc
A38: MAT | C38: =_xlfn.XLOOKUP(D38,'INSUMOS MAT '!B:B,'INSUMOS MAT '!C:C,"ERROR",0) | D38: MAT19-0096 | E38: =+_xlfn.XLOOKUP(D38,'BASE DATOS PRECIOS '!B:B,'BASE DATOS PRECIOS '!C:C) | F38: 1 | G38: =+_xlfn.XLOOKUP(D38,'BASE DATOS PRECIOS '!B:B,'BASE DATOS PRECIOS '!D:D) | H38: =+_xlfn.XLOOKUP(E38,'BASE DATOS PRECIOS '!C:C,'BASE DATOS PRECIOS '!F:F) | K38: =+F38*H38 | L38: =+F38*I38 | M38: =+F38*J38 | N38: =SUM(K38:M38) | O38: =SUM(K38:M38)/tc
A39: MAT | C39: =_xlfn.XLOOKUP(D39,'INSUMOS MAT '!B:B,'INSUMOS MAT '!C:C,"ERROR",0) | D39: MAT19-0125 | E39: =+_xlfn.XLOOKUP(D39,'BASE DATOS PRECIOS '!B:B,'BASE DATOS PRECIOS '!C:C) | F39: 1 | G39: =+_xlfn.XLOOKUP(D39,'BASE DATOS PRECIOS '!B:B,'BASE DATOS PRECIOS '!D:D) | H39: =+_xlfn.XLOOKUP(E39,'BASE DATOS PRECIOS '!C:C,'BASE DATOS PRECIOS '!F:F) | K39: =+F39*H39 | L39: =+F39*I39 | M39: =+F39*J39 | N39: =SUM(K39:M39) | O39: =SUM(K39:M39)/tc
A40: MAT | C40: =_xlfn.XLOOKUP(D40,'INSUMOS MAT '!B:B,'INSUMOS MAT '!C:C,"ERROR",0) | D40: MAT03-0002 | E40: =+_xlfn.XLOOKUP(D40,'BASE DATOS PRECIOS '!B:B,'BASE DATOS PRECIOS '!C:C) | F40: 0.5 | G40: =+_xlfn.XLOOKUP(D40,'BASE DATOS PRECIOS '!B:B,'BASE DATOS PRECIOS '!D:D) | H40: =+_xlfn.XLOOKUP(E40,'BASE DATOS PRECIOS '!C:C,'BASE DATOS PRECIOS '!F:F) | K40: =+F40*H40 | L40: =+F40*I40 | M40: =+F40*J40 | N40: =SUM(K40:M40) | O40: =SUM(K40:M40)/tc
A41: MAT | C41: =_xlfn.XLOOKUP(D41,'INSUMOS MAT '!B:B,'INSUMOS MAT '!C:C,"ERROR",0) | D41: MAT08-0091 | E41: =+_xlfn.XLOOKUP(D41,'BASE DATOS PRECIOS '!B:B,'BASE DATOS PRECIOS '!C:C) | F41: 1 | G41: =+_xlfn.XLOOKUP(D41,'BASE DATOS PRECIOS '!B:B,'BASE DATOS PRECIOS '!D:D) | H41: =+_xlfn.XLOOKUP(E41,'BASE DATOS PRECIOS '!C:C,'BASE DATOS PRECIOS '!F:F) | K41: =+F41*H41 | L41: =+F41*I41 | M41: =+F41*J41 | N41: =SUM(K41:M41) | O41: =SUM(K41:M41)/tc
A42: MAT | C42: =_xlfn.XLOOKUP(D42,'INSUMOS MAT '!B:B,'INSUMOS MAT '!C:C,"ERROR",0) | D42: MAT08-0034 | E42: =+_xlfn.XLOOKUP(D42,'BASE DATOS PRECIOS '!B:B,'BASE DATOS PRECIOS '!C:C) | F42: 1 | G42: =+_xlfn.XLOOKUP(D42,'BASE DATOS PRECIOS '!B:B,'BASE DATOS PRECIOS '!D:D) | H42: =+_xlfn.XLOOKUP(E42,'BASE DATOS PRECIOS '!C:C,'BASE DATOS PRECIOS '!F:F) | K42: =+F42*H42 | L42: =+F42*I42 | M42: =+F42*J42 | N42: =SUM(K42:M42) | O42: =SUM(K42:M42)/tc
A43: MAT | C43: =_xlfn.XLOOKUP(D43,'INSUMOS MAT '!B:B,'INSUMOS MAT '!C:C,"ERROR",0) | D43: MAT08-0031 | E43: =+_xlfn.XLOOKUP(D43,'BASE DATOS PRECIOS '!B:B,'BASE DATOS PRECIOS '!C:C) | F43: 1 | G43: =+_xlfn.XLOOKUP(D43,'BASE DATOS PRECIOS '!B:B,'BASE DATOS PRECIOS '!D:D) | H43: =+_xlfn.XLOOKUP(E43,'BASE DATOS PRECIOS '!C:C,'BASE DATOS PRECIOS '!F:F) | K43: =+F43*H43 | L43: =+F43*I43 | M43: =+F43*J43 | N43: =SUM(K43:M43) | O43: =SUM(K43:M43)/tc
A44: MAT | C44: =_xlfn.XLOOKUP(D44,'INSUMOS MAT '!B:B,'INSUMOS MAT '!C:C,"ERROR",0) | D44: MAT08-0003 | E44: =+_xlfn.XLOOKUP(D44,'BASE DATOS PRECIOS '!B:B,'BASE DATOS PRECIOS '!C:C) | F44: 1 | G44: =+_xlfn.XLOOKUP(D44,'BASE DATOS PRECIOS '!B:B,'BASE DATOS PRECIOS '!D:D) | H44: =+_xlfn.XLOOKUP(E44,'BASE DATOS PRECIOS '!C:C,'BASE DATOS PRECIOS '!F:F) | K44: =+F44*H44 | L44: =+F44*I44 | M44: =+F44*J44 | N44: =SUM(K44:M44) | O44: =SUM(K44:M44)/tc
E45: TUBERÍA ACOMETIDA ELÉCTRICA
A46: MAT | C46: =_xlfn.XLOOKUP(D46,'INSUMOS MAT '!B:B,'INSUMOS MAT '!C:C,"ERROR",0) | D46: MAT19-0084 | E46: =+_xlfn.XLOOKUP(D46,'BASE DATOS PRECIOS '!B:B,'BASE DATOS PRECIOS '!C:C) | F46: 6 | G46: =+_xlfn.XLOOKUP(D46,'BASE DATOS PRECIOS '!B:B,'BASE DATOS PRECIOS '!D:D) | H46: =+_xlfn.XLOOKUP(E46,'BASE DATOS PRECIOS '!C:C,'BASE DATOS PRECIOS '!F:F) | K46: =+F46*H46 | L46: =+F46*I46 | M46: =+F46*J46 | N46: =SUM(K46:M46) | O46: =SUM(K46:M46)/tc
A47: MAT | C47: =_xlfn.XLOOKUP(D47,'INSUMOS MAT '!B:B,'INSUMOS MAT '!C:C,"ERROR",0) | D47: MAT19-0085 | E47: =+_xlfn.XLOOKUP(D47,'BASE DATOS PRECIOS '!B:B,'BASE DATOS PRECIOS '!C:C) | F47: 6 | G47: =+_xlfn.XLOOKUP(D47,'BASE DATOS PRECIOS '!B:B,'BASE DATOS PRECIOS '!D:D) | H47: =+_xlfn.XLOOKUP(E47,'BASE DATOS PRECIOS '!C:C,'BASE DATOS PRECIOS '!F:F) | K47: =+F47*H47 | L47: =+F47*I47 | M47: =+F47*J47 | N47: =SUM(K47:M47) | O47: =SUM(K47:M47)/tc
A48: MAT | C48: =_xlfn.XLOOKUP(D48,'INSUMOS MAT '!B:B,'INSUMOS MAT '!C:C,"ERROR",0) | D48: MAT19-0031 | E48: =+_xlfn.XLOOKUP(D48,'BASE DATOS PRECIOS '!B:B,'BASE DATOS PRECIOS '!C:C) | F48: 2 | G48: =+_xlfn.XLOOKUP(D48,'BASE DATOS PRECIOS '!B:B,'BASE DATOS PRECIOS '!D:D) | H48: =+_xlfn.XLOOKUP(E48,'BASE DATOS PRECIOS '!C:C,'BASE DATOS PRECIOS '!F:F) | K48: =+F48*H48 | L48: =+F48*I48 | M48: =+F48*J48 | N48: =SUM(K48:M48) | O48: =SUM(K48:M48)/tc
A49: MAT | C49: =_xlfn.XLOOKUP(D49,'INSUMOS MAT '!B:B,'INSUMOS MAT '!C:C,"ERROR",0) | D49: MAT19-0032 | E49: =+_xlfn.XLOOKUP(D49,'BASE DATOS PRECIOS '!B:B,'BASE DATOS PRECIOS '!C:C) | F49: 2 | G49: =+_xlfn.XLOOKUP(D49,'BASE DATOS PRECIOS '!B:B,'BASE DATOS PRECIOS '!D:D) | H49: =+_xlfn.XLOOKUP(E49,'BASE DATOS PRECIOS '!C:C,'BASE DATOS PRECIOS '!F:F) | K49: =+F49*H49 | L49: =+F49*I49 | M49: =+F49*J49 | N49: =SUM(K49:M49) | O49: =SUM(K49:M49)/tc
A50: MAT | C50: =_xlfn.XLOOKUP(D50,'INSUMOS MAT '!B:B,'INSUMOS MAT '!C:C,"ERROR",0) | D50: MAT19-0104 | E50: =+_xlfn.XLOOKUP(D50,'BASE DATOS PRECIOS '!B:B,'BASE DATOS PRECIOS '!C:C) | F50: 2 | G50: =+_xlfn.XLOOKUP(D50,'BASE DATOS PRECIOS '!B:B,'BASE DATOS PRECIOS '!D:D) | H50: =+_xlfn.XLOOKUP(E50,'BASE DATOS PRECIOS '!C:C,'BASE DATOS PRECIOS '!F:F) | K50: =+F50*H50 | L50: =+F50*I50 | M50: =+F50*J50 | N50: =SUM(K50:M50) | O50: =SUM(K50:M50)/tc
A51: MAT | C51: =_xlfn.XLOOKUP(D51,'INSUMOS MAT '!B:B,'INSUMOS MAT '!C:C,"ERROR",0) | D51: MAT19-0105 | E51: =+_xlfn.XLOOKUP(D51,'BASE DATOS PRECIOS '!B:B,'BASE DATOS PRECIOS '!C:C) | F51: 2 | G51: =+_xlfn.XLOOKUP(D51,'BASE DATOS PRECIOS '!B:B,'BASE DATOS PRECIOS '!D:D) | H51: =+_xlfn.XLOOKUP(E51,'BASE DATOS PRECIOS '!C:C,'BASE DATOS PRECIOS '!F:F) | K51: =+F51*H51 | L51: =+F51*I51 | M51: =+F51*J51 | N51: =SUM(K51:M51) | O51: =SUM(K51:M51)/tc
A52: MAT | C52: =_xlfn.XLOOKUP(D52,'INSUMOS MAT '!B:B,'INSUMOS MAT '!C:C,"ERROR",0) | D52: MAT21-0009 | E52: =+_xlfn.XLOOKUP(D52,'BASE DATOS PRECIOS '!B:B,'BASE DATOS PRECIOS '!C:C) | F52: 1 | G52: =+_xlfn.XLOOKUP(D52,'BASE DATOS PRECIOS '!B:B,'BASE DATOS PRECIOS '!D:D) | H52: =+_xlfn.XLOOKUP(E52,'BASE DATOS PRECIOS '!C:C,'BASE DATOS PRECIOS '!F:F) | K52: =+F52*H52 | L52: =+F52*I52 | M52: =+F52*J52 | N52: =SUM(K52:M52) | O52: =SUM(K52:M52)/tc
A53: MAT | C53: =_xlfn.XLOOKUP(D53,'INSUMOS MAT '!B:B,'INSUMOS MAT '!C:C,"ERROR",0) | D53: MAT08-0018 | E53: =+_xlfn.XLOOKUP(D53,'BASE DATOS PRECIOS '!B:B,'BASE DATOS PRECIOS '!C:C) | F53: 1 | G53: =+_xlfn.XLOOKUP(D53,'BASE DATOS PRECIOS '!B:B,'BASE DATOS PRECIOS '!D:D) | H53: =+_xlfn.XLOOKUP(E53,'BASE DATOS PRECIOS '!C:C,'BASE DATOS PRECIOS '!F:F) | K53: =+F53*H53 | L53: =+F53*I53 | M53: =+F53*J53 | N53: =SUM(K53:M53) | O53: =SUM(K53:M53)/tc
A54: EQUIP | D54: BACK HOE | E54: =+_xlfn.XLOOKUP(D54,'BASE DATOS EQUIPOS Y SUBCONTRAT'!A:A,'BASE DATOS EQUIPOS Y SUBCONTRAT'!B:B) | F54: 1 | G54: =+_xlfn.XLOOKUP(D54,'BASE DATOS EQUIPOS Y SUBCONTRAT'!A:A,'BASE DATOS EQUIPOS Y SUBCONTRAT'!C:C) | H54: 0 | J54: =+_xlfn.XLOOKUP(D54,'BASE DATOS EQUIPOS Y SUBCONTRAT'!A:A,'BASE DATOS EQUIPOS Y SUBCONTRAT'!E:E) | K54: =+F54*H54 | L54: =+F54*I54 | M54: =+F54*J54 | N54: =SUM(K54:M54) | O54: =SUM(K54:M54)/tc
A55: EQUIP | D55: COMPACTADOR | E55: =+_xlfn.XLOOKUP(D55,'BASE DATOS EQUIPOS Y SUBCONTRAT'!A:A,'BASE DATOS EQUIPOS Y SUBCONTRAT'!B:B) | F55: 2 | G55: =+_xlfn.XLOOKUP(D55,'BASE DATOS EQUIPOS Y SUBCONTRAT'!A:A,'BASE DATOS EQUIPOS Y SUBCONTRAT'!C:C) | H55: 0 | J55: =+_xlfn.XLOOKUP(D55,'BASE DATOS EQUIPOS Y SUBCONTRAT'!A:A,'BASE DATOS EQUIPOS Y SUBCONTRAT'!E:E) | K55: =+F55*H55 | L55: =+F55*I55 | M55: =+F55*J55 | N55: =SUM(K55:M55) | O55: =SUM(K55:M55)/tc
A56: MO | B56: 01-02-01 | D56: OPERARIO | E56: =+_xlfn.XLOOKUP(D56,'BASE DATOS MANO DE OBRA'!A:A,'BASE DATOS MANO DE OBRA'!B:B) | F56: 15 | G56: =+_xlfn.XLOOKUP(D56,'BASE DATOS MANO DE OBRA'!A:A,'BASE DATOS MANO DE OBRA'!C:C) | H56: 0 | I56: =+_xlfn.XLOOKUP(D56,'BASE DATOS MANO DE OBRA'!A:A,'BASE DATOS MANO DE OBRA'!E:E) | J56: 0 | K56: =+F56*H56 | L56: =+F56*I56 | M56: =+F56*J56 | N56: =SUM(K56:M56) | O56: =SUM(K56:M56)/tc
A57: MO | B57: 01-02-01 | D57: AYUDANTE | E57: =+_xlfn.XLOOKUP(D57,'BASE DATOS MANO DE OBRA'!A:A,'BASE DATOS MANO DE OBRA'!B:B) | F57: 15 | G57: =+_xlfn.XLOOKUP(D57,'BASE DATOS MANO DE OBRA'!A:A,'BASE DATOS MANO DE OBRA'!C:C) | H57: 0 | I57: =+_xlfn.XLOOKUP(D57,'BASE DATOS MANO DE OBRA'!A:A,'BASE DATOS MANO DE OBRA'!E:E) | J57: 0 | K57: =+F57*H57 | L57: =+F57*I57 | M57: =+F57*J57 | N57: =SUM(K57:M57) | O57: =SUM(K57:M57)/tc
B58: 01-03 | D58: 1.3 | E58: SELLO DE CONCRETO | F58: 1 | G58: gb | K58: =SUM(K59:K68) | L58: =SUM(L59:L68) | M58: =SUM(M59:M68) | N58: =SUM(N59:N68) | O58: =SUM(O59:O68)
E59: CONCRETO
A60: MAT | C60: =_xlfn.XLOOKUP(D60,'INSUMOS MAT '!B:B,'INSUMOS MAT '!C:C,"ERROR",0) | D60: MAT04-0062 | E60: =+_xlfn.XLOOKUP(D60,'BASE DATOS PRECIOS '!B:B,'BASE DATOS PRECIOS '!C:C) | F60: 620 | G60: =+_xlfn.XLOOKUP(D60,'BASE DATOS PRECIOS '!B:B,'BASE DATOS PRECIOS '!D:D) | H60: =+_xlfn.XLOOKUP(E60,'BASE DATOS PRECIOS '!C:C,'BASE DATOS PRECIOS '!F:F) | K60: =+F60*H60 | L60: =+F60*I60 | M60: =+F60*J60 | N60: =SUM(K60:M60) | O60: =SUM(K60:M60)/tc
A61: MAT | C61: =_xlfn.XLOOKUP(D61,'INSUMOS MAT '!B:B,'INSUMOS MAT '!C:C,"ERROR",0) | D61: MAT03-0006 | E61: =+_xlfn.XLOOKUP(D61,'BASE DATOS PRECIOS '!B:B,'BASE DATOS PRECIOS '!C:C) | F61: 2.5 | G61: =+_xlfn.XLOOKUP(D61,'BASE DATOS PRECIOS '!B:B,'BASE DATOS PRECIOS '!D:D) | H61: =+_xlfn.XLOOKUP(E61,'BASE DATOS PRECIOS '!C:C,'BASE DATOS PRECIOS '!F:F) | K61: =+F61*H61 | L61: =+F61*I61 | M61: =+F61*J61 | N61: =SUM(K61:M61) | O61: =SUM(K61:M61)/tc
A62: MAT | C62: =_xlfn.XLOOKUP(D62,'INSUMOS MAT '!B:B,'INSUMOS MAT '!C:C,"ERROR",0) | D62: MAT03-0002 | E62: =+_xlfn.XLOOKUP(D62,'BASE DATOS PRECIOS '!B:B,'BASE DATOS PRECIOS '!C:C) | F62: 3 | G62: =+_xlfn.XLOOKUP(D62,'BASE DATOS PRECIOS '!B:B,'BASE DATOS PRECIOS '!D:D) | H62: =+_xlfn.XLOOKUP(E62,'BASE DATOS PRECIOS '!C:C,'BASE DATOS PRECIOS '!F:F) | K62: =+F62*H62 | L62: =+F62*I62 | M62: =+F62*J62 | N62: =SUM(K62:M62) | O62: =SUM(K62:M62)/tc
A63: MAT | C63: =_xlfn.XLOOKUP(D63,'INSUMOS MAT '!B:B,'INSUMOS MAT '!C:C,"ERROR",0) | D63: MAT02-0017 | E63: =+_xlfn.XLOOKUP(D63,'BASE DATOS PRECIOS '!B:B,'BASE DATOS PRECIOS '!C:C) | F63: 1 | G63: =+_xlfn.XLOOKUP(D63,'BASE DATOS PRECIOS '!B:B,'BASE DATOS PRECIOS '!D:D) | H63: =+_xlfn.XLOOKUP(E63,'BASE DATOS PRECIOS '!C:C,'BASE DATOS PRECIOS '!F:F) | K63: =+F63*H63 | L63: =+F63*I63 | M63: =+F63*J63 | N63: =SUM(K63:M63) | O63: =SUM(K63:M63)/tc
A64: MAT | C64: =_xlfn.XLOOKUP(D64,'INSUMOS MAT '!B:B,'INSUMOS MAT '!C:C,"ERROR",0) | D64: MAT02-0029 | E64: =+_xlfn.XLOOKUP(D64,'BASE DATOS PRECIOS '!B:B,'BASE DATOS PRECIOS '!C:C) | F64: 1 | G64: =+_xlfn.XLOOKUP(D64,'BASE DATOS PRECIOS '!B:B,'BASE DATOS PRECIOS '!D:D) | H64: =+_xlfn.XLOOKUP(E64,'BASE DATOS PRECIOS '!C:C,'BASE DATOS PRECIOS '!F:F) | K64: =+F64*H64 | L64: =+F64*I64 | M64: =+F64*J64 | N64: =SUM(K64:M64) | O64: =SUM(K64:M64)/tc
A65: MAT | C65: =_xlfn.XLOOKUP(D65,'INSUMOS MAT '!B:B,'INSUMOS MAT '!C:C,"ERROR",0) | D65: MAT08-0031 | E65: =+_xlfn.XLOOKUP(D65,'BASE DATOS PRECIOS '!B:B,'BASE DATOS PRECIOS '!C:C) | F65: 3 | G65: =+_xlfn.XLOOKUP(D65,'BASE DATOS PRECIOS '!B:B,'BASE DATOS PRECIOS '!D:D) | H65: =+_xlfn.XLOOKUP(E65,'BASE DATOS PRECIOS '!C:C,'BASE DATOS PRECIOS '!F:F) | K65: =+F65*H65 | L65: =+F65*I65 | M65: =+F65*J65 | N65: =SUM(K65:M65) | O65: =SUM(K65:M65)/tc
A66: MAT | C66: =_xlfn.XLOOKUP(D66,'INSUMOS MAT '!B:B,'INSUMOS MAT '!C:C,"ERROR",0) | D66: MAT08-0449 | E66: =+_xlfn.XLOOKUP(D66,'BASE DATOS PRECIOS '!B:B,'BASE DATOS PRECIOS '!C:C) | F66: 5 | G66: =+_xlfn.XLOOKUP(D66,'BASE DATOS PRECIOS '!B:B,'BASE DATOS PRECIOS '!D:D) | H66: =+_xlfn.XLOOKUP(E66,'BASE DATOS PRECIOS '!C:C,'BASE DATOS PRECIOS '!F:F) | K66: =+F66*H66 | L66: =+F66*I66 | M66: =+F66*J66 | N66: =SUM(K66:M66) | O66: =SUM(K66:M66)/tc
A67: MO | B67: 01-03-01 | D67: OPERARIO | E67: =+_xlfn.XLOOKUP(D67,'BASE DATOS MANO DE OBRA'!A:A,'BASE DATOS MANO DE OBRA'!B:B) | F67: 17 | G67: =+_xlfn.XLOOKUP(D67,'BASE DATOS MANO DE OBRA'!A:A,'BASE DATOS MANO DE OBRA'!C:C) | H67: 0 | I67: =+_xlfn.XLOOKUP(D67,'BASE DATOS MANO DE OBRA'!A:A,'BASE DATOS MANO DE OBRA'!E:E) | J67: 0 | K67: =+F67*H67 | L67: =+F67*I67 | M67: =+F67*J67 | N67: =SUM(K67:M67) | O67: =SUM(K67:M67)/tc
A68: MO | B68: 01-03-01 | D68: AYUDANTE | E68: =+_xlfn.XLOOKUP(D68,'BASE DATOS MANO DE OBRA'!A:A,'BASE DATOS MANO DE OBRA'!B:B) | F68: 17 | G68: =+_xlfn.XLOOKUP(D68,'BASE DATOS MANO DE OBRA'!A:A,'BASE DATOS MANO DE OBRA'!C:C) | H68: 0 | I68: =+_xlfn.XLOOKUP(D68,'BASE DATOS MANO DE OBRA'!A:A,'BASE DATOS MANO DE OBRA'!E:E) | J68: 0 | K68: =+F68*H68 | L68: =+F68*I68 | M68: =+F68*J68 | N68: =SUM(K68:M68) | O68: =SUM(K68:M68)/tc
B69: 01-04 | D69: 1.4 | E69: LOSA FLOTANTE (ACERO, ELECTROMECANICOS, CONCRETO) | F69: 54.54 | G69: m2 | K69: =SUM(K70:K122) | L69: =SUM(L70:L122) | M69: =SUM(M70:M122) | N69: =SUM(N70:N122) | O69: =SUM(O70:O122)
E70: CONCRETO
A71: MAT | C71: =_xlfn.XLOOKUP(D71,'INSUMOS MAT '!B:B,'INSUMOS MAT '!C:C,"ERROR",0) | D71: MAT04-0062 | E71: =+_xlfn.XLOOKUP(D71,'BASE DATOS PRECIOS '!B:B,'BASE DATOS PRECIOS '!C:C) | F71: 3807 | G71: =+_xlfn.XLOOKUP(D71,'BASE DATOS PRECIOS '!B:B,'BASE DATOS PRECIOS '!D:D) | H71: =+_xlfn.XLOOKUP(E71,'BASE DATOS PRECIOS '!C:C,'BASE DATOS PRECIOS '!F:F) | K71: =+F71*H71 | L71: =+F71*I71 | M71: =+F71*J71 | N71: =SUM(K71:M71) | O71: =SUM(K71:M71)/tc
A72: MAT | C72: =_xlfn.XLOOKUP(D72,'INSUMOS MAT '!B:B,'INSUMOS MAT '!C:C,"ERROR",0) | D72: MAT03-0006 | E72: =+_xlfn.XLOOKUP(D72,'BASE DATOS PRECIOS '!B:B,'BASE DATOS PRECIOS '!C:C) | F72: 8 | G72: =+_xlfn.XLOOKUP(D72,'BASE DATOS PRECIOS '!B:B,'BASE DATOS PRECIOS '!D:D) | H72: =+_xlfn.XLOOKUP(E72,'BASE DATOS PRECIOS '!C:C,'BASE DATOS PRECIOS '!F:F) | K72: =+F72*H72 | L72: =+F72*I72 | M72: =+F72*J72 | N72: =SUM(K72:M72) | O72: =SUM(K72:M72)/tc
A73: MAT | C73: =_xlfn.XLOOKUP(D73,'INSUMOS MAT '!B:B,'INSUMOS MAT '!C:C,"ERROR",0) | D73: MAT03-0002 | E73: =+_xlfn.XLOOKUP(D73,'BASE DATOS PRECIOS '!B:B,'BASE DATOS PRECIOS '!C:C) | F73: 7 | G73: =+_xlfn.XLOOKUP(D73,'BASE DATOS PRECIOS '!B:B,'BASE DATOS PRECIOS '!D:D) | H73: =+_xlfn.XLOOKUP(E73,'BASE DATOS PRECIOS '!C:C,'BASE DATOS PRECIOS '!F:F) | K73: =+F73*H73 | L73: =+F73*I73 | M73: =+F73*J73 | N73: =SUM(K73:M73) | O73: =SUM(K73:M73)/tc
A74: MAT | C74: =_xlfn.XLOOKUP(D74,'INSUMOS MAT '!B:B,'INSUMOS MAT '!C:C,"ERROR",0) | D74: MAT21-0028 | E74: =+_xlfn.XLOOKUP(D74,'BASE DATOS PRECIOS '!B:B,'BASE DATOS PRECIOS '!C:C) | F74: 23 | G74: =+_xlfn.XLOOKUP(D74,'BASE DATOS PRECIOS '!B:B,'BASE DATOS PRECIOS '!D:D) | H74: =(+_xlfn.XLOOKUP(E74,'BASE DATOS PRECIOS '!C:C,'BASE DATOS PRECIOS '!F:F))/18.9 | K74: =+F74*H74 | L74: =+F74*I74 | M74: =+F74*J74 | N74: =SUM(K74:M74) | O74: =SUM(K74:M74)/tc
A75: MAT | C75: =_xlfn.XLOOKUP(D75,'INSUMOS MAT '!B:B,'INSUMOS MAT '!C:C,"ERROR",0) | D75: MAT02-0010 | E75: =+_xlfn.XLOOKUP(D75,'BASE DATOS PRECIOS '!B:B,'BASE DATOS PRECIOS '!C:C) | F75: 12 | G75: =+_xlfn.XLOOKUP(D75,'BASE DATOS PRECIOS '!B:B,'BASE DATOS PRECIOS '!D:D) | H75: =+_xlfn.XLOOKUP(E75,'BASE DATOS PRECIOS '!C:C,'BASE DATOS PRECIOS '!F:F) | K75: =+F75*H75 | L75: =+F75*I75 | M75: =+F75*J75 | N75: =SUM(K75:M75) | O75: =SUM(K75:M75)/tc
A76: MAT | C76: =_xlfn.XLOOKUP(D76,'INSUMOS MAT '!B:B,'INSUMOS MAT '!C:C,"ERROR",0) | D76: MAT02-0027 | E76: =+_xlfn.XLOOKUP(D76,'BASE DATOS PRECIOS '!B:B,'BASE DATOS PRECIOS '!C:C) | F76: =37+65 | G76: =+_xlfn.XLOOKUP(D76,'BASE DATOS PRECIOS '!B:B,'BASE DATOS PRECIOS '!D:D) | H76: =+_xlfn.XLOOKUP(E76,'BASE DATOS PRECIOS '!C:C,'BASE DATOS PRECIOS '!F:F) | K76: =+F76*H76 | L76: =+F76*I76 | M76: =+F76*J76 | N76: =SUM(K76:M76) | O76: =SUM(K76:M76)/tc
A77: MAT | C77: =_xlfn.XLOOKUP(D77,'INSUMOS MAT '!B:B,'INSUMOS MAT '!C:C,"ERROR",0) | D77: MAT02-0025 | E77: =+_xlfn.XLOOKUP(D77,'BASE DATOS PRECIOS '!B:B,'BASE DATOS PRECIOS '!C:C) | F77: =47 | G77: =+_xlfn.XLOOKUP(D77,'BASE DATOS PRECIOS '!B:B,'BASE DATOS PRECIOS '!D:D) | H77: =+_xlfn.XLOOKUP(E77,'BASE DATOS PRECIOS '!C:C,'BASE DATOS PRECIOS '!F:F) | K77: =+F77*H77 | L77: =+F77*I77 | M77: =+F77*J77 | N77: =SUM(K77:M77) | O77: =SUM(K77:M77)/tc
A78: MAT | C78: =_xlfn.XLOOKUP(D78,'INSUMOS MAT '!B:B,'INSUMOS MAT '!C:C,"ERROR",0) | D78: MAT02-0001 | E78: =+_xlfn.XLOOKUP(D78,'BASE DATOS PRECIOS '!B:B,'BASE DATOS PRECIOS '!C:C) | F78: =25+10 | G78: =+_xlfn.XLOOKUP(D78,'BASE DATOS PRECIOS '!B:B,'BASE DATOS PRECIOS '!D:D) | H78: =+_xlfn.XLOOKUP(E78,'BASE DATOS PRECIOS '!C:C,'BASE DATOS PRECIOS '!F:F) | K78: =+F78*H78 | L78: =+F78*I78 | M78: =+F78*J78 | N78: =SUM(K78:M78) | O78: =SUM(K78:M78)/tc
A79: MAT | C79: =_xlfn.XLOOKUP(D79,'INSUMOS MAT '!B:B,'INSUMOS MAT '!C:C,"ERROR",0) | D79: MAT08-0108 | E79: =+_xlfn.XLOOKUP(D79,'BASE DATOS PRECIOS '!B:B,'BASE DATOS PRECIOS '!C:C) | F79: 120 | G79: =+_xlfn.XLOOKUP(D79,'BASE DATOS PRECIOS '!B:B,'BASE DATOS PRECIOS '!D:D) | H79: =+_xlfn.XLOOKUP(E79,'BASE DATOS PRECIOS '!C:C,'BASE DATOS PRECIOS '!F:F) | K79: =+F79*H79 | L79: =+F79*I79 | M79: =+F79*J79 | N79: =SUM(K79:M79) | O79: =SUM(K79:M79)/tc
A80: MAT | C80: =_xlfn.XLOOKUP(D80,'INSUMOS MAT '!B:B,'INSUMOS MAT '!C:C,"ERROR",0) | D80: MAT08-0141 | E80: =+_xlfn.XLOOKUP(D80,'BASE DATOS PRECIOS '!B:B,'BASE DATOS PRECIOS '!C:C) | F80: 75 | G80: =+_xlfn.XLOOKUP(D80,'BASE DATOS PRECIOS '!B:B,'BASE DATOS PRECIOS '!D:D) | H80: =+_xlfn.XLOOKUP(E80,'BASE DATOS PRECIOS '!C:C,'BASE DATOS PRECIOS '!F:F) | K80: =+F80*H80 | L80: =+F80*I80 | M80: =+F80*J80 | N80: =SUM(K80:M80) | O80: =SUM(K80:M80)/tc
A81: MAT | C81: =_xlfn.XLOOKUP(D81,'INSUMOS MAT '!B:B,'INSUMOS MAT '!C:C,"ERROR",0) | D81: MAT08-0038 | E81: =+_xlfn.XLOOKUP(D81,'BASE DATOS PRECIOS '!B:B,'BASE DATOS PRECIOS '!C:C) | F81: 4 | G81: =+_xlfn.XLOOKUP(D81,'BASE DATOS PRECIOS '!B:B,'BASE DATOS PRECIOS '!D:D) | H81: =+_xlfn.XLOOKUP(E81,'BASE DATOS PRECIOS '!C:C,'BASE DATOS PRECIOS '!F:F) | K81: =+F81*H81 | L81: =+F81*I81 | M81: =+F81*J81 | N81: =SUM(K81:M81) | O81: =SUM(K81:M81)/tc
E82: TUBERÍA MECÁNICA AGUA FRIA
A83: MAT | C83: =_xlfn.XLOOKUP(D83,'INSUMOS MAT '!B:B,'INSUMOS MAT '!C:C,"ERROR",0) | D83: MAT19-0011 | E83: =+_xlfn.XLOOKUP(D83,'BASE DATOS PRECIOS '!B:B,'BASE DATOS PRECIOS '!C:C) | F83: 2 | G83: =+_xlfn.XLOOKUP(D83,'BASE DATOS PRECIOS '!B:B,'BASE DATOS PRECIOS '!D:D) | H83: =+_xlfn.XLOOKUP(E83,'BASE DATOS PRECIOS '!C:C,'BASE DATOS PRECIOS '!F:F) | K83: =+F83*H83 | L83: =+F83*I83 | M83: =+F83*J83 | N83: =SUM(K83:M83) | O83: =SUM(K83:M83)/tc
A84: MAT | C84: =_xlfn.XLOOKUP(D84,'INSUMOS MAT '!B:B,'INSUMOS MAT '!C:C,"ERROR",0) | D84: MAT08-0072 | E84: =+_xlfn.XLOOKUP(D84,'BASE DATOS PRECIOS '!B:B,'BASE DATOS PRECIOS '!C:C) | F84: 1 | G84: =+_xlfn.XLOOKUP(D84,'BASE DATOS PRECIOS '!B:B,'BASE DATOS PRECIOS '!D:D) | H84: =+_xlfn.XLOOKUP(E84,'BASE DATOS PRECIOS '!C:C,'BASE DATOS PRECIOS '!F:F) | K84: =+F84*H84 | L84: =+F84*I84 | M84: =+F84*J84 | N84: =SUM(K84:M84) | O84: =SUM(K84:M84)/tc
A85: MAT | C85: =_xlfn.XLOOKUP(D85,'INSUMOS MAT '!B:B,'INSUMOS MAT '!C:C,"ERROR",0) | D85: MAT19-0020 | E85: =+_xlfn.XLOOKUP(D85,'BASE DATOS PRECIOS '!B:B,'BASE DATOS PRECIOS '!C:C) | F85: 15 | G85: =+_xlfn.XLOOKUP(D85,'BASE DATOS PRECIOS '!B:B,'BASE DATOS PRECIOS '!D:D) | H85: =+_xlfn.XLOOKUP(E85,'BASE DATOS PRECIOS '!C:C,'BASE DATOS PRECIOS '!F:F) | K85: =+F85*H85 | L85: =+F85*I85 | M85: =+F85*J85 | N85: =SUM(K85:M85) | O85: =SUM(K85:M85)/tc
A86: MAT | C86: =_xlfn.XLOOKUP(D86,'INSUMOS MAT '!B:B,'INSUMOS MAT '!C:C,"ERROR",0) | D86: MAT19-0077 | E86: =+_xlfn.XLOOKUP(D86,'BASE DATOS PRECIOS '!B:B,'BASE DATOS PRECIOS '!C:C) | F86: 10 | G86: =+_xlfn.XLOOKUP(D86,'BASE DATOS PRECIOS '!B:B,'BASE DATOS PRECIOS '!D:D) | H86: =+_xlfn.XLOOKUP(E86,'BASE DATOS PRECIOS '!C:C,'BASE DATOS PRECIOS '!F:F) | K86: =+F86*H86 | L86: =+F86*I86 | M86: =+F86*J86 | N86: =SUM(K86:M86) | O86: =SUM(K86:M86)/tc
A87: MAT | C87: =_xlfn.XLOOKUP(D87,'INSUMOS MAT '!B:B,'INSUMOS MAT '!C:C,"ERROR",0) | D87: MAT19-0061 | E87: =+_xlfn.XLOOKUP(D87,'BASE DATOS PRECIOS '!B:B,'BASE DATOS PRECIOS '!C:C) | F87: 10 | G87: =+_xlfn.XLOOKUP(D87,'BASE DATOS PRECIOS '!B:B,'BASE DATOS PRECIOS '!D:D) | H87: =+_xlfn.XLOOKUP(E87,'BASE DATOS PRECIOS '!C:C,'BASE DATOS PRECIOS '!F:F) | K87: =+F87*H87 | L87: =+F87*I87 | M87: =+F87*J87 | N87: =SUM(K87:M87) | O87: =SUM(K87:M87)/tc
A88: MAT | C88: =_xlfn.XLOOKUP(D88,'INSUMOS MAT '!B:B,'INSUMOS MAT '!C:C,"ERROR",0) | D88: MAT19-0092 | E88: =+_xlfn.XLOOKUP(D88,'BASE DATOS PRECIOS '!B:B,'BASE DATOS PRECIOS '!C:C) | F88: 5 | G88: =+_xlfn.XLOOKUP(D88,'BASE DATOS PRECIOS '!B:B,'BASE DATOS PRECIOS '!D:D) | H88: =+_xlfn.XLOOKUP(E88,'BASE DATOS PRECIOS '!C:C,'BASE DATOS PRECIOS '!F:F) | K88: =+F88*H88 | L88: =+F88*I88 | M88: =+F88*J88 | N88: =SUM(K88:M88) | O88: =SUM(K88:M88)/tc
E89: TUBERÍA MECÁNICA AGUA CALIENTE
A90: MAT | C90: =_xlfn.XLOOKUP(D90,'INSUMOS MAT '!B:B,'INSUMOS MAT '!C:C,"ERROR",0) | D90: MAT19-0075 | E90: =+_xlfn.XLOOKUP(D90,'BASE DATOS PRECIOS '!B:B,'BASE DATOS PRECIOS '!C:C) | F90: 5 | G90: =+_xlfn.XLOOKUP(D90,'BASE DATOS PRECIOS '!B:B,'BASE DATOS PRECIOS '!D:D) | H90: =+_xlfn.XLOOKUP(E90,'BASE DATOS PRECIOS '!C:C,'BASE DATOS PRECIOS '!F:F) | K90: =+F90*H90 | L90: =+F90*I90 | M90: =+F90*J90 | N90: =SUM(K90:M90) | O90: =SUM(K90:M90)/tc
A91: MAT | C91: =_xlfn.XLOOKUP(D91,'INSUMOS MAT '!B:B,'INSUMOS MAT '!C:C,"ERROR",0) | D91: MAT19-0021 | E91: =+_xlfn.XLOOKUP(D91,'BASE DATOS PRECIOS '!B:B,'BASE DATOS PRECIOS '!C:C) | F91: 11 | G91: =+_xlfn.XLOOKUP(D91,'BASE DATOS PRECIOS '!B:B,'BASE DATOS PRECIOS '!D:D) | H91: =+_xlfn.XLOOKUP(E91,'BASE DATOS PRECIOS '!C:C,'BASE DATOS PRECIOS '!F:F) | K91: =+F91*H91 | L91: =+F91*I91 | M91: =+F91*J91 | N91: =SUM(K91:M91) | O91: =SUM(K91:M91)/tc
A92: MAT | C92: =_xlfn.XLOOKUP(D92,'INSUMOS MAT '!B:B,'INSUMOS MAT '!C:C,"ERROR",0) | D92: MAT19-0088 | E92: =+_xlfn.XLOOKUP(D92,'BASE DATOS PRECIOS '!B:B,'BASE DATOS PRECIOS '!C:C) | F92: 4 | G92: =+_xlfn.XLOOKUP(D92,'BASE DATOS PRECIOS '!B:B,'BASE DATOS PRECIOS '!D:D) | H92: =+_xlfn.XLOOKUP(E92,'BASE DATOS PRECIOS '!C:C,'BASE DATOS PRECIOS '!F:F) | K92: =+F92*H92 | L92: =+F92*I92 | M92: =+F92*J92 | N92: =SUM(K92:M92) | O92: =SUM(K92:M92)/tc
A93: MAT | C93: =_xlfn.XLOOKUP(D93,'INSUMOS MAT '!B:B,'INSUMOS MAT '!C:C,"ERROR",0) | D93: MAT19-0009 | E93: =+_xlfn.XLOOKUP(D93,'BASE DATOS PRECIOS '!B:B,'BASE DATOS PRECIOS '!C:C) | F93: 1 | G93: =+_xlfn.XLOOKUP(D93,'BASE DATOS PRECIOS '!B:B,'BASE DATOS PRECIOS '!D:D) | H93: =+_xlfn.XLOOKUP(E93,'BASE DATOS PRECIOS '!C:C,'BASE DATOS PRECIOS '!F:F) | K93: =+F93*H93 | L93: =+F93*I93 | M93: =+F93*J93 | N93: =SUM(K93:M93) | O93: =SUM(K93:M93)/tc
A94: MAT | C94: =_xlfn.XLOOKUP(D94,'INSUMOS MAT '!B:B,'INSUMOS MAT '!C:C,"ERROR",0) | D94: MAT19-0066 | E94: =+_xlfn.XLOOKUP(D94,'BASE DATOS PRECIOS '!B:B,'BASE DATOS PRECIOS '!C:C) | F94: 6 | G94: =+_xlfn.XLOOKUP(D94,'BASE DATOS PRECIOS '!B:B,'BASE DATOS PRECIOS '!D:D) | H94: =+_xlfn.XLOOKUP(E94,'BASE DATOS PRECIOS '!C:C,'BASE DATOS PRECIOS '!F:F) | K94: =+F94*H94 | L94: =+F94*I94 | M94: =+F94*J94 | N94: =SUM(K94:M94) | O94: =SUM(K94:M94)/tc
E95: TUBERÍA VENTILACION BAÑO Y PREVISTA PARA LOSA CENITAL
A96: MAT | C96: =_xlfn.XLOOKUP(D96,'INSUMOS MAT '!B:B,'INSUMOS MAT '!C:C,"ERROR",0) | D96: MAT19-0094 | E96: =+_xlfn.XLOOKUP(D96,'BASE DATOS PRECIOS '!B:B,'BASE DATOS PRECIOS '!C:C) | F96: 2 | G96: =+_xlfn.XLOOKUP(D96,'BASE DATOS PRECIOS '!B:B,'BASE DATOS PRECIOS '!D:D) | H96: =+_xlfn.XLOOKUP(E96,'BASE DATOS PRECIOS '!C:C,'BASE DATOS PRECIOS '!F:F) | K96: =+F96*H96 | L96: =+F96*I96 | M96: =+F96*J96 | N96: =SUM(K96:M96) | O96: =SUM(K96:M96)/tc
A97: MAT | C97: =_xlfn.XLOOKUP(D97,'INSUMOS MAT '!B:B,'INSUMOS MAT '!C:C,"ERROR",0) | D97: MAT19-0023 | E97: =+_xlfn.XLOOKUP(D97,'BASE DATOS PRECIOS '!B:B,'BASE DATOS PRECIOS '!C:C) | F97: 6 | G97: =+_xlfn.XLOOKUP(D97,'BASE DATOS PRECIOS '!B:B,'BASE DATOS PRECIOS '!D:D) | H97: =+_xlfn.XLOOKUP(E97,'BASE DATOS PRECIOS '!C:C,'BASE DATOS PRECIOS '!F:F) | K97: =+F97*H97 | L97: =+F97*I97 | M97: =+F97*J97 | N97: =SUM(K97:M97) | O97: =SUM(K97:M97)/tc
A98: MAT | C98: =_xlfn.XLOOKUP(D98,'INSUMOS MAT '!B:B,'INSUMOS MAT '!C:C,"ERROR",0) | D98: MAT19-0038 | E98: =+_xlfn.XLOOKUP(D98,'BASE DATOS PRECIOS '!B:B,'BASE DATOS PRECIOS '!C:C) | F98: 6 | G98: =+_xlfn.XLOOKUP(D98,'BASE DATOS PRECIOS '!B:B,'BASE DATOS PRECIOS '!D:D) | H98: =+_xlfn.XLOOKUP(E98,'BASE DATOS PRECIOS '!C:C,'BASE DATOS PRECIOS '!F:F) | K98: =+F98*H98 | L98: =+F98*I98 | M98: =+F98*J98 | N98: =SUM(K98:M98) | O98: =SUM(K98:M98)/tc
A99: MAT | C99: =_xlfn.XLOOKUP(D99,'INSUMOS MAT '!B:B,'INSUMOS MAT '!C:C,"ERROR",0) | D99: MAT19-0110 | E99: =+_xlfn.XLOOKUP(D99,'BASE DATOS PRECIOS '!B:B,'BASE DATOS PRECIOS '!C:C) | F99: 2 | G99: =+_xlfn.XLOOKUP(D99,'BASE DATOS PRECIOS '!B:B,'BASE DATOS PRECIOS '!D:D) | H99: =+_xlfn.XLOOKUP(E99,'BASE DATOS PRECIOS '!C:C,'BASE DATOS PRECIOS '!F:F) | K99: =+F99*H99 | L99: =+F99*I99 | M99: =+F99*J99 | N99: =SUM(K99:M99) | O99: =SUM(K99:M99)/tc
E100: TUBERÍA ELÉCTRICA
A101: MAT | C101: =_xlfn.XLOOKUP(D101,'INSUMOS MAT '!B:B,'INSUMOS MAT '!C:C,"ERROR",0) | D101: MAT19-0086 | E101: =+_xlfn.XLOOKUP(D101,'BASE DATOS PRECIOS '!B:B,'BASE DATOS PRECIOS '!C:C) | F101: =40+6 | G101: =+_xlfn.XLOOKUP(D101,'BASE DATOS PRECIOS '!B:B,'BASE DATOS PRECIOS '!D:D) | H101: =+_xlfn.XLOOKUP(E101,'BASE DATOS PRECIOS '!C:C,'BASE DATOS PRECIOS '!F:F) | K101: =+F101*H101 | L101: =+F101*I101 | M101: =+F101*J101 | N101: =SUM(K101:M101) | O101: =SUM(K101:M101)/tc
A102: MAT | C102: =_xlfn.XLOOKUP(D102,'INSUMOS MAT '!B:B,'INSUMOS MAT '!C:C,"ERROR",0) | D102: MAT19-0087 | E102: =+_xlfn.XLOOKUP(D102,'BASE DATOS PRECIOS '!B:B,'BASE DATOS PRECIOS '!C:C) | F102: =20+2 | G102: =+_xlfn.XLOOKUP(D102,'BASE DATOS PRECIOS '!B:B,'BASE DATOS PRECIOS '!D:D) | H102: =+_xlfn.XLOOKUP(E102,'BASE DATOS PRECIOS '!C:C,'BASE DATOS PRECIOS '!F:F) | K102: =+F102*H102 | L102: =+F102*I102 | M102: =+F102*J102 | N102: =SUM(K102:M102) | O102: =SUM(K102:M102)/tc
...

Sheet GRAFICO 
A3: N° | B3: DESCRIPCION | C3: CANTIDAD | D3: UNIDAD | E3: TOTAL MATERIAL | F3: TOTAL MANO DE OBRA | G3: TOTAL SUB/EQUIPOS | H3: TOTAL DIRECTO COLONES | I3: TOTAL DÓLARES | J3: % MATERIAL | K3: % MANO DE OBRA | L3: % SUB/EQUIPOS | M3: % TOTAL DIRECTO
A4: 1 | B4: FUNDACIONES | C4: 1 | D4: Global | E4: =DESGLOSE!E4 | F4: =DESGLOSE!F4 | G4: =DESGLOSE!G4 | H4: =DESGLOSE!H4 | I4: =DESGLOSE!I4 | J4: =E4/$E$21 | K4: =F4/$F$21 | L4: =G4/$G$21 | M4: =H4/$H$21
A5: 2 | B5: SUPERESTRUCTURA PRIMER NIVEL | C5: 1 | D5: Global | E5: =DESGLOSE!E9 | F5: =DESGLOSE!F9 | G5: =DESGLOSE!G9 | H5: =DESGLOSE!H9 | I5: =DESGLOSE!I9 | J5: =E5/$E$21 | K5: =F5/$F$21 | L5: =G5/$G$21 | M5: =H5/$H$21
A6: 3 | B6: SUPERESTRUCTURA SEGUNDO NIVEL | C6: 1 | D6: Global | E6: =DESGLOSE!E13 | F6: =DESGLOSE!F13 | G6: =DESGLOSE!G13 | H6: =DESGLOSE!H13 | I6: =DESGLOSE!I13 | J6: =E6/$E$21 | K6: =F6/$F$21 | L6: =G6/$G$21 | M6: =H6/$H$21
A7: 4 | B7: OTROS GRIS | C7: 1 | D7: Global | E7: =DESGLOSE!E16 | F7: =DESGLOSE!F16 | G7: =DESGLOSE!G16 | H7: =DESGLOSE!H16 | I7: =DESGLOSE!I16 | J7: =E7/$E$21 | K7: =F7/$F$21 | L7: =G7/$G$21 | M7: =H7/$H$21
A8: 5 | B8: ESTRUCTURA METÁLICA Y CUBIERTAS | C8: 1 | D8: Global | E8: =DESGLOSE!E20 | F8: =DESGLOSE!F20 | G8: =DESGLOSE!G20 | H8: =DESGLOSE!H20 | I8: =DESGLOSE!I20 | J8: =E8/$E$21 | K8: =F8/$F$21 | L8: =G8/$G$21 | M8: =H8/$H$21
A9: 6 | B9: LIVIANO | C9: 1 | D9: Global | E9: =DESGLOSE!E29 | F9: =DESGLOSE!F29 | G9: =DESGLOSE!G29 | H9: =DESGLOSE!H29 | I9: =DESGLOSE!I29 | J9: =E9/$E$21 | K9: =F9/$F$21 | L9: =G9/$G$21 | M9: =H9/$H$21
A10: 7 | B10: REPELLOS | C10: 1 | D10: Global | E10: =DESGLOSE!E32 | F10: =DESGLOSE!F32 | G10: =DESGLOSE!G32 | H10: =DESGLOSE!H32 | I10: =DESGLOSE!I32 | J10: =E10/$E$21 | K10: =F10/$F$21 | L10: =G10/$G$21 | M10: =H10/$H$21
A11: 8 | B11: ENCHAPES | C11: 1 | D11: Global | E11: =DESGLOSE!E35 | F11: =DESGLOSE!F35 | G11: =DESGLOSE!G35 | H11: =DESGLOSE!H35 | I11: =DESGLOSE!I35 | J11: =E11/$E$21 | K11: =F11/$F$21 | L11: =G11/$G$21 | M11: =H11/$H$21
A12: 9 | B12: MUEBLES Y PUERTAS | C12: 1 | D12: Global | E12: =DESGLOSE!E37 | F12: =DESGLOSE!F37 | G12: =DESGLOSE!G37 | H12: =DESGLOSE!H37 | I12: =DESGLOSE!I37 | J12: =E12/$E$21 | K12: =F12/$F$21 | L12: =G12/$G$21 | M12: =H12/$H$21
A13: 10 | B13: OBRAS ADICIONALES | C13: 1 | D13: Global | E13: =DESGLOSE!E40 | F13: =DESGLOSE!F40 | G13: =DESGLOSE!G40 | H13: =DESGLOSE!H40 | I13: =DESGLOSE!I40 | J13: =E13/$E$21 | K13: =F13/$F$21 | L13: =G13/$G$21 | M13: =H13/$H$21
A14: 11 | B14: ACABADOS | C14: 1 | D14: Global | E14: =DESGLOSE!E44 | F14: =DESGLOSE!F44 | G14: =DESGLOSE!G44 | H14: =DESGLOSE!H44 | I14: =DESGLOSE!I44 | J14: =E14/$E$21 | K14: =F14/$F$21 | L14: =G14/$G$21 | M14: =H14/$H$21
A15: 12 | B15: VENTANERIA | C15: 1 | D15: Global | E15: =DESGLOSE!E49 | F15: =DESGLOSE!F49 | G15: =DESGLOSE!G49 | H15: =DESGLOSE!H49 | I15: =DESGLOSE!I49 | J15: =E15/$E$21 | K15: =F15/$F$21 | L15: =G15/$G$21 | M15: =H15/$H$21
A16: 13 | B16: ELÉCTRICO | C16: 1 | D16: Global | E16: =DESGLOSE!E51 | F16: =DESGLOSE!F51 | G16: =DESGLOSE!G51 | H16: =DESGLOSE!H51 | I16: =DESGLOSE!I51 | J16: =E16/$E$21 | K16: =F16/$F$21 | L16: =G16/$G$21 | M16: =H16/$H$21
A17: 14 | B17: MECÁNICO | C17: 1 | D17: Global | E17: =DESGLOSE!E61 | F17: =DESGLOSE!F61 | G17: =DESGLOSE!G61 | H17: =DESGLOSE!H61 | I17: =DESGLOSE!I61 | J17: =E17/$E$21 | K17: =F17/$F$21 | L17: =G17/$G$21 | M17: =H17/$H$21
A18: 15 | B18: ALQUILERES | C18: 1 | D18: Global | E18: =DESGLOSE!E65 | F18: =DESGLOSE!F65 | G18: =DESGLOSE!G65 | H18: =DESGLOSE!H65 | I18: =DESGLOSE!I65 | J18: =E18/$E$21 | K18: =F18/$F$21 | L18: =G18/$G$21 | M18: =H18/$H$21
A19: 16 | B19: MANO DE OBRA | C19: 1 | D19: Global | E19: =DESGLOSE!E67 | F19: =DESGLOSE!F67 | G19: =DESGLOSE!G67 | H19: =DESGLOSE!H67 | I19: =DESGLOSE!I67 | J19: =E19/$E$21 | K19: =F19/$F$21 | L19: =G19/$G$21 | M19: =H19/$H$21
L20: =G20/$G$21 | M20: =H20/$H$21
D21: TOTAL | E21: =SUM(E4:E20) | F21: =SUM(F4:F20) | G21: =SUM(G4:G20) | H21: =SUM(H4:H20) | I21: =SUM(I4:I20) | J21: =SUM(J4:J20) | K21: =SUM(K4:K20) | L21: =SUM(L4:L20) | M21: =SUM(M4:M20)
G22: VERIFICACION | H22: =H21-'IKARIA TECHO'!N10

Sheet DESGLOSE
A3: N° | B3: DESCRIPCION | C3: CANTIDAD | D3: UNIDAD | E3: TOTAL MATERIAL | F3: TOTAL MANO DE OBRA | G3: TOTAL SUB/EQUIPOS | H3: TOTAL DIRECTO COLONES | I3: TOTAL DÓLARES
A4: 1 | B4: FUNDACIONES | C4: 1 | D4: Global | E4: =SUM(E5:E8) | F4: =SUM(F5:F8) | G4: =SUM(G5:G8) | H4: =SUM(H5:H8) | I4: =SUM(I5:I8)
A5: 1.1 | B5: OBRAS PRELIMINARES Y RELLENOS | C5: 1 | D5: Global | E5: ='IKARIA TECHO'!K12 | F5: ='IKARIA TECHO'!L12 | G5: ='IKARIA TECHO'!M12 | H5: ='IKARIA TECHO'!N12 | I5: ='IKARIA TECHO'!O12
A6: 1.2 | B6: EXCAVACIÓN Y TUBERÍAS MECÁNICAS (INCLUYE ACOMETIDA) | C6: 1 | D6: Global | E6: ='IKARIA TECHO'!K21 | F6: ='IKARIA TECHO'!L21 | G6: ='IKARIA TECHO'!M21 | H6: ='IKARIA TECHO'!N21 | I6: ='IKARIA TECHO'!O21
A7: 1.3 | B7: SELLO DE CONCRETO | C7: 1 | D7: Global | E7: ='IKARIA TECHO'!K58 | F7: ='IKARIA TECHO'!L58 | G7: ='IKARIA TECHO'!M58 | H7: ='IKARIA TECHO'!N58 | I7: ='IKARIA TECHO'!O58
A8: 1.4 | B8: LOSA FLOTANTE (ACERO, ELECTROMECANICOS, CONCRETO) | C8: 1 | D8: Global | E8: ='IKARIA TECHO'!K69 | F8: ='IKARIA TECHO'!L69 | G8: ='IKARIA TECHO'!M69 | H8: ='IKARIA TECHO'!N69 | I8: ='IKARIA TECHO'!O69
A9: 2 | B9: SUPERESTRUCTURA PRIMER NIVEL | C9: 1 | D9: Global | E9: =SUM(E10:E12) | F9: =SUM(F10:F12) | G9: =SUM(G10:G12) | H9: =SUM(H10:H12) | I9: =SUM(I10:I12)
A10: 2.1 | B10: ACERO EN PAREDES MUROS N1 (ELECTROMECANICO) | C10: 1 | D10: Global | E10: ='IKARIA TECHO'!K124 | F10: ='IKARIA TECHO'!L124 | G10: ='IKARIA TECHO'!M124 | H10: ='IKARIA TECHO'!N124 | I10: ='IKARIA TECHO'!O124
A11: 2.2 | B11: PAREDES, MUROS, ENTREPISO N1 (FORMALETA, CONCRETO, DESENCOFRADO) | C11: 1 | D11: Global | E11: ='IKARIA TECHO'!K154 | F11: ='IKARIA TECHO'!L154 | G11: ='IKARIA TECHO'!M154 | H11: ='IKARIA TECHO'!N154 | I11: ='IKARIA TECHO'!O154
A12: 2.3 | B12: MAMPOSTERIA | C12: 1 | D12: Global | E12: ='IKARIA TECHO'!K169 | F12: ='IKARIA TECHO'!L169 | G12: ='IKARIA TECHO'!M169 | H12: ='IKARIA TECHO'!N169 | I12: ='IKARIA TECHO'!O169
A13: 3 | B13: SUPERESTRUCTURA SEGUNDO NIVEL | C13: 1 | D13: Global | E13: =SUM(E14:E15) | F13: =SUM(F14:F15) | G13: =SUM(G14:G15) | H13: =SUM(H14:H15) | I13: =SUM(I14:I15)
A14: 3.1 | B14: ACERO EN PAREDES MUROS N2 (ELECTROMECANICO) | C14: 1 | D14: Global | E14: ='IKARIA TECHO'!K183 | F14: ='IKARIA TECHO'!L183 | G14: ='IKARIA TECHO'!M183 | H14: ='IKARIA TECHO'!N183 | I14: ='IKARIA TECHO'!O183
A15: 3.2 | B15: PAREDES, MUROS, ENTREPISO N2 (FORMALETA, CONCRETO, DESENCOFRADO) | C15: 1 | D15: Global | E15: ='IKARIA TECHO'!K201 | F15: ='IKARIA TECHO'!L201 | G15: ='IKARIA TECHO'!M201 | H15: ='IKARIA TECHO'!N201 | I15: ='IKARIA TECHO'!O201
A16: 4 | B16: OTROS GRIS | C16: 1 | D16: Global | E16: =SUM(E17:E19) | F16: =SUM(F17:F19) | G16: =SUM(G17:G19) | H16: =SUM(H17:H19) | I16: =SUM(I17:I19)
A17: 4.1 | B17: GRADAS EN CONCRETO | C17: 1 | D17: Global | E17: ='IKARIA TECHO'!K215 | F17: ='IKARIA TECHO'!L215 | G17: ='IKARIA TECHO'!M215 | H17: ='IKARIA TECHO'!N215 | I17: ='IKARIA TECHO'!O215
A18: 4.2 | B18: COLUMNAS (MEDIDOR) | C18: 1 | D18: Global | E18: ='IKARIA TECHO'!K253 | F18: ='IKARIA TECHO'!L253 | G18: ='IKARIA TECHO'!M253 | H18: ='IKARIA TECHO'!N253 | I18: ='IKARIA TECHO'!O253
A19: 4.3 | B19: CHORREA DE COCHERAS Y PILAS | C19: 1 | D19: Global | E19: ='IKARIA TECHO'!K288 | F19: ='IKARIA TECHO'!L288 | G19: ='IKARIA TECHO'!M288 | H19: ='IKARIA TECHO'!N288 | I19: ='IKARIA TECHO'!O288
A20: 5 | B20: ESTRUCTURA METÁLICA Y CUBIERTAS | C20: 1 | D20: Global | E20: =SUM(E21:E28) | F20: =SUM(F21:F28) | G20: =SUM(G21:G28) | H20: =SUM(H21:H28) | I20: =SUM(I21:I28)
A21: 5.1 | B21: ESTRUCTURA TECHO CASA | C21: 1 | D21: Global | E21: ='IKARIA TECHO'!K310 | F21: ='IKARIA TECHO'!L310 | G21: ='IKARIA TECHO'!M310 | H21: ='IKARIA TECHO'!N310 | I21: ='IKARIA TECHO'!O310
A22: 5.2 | B22: ESTRUCTURA TECHO COCHERA | C22: 1 | D22: Global | E22: ='IKARIA TECHO'!K327 | F22: ='IKARIA TECHO'!L327 | G22: ='IKARIA TECHO'!M327 | H22: ='IKARIA TECHO'!N327 | I22: ='IKARIA TECHO'!O327
A23: 5.3 | B23: CUBIERTA TECHO CASA | C23: 1 | D23: Global | E23: ='IKARIA TECHO'!K348 | F23: ='IKARIA TECHO'!L348 | G23: ='IKARIA TECHO'!M348 | H23: ='IKARIA TECHO'!N348 | I23: ='IKARIA TECHO'!O348
A24: 5.4 | B24: CUBIERTA TECHO COCHERA | C24: 1 | D24: Global | E24: ='IKARIA TECHO'!K356 | F24: ='IKARIA TECHO'!L356 | G24: ='IKARIA TECHO'!M356 | H24: ='IKARIA TECHO'!N356 | I24: ='IKARIA TECHO'!O356
A25: 5.5 | B25: HOJALATERIA Y CANOAS | C25: 1 | D25: Global | E25: ='IKARIA TECHO'!K368 | F25: ='IKARIA TECHO'!L368 | G25: ='IKARIA TECHO'!M368 | H25: ='IKARIA TECHO'!N368 | I25: ='IKARIA TECHO'!O368
A26: 5.6 | B26: GRADAS ESTRUCTURA, PINTADO Y ACABADO | C26: 1 | D26: Global | E26: ='IKARIA TECHO'!K380 | F26: ='IKARIA TECHO'!L380 | G26: ='IKARIA TECHO'!M380 | H26: ='IKARIA TECHO'!N380 | I26: ='IKARIA TECHO'!O380
A27: 5.7 | B27: BARANDA DE GRADAS (N2) | C27: 1 | D27: Global | E27: ='IKARIA TECHO'!K394 | F27: ='IKARIA TECHO'!L394 | G27: ='IKARIA TECHO'!M394 | H27: ='IKARIA TECHO'!N394 | I27: ='IKARIA TECHO'!O394
A28: 5.8 | B28: ESTRUCTURA METÁLICA INTERNA | C28: 1 | D28: Global | E28: ='IKARIA TECHO'!K408 | F28: ='IKARIA TECHO'!L408 | G28: ='IKARIA TECHO'!M408 | H28: ='IKARIA TECHO'!N408 | I28: ='IKARIA TECHO'!O408
A29: 6 | B29: LIVIANO | C29: 1 | D29: Global | E29: =SUM(E30:E31) | F29: =SUM(F30:F31) | G29: =SUM(G30:G31) | H29: =SUM(H30:H31) | I29: =SUM(I30:I31)
A30: 6.1 | B30: LIVIANO EXTERIORES | C30: 1 | D30: Global | E30: ='IKARIA TECHO'!K423 | F30: ='IKARIA TECHO'!L423 | G30: ='IKARIA TECHO'!M423 | H30: ='IKARIA TECHO'!N423 | I30: ='IKARIA TECHO'!O423
A31: 6.2 | B31: LIVIANO INTERIORES ( PAREDES LIVIANAS Y CIELOS) | C31: 1 | D31: Global | E31: ='IKARIA TECHO'!K455 | F31: ='IKARIA TECHO'!L455 | G31: ='IKARIA TECHO'!M455 | H31: ='IKARIA TECHO'!N455 | I31: ='IKARIA TECHO'!O455
A32: 7 | B32: REPELLOS | C32: 1 | D32: Global | E32: =SUM(E33:E34) | F32: =SUM(F33:F34) | G32: =SUM(G33:G34) | H32: =SUM(H33:H34) | I32: =SUM(I33:I34)
A33: 7.1 | B33: REPELLOS INTERNO Y EXTERNO | C33: 1 | D33: Global | E33: ='IKARIA TECHO'!K505 | F33: ='IKARIA TECHO'!L505 | G33: ='IKARIA TECHO'!M505 | H33: ='IKARIA TECHO'!N505 | I33: ='IKARIA TECHO'!O505
A34: 7.2 | B34: EMPASTE | C34: 1 | D34: Global | E34: ='IKARIA TECHO'!K521 | F34: ='IKARIA TECHO'!L521 | G34: ='IKARIA TECHO'!M521 | H34: ='IKARIA TECHO'!N521 | I34: ='IKARIA TECHO'!O521
A35: 8 | B35: ENCHAPES | C35: 1 | D35: Global | E35: =E36 | F35: =F36 | G35: =G36 | H35: =H36 | I35: =I36
A36: 8.1 | B36: ENCHAPES (INTERNO Y EXTERNO) | C36: 1 | D36: Global | E36: ='IKARIA TECHO'!K529 | F36: ='IKARIA TECHO'!L529 | G36: ='IKARIA TECHO'!M529 | H36: ='IKARIA TECHO'!N529 | I36: ='IKARIA TECHO'!O529
A37: 9 | B37: MUEBLES Y PUERTAS | C37: 1 | D37: Global | E37: =SUM(E38:E39) | F37: =SUM(F38:F39) | G37: =SUM(G38:G39) | H37: =SUM(H38:H39) | I37: =SUM(I38:I39)
A38: 9.1 | B38: MUEBLES | C38: 1 | D38: Global | E38: ='IKARIA TECHO'!K561 | F38: ='IKARIA TECHO'!L561 | G38: ='IKARIA TECHO'!M561 | H38: ='IKARIA TECHO'!N561 | I38: ='IKARIA TECHO'!O561
A39: 9.2 | B39: PUERTAS Y RODAPIE | C39: 1 | D39: Global | E39: ='IKARIA TECHO'!K626 | F39: ='IKARIA TECHO'!L626 | G39: ='IKARIA TECHO'!M626 | H39: ='IKARIA TECHO'!N626 | I39: ='IKARIA TECHO'!O626
A40: 10 | B40: OBRAS ADICIONALES | C40: 1 | D40: Global | E40: =SUM(E41:E43) | F40: =SUM(F41:F43) | G40: =SUM(G41:G43) | H40: =SUM(H41:H43) | I40: =SUM(I41:I43)
A41: 10.1 | B41: ZACATE | C41: 1 | D41: Global | E41: ='IKARIA TECHO'!K639 | F41: ='IKARIA TECHO'!L639 | G41: ='IKARIA TECHO'!M639 | H41: ='IKARIA TECHO'!N639 | I41: ='IKARIA TECHO'!O639
A42: 10.2 | B42: TAPIAS PREFABRICADAS | C42: 1 | D42: Global | E42: ='IKARIA TECHO'!K647 | F42: ='IKARIA TECHO'!L647 | G42: ='IKARIA TECHO'!M647 | H42: ='IKARIA TECHO'!N647 | I42: ='IKARIA TECHO'!O647
A43: 10.3 | B43: ACERAS | C43: 1 | D43: Global | E43: ='IKARIA TECHO'!K657 | F43: ='IKARIA TECHO'!L657 | G43: ='IKARIA TECHO'!M657 | H43: ='IKARIA TECHO'!N657 | I43: ='IKARIA TECHO'!O657
A44: 11 | B44: ACABADOS | C44: 1 | D44: Global | E44: =SUM(E45:E48) | F44: =SUM(F45:F48) | G44: =SUM(G45:G48) | H44: =SUM(H45:H48) | I44: =SUM(I45:I48)
A45: 11.1 | B45: PINTURA | C45: 1 | D45: Global | E45: ='IKARIA TECHO'!K668 | F45: ='IKARIA TECHO'!L668 | G45: ='IKARIA TECHO'!M668 | H45: ='IKARIA TECHO'!N668 | I45: ='IKARIA TECHO'!O668
A46: 11.2 | B46: LOSA SANITARIA, GRIFERIA | C46: 1 | D46: Global | E46: ='IKARIA TECHO'!K697 | F46: ='IKARIA TECHO'!L697 | G46: ='IKARIA TECHO'!M697 | H46: ='IKARIA TECHO'!N697 | I46: ='IKARIA TECHO'!O697
A47: 11.3 | B47: ACABADOS DE AZOTEA | C47: 1 | D47: Global | E47: ='IKARIA TECHO'!K717 | F47: ='IKARIA TECHO'!L717 | G47: ='IKARIA TECHO'!M717 | H47: ='IKARIA TECHO'!N717 | I47: ='IKARIA TECHO'!O717
A48: 11.4 | B48: PONCHEO FINAL | C48: 1 | D48: Global | E48: ='IKARIA TECHO'!K731 | F48: ='IKARIA TECHO'!L731 | G48: ='IKARIA TECHO'!M731 | H48: ='IKARIA TECHO'!N731 | I48: ='IKARIA TECHO'!O731
A49: 12 | B49: VENTANERIA | C49: 1 | D49: Global | E49: =E50 | F49: =F50 | G49: =G50 | H49: =H50 | I49: =I50
A50: 12.1 | B50: VENTANERIA | C50: 1 | D50: Global | E50: ='IKARIA TECHO'!K739 | F50: ='IKARIA TECHO'!L739 | G50: ='IKARIA TECHO'!M739 | H50: ='IKARIA TECHO'!N739 | I50: ='IKARIA TECHO'!O739
A51: 13 | B51: ELÉCTRICO | C51: 1 | D51: Global | E51: =SUM(E52:E60) | F51: =SUM(F52:F60) | G51: =SUM(G52:G60) | H51: =SUM(H52:H60) | I51: =SUM(I52:I60)
A52: 13.1 | B52: ACOMETIDA | C52: 1 | D52: Global | E52: ='IKARIA TECHO'!K744 | F52: ='IKARIA TECHO'!L744 | G52: ='IKARIA TECHO'!M744 | H52: ='IKARIA TECHO'!N744 | I52: ='IKARIA TECHO'!O744
A53: 13.2 | B53: ELÉCTRICO LOSA | C53: 1 | D53: Global | E53: ='IKARIA TECHO'!K748 | F53: ='IKARIA TECHO'!L748 | G53: ='IKARIA TECHO'!M748 | H53: ='IKARIA TECHO'!N748 | I53: ='IKARIA TECHO'!O748
A54: 13.3 | B54: ELÉCTRICO MUROS | C54: 1 | D54: Global | E54: ='IKARIA TECHO'!K752 | F54: ='IKARIA TECHO'!L752 | G54: ='IKARIA TECHO'!M752 | H54: ='IKARIA TECHO'!N752 | I54: ='IKARIA TECHO'!O752
A55: 13.4 | B55: BASE MEDIDOR | C55: 1 | D55: Global | E55: ='IKARIA TECHO'!K756 | F55: ='IKARIA TECHO'!L756 | G55: ='IKARIA TECHO'!M756 | H55: ='IKARIA TECHO'!N756 | I55: ='IKARIA TECHO'!O756
A56: 13.5 | B56: ELÉCTRICO ILUMINACIÓN | C56: 1 | D56: Global | E56: ='IKARIA TECHO'!K762 | F56: ='IKARIA TECHO'!L762 | G56: ='IKARIA TECHO'!M762 | H56: ='IKARIA TECHO'!N762 | I56: ='IKARIA TECHO'!O762
A57: 13.6 | B57: TABLERO ELÉCTRICO | C57: 1 | D57: Global | E57: ='IKARIA TECHO'!K771 | F57: ='IKARIA TECHO'!L771 | G57: ='IKARIA TECHO'!M771 | H57: ='IKARIA TECHO'!N771 | I57: ='IKARIA TECHO'!O771
A58: 13.7 | B58: CABLEADO ELÉCTRICO | C58: 1 | D58: Global | E58: ='IKARIA TECHO'!K781 | F58: ='IKARIA TECHO'!L781 | G58: ='IKARIA TECHO'!M781 | H58: ='IKARIA TECHO'!N781 | I58: ='IKARIA TECHO'!O781
A59: 13.8 | B59: PLAQUERIA | C59: 1 | D59: Global | E59: ='IKARIA TECHO'!K813 | F59: ='IKARIA TECHO'!L813 | G59: ='IKARIA TECHO'!M813 | H59: ='IKARIA TECHO'!N813 | I59: ='IKARIA TECHO'!O813
A60: 13.9 | B60: ACABADOS FINALES Y BREAKERS | C60: 1 | D60: Global | E60: ='IKARIA TECHO'!K822 | F60: ='IKARIA TECHO'!L822 | G60: ='IKARIA TECHO'!M822 | H60: ='IKARIA TECHO'!N822 | I60: ='IKARIA TECHO'!O822
A61: 14 | B61: MECÁNICO | C61: 1 | D61: Global | E61: =SUM(E62:E64) | F61: =SUM(F62:F64) | G61: =SUM(G62:G64) | H61: =SUM(H62:H64) | I61: =SUM(I62:I64)
A62: 14.03 | B62: CAJAS Y TUBERIAS MECÁNICAS | C62: 1 | D62: Global | E62: ='IKARIA TECHO'!K835 | F62: ='IKARIA TECHO'!L835 | G62: ='IKARIA TECHO'!M835 | H62: ='IKARIA TECHO'!N835 | I62: ='IKARIA TECHO'!O835
A63: 14.04 | B63: BAJANTES | C63: 1 | D63: Global | E63: ='IKARIA TECHO'!K851 | F63: ='IKARIA TECHO'!L851 | G63: ='IKARIA TECHO'!M851 | H63: ='IKARIA TECHO'!N851 | I63: ='IKARIA TECHO'!O851
A64: 14.05 | B64: ACABADOS MECÁNICOS | C64: 1 | D64: Global | E64: ='IKARIA TECHO'!K857 | F64: ='IKARIA TECHO'!L857 | G64: ='IKARIA TECHO'!M857 | H64: ='IKARIA TECHO'!N857 | I64: ='IKARIA TECHO'!O857
A65: 15 | B65: ALQUILERES | C65: 1 | D65: Global | E65: =E66 | F65: =F66 | G65: =G66 | H65: =H66 | I65: =I66
A66: 15.1 | B66: ALQUILERES | C66: 1 | D66: Global | E66: ='IKARIA TECHO'!K887 | F66: ='IKARIA TECHO'!L887 | G66: ='IKARIA TECHO'!M887 | H66: ='IKARIA TECHO'!N887 | I66: ='IKARIA TECHO'!O887
A67: 16 | B67: MANO DE OBRA | C67: 1 | D67: Global | E67: ='IKARIA TECHO'!K906 | F67: =F68 | G67: =G68 | H67: =H68 | I67: =I68
A68: 16.1 | B68: MANO DE OBRA | C68: 1 | D68: Global | E68: ='IKARIA TECHO'!K906 | F68: ='IKARIA TECHO'!L906 | G68: ='IKARIA TECHO'!M906 | H68: ='IKARIA TECHO'!N906 | I68: ='IKARIA TECHO'!O906 | K68: VERFICACION | L68: =H70-'IKARIA TECHO'!N910
D70: TOTAL | E70: =SUM(E4:E68)/2 | F70: =SUM(F4:F68)/2 | G70: =SUM(G4:G68)/2 | H70: =SUM(H4:H68)/2 | I70: =SUM(I4:I68)/2
B77: Hechura cubierta techo | C77: m2 | D77: Costo/m2 | E77: Costo Total
C78: =62.05-2.19 | D78: 3400 | E78: =C78*D78
C80: FC=210 kg/cm2 REGULAR
B81: Hechura concreto | C81: Costo adelante (m3) | D81: Costo Orosi (m3) | E81: Hechura (m3)
C82: 61339.064 | D82: 75000 | E82: =D82-C82
B85: Bomba de concreto | C85: Costo Orosi costo/(m3)
C86: =(129807.75*1.04)/15

Sheet BASE DATOS PRECIOS 
A1: CODIGO ACUMATICA | B1: CODIGO | C1: DESCRIPCION | D1: UNIDAD | E1: PRECIO | F1: PRECIO CON IVA | G1: PRECIO ANTERIOR | H1: DIFERENCIA | I1: OBSERVACIONES | J1: FECHA ÚLTIMO MOVIMIENTO | K1: FAMILIA DEL INSUMO
B2: EQU20-0001 | C2: ACEITE 15W40 | D2: UND | E2: 4821.3212 | F2: =E2*$N$2 | G2: 0 | H2: =F2-G2 | J2: 44695 | K2: REPUESTOS-COMBUSTIBLES | M2: IVA | N2: 1.13 | O2: GENERAL
A3: =_xlfn.XLOOKUP(B3,'INSUMOS MAT '!B:B,'INSUMOS MAT '!C:C,"ERROR",0) | B3: MAT05-0105 | C3: ACERO SUAVE BLANCO 0.44 X 914 | D3: KG | E3: 1581.5384 | F3: =E3*$N$2 | G3: 0 | H3: =F3-G3 | J3: 44720 | K3: CUBIERTAS E IMPERMEBILIZANTES | M3: IVA | N3: 1.1 | O3: MADERA
A4: =_xlfn.XLOOKUP(B4,'INSUMOS MAT '!B:B,'INSUMOS MAT '!C:C,"ERROR",0) | B4: MAT08-0003 | C4: ACETONA | D4: LITRO | E4: 6171.11 | F4: =E4*$N$2 | G4: 0 | H4: =F4-G4 | J4: 44715 | K4: FERRETERIA GENERAL | M4: IVA | N4: 1 | O4: SIN IVA
A5: =_xlfn.XLOOKUP(B5,'INSUMOS MAT '!B:B,'INSUMOS MAT '!C:C,"ERROR",0) | B5: MAT08-0310 | C5: ACIDO | D5: GALON | E5: 3001.78 | F5: =E5*$N$2 | G5: 0 | H5: =F5-G5 | J5: 44707 | K5: FERRETERIA GENERAL
A6: =_xlfn.XLOOKUP(B6,'INSUMOS MAT '!B:B,'INSUMOS MAT '!C:C,"ERROR",0) | B6: MAT08-0005 | C6: ACOPLE HEMBRA POLIETILENO 12MM | D6: UND | E6: 3046.9321 | F6: =E6*$N$2 | G6: 0 | H6: =F6-G6 | J6: 44692 | K6: FERRETERIA GENERAL
A7: =_xlfn.XLOOKUP(B7,'INSUMOS MAT '!B:B,'INSUMOS MAT '!C:C,"ERROR",0) | B7: MAT08-0481 | C7: ACOPLE MACHO DE POLIETILENO 12MM | D7: UND | E7: 2251.638 | F7: =E7*$N$2 | G7: 0 | H7: =F7-G7 | J7: 44700 | K7: FERRETERIA GENERAL
A8: =_xlfn.XLOOKUP(B8,'INSUMOS MAT '!B:B,'INSUMOS MAT '!C:C,"ERROR",0) | B8: MAT06-0004 | C8: ADAPT SECILLO 1 MODULO 5521-5EW DECORADOR BLANCO | D8: UND | E8: 2803.2737 | F8: =E8*$N$2 | G8: 0 | H8: =F8-G8 | J8: 44715 | K8: ELECTRICO
A9: =_xlfn.XLOOKUP(B9,'INSUMOS MAT '!B:B,'INSUMOS MAT '!C:C,"ERROR",0) | B9: MAT06-0005 | C9: ADAPTA DOBLE 2 MODULOS 5522-5EW DECORADOR BLANCO | D9: UND | E9: 688.2492 | F9: =E9*$N$2 | G9: 0 | H9: =F9-G9 | J9: 44714 | K9: ELECTRICO
A10: =_xlfn.XLOOKUP(B10,'INSUMOS MAT '!B:B,'INSUMOS MAT '!C:C,"ERROR",0) | B10: MAT19-0171 | C10: ADAPTADOR TRAMPA 1 1/2" A 1 1/4" | D10: UND | E10: 1196.9865 | F10: =E10*$N$2 | G10: 0 | H10: =F10-G10 | J10: 44692 | K10: PVC
A11: =_xlfn.XLOOKUP(B11,'INSUMOS MAT '!B:B,'INSUMOS MAT '!C:C,"ERROR",0) | B11: MAT19-0003 | C11: ADAPTADOR HEMBRA CPVC 1/2" | D11: UND | E11: 1132.77 | F11: =E11*$N$2 | G11: 0 | H11: =F11-G11 | J11: 44692 | K11: PVC
A12: =_xlfn.XLOOKUP(B12,'INSUMOS MAT '!B:B,'INSUMOS MAT '!C:C,"ERROR",0) | B12: MAT19-0004 | C12: ADAPTADOR HEMBRA PVC 1 1/2" | D12: UND | E12: 755.79 | F12: =E12*$N$2 | G12: 0 | H12: =F12-G12 | J12: 44720 | K12: PVC
A13: =_xlfn.XLOOKUP(B13,'INSUMOS MAT '!B:B,'INSUMOS MAT '!C:C,"ERROR",0) | B13: MAT19-0005 | C13: ADAPTADOR HEMBRA PVC 1 1/4" | D13: UND | E13: 652.57 | F13: =E13*$N$2 | G13: 0 | H13: =F13-G13 | J13: 44701 | K13: PVC
A14: =_xlfn.XLOOKUP(B14,'INSUMOS MAT '!B:B,'INSUMOS MAT '!C:C,"ERROR",0) | B14: MAT19-0006 | C14: ADAPTADOR HEMBRA PVC 1/2" | D14: UND | E14: 163.6 | F14: =E14*$N$2 | G14: 0 | H14: =F14-G14 | J14: 44692 | K14: PVC
A15: =_xlfn.XLOOKUP(B15,'INSUMOS MAT '!B:B,'INSUMOS MAT '!C:C,"ERROR",0) | B15: MAT19-0008 | C15: ADAPTADOR HEMBRA PVC 3/4" | D15: UND | E15: 587.6 | F15: =E15*$N$2 | G15: 0 | H15: =F15-G15 | J15: 44650 | K15: PVC
A16: =_xlfn.XLOOKUP(B16,'INSUMOS MAT '!B:B,'INSUMOS MAT '!C:C,"ERROR",0) | B16: MAT19-0009 | C16: ADAPTADOR MACHO CPVC 1/2 | D16: UND | E16: 358.31 | F16: =E16*$N$2 | G16: 0 | H16: =F16-G16 | J16: 44722 | K16: PVC
... A28: =_xlfn.XLOOKUP(B28,'INSUMOS MAT '!B:B,'INSUMOS MAT '!C:C,"ERROR",0) | B28: MAT16-0101 | C28: ANTICORROSIVO GRIS | D28: CUBETA | E28: 76503.19 | F28: =E28*$N$2 | G28: 0 | H28: =F28-G28 | J28: 44685 | K28: PINTURAS Y REVESTIMIENTOS
B29: MAT16-0102 | C29: ANTICORROSIVO MINIO GRIS | D29: GALON | E29: 15009.54 | F29: =E29*$N$2 | G29: 0 | H29: =F29-G29 | J29: 44700 | K29: PINTURAS Y REVESTIMIENTOS
A30: =_xlfn.XLOOKUP(B30,'INSUMOS MAT '!B:B,'INSUMOS MAT '!C:C,"ERROR",0) | B30: MAT16-0100 | C30: ANTICORROSIVO MINIO ROJO | D30: CUBETA | E30: 63360.66 | F30: =E30*$N$2 | G30: 0 | H30: =F30-G30 | J30: 44685 | K30: PINTURAS Y REVESTIMIENTOS
A31: =_xlfn.XLOOKUP(B31,'INSUMOS MAT '!B:B,'INSUMOS MAT '!C:C,"ERROR",0) | B31: MAT16-0001 | C31: ANTICORROSIVO MINIO AZUL | D31: GALON | E31: 12562.663 | F31: =E31*$N$2 | G31: 0 | H31: =F31-G31 | J31: 44719 | K31: PINTURAS Y REVESTIMIENTOS
A32: =_xlfn.XLOOKUP(B32,'INSUMOS MAT '!B:B,'INSUMOS MAT '!C:C,"ERROR",0) | B32: MAT16-0083 | C32: ANTICORROSIVO MINIO BLANCO | D32: GAL | E32: 11340.093 | F32: =E32*$N$2 | G32: 0 | H32: =F32-G32 | J32: 44692 | K32: PINTURAS Y REVESTIMIENTOS
A33: =_xlfn.XLOOKUP(B33,'INSUMOS MAT '!B:B,'INSUMOS MAT '!C:C,"ERROR",0) | B33: MAT16-0002 | C33: ANTICORROSIVO MINIO ROJO | D33: GALON | E33: 12291.091 | F33: =E33*$N$2 | G33: 0 | H33: =F33-G33 | J33: 44700 | K33: PINTURAS Y REVESTIMIENTOS
A34: =_xlfn.XLOOKUP(B34,'INSUMOS MAT '!B:B,'INSUMOS MAT '!C:C,"ERROR",0) | B34: MAT06-0006 | C34: APAGADOR DOBLE 15A 120 DECO | D34: UND | E34: 2858.7757 | F34: =E34*$N$2 | G34: 0 | H34: =F34-G34 | J34: 44714 | K34: ELECTRICO
A35: =_xlfn.XLOOKUP(B35,'INSUMOS MAT '!B:B,'INSUMOS MAT '!C:C,"ERROR",0) | B35: MAT06-0008 | C35: APAGADOR DOBLE TRIWAY DECO | D35: UND | E35: 8006.5005 | F35: =E35*$N$2 | G35: 0 | H35: =F35-G35 | J35: 44700 | K35: ELECTRICO
A36: =_xlfn.XLOOKUP(B36,'INSUMOS MAT '!B:B,'INSUMOS MAT '!C:C,"ERROR",0) | B36: MAT06-0009 | C36: APAGADOR SENCILLO 15A 120 DECO | D36: UND | E36: 1041.8373 | F36: =E36*$N$2 | G36: 0 | H36: =F36-G36 | J36: 44715 | K36: ELECTRICO
A37: =_xlfn.XLOOKUP(B37,'INSUMOS MAT '!B:B,'INSUMOS MAT '!C:C,"ERROR",0) | B37: MAT06-0011 | C37: APAGADOR SENCILLO TRIWAY | D37: UND | E37: 2005.6972 | F37: =E37*$N$2 | G37: 0 | H37: =F37-G37 | J37: 44721 | K37: ELECTRICO
A38: =_xlfn.XLOOKUP(B38,'INSUMOS MAT '!B:B,'INSUMOS MAT '!C:C,"ERROR",0) | B38: MAT06-0012 | C38: APAGADOR TRIPLE 15A 120 DECO | D38: UND | E38: 3895.462 | F38: =E38*$N$2 | G38: 0 | H38: =F38-G38 | J38: 44714 | K38: ELECTRICO
A39: =_xlfn.XLOOKUP(B39,'INSUMOS MAT '!B:B,'INSUMOS MAT '!C:C,"ERROR",0) | B39: MAT05-0111 | C39: ARENA SILICA (KG) | D39: KG | E39: 1251.0027 | F39: =E39*$N$2 | G39: 0 | H39: =F39-G39 | J39: 44706 | K39: CUBIERTAS E IMPERMEBILIZANTES
A40: =_xlfn.XLOOKUP(B40,'INSUMOS MAT '!B:B,'INSUMOS MAT '!C:C,"ERROR",0) | B40: MAT06-0015 | C40: ARO REPELLO EMT 4X4 1GANG | D40: UND | E40: 264.88 | F40: =E40*$N$2 | G40: 0 | H40: =F40-G40 | J40: 44692 | K40: ELECTRICO
A41: =_xlfn.XLOOKUP(B41,'INSUMOS MAT '!B:B,'INSUMOS MAT '!C:C,"ERROR",0) | B41: MAT06-0016 | C41: ARO REPELLO EMT 4X4 2GANG | D41: UND | E41: 497.2 | F41: =E41*$N$2 | G41: 0 | H41: =F41-G41 | J41: 44719 | K41: ELECTRICO
... A58: =_xlfn.XLOOKUP(B58,'INSUMOS MAT '!B:B,'INSUMOS MAT '!C:C,"ERROR",0) | B58: MAT06-0025 | C58: BREAKER QO240 2P/40AMP | D58: UND | E58: 15255 | F58: =E58*$N$2 | G58: 0 | H58: =F58-G58 | J58: 44718 | K58: ELECTRICO
B59: MAT08-0009 | C59: BRIDA FLEXIBLE 3" PVC | D59: UND | E59: 4999.8774 | F59: =E59*$N$2 | G59: 0 | H59: =F59-G59 | J59: 44707 | K59: FERRETERIA GENERAL
A60: =_xlfn.XLOOKUP(B60,'INSUMOS MAT '!B:B,'INSUMOS MAT '!C:C,"ERROR",0) | B60: MAT08-0229 | C60: BROCA P/CONCRETO DE 5/32X 6" | D60: UND | E60: 1052.2674 | F60: =E60*$N$2 | G60: 0 | H60: =F60-G60 | J60: 44708 | K60: FERRETERIA GENERAL
A61: =_xlfn.XLOOKUP(B61,'INSUMOS MAT '!B:B,'INSUMOS MAT '!C:C,"ERROR",0) | B61: MAT08-0223 | C61: BROCA P/CONCRETO EN 3/8 CORRIENTE | D61: UND | E61: 2276.3958 | F61: =E61*$N$2 | G61: 0 | H61: =F61-G61 | J61: 44712 | K61: FERRETERIA GENERAL
A62: =_xlfn.XLOOKUP(B62,'INSUMOS MAT '!B:B,'INSUMOS MAT '!C:C,"ERROR",0) | B62: MAT08-0222 | C62: BROCA P/CONCRETO TIPO HILTY EN 3/8 | D62: UND | E62: 6211.44 | F62: =E62*$N$2 | G62: 0 | H62: =F62-G62 | J62: 44714 | K62: FERRETERIA GENERAL
A63: =_xlfn.XLOOKUP(B63,'INSUMOS MAT '!B:B,'INSUMOS MAT '!C:C,"ERROR",0) | B63: MAT08-0250 | C63: BROCA SIERRA | D63: UND | E63: 33787 | F63: =E63*$N$2 | G63: 0 | H63: =F63-G63 | J63: 44495 | K63: FERRETERIA GENERAL
A64: =_xlfn.XLOOKUP(B64,'INSUMOS MAT '!B:B,'INSUMOS MAT '!C:C,"ERROR",0) | B64: MAT08-0011 | C64: BROCA P/CONCRETO 5/16 PULG | D64: UND | E64: 1720.8061 | F64: =E64*$N$2 | G64: 0 | H64: =F64-G64 | J64: 44720 | K64: FERRETERIA GENERAL
A65: =_xlfn.XLOOKUP(B65,'INSUMOS MAT '!B:B,'INSUMOS MAT '!C:C,"ERROR",0) | B65: MAT08-0012 | C65: BROCHA CORRIENTE 2" | D65: UND | E65: 1471.5988 | F65: =E65*$N$2 | G65: 0 | H65: =F65-G65 | J65: 44721 | K65: FERRETERIA GENERAL
A66: =_xlfn.XLOOKUP(B66,'INSUMOS MAT '!B:B,'INSUMOS MAT '!C:C,"ERROR",0) | B66: MAT08-0013 | C66: BROCHA CORRIENTE 3" | D66: UND | E66: 1807.5316 | F66: =E66*$N$2 | G66: 0 | H66: =F66-G66 | J66: 44720 | K66: FERRETERIA GENERAL
A67: =_xlfn.XLOOKUP(B67,'INSUMOS MAT '!B:B,'INSUMOS MAT '!C:C,"ERROR",0) | B67: MAT06-0155 | C67: CABLE #4 TRIPLEX | D67: M | E67: 1299.4662 | F67: =E67*$N$2 | G67: 0 | H67: =F67-G67 | J67: 44498 | K67: ELECTRICO
A68: =_xlfn.XLOOKUP(B68,'INSUMOS MAT '!B:B,'INSUMOS MAT '!C:C,"ERROR",0) | B68: MAT06-0248 | C68: CABLE 1/0 TRIPLEX | D68: M | E68: 2624.1538 | F68: =E68*$N$2 | G68: 0 | H68: =F68-G68 | J68: 44692 | K68: ELECTRICO
A69: =_xlfn.XLOOKUP(B69,'INSUMOS MAT '!B:B,'INSUMOS MAT '!C:C,"ERROR",0) | B69: MAT06-0027 | C69: CABLE #10 BLANCO | D69: M | E69: 379.5597 | F69: =E69*$N$2 | G69: 0 | H69: =F69-G69 | J69: 44692 | K69: ELECTRICO
A70: =_xlfn.XLOOKUP(B70,'INSUMOS MAT '!B:B,'INSUMOS MAT '!C:C,"ERROR",0) | B70: MAT06-0028 | C70: CABLE #10 ROJO | D70: M | E70: 562.5366 | F70: =E70*$N$2 | G70: 0 | H70: =F70-G70 | J70: 44719 | K70: ELECTRICO
A71: =_xlfn.XLOOKUP(B71,'INSUMOS MAT '!B:B,'INSUMOS MAT '!C:C,"ERROR",0) | B71: MAT06-0029 | C71: CABLE #10 VERDE | D71: M | E71: 562.5366 | F71: =E71*$N$2 | G71: 0 | H71: =F71-G71 | J71: 44712 | K71: ELECTRICO
... A74: =_xlfn.XLOOKUP(B74,'INSUMOS MAT '!B:B,'INSUMOS MAT '!C:C,"ERROR",0) | B74: MAT06-0032 | C74: CABLE #12 NEGRO | D74: M | E74: 331.7567 | F74: =E74*$N$2 | G74: 0 | H74: =F74-G74 | J74: 44722 | K74: ELECTRICO
B75: MAT0320 | C75: CABLE #12 ROJO | D75: M | E75: 317.2814 | F75: =E75*$N$2 | G75: 0 | H75: =F75-G75 | J75: 44692 | K75: 0
A76: =_xlfn.XLOOKUP(B76,'INSUMOS MAT '!B:B,'INSUMOS MAT '!C:C,"ERROR",0) | B76: MAT06-0033 | C76: CABLE #12 ROJO | D76: M | E76: 331.7567 | F76: =E76*$N$2 | G76: 0 | H76: =F76-G76 | J76: 44720 | K76: ELECTRICO
A77: =_xlfn.XLOOKUP(B77,'INSUMOS MAT '!B:B,'INSUMOS MAT '!C:C,"ERROR",0) | B77: MAT06-0034 | C77: CABLE #12 VERDE | D77: M | E77: 331.7567 | F77: =E77*$N$2 | G77: 0 | H77: =F77-G77 | J77: 44721 | K77: ELECTRICO
A78: =_xlfn.XLOOKUP(B78,'INSUMOS MAT '!B:B,'INSUMOS MAT '!C:C,"ERROR",0) | B78: MAT06-0037 | C78: CABLE #8 BLANCO | D78: M | E78: 977.0093 | F78: =E78*$N$2 | G78: 0 | H78: =F78-G78 | J78: 44721 | K78: ELECTRICO
A79: =_xlfn.XLOOKUP(B79,'INSUMOS MAT '!B:B,'INSUMOS MAT '!C:C,"ERROR",0) | B79: MAT06-0038 | C79: CABLE #8 ROJO | D79: M | E79: 1025.4524 | F79: =E79*$N$2 | G79: 0 | H79: =F79-G79 | J79: 44721 | K79: ELECTRICO
A80: =_xlfn.XLOOKUP(B80,'INSUMOS MAT '!B:B,'INSUMOS MAT '!C:C,"ERROR",0) | B80: MAT06-0039 | C80: CABLE #8 VERDE | D80: M | E80: 976.7735 | F80: =E80*$N$2 | G80: 0 | H80: =F80-G80 | J80: 44712 | K80: ELECTRICO
A81: =_xlfn.XLOOKUP(B81,'INSUMOS MAT '!B:B,'INSUMOS MAT '!C:C,"ERROR",0) | B81: MAT06-0040 | C81: CABLE ALUMINIO 1/0 SERIE 8000 | D81: M | E81: 1129.4915 | F81: =E81*$N$2 | G81: 0 | H81: =F81-G81 | J81: 44720 | K81: ELECTRICO
A82: =_xlfn.XLOOKUP(B82,'INSUMOS MAT '!B:B,'INSUMOS MAT '!C:C,"ERROR",0) | B82: MAT06-0235 | C82: CABLE DE ALUMINIO #4 SERIE 8000 | D82: M | E82: 393.24 | F82: =E82*$N$2 | G82: 0 | H82: =F82-G82 | J82: 44433 | K82: ELECTRICO
A83: =_xlfn.XLOOKUP(B83,'INSUMOS MAT '!B:B,'INSUMOS MAT '!C:C,"ERROR",0) | B83: MAT06-0041 | C83: CABLE DE ALUMINIO #6 SERIE 8000 | D83: M | E83: 356.8345 | F83: =E83*$N$2 | G83: 0 | H83: =F83-G83 | J83: 44720 | K83: ELECTRICO
A84: =_xlfn.XLOOKUP(B84,'INSUMOS MAT '!B:B,'INSUMOS MAT '!C:C,"ERROR",0) | B84: MAT06-0042 | C84: CABLE TGP 3X12 | D84: M | E84: 1617.5391 | F84: =E84*$N$2 | G84: 0 | H84: =F84-G84 | J84: 44714 | K84: ELECTRICO
A85: =_xlfn.XLOOKUP(B85,'INSUMOS MAT '!B:B,'INSUMOS MAT '!C:C,"ERROR",0) | B85: MAT06-0043 | C85: CABLE UTP CAT 5 AZUL | D85: M | E85: 314.7448 | F85: =E85*$N$2 | G85: 0 | H85: =F85-G85 | J85: 44720 | K85: ELECTRICO
A86: =_xlfn.XLOOKUP(B86,'INSUMOS MAT '!B:B,'INSUMOS MAT '!C:C,"ERROR",0) | B86: MAT06-0136 | C86: CABLE UTP CAT 6 AZUL | D86: M | E86: 259.5307 | F86: =E86*$N$2 | G86: 0 | H86: =F86-G86 | J86: 44692 | K86: ELECTRICO
A87: =_xlfn.XLOOKUP(B87,'INSUMOS MAT '!B:B,'INSUMOS MAT '!C:C,"ERROR",0) | B87: MAT01-0053 | C87: CACHERA FREGADERO MONOCOMANDO KORAL | D87: UND | E87: 28815 | F87: =E87*$N$2 | G87: 0 | H87: =F87-G87 | J87: 44719 | K87: ACABADOS
... A135: =_xlfn.XLOOKUP(B135,'INSUMOS MAT '!B:B,'INSUMOS MAT '!C:C,"ERROR",0) | B135: MAT08-0028 | C135: CODO 90 HG 1/2" | D135: UND | E135: 499.5075 | F135: =E135*$N$2 | G135: 0 | H135: =F135-G135 | J135: 44694 | K135: FERRETERIA GENERAL
B136: MAT0528 | C136: CODO 1/2X90 HG | D136: UND | E136: 483.0976 | F136: =E136*$N$2 | G136: 0 | H136: =F136-G136 | J136: 44701 | K136: 0
A137: =_xlfn.XLOOKUP(B137,'INSUMOS MAT '!B:B,'INSUMOS MAT '!C:C,"ERROR",0) | B137: MAT19-0018 | C137: CODO 45 PVC PARED DELGADA 4" | D137: UND | E137: 3119.052 | F137: =E137*$N$2 | G137: 0 | H137: =F137-G137 | J137: 44722 | K137: PVC
A138: =_xlfn.XLOOKUP(B138,'INSUMOS MAT '!B:B,'INSUMOS MAT '!C:C,"ERROR",0) | B138: MAT19-0016 | C138: CODO 45 PVC PARED DELGADA 1.1/2" | D138: UND | E138: 2046.0116 | F138: =E138*$N$2 | G138: 0 | H138: =F138-G138 | J138: 44692 | K138: PVC
A139: =_xlfn.XLOOKUP(B139,'INSUMOS MAT '!B:B,'INSUMOS MAT '!C:C,"ERROR",0) | B139: MAT19-0015 | C139: CODO 45 PVC PARED DELGADA 1.1/4" | D139: UND | E139: 1156.926 | F139: =E139*$N$2 | G139: 0 | H139: =F139-G139 | J139: 44692 | K139: PVC
A140: =_xlfn.XLOOKUP(B140,'INSUMOS MAT '!B:B,'INSUMOS MAT '!C:C,"ERROR",0) | B140: MAT19-0017 | C140: CODO 45 PVC PARED DELGADA 3" | D140: UND | E140: 1813.6551 | F140: =E140*$N$2 | G140: 0 | H140: =F140-G140 | J140: 44722 | K140: PVC
A141: =_xlfn.XLOOKUP(B141,'INSUMOS MAT '!B:B,'INSUMOS MAT '!C:C,"ERROR",0) | B141: MAT19-0013 | C141: CODO 45 CPVC 1/2" | D141: UND | E141: 570.8547 | F141: =E141*$N$2 | G141: 0 | H141: =F141-G141 | J141: 44719 | K141: PVC
A142: =_xlfn.XLOOKUP(B142,'INSUMOS MAT '!B:B,'INSUMOS MAT '!C:C,"ERROR",0) | B142: MAT19-0014 | C142: CODO 45 PVC LISO 1/2" | D142: UND | E142: 229.85 | F142: =E142*$N$2 | G142: 0 | H142: =F142-G142 | J142: 44692 | K142: PVC
A143: =_xlfn.XLOOKUP(B143,'INSUMOS MAT '!B:B,'INSUMOS MAT '!C:C,"ERROR",0) | B143: MAT19-0019 | C143: CODO 45 PVC PARED DELGADA SANITARIO 2" | D143: UND | E143: 693.57 | F143: =E143*$N$2 | G143: 0 | H143: =F143-G143 | J143: 44722 | K143: PVC
A144: =_xlfn.XLOOKUP(B144,'INSUMOS MAT '!B:B,'INSUMOS MAT '!C:C,"ERROR",0) | B144: MAT19-0022 | C144: CODO 90 PVC PARED DELGADA 1 1/2" | D144: UND | E144: 595.848 | F144: =E144*$N$2 | G144: 0 | H144: =F144-G144 | J144: 44719 | K144: PVC
A145: =_xlfn.XLOOKUP(B145,'INSUMOS MAT '!B:B,'INSUMOS MAT '!C:C,"ERROR",0) | B145: MAT19-0021 | C145: CODO 90 CPVC 1/2" | D145: UND | E145: 362.6735 | F145: =E145*$N$2 | G145: 0 | H145: =F145-G145 | J145: 44719 | K145: PVC
A146: =_xlfn.XLOOKUP(B146,'INSUMOS MAT '!B:B,'INSUMOS MAT '!C:C,"ERROR",0) | B146: MAT19-0023 | C146: CODO 90 PVC PARED DELGADA 1 1/4" | D146: UND | E146: 589.992 | F146: =E146*$N$2 | G146: 0 | H146: =F146-G146 | J146: 44700 | K146: PVC
A147: =_xlfn.XLOOKUP(B147,'INSUMOS MAT '!B:B,'INSUMOS MAT '!C:C,"ERROR",0) | B147: MAT19-0024 | C147: CODO 90 PVC PARED DELGADA 2" | D147: UND | E147: 757.986 | F147: =E147*$N$2 | G147: 0 | H147: =F147-G147 | J147: 44718 | K147: PVC
A148: =_xlfn.XLOOKUP(B148,'INSUMOS MAT '!B:B,'INSUMOS MAT '!C:C,"ERROR",0) | B148: MAT19-0025 | C148: CODO 90 PVC PARED DELGADA 3" | D148: UND | E148: 1995.066 | F148: =E148*$N$2 | G148: 0 | H148: =F148-G148 | J148: 44721 | K148: PVC
... A175: =_xlfn.XLOOKUP(B175,'INSUMOS MAT '!B:B,'INSUMOS MAT '!C:C,"ERROR",0) | B175: MAT08-0029 | C175: CRAYON AMARILLO | D175: UND | E175: 464.5883 | F175: =E175*$N$2 | G175: 0 | H175: =F175-G175 | J175: 44721 | K175: FERRETERIA GENERAL
B176: MAT08-0295 | C176: CUBO MAGNETICO P/TORN.TECHO 3/8" | D176: UND | E176: 564.8117 | F176: =E176*$N$2 | G176: 0 | H176: =F176-G176 | J176: 44692 | K176: FERRETERIA GENERAL
B177: MAT08-0339 | C177: CUERDA PARA MOTOGUADAÑA | D177: M | E177: 81.0617 | F177: =E177*$N$2 | G177: 0 | H177: =F177-G177 | J177: 44692 | K177: FERRETERIA GENERAL
A178: =_xlfn.XLOOKUP(B178,'INSUMOS MAT '!B:B,'INSUMOS MAT '!C:C,"ERROR",0) | B178: MAT08-0031 | C178: CUERDA ALBAÑIL BLANCA | D178: UND | E178: 827.4714 | F178: =E178*$N$2 | G178: 0 | H178: =F178-G178 | J178: 44723 | K178: FERRETERIA GENERAL
A179: =_xlfn.XLOOKUP(B179,'INSUMOS MAT '!B:B,'INSUMOS MAT '!C:C,"ERROR",0) | B179: MAT21-0002 | C179: CURADOR CURING ECO | D179: ESTAÑON | E179: 231036.67 | F179: =E179*$N$2 | G179: 0 | H179: =F179-G179 | J179: 44706 | K179: SILICONES-SELLADORES-ADITIVOS
A180: =_xlfn.XLOOKUP(B180,'INSUMOS MAT '!B:B,'INSUMOS MAT '!C:C,"ERROR",0) | B180: MAT06-0308 | C180: CURVA EMT 1/2 PULG | D180: UND | E180: 707.2444 | F180: =E180*$N$2 | G180: 0 | H180: =F180-G180 | J180: 44701 | K180: ELECTRICO
B181: MAT0678 | C181: CURVA CONDUIT 1 1/2 UL | D181: UND | E181: 2242.7706 | F181: =E181*$N$2 | G181: 0 | H181: =F181-G181 | J181: 44718 | K181: 0
A182: =_xlfn.XLOOKUP(B182,'INSUMOS MAT '!B:B,'INSUMOS MAT '!C:C,"ERROR",0) | B182: MAT19-0031 | C182: CURVA CONDUIT 1 1/2 UL | D182: UND | E182: 2078.514 | F182: =E182*$N$2 | G182: 0 | H182: =F182-G182 | J182: 44701 | K182: PVC
A183: =_xlfn.XLOOKUP(B183,'INSUMOS MAT '!B:B,'INSUMOS MAT '!C:C,"ERROR",0) | B183: MAT19-0032 | C183: CURVA CONDUIT 1 UL | D183: UND | E183: 715.896 | F183: =E183*$N$2 | G183: 0 | H183: =F183-G183 | J183: 44701 | K183: PVC
A184: =_xlfn.XLOOKUP(B184,'INSUMOS MAT '!B:B,'INSUMOS MAT '!C:C,"ERROR",0) | B184: MAT19-0033 | C184: CURVA CONDUIT 1/2 UL | D184: UND | E184: 480.558 | F184: =E184*$N$2 | G184: 0 | H184: =F184-G184 | J184: 44720 | K184: PVC
A185: =_xlfn.XLOOKUP(B185,'INSUMOS MAT '!B:B,'INSUMOS MAT '!C:C,"ERROR",0) | B185: MAT19-0138 | C185: CURVA CONDUIT 2 UL | D185: UND | E185: 3115.3538 | F185: =E185*$N$2 | G185: 0 | H185: =F185-G185 | J185: 44692 | K185: PVC
B186: MAT0681 | C186: CURVA CONDUIT 3/4 UL | D186: UND | E186: 589.26 | F186: =E186*$N$2 | G186: 0 | H186: =F186-G186 | J186: 44718 | K186: 0
A187: =_xlfn.XLOOKUP(B187,'INSUMOS MAT '!B:B,'INSUMOS MAT '!C:C,"ERROR",0) | B187: MAT19-0034 | C187: CURVA CONDUIT 3/4 UL | D187: UND | E187: 589.26 | F187: =E187*$N$2 | G187: 0 | H187: =F187-G187 | J187: 44719 | K187: PVC
A188: =_xlfn.XLOOKUP(B188,'INSUMOS MAT '!B:B,'INSUMOS MAT '!C:C,"ERROR",0) | B188: MAT08-0033 | C188: DESAGUE METAL PARA LAVATORIO 11/4 | D188: UND | E188: 1516.1093 | F188: =E188*$N$2 | G188: 0 | H188: =F188-G188 | J188: 44722 | K188: FERRETERIA GENERAL
A189: =_xlfn.XLOOKUP(B189,'INSUMOS MAT '!B:B,'INSUMOS MAT '!C:C,"ERROR",0) | B189: MAT08-0057 | C189: DESATORADOR | D189: LITRO | E189: 3789.0839 | F189: =E189*$N$2 | G189: 0 | H189: =F189-G189 | J189: 44692 | K189: FERRETERIA GENERAL
A190: =_xlfn.XLOOKUP(B190,'INSUMOS MAT '!B:B,'INSUMOS MAT '!C:C,"ERROR",0) | B190: MAT21-0003 | C190: DESMOLDANTE CASSEROIL | D190: ESTAÑON | E190: 393116.8 | F190: =E190*$N$2 | G190: 0 | H190: =F190-G190 | J190: 44712 | K190: SILICONES-SELLADORES-ADITIVOS
B191: MAT08-0143 | C191: DILUYENTE AGUARRAS | D191: GALON | E191: 5822.665 | F191: =E191*$N$2 | G191: 0 | H191: =F191-G191 | J191: 44692 | K191: FERRETERIA GENERAL
B192: MAT08-0508 | C192: DISCO COPA DIAMANTE DE 7" | D192: UND | E192: 38902.285 | F192: =E192*$N$2 | G192: 0 | H192: =F192-G192 | J192: 44623 | K192: FERRETERIA GENERAL
A193: =_xlfn.XLOOKUP(B193,'INSUMOS MAT '!B:B,'INSUMOS MAT '!C:C,"ERROR",0) | B193: MAT08-0327 | C193: DISCO CORTE CONCRETO DIAM CONTINUIO 4 1/2 | D193: UND | E193: 3006.017 | F193: =E193*$N$2 | G193: 0 | H193: =F193-G193 | J193: 44692 | K193: FERRETERIA GENERAL
A194: =_xlfn.XLOOKUP(B194,'INSUMOS MAT '!B:B,'INSUMOS MAT '!C:C,"ERROR",0) | B194: MAT08-0036 | C194: DISCO CORTE METAL 14" | D194: UND | E194: 4176.7391 | F194: =E194*$N$2 | G194: 0 | H194: =F194-G194 | J194: 44692 | K194: FERRETERIA GENERAL
A195: =_xlfn.XLOOKUP(B195,'INSUMOS MAT '!B:B,'INSUMOS MAT '!C:C,"ERROR",0) | B195: MAT08-0446 | C195: DISCO CORTE METAL 4 1/2 PULGADA | D195: UND | E195: 564.9773 | F195: =E195*$N$2 | G195: 0 | H195: =F195-G195 | J195: 44718 | K195: FERRETERIA GENERAL
A196: =_xlfn.XLOOKUP(B196,'INSUMOS MAT '!B:B,'INSUMOS MAT '!C:C,"ERROR",0) | B196: MAT08-0309 | C196: DISCO DIAMANTADO CONCRETO 14" | D196: UND | E196: 80414.85 | F196: =E196*$N$2 | G196: 0 | H196: =F196-G196 | J196: 44706 | K196: FERRETERIA GENERAL
A197: =_xlfn.XLOOKUP(B197,'INSUMOS MAT '!B:B,'INSUMOS MAT '!C:C,"ERROR",0) | B197: MAT08-0486 | C197: DISCO DIAMANTADO PARA CONCRETO 5" | D197: UND | E197: 52039.913 | F197: =E197*$N$2 | G197: 0 | H197: =F197-G197 | J197: 44692 | K197: FERRETERIA GENERAL
A198: =_xlfn.XLOOKUP(B198,'INSUMOS MAT '!B:B,'INSUMOS MAT '!C:C,"ERROR",0) | B198: MAT08-0035 | C198: DISCO PARA ESMERILAR DE 9 PULGADAS | D198: UND | E198: 4014.325 | F198: =E198*$N$2 | G198: 0 | H198: =F198-G198 | J198: 44692 | K198: FERRETERIA GENERAL
A199: =_xlfn.XLOOKUP(B199,'INSUMOS MAT '!B:B,'INSUMOS MAT '!C:C,"ERROR",0) | B199: MAT08-0257 | C199: DISCO SIERRA CIRCULAR 7-1/4 | D199: UND | E199: 11424.3 | F199: =E199*$N$2 | G199: 0 | H199: =F199-G199 | J199: 44692 | K199: FERRETERIA GENERAL
A200: =_xlfn.XLOOKUP(B200,'INSUMOS MAT '!B:B,'INSUMOS MAT '!C:C,"ERROR",0) | B200: MAT08-0038 | C200: DISCO CORTE METAL FINO 9" | D200: UND | E200: 1369.702 | F200: =E200*$N$2 | G200: 0 | H200: =F200-G200 | J200: 44701 | K200: FERRETERIA GENERAL
A201: =_xlfn.XLOOKUP(B201,'INSUMOS MAT '!B:B,'INSUMOS MAT '!C:C,"ERROR",0) | B201: MAT08-0040 | C201: DISCO ESMERILAR 4 1/2 | D201: UND | E201: 881.4888 | F201: =E201*$N$2 | G201: 0 | H201: =F201-G201 | J201: 44709 | K201: FERRETERIA GENERAL
A202: =_xlfn.XLOOKUP(B202,'INSUMOS MAT '!B:B,'INSUMOS MAT '!C:C,"ERROR",0) | B202: MAT08-0042 | C202: DISCO FLAP G60 4 1/2" | D202: UND | E202: 1298.6905 | F202: =E202*$N$2 | G202: 0 | H202: =F202-G202 | J202: 44721 | K202: FERRETERIA GENERAL
...

Sheet BASE DATOS EQUIPOS Y SUBCONTRAT
A1: CODIGO | B1: DESCRIPCION | C1: UNIDAD | D1: PRECIO | E1: PRECIO CON IVA | F1: PRECIO ANTERIOR | G1: DIFERENCIA | H1: OBSERVACIONES | I1: FECHA ÚLTIMO MOVIMIENTO | J1: FAMILIA DEL INSUMO
A2: BACK HOE | B2: BACK HOE | C2: HORA | D2: =18500 | E2: =D2 | L2: IVA | M2: 1.13 | N2: GENERAL
A3: COMPACTADOR | B3: COMPACTADOR | C3: HORA | D3: 12000 | E3: =D3 | L3: IVA | M3: 1.1 | N3: MADERA
B10: SUBCONTRATO ELÉCTRICO
A12: SUB ACOMETIDA | B12: M.O. ACOMETIDA ELÉCTRICA | C12: GLOBAL | E12: 25000
A13: SUB ELECTRICO LOSA | B13: M.O. TUBERIA ELECTRICA LOSA | C13: GLOBAL | E13: 84000
A14: SUB ELECTRICO MUROS | B14: M.O. TUBERIA ELECTRICA MUROS | C14: GLOBAL | E14: 36000
A15: SUB BASE MEDIDOR | B15: M.O. INSTALACIÓN BASE MEDIDOR | C15: GLOBAL | E15: 15000
A16: SUB ILUMINACION | B16: M.O. SALIDAS DE ILUMINACION | C16: GLOBAL | E16: 48000
A17: SUB TABLEROS | B17: M.O. ARMADO TABLEROS | C17: GLOBAL | E17: 27500
A18: SUB CABLEADO | B18: M.O. CABLEADO ELÉCTRICO | C18: GLOBAL | E18: 112000
A19: SUB PLAQUERIA | B19: M.O. COLOCACIÓN DE PLAQUERÍA | C19: GLOBAL | E19: 60000
A20: SUB ENTREGA FINAL | B20: M.O. TRABAJOS ELÉCTRICOS PARA ENTREGA FINAL | C20: GLOBAL | E20: 87500
E21: =SUM(E12:E20)
B29: FORMALETA
A31: FORMALETA LOSA | B31: FORMALETA LOSA FLOTANTE | C31: GLOBAL
A32: FORMALETA MUROS | B32: FORMALETA MUROS | C32: GLOBAL | E32: 0
A33: FORMALETA COLUMNAS | B33: FORMALETA COLUMNAS | C33: GLOBAL | E33: 0
B38: OTROS
A39: GRANITO | B39: GRANITO CON INSTALACION | C39: M | D39: =85250*1.03 | E39: =D39*'BASE DATOS PRECIOS '!$N$4 | F39: 0 | G39: =E39-F39
A40: VENTANERIA IKARIA | B40: SUBCONTRATO VENTANERIA (MATERIAL Y MANO DE OBRA) | C40: GLOBAL | D40: =896000*1.03 | E40: =D40*'BASE DATOS PRECIOS '!$N$4 | F40: 0 | G40: =E40-F40
A41: VENTANERIA SKYROS | B41: SUBCONTRATO VENTANERIA (MATERIAL Y MANO DE OBRA) | C41: GLOBAL | D41: =947511.36*1.03 | E41: =D41*'[3]BASE DATOS PRECIOS '!$N$4 | F41: 0 | G41: =E41-F41
K680: =+(37168.41*1.13)/(0.93*5.45)

Sheet BASE DATOS MANO DE OBRA
A1: CODIGO | B1: DESCRIPCION | C1: UNIDAD | D1: PRECIO | E1: PRECIO CON CARGAS SOCIALES | F1: PRECIO ANTERIOR | G1: DIFERENCIA | H1: OBSERVACIONES | I1: FECHA ÚLTIMO MOVIMIENTO | J1: FAMILIA DEL INSUMO
A2: ENCARGADO | B2: ENCARGADO PLUS | C2: hora | D2: 2000 | E2: =D2*1.5 | G2: =E2-F2 | L2: IVA | M2: 1.13 | N2: GENERAL
A3: OP CALIFICADO | B3: OPERARIO CALIFICADO PLUS | C3: hora | D3: 2000 | E3: =D3*1.5 | G3: =E3-F3 | L3: IVA | M3: 1.1 | N3: MADERA
A4: OPERARIO | B4: OPERARIO PLUS | C4: hora | D4: 1900 | E4: =D4*1.5 | G4: =E4-F4 | L4: IVA | M4: 1 | N4: SIN IVA
A5: AYUDANTE | B5: AYUDANTE PLUS | C5: hora | D5: 1550 | E5: =D5*1.5 | G5: =E5-F5
B16: <
K659: =+(37168.41*1.13)/(0.93*5.45)

Sheet INSUMOS MAT 
B1: (ID) Insumo | D1: Descripción | E1: Unidad | F1: Grupo de Insumo | G1: Familia de Insumos
B2: MAT01-0001 | C2: 0101-0001 | D2: GRIFERIA ALTA NOVO CROMADA P/VESSEL | E2: UND | F2: MATERIALES | G2: ACABADOS
B3: MAT01-0002 | C3: 0101-0002 | D3: GRIFERIA DUCHA BREZZA MONO S/LAVAPIES EZ4015551 SSB | E3: UND | F3: MATERIALES | G3: ACABADOS
B4: MAT01-0005 | C4: 0101-0005 | D4: GRIFERIA LAV.CROMA METAL 4" PALANCA CROMO P/LAV MILANO | E4: UND | F4: MATERIALES | G4: ACABADOS
B5: MAT01-0006 | C5: 0101-0006 | D5: GRIFERIA LAVAPLATOS KENAI MONO | E5: UND | F5: MATERIALES | G5: ACABADOS
B6: MAT01-0007 | C6: 0101-0007 | D6: GRIFERIA BREZZA MONO BAJA MU1015551 | E6: UND | F6: MATERIALES | G6: ACABADOS
B7: MAT01-0008 | C7: 0101-0008 | D7: INODORO CORONA SMART BLANCO | E7: UND | F7: MATERIALES | G7: ACABADOS
B8: MAT01-0010 | C8: 0101-0010 | D8: LAVATORIO SPAZIO DE SOBREPONER BLANCO | E8: UND | F8: MATERIALES | G8: ACABADOS
B9: MAT01-0011 | C9: 0101-0011 | D9: LAVATORIO MILANO BLANCO CON PEDESTAL | E9: UND | F9: MATERIALES | G9: ACABADOS
B10: MAT01-0012 | C10: 0101-0012 | D10: LAVATORIO OLYMPUS II CON PEDESTAL | E10: UND | F10: MATERIALES | G10: ACABADOS
B11: MAT01-0013 | C11: 0101-0013 | D11: PILA Y MUEBLE FIBRA DE VIDRIO 50X70CM | E11: UND | F11: MATERIALES | G11: ACABADOS
B12: MAT01-0014 | C12: 0101-0014 | D12: REJILLA P/BAÑO CUADRADA / REJ-10'2" (50mm) | E12: UND | F12: MATERIALES | G12: ACABADOS
B13: MAT01-0015 | C13: 0101-0015 | D13: DESVIADOR DE 1 VIA | E13: UND | F13: MATERIALES | G13: ACABADOS
... B50: MAT01-0054 | C50: 0101-0054 | D50: LLAVIN Y ACCESORIO CARBONE | E50: UND | F50: MATERIALES | G50: ACABADOS
B51: (ID) Insumo | D51: Descripción | E51: Unidad | F51: Grupo de Insumo | G51: Familia de Insumos
B52: MAT02-0001 | C52: 0102-0001 | D52: ALAMBRE NEGRO #16 (1.68MM) | E52: KG | F52: MATERIALES | G52: ACEROS Y METALES
B53: MAT02-0002 | C53: 0102-0002 | D53: ANGULAR 1 1/4"X3/16" | E53: UND | F53: MATERIALES | G53: ACEROS Y METALES
B54: MAT02-0003 | C54: 0102-0003 | D54: ANGULAR DE 2"x 3/16" | E54: UND | F54: MATERIALES | G54: ACEROS Y METALES
B55: MAT02-0004 | C55: 0102-0004 | D55: ANGULAR HN 1 1/4"x1.8" | E55: UND | F55: MATERIALES | G55: ACEROS Y METALES
B56: MAT02-0005 | C56: 0102-0005 | D56: LAMINA DE JORDOMEX #1 ACS 4X8X3MM | E56: UND | F56: MATERIALES | G56: ACEROS Y METALES
B57: MAT02-0006 | C57: 0102-0006 | D57: LAMINA DE JORDOMEX #3 (1/2) ROMBO 13X32 3MM ESPESOR | E57: UND | F57: MATERIALES | G57: ACEROS Y METALES
B58: MAT02-0007 | C58: 0102-0007 | D58: LAMINA H.N. ANTIDESLIZ 1.22X2.44X3MM | E58: UND | F58: MATERIALES | G58: ACEROS Y METALES
B59: MAT02-0008 | C59: 0102-0008 | D59: MALLA ELECTROSOLDADA 4.88MM | E59: UND | F59: MATERIALES | G59: ACEROS Y METALES
B60: MAT02-0009 | C60: 0102-0009 | D60: MALLA ELECTROSOLDADA #1 (4.11MM) | E60: UND | F60: MATERIALES | G60: ACEROS Y METALES
B61: MAT02-0010 | C61: 0102-0010 | D61: MALLA ELECTROSOLDADA #2 (5.3 MM) | E61: UND | F61: MATERIALES | G61: ACEROS Y METALES
B62: MAT02-0011 | C62: 0102-0011 | D62: PERLING 3X2X15MM EN 1.2MM H.G. | E62: UND | F62: MATERIALES | G62: ACEROS Y METALES
B63: MAT02-0012 | C63: 0102-0012 | D63: PLATINA 3"x1/4" | E63: UND | F63: MATERIALES | G63: ACEROS Y METALES
... B218: MAT02-0168 | C218: 0102-0168 | D218: VIGA U 4x1/4" | E218: UND | F218: MATERIALES | G218: ACEROS Y METALES
B219: (ID) Insumo | D219: Descripción | E219: Unidad | F219: Grupo de Insumo | G219: Familia de Insumos
B220: MAT03-0001 | C220: 0103-0001 | D220: ARENA SILICA | E220: SACO | F220: MATERIALES | G220: AGREGADOS
B221: MAT03-0002 | C221: 0103-0002 | D221: ARENA FINA DE RIO | E221: M3 | F221: MATERIALES | G221: AGREGADOS
B222: MAT03-0003 | C222: 0103-0003 | D222: ARENA LAVADA | E222: M3 | F222: MATERIALES | G222: AGREGADOS
B223: MAT03-0004 | C223: 0103-0004 | D223: BASE GRANULAR | E223: M3 | F223: MATERIALES | G223: AGREGADOS
B224: MAT03-0005 | C224: 0103-0005 | D224: LASTRE GRUESO | E224: M3 | F224: MATERIALES | G224: AGREGADOS
B225: MAT03-0006 | C225: 0103-0006 | D225: PIEDRA CUARTILLA | E225: M3 | F225: MATERIALES | G225: AGREGADOS
B226: MAT03-0007 | C226: 0103-0007 | D226: PIEDRA QUINTILLA | E226: M3 | F226: MATERIALES | G226: AGREGADOS
B227: MAT03-0008 | C227: 0103-0008 | D227: POLVO DE PIEDRA | E227: M3 | F227: MATERIALES | G227: AGREGADOS
B228: MAT03-0009 | C228: 0103-0009 | D228: SUB BASE GRANULAR | E228: M3 | F228: MATERIALES | G228: AGREGADOS
B229: MAT03-0010 | C229: 0103-0010 | D229: TIERRA | E229: M3 | F229: MATERIALES | G229: AGREGADOS
B230: MAT03-0011 | C230: 0103-0011 | D230: PIEDRA TERCERA | E230: M3 | F230: MATERIALES | G230: AGREGADOS
B231: MAT03-0012 | C231: 0103-0012 | D231: PIEDRA GRUESA GRIS CON VERDE | E231: SACO | F231: MATERIALES | G231: AGREGADOS
B232: MAT03-0013 | C232: 0103-0013 | D232: PIEDRA HUEVILLO | E232: M3 | F232: MATERIALES | G232: AGREGADOS
B233: MAT03-0014 | C233: 0103-0014 | D233: LASTRE FINO | E233: M3 | F233: MATERIALES
B234: MAT03-0015 | C234: 0103-0015 | D234: DESTAPE | E234: M3 | F234: MATERIALES | G234: AGREGADOS
B235: MAT03-0016 | C235: 0103-0016 | D235: PIEDRA BLANCA DECORATIVA | E235: SACO | F235: MATERIALES | G235: AGREGADOS
B236: MAT03-0017 | C236: 0103-0017 | D236: PIEDRA BOLA (P/ DRENAJE) | E236: M3 | F236: MATERIALES | G236: AGREGADOS
B237: MAT03-0018 | C237: 0103-0018 | D237: CEMENTO HIDRAULICO | E237: SACO | F237: MATERIALES | G237: AGREGADOS
B238: (ID) Insumo | D238: Descripción | E238: Unidad | F238: Grupo de Insumo | G238: Familia de Insumos
B239: MAT04-0001 | C239: 0104-0001 | D239: ASFALTO | E239: TON | F239: MATERIALES | G239: CONCRETOS CEMENTOS Y MORTEROS
B240: MAT04-0002 | C240: 0104-0002 | D240: CAJA DE REGISTRO 30X30 PARA VARILLA COPERWELL | E240: UND | F240: MATERIALES | G240: CONCRETOS CEMENTOS Y MORTEROS
B241: MAT04-0003 | C241: 0104-0003 | D241: CEMENTO UG | E241: UND | F241: MATERIALES | G241: CONCRETOS CEMENTOS Y MORTEROS
B242: MAT04-0004 | C242: 0104-0004 | D242: CENICERO DE CONCRETO 4" (100mm) | E242: UND | F242: MATERIALES | G242: CONCRETOS CEMENTOS Y MORTEROS
B243: MAT04-0005 | C243: 0104-0005 | D243: CONCRETO FC 210 KG/CM2 AUTOCOMPACTABLE | E243: M3 | F243: MATERIALES | G243: CONCRETOS CEMENTOS Y MORTEROS
B244: MAT04-0006 | C244: 0104-0006 | D244: CONCRETO FC 210 KG/CM2 CONCRELIC | E244: M3 | F244: MATERIALES | G244: CONCRETOS CEMENTOS Y MORTEROS
B245: MAT04-0007 | C245: 0104-0007 | D245: CONCRETO FC 210 KG/CM2 NORMAL | E245: M3 | F245: MATERIALES | G245: CONCRETOS CEMENTOS Y MORTEROS
B246: MAT04-0008 | C246: 0104-0008 | D246: EMPASTE CEMENTICIO BLANCO CEMEX 20KG | E246: UND | F246: MATERIALES | G246: CONCRETOS CEMENTOS Y MORTEROS
B247: MAT04-0009 | C247: 0104-0009 | D247: FIBRA DE CARBONO 1KG | E247: BOLSA | F247: MATERIALES | G247: CONCRETOS CEMENTOS Y MORTEROS
B248: MAT04-0010 | C248: 0104-0010 | D248: FIBRA PP MONOFILAMENTO 600G | E248: BOLSA | F248: MATERIALES | G248: CONCRETOS CEMENTOS Y MORTEROS
B249: MAT04-0011 | C249: 0104-0011 | D249: FRAGUA INTACO ARENA #28 CON ARENA | E249: UND | F249: MATERIALES | G249: CONCRETOS CEMENTOS Y MORTEROS
B250: MAT04-0012 | C250: 0104-0012 | D250: FRAGUA INTACO GRAFITO #12 CON ARENA | E250: UND | F250: MATERIALES | G250: CONCRETOS CEMENTOS Y MORTEROS
... B301: MAT04-0063 | C301: 0104-0063 | D301: MAXIBED | E301: SACO | F301: MATERIALES | G301: CONCRETOS CEMENTOS Y MORTEROS
B302: MAT04-0064 | C302: 0104-0064 | D302: CONCRETO 105 KG/CM2 | E302: M3 | F302: MATERIALES
B303: MAT04-0065 | C303: 0104-0065 | D303: EMPASTE CEMENTICIO GRIS CEMEX 20KG | E303: SACO | F303: MATERIALES | G303: CONCRETOS CEMENTOS Y MORTEROS
B304: MAT04-0066 | C304: 0104-0066 | D304: CONCRETO FC 280 KG/CM2 | E304: M3 | F304: MATERIALES | G304: CONCRETOS CEMENTOS Y MORTEROS
B305: MAT04-0067 | C305: 0104-0067 | D305: REPELLO GRUESO REPEMAX INTACO 40K | E305: SACO | F305: MATERIALES | G305: CONCRETOS CEMENTOS Y MORTEROS
B306: MAT04-0068 | C306: 0104-0068 | D306: REPELLO EXTRA FINO GRIS MORCEMSEC | E306: SACO | F306: MATERIALES | G306: CONCRETOS CEMENTOS Y MORTEROS
B307: MAT04-0069 | C307: 0104-0069 | D307: REPEMAX CAPA FINA 50XA INTACO 40KG ALTA ADHERENCIA | E307: SACO | F307: MATERIALES | G307: CONCRETOS CEMENTOS Y MORTEROS
B308: MAT04-0070 | C308: 0104-0070 | D308: CONCRETO EXPANSIVO | E308: SACO | F308: MATERIALES | G308: CONCRETOS CEMENTOS Y MORTEROS
B309: MAT04-0071 | C309: 0104-0071 | D309: FRAGUA ARTICA SIN ARENA | E309: BOLSA | F309: MATERIALES | G309: CONCRETOS CEMENTOS Y MORTEROS
B310: MAT04-0072 | C310: 0104-0072 | D310: COLUMNA C PREFABRICADA 3.80M | E310: UND | F310: MATERIALES | G310: CONCRETOS CEMENTOS Y MORTEROS
B311: MAT04-0073 | C311: 0104-0073 | D311: FIBRA DE CARBONO | E311: M3 | F311: MATERIALES | G311: CONCRETOS CEMENTOS Y MORTEROS
B312: MAT04-0074 | C312: 0104-0074 | D312: PEGAMENTO ORO KERMILL MPI 740 | E312: SACO | F312: MATERIALES | G312: CONCRETOS CEMENTOS Y MORTEROS
B313: MAT04-0075 | C313: 0104-0075 | D313: SIKA MONOROP 412 SM 25K | E313: SACO | F313: MATERIALES | G313: CONCRETOS CEMENTOS Y MORTEROS
B314: MAT04-0076 | C314: 0104-0076 | D314: LOSETA DE CONCRETO | E314: UND | F314: MATERIALES | G314: CONCRETOS CEMENTOS Y MORTEROS
B315: MAT04-0077 | C315: 0104-0077 | D315: FRAGUA INTACO PLATA CON ARENA | E315: BOLSA | F315: MATERIALES | G315: CONCRETOS CEMENTOS Y MORTEROS
B316: MAT04-066 | C316: 0104-066 | D316: EMPASTE CEMENTICIO GRIS CEMEX 20KG | E316: SACO | F316: MATERIALES
B317: (ID) Insumo | D317: Descripción | E317: Unidad | F317: Grupo de Insumo | G317: Familia de Insumos
B318: MAT05-0001 | C318: 0105-0001 | D318: IMPERMEABILIZANTE BASE 201 | E318: CUBETA | F318: MATERIALES | G318: CUBIERTAS E IMPERMEBILIZANTES
B319: MAT05-0002 | C319: 0105-0002 | D319: IMPERMEABILIZANTE TOP 202 | E319: CUBETA | F319: MATERIALES | G319: CUBIERTAS E IMPERMEBILIZANTES
B320: MAT05-0003 | C320: 0105-0003 | D320: LAMINA RECT ESMALTADA BLANCA #26 1.08x6.00 | E320: UND | F320: MATERIALES | G320: CUBIERTAS E IMPERMEBILIZANTES
B321: MAT05-0004 | C321: 0105-0004 | D321: LAMINA UPVC 1.13mx3.80mx3mm | E321: UND | F321: MATERIALES | G321: CUBIERTAS E IMPERMEBILIZANTES
B322: MAT05-0005 | C322: 0105-0005 | D322: LAMINA RECT ESMALTADA BLANCA #26 1.08mx9.00 | E322: UND | F322: MATERIALES | G322: CUBIERTAS E IMPERMEBILIZANTES
B323: MAT05-0006 | C323: 0105-0006 | D323: LAMINA RECT ESMALTADA BLANCA #26 1.08mx4.12 | E323: UND | F323: MATERIALES | G323: CUBIERTAS E IMPERMEBILIZANTES
B324: MAT05-0007 | C324: 0105-0007 | D324: LAMINA RECT ESMALTADA BLANCA #26 1.08mx5.30 | E324: UND | F324: MATERIALES | G324: CUBIERTAS E IMPERMEBILIZANTES
B325: MAT05-0008 | C325: 0105-0008 | D325: LAMINA RECT ESMALTADA BLANCA #26 1.08mx4.60 | E325: UND | F325: MATERIALES | G325: CUBIERTAS E IMPERMEBILIZANTES
B326: MAT05-0009 | C326: 0105-0009 | D326: LAMINA RECT ESMALTADA BLANCA #26 1.08mx11.9 | E326: UND | F326: MATERIALES | G326: CUBIERTAS E IMPERMEBILIZANTES
B327: MAT05-0010 | C327: 0105-0010 | D327: LAMINA RECT ESMALTADA BLANCA #26 1.08mx4.20 | E327: UND | F327: MATERIALES | G327: CUBIERTAS E IMPERMEBILIZANTES
B328: MAT05-0011 | C328: 0105-0011 | D328: LAMINA RECT ESMALTADA BLANCA #26 1.08mx8.80 | E328: UND | F328: MATERIALES | G328: CUBIERTAS E IMPERMEBILIZANTES
B329: MAT05-0012 | C329: 0105-0012 | D329: LAMINA RECT ESMALTADA BLANCA #26 1.08mx9.50 | E329: UND | F329: MATERIALES | G329: CUBIERTAS E IMPERMEBILIZANTES
... B429: MAT08-0522 | C429: 0108-0522 | D429: BONDEX GRIS PREMIUM ORO 25KG | E429: SACO | F429: MATERIALES | G429: FERRETERIA GENERAL
B430: (ID) Insumo | D430: Descripción | E430: Unidad | F430: Grupo de Insumo | G430: Familia de Insumos
B431: MAT06-0002 | C431: 0106-0002 | D431: ACOPLE P/ BASE MEDIDOR 2 | E431: UND | F431: MATERIALES | G431: ELECTRICO
B432: MAT06-0003 | C432: 0106-0003 | D432: ACOPLE P/BASE DE MEDIDOR 1 1/2 A150 S.D | E432: UND | F432: MATERIALES | G432: ELECTRICO
B433: MAT06-0004 | C433: 0106-0004 | D433: ADAPT SECILLO 1 MODULO 5521-5EW DECORADOR BLANCO | E433: UND | F433: MATERIALES | G433: ELECTRICO
B434: MAT06-0005 | C434: 0106-0005 | D434: ADAPTA DOBLE 2 MODULOS 5522-5EW DECORADOR BLANCO | E434: UND | F434: MATERIALES | G434: ELECTRICO
B435: MAT06-0006 | C435: 0106-0006 | D435: APAGADOR DOBLE 15A 120 DECO | E435: UND | F435: MATERIALES | G435: ELECTRICO
B436: MAT06-0007 | C436: 0106-0007 | D436: APAGADOR DOBLE COOPER | E436: UND | F436: MATERIALES | G436: ELECTRICO
B437: MAT06-0008 | C437: 0106-0008 | D437: APAGADOR DOBLE TRIWAY DECO | E437: UND | F437: MATERIALES | G437: ELECTRICO
B438: MAT06-0009 | C438: 0106-0009 | D438: APAGADOR SENCILLO 15A 120 DECO | E438: UND | F438: MATERIALES | G438: ELECTRICO
B439: MAT06-0010 | C439: 0106-0010 | D439: APAGADOR SENCILLO COOPER | E439: UND | F439: MATERIALES | G439: ELECTRICO
...

Sheet CALCULO CANTIDADES 
D3: IKARIA TECHO
C7: 1 | D7: RELLENOS
C9: Lastre
C10: Espesor: | D10: 0.15 | E10: m
C11: Área casa (incluye área de pilas) | D11: 394.99 | E11: m2
C13: m3 totales | D13: 59.2485 | E13: m3 | J13: Diferencia
G14: COMPARACION SISTEMA
D15: Costo | E15: Costo Total | G15: Horas | H15: Costo/hora | I15: Costo Total
C16: Mano de obra (trazado) (m2) | D16: 1273.55 | E16: =D16*D11 | F16: Trazo | G16: 30 | H16: 1700 | I16: =G16*H16
C17: Mano de obra (excavación) (m3) | D17: 18148.02 | F17: Zanjeo | G17: 39 | H17: 1700 | I17: =G17*H17
C18: Mano de obra (relleno ) (m3) | D18: 28973.15 | E18: =D18*D13 | I18: =SUM(I16:I17) | J18: =E19-I18
D19: Total | E19: =SUM(E16:E18)
C23: 2 | D23: SELLO DE CONCRETO
C25: Sello concreto
C26: Espesor: | D26: 0.06 | E26: m
C27: Área casa (NO incluye área de pilas) | D27: 343.6413 | E27: m2
C29: m3 totales | D29: 23.6994 | E29: m3
C31: Cemento | D31: 142.2 | E31: sacos
C32: Arena | D32: 17.7746 | E32: m3
C33: Piedra | D33: 18.9595 | E33: m3
C35: CANTIDADES DOSIFICACION ADELANTE (DIEGO - JARDEL)
C36: Cemento | D36: =D29*180 | E36: kilos
C37: Arena | D37: =D29*0.73 | E37: m3
C38: Piedra | D38: =D29*0.6 | E38: m3
J41: Diferencia
G42: COMPARACION SISTEMA
D43: Costo | E43: Costo Total | G43: Horas | H43: Costo/hora | I43: Costo Total
C44: Mano de obra (concreto) (m3) | D44: 41390.21 | E44: =D44*D29 | F44: Sello | G44: 27 | H44: 1700 | I44: =G44*H44 | J44: =E44-I44
C48: 3 | D48: LOSA FLOTANTE
C50: CONCRETO
C52: Espesor: | D52: 0.2 | E52: m
C53: Área casa (NO incluye área de pilas) | D53: 343.6413 | E53: m2
C55: m3 totales | D55: 68.7283 | E55: m3
C57: Cemento | D57: 549.83 | E57: sacos
C58: Arena | D58: 51.5462 | E58: m3
C59: Piedra | D59: 54.9826 | E59: m3
C62: CANTIDADES DOSIFICACION ADELANTE (DIEGO - JARDEL)
C63: Cemento | D63: =D55*333 | E63: kilos
C64: Arena | D64: =D55*0.59 | E64: m3
C65: Piedra | D65: =D55*0.67 | E65: m3
C66: ADITIVO 2 (litros) (EUDO 100 C ) | D66: 137.4565 | E66: litro
C72: PREVISTA TUBERIA ELECTRICA
G74: CANTIDAD
C75: Tomas 30 cm altura | G75: 17
C76: Tomas 1.1 m altura | G76: 6
C77: Tomas de 1,50 m altura | G77: 4
C78: Salida voz 1,5 | G78: 4
G79: =SUM(G75:G78) | H79: un
D80: m | E80: tubos (un)
C81: Tubo 1/2" | D81: =G75*0.3 | E81: =D81/6
C82: Tubo 1/2" | D82: =G76*1.1 | E82: =D82/6 | F82: =E81+E82+E83 | G82: un
C83: Tubo 1/2" | D83: =G77*1.5 | E83: =D83/6
C84: Tubo 1" | D84: =G78*1.5 | E84: =D84/6
C85: Tubo 3/4" | D85: =G78*1.5 | E85: =D85/6
F87: CANTIDADES ADICIONALES
F88: CANTIDAD | G88: TIPO TUBO
C89: 8 | D89: 1/2" | E89: =(C89*1.8)/6 | F89: =F82+E89 | G89: 1/2"
C90: 1 | D90: 1" | E90: =(C90*1.8)/6 | F90: =E84+E90 | G90: 1"
C91: 2 | D91: 3/4" | E91: =(C91*1.8)/6 | F91: =E85+E91 | G91: 3/4"
C92: 1 | D92: 1 1/2" | E92: =(C92*1.8)/6
C93: =SUM(C89:C92)
C95: VIGAS PERIMETRALES
C97: LARGO | D97: 7.82
D98: 30.21
D99: 5.92 | I99: 0.05
D100: 4.41 | I100: 0.06
D101: 1.56 | I101: 0.06
D102: 2.7 | I102: 0.09
D103: =SUM(D97:D102) | E103: m | I103: 0.05
I104: 0.11
I105: 0.19
C106: ANCHO | D106: 0.2 | E106: m | I106: 0.44
C107: ESPESOR | D107: 0.2 | E107: m | I107: 0.17
C108: LARGO | D108: =D103 | E108: m | I108: 0.01
I109: 0.01
F110: verificacion planos | I110: 0.11
C111: CONCRETO | D111: =(D106*D107*D108)*1.05 | E111: m3 | I111: 0.1
I112: 0.11
C113: Cemento | D113: =D111*8 | E113: sacos | I113: 0.44
C114: Arena | D114: =D111*0.75 | E114: m3 | I114: =SUM(I99:I113) | J114: m3
C115: Piedra | D115: =D111*0.8 | E115: m3
C119: MALLA ELECTROSOLDADA #2 | E119: (2,2 X 6 M)
C121: Área casa (incluye área de pilas) | D121: =54.44+7.59 | E121: m2
F122: Peso | G122: kg
C123: # Malla electrosoldada | D123: =D121/(1.9*5.7) | E123: un | F123: 30.87 | G123: =D123*F123
C126: ARMADURA | D126: 4 # 3 AROS # 3 @ 20 cm
C128: Varilla longituginal | D128: 4#3
C130: Cantidad | D130: 4 | E130: un
C131: Largo | D131: =D103 | E131: m
F132: Peso | G132: kg
C133: Varilla # 3 Longitudinal | D133: =(D130*D131)/5.7 | E133: un | F133: 3.36 | G133: =D133*F133
C136: Aros | D136: # 3 @ 20 cm
C138: Largo | D138: =D103 | E138: m
C139: Longitud de aro | D139: =(4*0.2)+0.2 | E139: m
C140: #Aros | D140: =D138/0.2 | E140: un
F141: Peso | G141: kg
C142: #Varilla #3 Aros | D142: =(D139*D140)/5.7 | E142: un | F142: 3.36 | G142: =D142*F142
G143: =SUM(G133:G142)
C144: Alambre negro | D144: =+(G143)*4.5% | E144: kg
C146: FORMALETA
...

Sheet TABLA DE AVANCE 
I1: VERIFICACION | J1: =D4-'IKARIA TECHO'!N10
A3: CODIGO | B3: N° | C3: Descripcion actividad | D3: Total Directo Colones | E3: porcentaje de avance | F3: monto | G3: Monto faltante por gastar
C4: TOTAL PRESUPUESTO | D4: =SUM(D5:D69)/2
A5: 01 | B5: 1 | C5: FUNDACIONES | D5: ='IKARIA TECHO'!N11 | E5: 0.1 | F5: =D5*E5 | G5: =D5-F5
A6: 01-01 | B6: 1.1 | C6: OBRAS PRELIMINARES Y RELLENOS | D6: ='IKARIA TECHO'!N12 | F6: =D6*E6 | G6: =D6-F6
A7: 01-02 | B7: 1.2 | C7: EXCAVACIÓN Y TUBERÍAS MECÁNICAS | D7: ='IKARIA TECHO'!N21 | F7: =D7*E7 | G7: =D7-F7
A8: 01-03 | B8: 1.3 | C8: SELLO DE CONCRETO | D8: ='IKARIA TECHO'!N58 | F8: =D8*E8 | G8: =D8-F8
A9: 01-04 | B9: 1.4 | C9: LOSA FLOTANTE (ACERO, ELECTROMECANICOS, CONCRETO) | D9: ='IKARIA TECHO'!N69 | F9: =D9*E9 | G9: =D9-F9
A10: 02 | B10: 2 | C10: SUPERESTRUCTURA PRIMER NIVEL | D10: ='IKARIA TECHO'!N123 | F10: =D10*E10 | G10: =D10-F10
A11: 02-01 | B11: 2.1 | C11: ACERO EN PAREDES MUROS N1 (ELECTROMECANICO) | D11: ='IKARIA TECHO'!N124 | F11: =D11*E11 | G11: =D11-F11
A12: 02-02 | B12: 2.2 | C12: PAREDES, MUROS, ENTREPISO N1 (FORMALETA, CONCRETO, DESENCOFRADO) | D12: ='IKARIA TECHO'!N154 | F12: =D12*E12 | G12: =D12-F12
A13: 02-03 | B13: 2.3 | C13: MAMPOSTERIA | D13: ='IKARIA TECHO'!N169 | F13: =D13*E13 | G13: =D13-F13
A14: 03 | B14: 3 | C14: SUPERESTRUCTURA SEGUNDO NIVEL | D14: ='IKARIA TECHO'!N182 | F14: =D14*E14 | G14: =D14-F14
A15: 03-01 | B15: 3.1 | C15: ACERO EN PAREDES MUROS N2 (ELECTROMECANICO) | D15: ='IKARIA TECHO'!N183 | F15: =D15*E15 | G15: =D15-F15
A16: 03-02 | B16: 3.2 | C16: PAREDES, MUROS, ENTREPISO N2 (FORMALETA, CONCRETO, DESENCOFRADO) | D16: ='IKARIA TECHO'!N201 | F16: =D16*E16 | G16: =D16-F16
A17: 04 | B17: 4 | C17: OTROS GRIS | D17: ='IKARIA TECHO'!N214 | F17: =D17*E17 | G17: =D17-F17
A18: 04-01 | B18: 4.1 | C18: GRADAS EN CONCRETO | D18: ='IKARIA TECHO'!N215 | F18: =D18*E18 | G18: =D18-F18
A19: 04-02 | B19: 4.2 | C19: COLUMNAS (MEDIDOR) | D19: ='IKARIA TECHO'!N253 | F19: =D19*E19 | G19: =D19-F19
A20: 04-03 | B20: 4.3 | C20: CHORREA DE COCHERAS Y PILAS | D20: ='IKARIA TECHO'!N288 | F20: =D20*E20 | G20: =D20-F20
A21: 05 | B21: 5 | C21: ESTRUCTURA METÁLICA Y CUBIERTAS | D21: ='IKARIA TECHO'!N309 | F21: =D21*E21 | G21: =D21-F21
A22: 05-01 | B22: 5.1 | C22: ESTRUCTURA TECHO CASA | D22: ='IKARIA TECHO'!N310 | F22: =D22*E22 | G22: =D22-F22
A23: 05-02 | B23: 5.2 | C23: ESTRUCTURA TECHO COCHERA | D23: ='IKARIA TECHO'!N327 | F23: =D23*E23 | G23: =D23-F23
A24: 05-03 | B24: 5.3 | C24: CUBIERTA TECHO CASA | D24: ='IKARIA TECHO'!N348 | F24: =D24*E24 | G24: =D24-F24
A25: 05-04 | B25: 5.4 | C25: CUBIERTA TECHO COCHERA | D25: ='IKARIA TECHO'!N356 | F25: =D25*E25 | G25: =D25-F25
A26: 05-05 | B26: 5.5 | C26: HOJALATERIA Y CANOAS | D26: ='IKARIA TECHO'!N368 | F26: =D26*E26 | G26: =D26-F26
A27: 05-06 | B27: 5.6 | C27: GRADAS ESTRUCTURA, PINTADO Y ACABADO | D27: ='IKARIA TECHO'!N380 | F27: =D27*E27 | G27: =D27-F27
A28: 05-07 | B28: 5.7 | C28: BARANDA DE GRADAS (N2) | D28: ='IKARIA TECHO'!N394 | F28: =D28*E28 | G28: =D28-F28
A29: 05-08 | B29: 5.8 | C29: ESTRUCTURA METÁLICA INTERNA | D29: ='IKARIA TECHO'!N408 | F29: =D29*E29 | G29: =D29-F29
A30: 06 | B30: 6 | C30: LIVIANO | D30: ='IKARIA TECHO'!N422 | F30: =D30*E30 | G30: =D30-F30
A31: 06-01 | B31: 6.1 | C31: LIVIANO EXTERIORES | D31: ='IKARIA TECHO'!N423 | F31: =D31*E31 | G31: =D31-F31
A32: 06-02 | B32: 6.2 | C32: LIVIANO INTERIORES ( PAREDES LIVIANAS Y CIELOS) | D32: ='IKARIA TECHO'!N455 | F32: =D32*E32 | G32: =D32-F32
A33: 07 | B33: 7 | C33: REPELLOS | D33: ='IKARIA TECHO'!N504 | F33: =D33*E33 | G33: =D33-F33
A34: 07-01 | B34: 7.1 | C34: REPELLOS INTERNO Y EXTERNO | D34: ='IKARIA TECHO'!N505 | F34: =D34*E34 | G34: =D34-F34
A35: 07-02 | B35: 7.2 | C35: EMPASTE | D35: ='IKARIA TECHO'!N521 | F35: =D35*E35 | G35: =D35-F35
A36: 08 | B36: 8 | C36: ENCHAPES | D36: ='IKARIA TECHO'!N528 | F36: =D36*E36 | G36: =D36-F36
A37: 08-01 | B37: 8.1 | C37: ENCHAPES (INTERNO Y EXTERNO) | D37: ='IKARIA TECHO'!N529 | F37: =D37*E37 | G37: =D37-F37
A38: 09 | B38: 9 | C38: MUEBLES Y PUERTAS | D38: ='IKARIA TECHO'!N560 | F38: =D38*E38 | G38: =D38-F38
A39: 09-01 | B39: 9.1 | C39: MUEBLES | D39: ='IKARIA TECHO'!N561 | F39: =D39*E39 | G39: =D39-F39
A40: 09-02 | B40: 9.2 | C40: PUERTAS Y RODAPIE | D40: ='IKARIA TECHO'!N626 | F40: =D40*E40 | G40: =D40-F40
A41: 10 | B41: 10 | C41: OBRAS ADICIONALES | D41: ='IKARIA TECHO'!N638 | F41: =D41*E41 | G41: =D41-F41
A42: 10-01 | B42: 10.1 | C42: ZACATE | D42: ='IKARIA TECHO'!N639 | F42: =D42*E42 | G42: =D42-F42
A43: 10-02 | B43: 10.2 | C43: TAPIAS PREFABRICADAS | D43: ='IKARIA TECHO'!N647 | F43: =D43*E43 | G43: =D43-F43
A44: 10-03 | B44: 10.3 | C44: ACERAS | D44: ='IKARIA TECHO'!N657 | F44: =D44*E44 | G44: =D44-F44
A45: 11 | B45: 11 | C45: ACABADOS | D45: ='IKARIA TECHO'!N667 | F45: =D45*E45 | G45: =D45-F45
A46: 11-01 | B46: 11.1 | C46: PINTURA | D46: ='IKARIA TECHO'!N668 | F46: =D46*E46 | G46: =D46-F46
A47: 11-02 | B47: 11.2 | C47: LOSA SANITARIA, GRIFERIA | D47: ='IKARIA TECHO'!N697 | F47: =D47*E47 | G47: =D47-F47
A48: 11-03 | B48: 11.3 | C48: ACABADOS DE AZOTEA | D48: ='IKARIA TECHO'!N717 | F48: =D48*E48 | G48: =D48-F48
A49: 11-04 | B49: 11.4 | C49: PONCHEO FINAL | D49: ='IKARIA TECHO'!N731 | F49: =D49*E49 | G49: =D49-F49
A50: 12 | B50: 12 | C50: VENTANERIA | D50: ='IKARIA TECHO'!N738 | F50: =D50*E50 | G50: =D50-F50
A51: 12-01 | B51: 12.1 | C51: VENTANERIA | D51: ='IKARIA TECHO'!N739 | F51: =D51*E51 | G51: =D51-F51
B52: 13 | C52: ELÉCTRICO | D52: ='IKARIA TECHO'!N743 | F52: =D52*E52 | G52: =D52-F52
A53: 13-01 | B53: 13.01 | C53: ACOMETIDA | D53: ='IKARIA TECHO'!N744 | F53: =D53*E53 | G53: =D53-F53
A54: 13-02 | B54: 13.02 | C54: ELÉCTRICO LOSA | D54: ='IKARIA TECHO'!N748 | F54: =D54*E54 | G54: =D54-F54
A55: 13-03 | B55: 13.03 | C55: ELÉCTRICO MUROS | D55: ='IKARIA TECHO'!N752 | F55: =D55*E55 | G55: =D55-F55
A56: 13-04 | B56: 13.04 | C56: BASE MEDIDOR | D56: ='IKARIA TECHO'!N756 | F56: =D56*E56 | G56: =D56-F56
A57: 13-05 | B57: 13.05 | C57: ELÉCTRICO ILUMINACIÓN | D57: ='IKARIA TECHO'!N762 | F57: =D57*E57 | G57: =D57-F57
A58: 13-06 | B58: 13.06 | C58: TABLERO ELÉCTRICO | D58: ='IKARIA TECHO'!N771 | F58: =D58*E58 | G58: =D58-F58
A59: 13-07 | B59: 13.07 | C59: CABLEADO ELÉCTRICO | D59: ='IKARIA TECHO'!N781 | F59: =D59*E59 | G59: =D59-F59
A60: 13-08 | B60: 13.08 | C60: PLAQUERIA | D60: ='IKARIA TECHO'!N813 | F60: =D60*E60 | G60: =D60-F60
A61: 13-09 | B61: 13.09 | C61: ACABADOS FINALES Y BREAKERS | D61: ='IKARIA TECHO'!N822 | F61: =D61*E61 | G61: =D61-F61
B62: 14 | C62: MECÁNICO | D62: ='IKARIA TECHO'!N834 | F62: =D62*E62 | G62: =D62-F62
A63: 14-03 | B63: 14.03 | C63: CAJAS Y TUBERIAS MECÁNICAS | D63: ='IKARIA TECHO'!N835 | F63: =D63*E63 | G63: =D63-F63
A64: 14-04 | B64: 14.04 | C64: BAJANTES | D64: ='IKARIA TECHO'!N851 | F64: =D64*E64 | G64: =D64-F64
A65: 14-05 | B65: 14.05 | C65: ACABADOS MECÁNICOS | D65: ='IKARIA TECHO'!N857 | F65: =D65*E65 | G65: =D65-F65
A66: 15 | B66: 15 | C66: ALQUILERES | D66: ='IKARIA TECHO'!N886 | F66: =D66*E66 | G66: =D66-F66
A67: 15-01 | B67: 15.1 | C67: ALQUILERES | D67: ='IKARIA TECHO'!N887 | F67: =D67*E67 | G67: =D67-F67
A68: 16 | B68: 16 | C68: MANO DE OBRA | D68: ='IKARIA TECHO'!N905 | F68: =D68*E68 | G68: =D68-F68
A69: 16-01 | B69: 16.1 | C69: MANO DE OBRA | D69: ='IKARIA TECHO'!N906 | F69: =D69*E69 | G69: =D69-F69

Sheet Costo personal
C3: SALARIO POR HORA APROBADO POR GERENCIA
C4: Fecha de aprobación: 08/02/2022
C5: Vigente desde: 08/02/2022
C8: Descripción de Puesto | D8: Salario x Hora | E8: Bono | G8: cargas sociales | H8: 48 Horas semanales | I8: Horas Extra Por Semana | J8: Costo Por Semana | K8: Cargas Sociales | L8: Total a Pagar x Semana | M8: Total a Pagar x Mes
B10: MO-01-01 | C10: Encargado Plus | D10: 2000 | E10: 500 | F10: =SUM(D10:E10) | G10: =+F10*1.5 | H10: =+(D10+E10)*48 | I10: =+(D10+E10)*7*1.5 | J10: =+I10+H10 | K10: =+J10*0.5 | L10: =+K10+J10 | M10: =+L10*4.32
B11: MO-01-02 | C11: Encargado Avanzado | D11: 2000 | E11: 300 | F11: =SUM(D11:E11) | G11: =+F11*1.5 | H11: =+(D11+E11)*48 | I11: =+(D11+E11)*7*1.5 | J11: =+I11+H11 | K11: =+J11*0.5 | L11: =+K11+J11 | M11: =+L11*4.32
B12: MO-01-03 | C12: Encargado | D12: 2000 | E12: 200 | F12: =SUM(D12:E12) | G12: =+F12*1.5 | H12: =+(D12+E12)*48 | I12: =+(D12+E12)*7*1.5 | J12: =+I12+H12 | K12: =+J12*0.5 | L12: =+K12+J12 | M12: =+L12*4.32
B14: MO-02-01 | C14: Operario calificado Plus | D14: 2000 | F14: =SUM(D14:E14) | G14: =+F14*1.5 | H14: =+(D14+E14)*48 | I14: =+(D14+E14)*7*1.5 | J14: =+I14+H14 | K14: =+J14*0.5 | L14: =+K14+J14 | M14: =+L14*4.32
B15: MO-02-02 | C15: Operario calificado Avanzado | D15: 1900 | F15: =SUM(D15:E15) | G15: =+F15*1.5 | H15: =+(D15+E15)*48 | I15: =+(D15+E15)*7*1.5 | J15: =+I15+H15 | K15: =+J15*0.5 | L15: =+K15+J15 | M15: =+L15*4.32
C16: Operario calificado (nuevo ingreso) | D16: 1700 | F16: =SUM(D16:E16) | G16: =+F16*1.5 | H16: =+(D16+E16)*48 | I16: =+(D16+E16)*7*1.5 | J16: =+I16+H16 | K16: =+J16*0.5 | L16: =+K16+J16 | M16: =+L16*4.32
B18: MO-03-01 | C18: Operario Plus | D18: 1900 | F18: =SUM(D18:E18) | G18: =+F18*1.5 | H18: =+(D18+E18)*48 | I18: =+(D18+E18)*7*1.5 | J18: =+I18+H18 | K18: =+J18*0.5 | L18: =+K18+J18 | M18: =+L18*4.32
B19: MO-03-02 | C19: Operario Avanzado | D19: 1800 | F19: =SUM(D19:E19) | G19: =+F19*1.5 | H19: =+(D19+E19)*48 | I19: =+(D19+E19)*7*1.5 | J19: =+I19+H19 | K19: =+J19*0.5 | L19: =+K19+J19 | M19: =+L19*4.32
B20: MO-03-03 | C20: Operario (nuevo ingreso) | D20: 1600 | F20: =SUM(D20:E20) | G20: =+F20*1.5 | H20: =+(D20+E20)*48 | I20: =+(D20+E20)*7*1.5 | J20: =+I20+H20 | K20: =+J20*0.5 | L20: =+K20+J20 | M20: =+L20*4.32
B22: MO-04-01 | C22: Ayudante Plus | D22: 1550 | F22: =SUM(D22:E22) | G22: =+F22*1.5 | H22: =+(D22+E22)*48 | I22: =+(D22+E22)*7*1.5 | J22: =+I22+H22 | K22: =+J22*0.5 | L22: =+K22+J22 | M22: =+L22*4.32
B23: MO-04-02 | C23: Ayudante Avanzado | D23: 1450 | F23: =SUM(D23:E23) | G23: =+F23*1.5 | H23: =+(D23+E23)*48 | I23: =+(D23+E23)*7*1.5 | J23: =+I23+H23 | K23: =+J23*0.5 | L23: =+K23+J23 | M23: =+L23*4.32
B24: MO-04-03 | C24: Ayudante (nuevo ingreso) | D24: 1360 | F24: =SUM(D24:E24) | G24: =+F24*1.5 | H24: =+(D24+E24)*48 | I24: =+(D24+E24)*7*1.5 | J24: =+I24+H24 | K24: =+J24*0.5 | L24: =+K24+J24 | M24: =+L24*4.32
C27: NOTAS:
C28: Operario Calificado: Soldadores y Ebanistas
C29: Operario: Repellos, Enchapes, Pasta, Armadura, Formaleta, Fontaneros, Obras Complementarias
C31: ACLARACIONES:
C32: - Los ingresos se harán con Los parámetros indicados
C33: - Para ingresar en Rango de avanzado debe contar como mínimo 1 mes de laborar en la empresa demostrando que es merecedor de la mejora salarial. (Este lo revisara el maestro de Obras)
C34: - Para ingresar en Rango de Plus debe contar como mínimo 6 mes de laborar en la empresa demostrando que es merecedor de la mejora salarial. (Este lo revisara el maestro de Obras)

Sheet HORAS MANO DE OBRA
A1: Nivel | B1: CODIGO | C1: DESCRIPCION | D1: TOTAL HORAS
A2: 1 | B2: 01 | C2: FUNDACIONES
A3: 2 | B3: 01-01 | C3: OBRAS PRELIMINARES Y RELLENOS
A4: 3 | B4: 01-01-01 | C4: TRAZO LASTRE Y COMPACTACION | D4: =SUMIF('IKARIA TECHO'!B:B,'HORAS MANO DE OBRA'!B4,'IKARIA TECHO'!F:F)
A5: 2 | B5: 01-02 | C5: EXCAVACION
A6: 3 | B6: 01-02-01 | C6: ZANJEO | D6: =SUMIF('IKARIA TECHO'!B:B,'HORAS MANO DE OBRA'!B6,'IKARIA TECHO'!F:F)
A7: 2 | B7: 01-03 | C7: SELLO DE CONCRETO
A8: 3 | B8: 01-03-01 | C8: SELLO | D8: =SUMIF('IKARIA TECHO'!B:B,'HORAS MANO DE OBRA'!B8,'IKARIA TECHO'!F:F)
A9: 2 | B9: 01-04 | C9: LOSA FLOTANTE (ACERO, MECANICO, CONCRETO)
A10: 3 | B10: 01-04-01 | C10: ACERO LOSA | D10: =SUMIF('IKARIA TECHO'!B:B,'HORAS MANO DE OBRA'!B10,'IKARIA TECHO'!F:F)
A11: 3 | B11: 01-04-02 | C11: FORMALETA LOSA | D11: =SUMIF('IKARIA TECHO'!B:B,'HORAS MANO DE OBRA'!B11,'IKARIA TECHO'!F:F)
A12: 3 | B12: 01-04-03 | C12: COLADO LOSA | D12: =SUMIF('IKARIA TECHO'!B:B,'HORAS MANO DE OBRA'!B12,'IKARIA TECHO'!F:F)
A13: 3 | B13: 01-04-04 | C13: INSTALACION MECANICA LOSAS | D13: =SUMIF('IKARIA TECHO'!B:B,'HORAS MANO DE OBRA'!B13,'IKARIA TECHO'!F:F)
A14: 3 | B14: 01-04-05 | C14: POTABLE LOSA | D14: =SUMIF('IKARIA TECHO'!B:B,'HORAS MANO DE OBRA'!B14,'IKARIA TECHO'!F:F)
A15: 1 | B15: 02 | C15: SUPERESTRUCTURAS NI
A16: 2 | B16: 02-01 | C16: ACERO Y MECANICO MUROS N1
A17: 3 | B17: 02-01-01 | C17: ACERO MUROS N1 | D17: =SUMIF('IKARIA TECHO'!B:B,'HORAS MANO DE OBRA'!B17,'IKARIA TECHO'!F:F)
A18: 3 | B18: 02-01-02 | C18: FORMALETA N1 | D18: =SUMIF('IKARIA TECHO'!B:B,'HORAS MANO DE OBRA'!B18,'IKARIA TECHO'!F:F)
A19: 3 | B19: 02-01-03 | C19: INSTALACION MECANICA MUROS N1 | D19: =SUMIF('IKARIA TECHO'!B:B,'HORAS MANO DE OBRA'!B19,'IKARIA TECHO'!F:F)
A20: 2 | B20: 02-02 | C20: COLADO MUROS N1
A21: 3 | B21: 02-02-01 | C21: COLADO MUROS N1 | D21: =SUMIF('IKARIA TECHO'!B:B,'HORAS MANO DE OBRA'!B21,'IKARIA TECHO'!F:F)
A22: 3 | B22: 02-02-02 | C22: TRAZO FORMALETA N1 | D22: =SUMIF('IKARIA TECHO'!B:B,'HORAS MANO DE OBRA'!B22,'IKARIA TECHO'!F:F)
A23: 3 | B23: 02-02-03 | C23: DESENCOFRE MUROS N1 | D23: =SUMIF('IKARIA TECHO'!B:B,'HORAS MANO DE OBRA'!B23,'IKARIA TECHO'!F:F)
A24: 2 | B24: 02-03 | C24: MAMPOSTERIA
A25: 3 | B25: 02-03-01 | C25: MAMPOSTERIA | D25: =SUMIF('IKARIA TECHO'!B:B,'HORAS MANO DE OBRA'!B25,'IKARIA TECHO'!F:F)
A26: 1 | B26: 03 | C26: SUPERESTRUCTURAS N2
A27: 2 | B27: 03-01 | C27: ACERO MUROS N2
A28: 3 | B28: 03-01-01 | C28: ACERO MUROS N2 | D28: =SUMIF('IKARIA TECHO'!B:B,'HORAS MANO DE OBRA'!B28,'IKARIA TECHO'!F:F)
A29: 3 | B29: 03-01-02 | C29: FORMALETA N2 | D29: =SUMIF('IKARIA TECHO'!B:B,'HORAS MANO DE OBRA'!B29,'IKARIA TECHO'!F:F)
A30: 3 | B30: 03-01-03 | C30: INSTALACION MECANICA MUROS N2 | D30: =SUMIF('IKARIA TECHO'!B:B,'HORAS MANO DE OBRA'!B30,'IKARIA TECHO'!F:F)
A31: 2 | B31: 03-02 | C31: COLADO MUROS N2
A32: 3 | B32: 03-02-01 | C32: COLADO MUROS N2 | D32: =SUMIF('IKARIA TECHO'!B:B,'HORAS MANO DE OBRA'!B32,'IKARIA TECHO'!F:F)
A33: 3 | B33: 03-02-02 | C33: TRAZO FORMALETA N2 | D33: =SUMIF('IKARIA TECHO'!B:B,'HORAS MANO DE OBRA'!B33,'IKARIA TECHO'!F:F)
A34: 3 | B34: 03-02-03 | C34: DESENCOFRE MUROS N2 | D34: =SUMIF('IKARIA TECHO'!B:B,'HORAS MANO DE OBRA'!B34,'IKARIA TECHO'!F:F)
A35: 1 | B35: 04 | C35: OTROS GRIS
A36: 2 | B36: 04-01 | C36: GRADAS CONCRETO
A37: 3 | B37: 04-01-01 | C37: ACERO GRADAS N1 | D37: =SUMIF('IKARIA TECHO'!B:B,'HORAS MANO DE OBRA'!B37,'IKARIA TECHO'!F:F)
A38: 3 | B38: 04-01-02 | C38: FORMALETA GRADAS N1 | D38: =SUMIF('IKARIA TECHO'!B:B,'HORAS MANO DE OBRA'!B38,'IKARIA TECHO'!F:F)
A39: 3 | B39: 04-01-03 | C39: COLADO GRADAS N1 | D39: =SUMIF('IKARIA TECHO'!B:B,'HORAS MANO DE OBRA'!B39,'IKARIA TECHO'!F:F)
A40: 3 | B40: 04-01-04 | C40: DESENCOFRE GRADAS N1 | D40: =SUMIF('IKARIA TECHO'!B:B,'HORAS MANO DE OBRA'!B40,'IKARIA TECHO'!F:F)
A41: 3 | B41: 04-01-05 | C41: ACERO GRADAS N2 | D41: =SUMIF('IKARIA TECHO'!B:B,'HORAS MANO DE OBRA'!B41,'IKARIA TECHO'!F:F)
A42: 3 | B42: 04-01-06 | C42: FORMALETA GRADAS N2 | D42: =SUMIF('IKARIA TECHO'!B:B,'HORAS MANO DE OBRA'!B42,'IKARIA TECHO'!F:F)
A43: 3 | B43: 04-01-07 | C43: COLADO GRADAS N2 | D43: =SUMIF('IKARIA TECHO'!B:B,'HORAS MANO DE OBRA'!B43,'IKARIA TECHO'!F:F)
A44: 3 | B44: 04-01-08 | C44: DESENCOFRE GRADAS N2 | D44: =SUMIF('IKARIA TECHO'!B:B,'HORAS MANO DE OBRA'!B44,'IKARIA TECHO'!F:F)
A45: 2 | B45: 04-02 | C45: COLUMNAS
A46: 3 | B46: 04-02-01 | C46: COLUMNA COCHERA | D46: =SUMIF('IKARIA TECHO'!B:B,'HORAS MANO DE OBRA'!B46,'IKARIA TECHO'!F:F)
A47: 3 | B47: 04-02-02 | C47: COLUMNA MEDIDOR | D47: =SUMIF('IKARIA TECHO'!B:B,'HORAS MANO DE OBRA'!B47,'IKARIA TECHO'!F:F)
A48: 2 | B48: 04-03 | C48: LOSA COCHERA Y PILAS
A49: 3 | B49: 04-03-01 | C49: LASTRE Y COMPACTACION COCHERA | D49: =SUMIF('IKARIA TECHO'!B:B,'HORAS MANO DE OBRA'!B49,'IKARIA TECHO'!F:F)
A50: 3 | B50: 04-03-02 | C50: COLADO LOSA COCHERA | D50: =SUMIF('IKARIA TECHO'!B:B,'HORAS MANO DE OBRA'!B50,'IKARIA TECHO'!F:F)
A51: 3 | B51: 04-03-03 | C51: ACABADO LAVADO COCHERA | D51: =SUMIF('IKARIA TECHO'!B:B,'HORAS MANO DE OBRA'!B51,'IKARIA TECHO'!F:F)
A52: 3 | B52: 04-03-04 | C52: LASTRE Y COMPACTACION TERRAZA | D52: =SUMIF('IKARIA TECHO'!B:B,'HORAS MANO DE OBRA'!B52,'IKARIA TECHO'!F:F)
A53: 3 | B53: 04-03-05 | C53: COLADO LOSA TERRAZA | D53: =SUMIF('IKARIA TECHO'!B:B,'HORAS MANO DE OBRA'!B53,'IKARIA TECHO'!F:F)
A54: 3 | B54: 04-03-06 | C54: ACABADO LAVADO TERRAZA | D54: =SUMIF('IKARIA TECHO'!B:B,'HORAS MANO DE OBRA'!B54,'IKARIA TECHO'!F:F)
A55: 1 | B55: 05 | C55: ESTRUCTURAS METALICAS
A56: 2 | B56: 05-01 | C56: ESTRUCTURA DE TECHO DE CASA
A57: 3 | B57: 05-01-01 | C57: ESTRUCTURA METALICA TECHO | D57: =SUMIF('IKARIA TECHO'!B:B,'HORAS MANO DE OBRA'!B57,'IKARIA TECHO'!F:F)
A58: 3 | B58: 05-01-02 | C58: M.O. ESTRUCTURA TECHO PINTURA | D58: =SUMIF('IKARIA TECHO'!B:B,'HORAS MANO DE OBRA'!B58,'IKARIA TECHO'!F:F)
A59: 2 | B59: 05-02 | C59: ESTRUCTURA DE TECHO COCHERA
A60: 3 | B60: 05-02-01 | C60: ESTRUCTURA METALICA COCHERA | D60: =SUMIF('IKARIA TECHO'!B:B,'HORAS MANO DE OBRA'!B60,'IKARIA TECHO'!F:F)
A61: 3 | B61: 05-02-02 | C61: M.O. ESTRUCTURA TECHO COCHERA PINTURA | D61: =SUMIF('IKARIA TECHO'!B:B,'HORAS MANO DE OBRA'!B61,'IKARIA TECHO'!F:F)
A62: 2 | B62: 05-03 | C62: CUBIERTA TECHO CASA
A63: 3 | B63: 05-03-01 | C63: CUBIERTA TECHO | D63: =SUMIF('IKARIA TECHO'!B:B,'HORAS MANO DE OBRA'!B63,'IKARIA TECHO'!F:F)
A64: 2 | B64: 05-04 | C64: CUBIERTA TECHO CASA
A65: 3 | B65: 05-04-01 | C65: CUBIERTA COCHERA | D65: =SUMIF('IKARIA TECHO'!B:B,'HORAS MANO DE OBRA'!B65,'IKARIA TECHO'!F:F)
A66: 2 | B66: 05-05 | C66: HOJALATERÍA Y CANOAS
A67: 3 | B67: 05-05-01 | C67: HOJALATERIA GENERAL | D67: =SUMIF('IKARIA TECHO'!B:B,'HORAS MANO DE OBRA'!B67,'IKARIA TECHO'!F:F)
A68: 3 | B68: 05-05-02 | C68: TALLER DE FABRICACIÓN | D68: =SUMIF('IKARIA TECHO'!B:B,'HORAS MANO DE OBRA'!B68,'IKARIA TECHO'!F:F)
A69: 3 | B69: 05-05-03 | C69: INSTALACIÓN DE HOJALATERÍA | D69: =SUMIF('IKARIA TECHO'!B:B,'HORAS MANO DE OBRA'!B69,'IKARIA TECHO'!F:F)
A70: 2 | B70: 05-06 | C70: GRADAS
A71: 3 | B71: 05-06-01 | C71: MO DE PINTURA DE GRADAS | D71: =SUMIF('IKARIA TECHO'!B:B,'HORAS MANO DE OBRA'!B71,'IKARIA TECHO'!F:F)
A72: 3 | B72: 05-06-02 | C72: MO COLADO DE GRADAS METALICAS | D72: =SUMIF('IKARIA TECHO'!B:B,'HORAS MANO DE OBRA'!B72,'IKARIA TECHO'!F:F)
A73: 3 | B73: 05-06-03 | C73: PASAMANOS DE GRADAS | D73: =SUMIF('IKARIA TECHO'!B:B,'HORAS MANO DE OBRA'!B73,'IKARIA TECHO'!F:F)
A74: 3 | B74: 05-06-04 | C74: ESTRUCTURA METALICA GRADAS Y BARANDAS | D74: =SUMIF('IKARIA TECHO'!B:B,'HORAS MANO DE OBRA'!B74,'IKARIA TECHO'!F:F)
A75: 2 | B75: 05-07 | C75: BARANDA DE GRADAS (N2)
A76: 3 | B76: 05-07-01 | C76: BARANDAS N2 | D76: =SUMIF('IKARIA TECHO'!B:B,'HORAS MANO DE OBRA'!B76,'IKARIA TECHO'!F:F)
A77: 2 | B77: 05-08 | C77: ESTRUCTURA METALICA INTERNA
A78: 3 | B78: 05-08-01 | C78: ESTRUCTURA METALICA INTERNA | D78: =SUMIF('IKARIA TECHO'!B:B,'HORAS MANO DE OBRA'!B78,'IKARIA TECHO'!F:F)
A79: 3 | B79: 05-08-02 | C79: ESTRUCTURA METALICA DUCTO | D79: =SUMIF('IKARIA TECHO'!B:B,'HORAS MANO DE OBRA'!B79,'IKARIA TECHO'!F:F)
A80: 1 | B80: 06 | C80: LIVIANO
A81: 2 | B81: 06-01 | C81: LIVIANO EXTERIORES
A82: 3 | B82: 06-01-01 | C82: ESTRUCTURA LIVIANA DE TAPICHELES | D82: =SUMIF('IKARIA TECHO'!B:B,'HORAS MANO DE OBRA'!B82,'IKARIA TECHO'!F:F)
A83: 3 | B83: 06-01-02 | C83: FORRO DE TAPICHELES | D83: =SUMIF('IKARIA TECHO'!B:B,'HORAS MANO DE OBRA'!B83,'IKARIA TECHO'!F:F)
A84: 2 | B84: 06-02 | C84: LIVIANO INTERNO
A85: 3 | B85: 06-02-01 | C85: ESTRUCTURA LIVIANA INTERNA | D85: =SUMIF('IKARIA TECHO'!B:B,'HORAS MANO DE OBRA'!B85,'IKARIA TECHO'!F:F)
A86: 3 | B86: 06-02-02 | C86: FORRO LIVIANO INTERNO | D86: =SUMIF('IKARIA TECHO'!B:B,'HORAS MANO DE OBRA'!B86,'IKARIA TECHO'!F:F)
A87: 3 | B87: 06-02-03 | C87: FORRO ALEROS Y TABLILLA | D87: =SUMIF('IKARIA TECHO'!B:B,'HORAS MANO DE OBRA'!B87,'IKARIA TECHO'!F:F)
A88: 3 | B88: 06-02-04 | C88: ESTRUCTURA Y FORRO PILA | D88: =SUMIF('IKARIA TECHO'!B:B,'HORAS MANO DE OBRA'!B88,'IKARIA TECHO'!F:F)
A89: 3 | B89: 06-02-05 | C89: FORRO DE DUCTOS MECANICOS | D89: =SUMIF('IKARIA TECHO'!B:B,'HORAS MANO DE OBRA'!B89,'IKARIA TECHO'!F:F)
A90: 3 | B90: 06-02-06 | C90: ESTRUCTURA LIVIANA DUCTO DE ESCALERA | D90: =SUMIF('IKARIA TECHO'!B:B,'HORAS MANO DE OBRA'!B90,'IKARIA TECHO'!F:F)
A91: 3 | B91: 06-02-07 | C91: FORRO DUCTO DE ESCALERAS | D91: =SUMIF('IKARIA TECHO'!B:B,'HORAS MANO DE OBRA'!B91,'IKARIA TECHO'!F:F)
A92: 1 | B92: 07 | C92: REPELLOS
A93: 2 | B93: 07-01 | C93: REPELLO INTERNO Y EXTERNO
A94: 3 | B94: 07-01-01 | C94: RELLENO DE CORBATAS | D94: =SUMIF('IKARIA TECHO'!B:B,'HORAS MANO DE OBRA'!B94,'IKARIA TECHO'!F:F)
A95: 3 | B95: 07-01-02 | C95: CODALES VENTANAS | D95: =SUMIF('IKARIA TECHO'!B:B,'HORAS MANO DE OBRA'!B95,'IKARIA TECHO'!F:F)
A96: 3 | B96: 07-01-03 | C96: MURO SECO INTERIOR | D96: =SUMIF('IKARIA TECHO'!B:B,'HORAS MANO DE OBRA'!B96,'IKARIA TECHO'!F:F)
A97: 3 | B97: 07-01-04 | C97: MURO SECO EXT | D97: =SUMIF('IKARIA TECHO'!B:B,'HORAS MANO DE OBRA'!B97,'IKARIA TECHO'!F:F)
A98: 3 | B98: 07-01-05 | C98: REPELLO TAPIA | D98: =SUMIF('IKARIA TECHO'!B:B,'HORAS MANO DE OBRA'!B98,'IKARIA TECHO'!F:F)
A99: 3 | B99: 07-01-06 | C99: REPELLO DE CIELOS | D99: =SUMIF('IKARIA TECHO'!B:B,'HORAS MANO DE OBRA'!B99,'IKARIA TECHO'!F:F)
A100: 2 | B100: 07-02 | C100: EMPASTES
...

Sheet ANALISIS
B1: CODIGO ACUMATICA | C1: CODIGO | D1: DESCRIPCION | E1: CANTIDAD | F1: PRECIO UNITARIO | G1: PRECIO TOTAL | H1: % PORCENTAJE
B2: =_xlfn.XLOOKUP(C2,'INSUMOS MAT '!B:B,'INSUMOS MAT '!C:C,"ERROR",0) | C2: MAT03-0014 | D2: =_xlfn.XLOOKUP(C2,'IKARIA TECHO'!D:D,'IKARIA TECHO'!E:E,"ERROR",0) | E2: =SUMIF('IKARIA TECHO'!D:D,ANALISIS!C2,'IKARIA TECHO'!F:F) | F2: =_xlfn.XLOOKUP(C2,'IKARIA TECHO'!D:D,'IKARIA TECHO'!H:H,"ERROR",0) | G2: =E2*F2 | H2: =G2/$G$289
B3: =_xlfn.XLOOKUP(C3,'INSUMOS MAT '!B:B,'INSUMOS MAT '!C:C,"ERROR",0) | C3: MAT08-0017 | D3: =_xlfn.XLOOKUP(C3,'IKARIA TECHO'!D:D,'IKARIA TECHO'!E:E,"ERROR",0) | E3: =SUMIF('IKARIA TECHO'!D:D,ANALISIS!C3,'IKARIA TECHO'!F:F) | F3: =_xlfn.XLOOKUP(C3,'IKARIA TECHO'!D:D,'IKARIA TECHO'!H:H,"ERROR",0) | G3: =E3*F3 | H3: =G3/$G$289
B4: =_xlfn.XLOOKUP(C4,'INSUMOS MAT '!B:B,'INSUMOS MAT '!C:C,"ERROR",0) | C4: MAT08-0029 | D4: =_xlfn.XLOOKUP(C4,'IKARIA TECHO'!D:D,'IKARIA TECHO'!E:E,"ERROR",0) | E4: =SUMIF('IKARIA TECHO'!D:D,ANALISIS!C4,'IKARIA TECHO'!F:F) | F4: =_xlfn.XLOOKUP(C4,'IKARIA TECHO'!D:D,'IKARIA TECHO'!H:H,"ERROR",0) | G4: =E4*F4 | H4: =G4/$G$289
B5: =_xlfn.XLOOKUP(C5,'INSUMOS MAT '!B:B,'INSUMOS MAT '!C:C,"ERROR",0) | C5: MAT08-0031 | D5: =_xlfn.XLOOKUP(C5,'IKARIA TECHO'!D:D,'IKARIA TECHO'!E:E,"ERROR",0) | E5: =SUMIF('IKARIA TECHO'!D:D,ANALISIS!C5,'IKARIA TECHO'!F:F) | F5: =_xlfn.XLOOKUP(C5,'IKARIA TECHO'!D:D,'IKARIA TECHO'!H:H,"ERROR",0) | G5: =E5*F5 | H5: =G5/$G$289
B6: =_xlfn.XLOOKUP(C6,'INSUMOS MAT '!B:B,'INSUMOS MAT '!C:C,"ERROR",0) | C6: MAT19-0100 | D6: =_xlfn.XLOOKUP(C6,'IKARIA TECHO'!D:D,'IKARIA TECHO'!E:E,"ERROR",0) | E6: =SUMIF('IKARIA TECHO'!D:D,ANALISIS!C6,'IKARIA TECHO'!F:F) | F6: =_xlfn.XLOOKUP(C6,'IKARIA TECHO'!D:D,'IKARIA TECHO'!H:H,"ERROR",0) | G6: =E6*F6 | H6: =G6/$G$289
B7: =_xlfn.XLOOKUP(C7,'INSUMOS MAT '!B:B,'INSUMOS MAT '!C:C,"ERROR",0) | C7: MAT19-0095 | D7: =_xlfn.XLOOKUP(C7,'IKARIA TECHO'!D:D,'IKARIA TECHO'!E:E,"ERROR",0) | E7: =SUMIF('IKARIA TECHO'!D:D,ANALISIS!C7,'IKARIA TECHO'!F:F) | F7: =_xlfn.XLOOKUP(C7,'IKARIA TECHO'!D:D,'IKARIA TECHO'!H:H,"ERROR",0) | G7: =E7*F7 | H7: =G7/$G$289
B8: =_xlfn.XLOOKUP(C8,'INSUMOS MAT '!B:B,'INSUMOS MAT '!C:C,"ERROR",0) | C8: MAT19-0094 | D8: =_xlfn.XLOOKUP(C8,'IKARIA TECHO'!D:D,'IKARIA TECHO'!E:E,"ERROR",0) | E8: =SUMIF('IKARIA TECHO'!D:D,ANALISIS!C8,'IKARIA TECHO'!F:F) | F8: =_xlfn.XLOOKUP(C8,'IKARIA TECHO'!D:D,'IKARIA TECHO'!H:H,"ERROR",0) | G8: =E8*F8 | H8: =G8/$G$289
B9: =_xlfn.XLOOKUP(C9,'INSUMOS MAT '!B:B,'INSUMOS MAT '!C:C,"ERROR",0) | C9: MAT19-0081 | D9: =_xlfn.XLOOKUP(C9,'IKARIA TECHO'!D:D,'IKARIA TECHO'!E:E,"ERROR",0) | E9: =SUMIF('IKARIA TECHO'!D:D,ANALISIS!C9,'IKARIA TECHO'!F:F) | F9: =_xlfn.XLOOKUP(C9,'IKARIA TECHO'!D:D,'IKARIA TECHO'!H:H,"ERROR",0) | G9: =E9*F9 | H9: =G9/$G$289
B10: =_xlfn.XLOOKUP(C10,'INSUMOS MAT '!B:B,'INSUMOS MAT '!C:C,"ERROR",0) | C10: MAT19-0044 | D10: =_xlfn.XLOOKUP(C10,'IKARIA TECHO'!D:D,'IKARIA TECHO'!E:E,"ERROR",0) | E10: =SUMIF('IKARIA TECHO'!D:D,ANALISIS!C10,'IKARIA TECHO'!F:F) | F10: =_xlfn.XLOOKUP(C10,'IKARIA TECHO'!D:D,'IKARIA TECHO'!H:H,"ERROR",0) | G10: =E10*F10 | H10: =G10/$G$289
B11: =_xlfn.XLOOKUP(C11,'INSUMOS MAT '!B:B,'INSUMOS MAT '!C:C,"ERROR",0) | C11: MAT19-0118 | D11: =_xlfn.XLOOKUP(C11,'IKARIA TECHO'!D:D,'IKARIA TECHO'!E:E,"ERROR",0) | E11: =SUMIF('IKARIA TECHO'!D:D,ANALISIS!C11,'IKARIA TECHO'!F:F) | F11: =_xlfn.XLOOKUP(C11,'IKARIA TECHO'!D:D,'IKARIA TECHO'!H:H,"ERROR",0) | G11: =E11*F11 | H11: =G11/$G$289
B12: =_xlfn.XLOOKUP(C12,'INSUMOS MAT '!B:B,'INSUMOS MAT '!C:C,"ERROR",0) | C12: MAT19-0024 | D12: =_xlfn.XLOOKUP(C12,'IKARIA TECHO'!D:D,'IKARIA TECHO'!E:E,"ERROR",0) | E12: =SUMIF('IKARIA TECHO'!D:D,ANALISIS!C12,'IKARIA TECHO'!F:F) | F12: =_xlfn.XLOOKUP(C12,'IKARIA TECHO'!D:D,'IKARIA TECHO'!H:H,"ERROR",0) | G12: =E12*F12 | H12: =G12/$G$289
B13: =_xlfn.XLOOKUP(C13,'INSUMOS MAT '!B:B,'INSUMOS MAT '!C:C,"ERROR",0) | C13: MAT19-0049 | D13: =_xlfn.XLOOKUP(C13,'IKARIA TECHO'!D:D,'IKARIA TECHO'!E:E,"ERROR",0) | E13: =SUMIF('IKARIA TECHO'!D:D,ANALISIS!C13,'IKARIA TECHO'!F:F) | F13: =_xlfn.XLOOKUP(C13,'IKARIA TECHO'!D:D,'IKARIA TECHO'!H:H,"ERROR",0) | G13: =E13*F13 | H13: =G13/$G$289
... B67: =_xlfn.XLOOKUP(C67,'INSUMOS MAT '!B:B,'INSUMOS MAT '!C:C,"ERROR",0) | C67: MAT19-0106 | D67: =_xlfn.XLOOKUP(C67,'IKARIA TECHO'!D:D,'IKARIA TECHO'!E:E,"ERROR",0) | E67: =SUMIF('IKARIA TECHO'!D:D,ANALISIS!C67,'IKARIA TECHO'!F:F) | F67: =_xlfn.XLOOKUP(C67,'IKARIA TECHO'!D:D,'IKARIA TECHO'!H:H,"ERROR",0) | G67: =E67*F67 | H67: =G67/$G$289
C68: EQU20-0005 | D68: =_xlfn.XLOOKUP(C68,'IKARIA TECHO'!D:D,'IKARIA TECHO'!E:E,"ERROR",0) | E68: =SUMIF('IKARIA TECHO'!D:D,ANALISIS!C68,'IKARIA TECHO'!F:F) | F68: =_xlfn.XLOOKUP(C68,'IKARIA TECHO'!D:D,'IKARIA TECHO'!H:H,"ERROR",0) | G68: =E68*F68 | H68: =G68/$G$289
B69: =_xlfn.XLOOKUP(C69,'INSUMOS MAT '!B:B,'INSUMOS MAT '!C:C,"ERROR",0) | C69: MAT02-0025 | D69: =_xlfn.XLOOKUP(C69,'IKARIA TECHO'!D:D,'IKARIA TECHO'!E:E,"ERROR",0) | E69: =SUMIF('IKARIA TECHO'!D:D,ANALISIS!C69,'IKARIA TECHO'!F:F) | F69: =_xlfn.XLOOKUP(C69,'IKARIA TECHO'!D:D,'IKARIA TECHO'!H:H,"ERROR",0) | G69: =E69*F69 | H69: =G69/$G$289
B70: =_xlfn.XLOOKUP(C70,'INSUMOS MAT '!B:B,'INSUMOS MAT '!C:C,"ERROR",0) | C70: MAT02-0026 | D70: =_xlfn.XLOOKUP(C70,'IKARIA TECHO'!D:D,'IKARIA TECHO'!E:E,"ERROR",0) | E70: =SUMIF('IKARIA TECHO'!D:D,ANALISIS!C70,'IKARIA TECHO'!F:F) | F70: =_xlfn.XLOOKUP(C70,'IKARIA TECHO'!D:D,'IKARIA TECHO'!H:H,"ERROR",0) | G70: =E70*F70 | H70: =G70/$G$289
B71: =_xlfn.XLOOKUP(C71,'INSUMOS MAT '!B:B,'INSUMOS MAT '!C:C,"ERROR",0) | C71: MAT08-0446 | D71: =_xlfn.XLOOKUP(C71,'IKARIA TECHO'!D:D,'IKARIA TECHO'!E:E,"ERROR",0) | E71: =SUMIF('IKARIA TECHO'!D:D,ANALISIS!C71,'IKARIA TECHO'!F:F) | F71: =_xlfn.XLOOKUP(C71,'IKARIA TECHO'!D:D,'IKARIA TECHO'!H:H,"ERROR",0) | G71: =E71*F71 | H71: =G71/$G$289
B72: =_xlfn.XLOOKUP(C72,'INSUMOS MAT '!B:B,'INSUMOS MAT '!C:C,"ERROR",0) | C72: MAT19-0073 | D72: =_xlfn.XLOOKUP(C72,'IKARIA TECHO'!D:D,'IKARIA TECHO'!E:E,"ERROR",0) | E72: =SUMIF('IKARIA TECHO'!D:D,ANALISIS!C72,'IKARIA TECHO'!F:F) | F72: =_xlfn.XLOOKUP(C72,'IKARIA TECHO'!D:D,'IKARIA TECHO'!H:H,"ERROR",0) | G72: =E72*F72 | H72: =G72/$G$289
B73: =_xlfn.XLOOKUP(C73,'INSUMOS MAT '!B:B,'INSUMOS MAT '!C:C,"ERROR",0) | C73: MAT19-0072 | D73: =_xlfn.XLOOKUP(C73,'IKARIA TECHO'!D:D,'IKARIA TECHO'!E:E,"ERROR",0) | E73: =SUMIF('IKARIA TECHO'!D:D,ANALISIS!C73,'IKARIA TECHO'!F:F) | F73: =_xlfn.XLOOKUP(C73,'IKARIA TECHO'!D:D,'IKARIA TECHO'!H:H,"ERROR",0) | G73: =E73*F73 | H73: =G73/$G$289
B74: =_xlfn.XLOOKUP(C74,'INSUMOS MAT '!B:B,'INSUMOS MAT '!C:C,"ERROR",0) | C74: MAT08-0065 | D74: =_xlfn.XLOOKUP(C74,'IKARIA TECHO'!D:D,'IKARIA TECHO'!E:E,"ERROR",0) | E74: =SUMIF('IKARIA TECHO'!D:D,ANALISIS!C74,'IKARIA TECHO'!F:F) | F74: =_xlfn.XLOOKUP(C74,'IKARIA TECHO'!D:D,'IKARIA TECHO'!H:H,"ERROR",0) | G74: =E74*F74 | H74: =G74/$G$289
B75: =_xlfn.XLOOKUP(C75,'INSUMOS MAT '!B:B,'INSUMOS MAT '!C:C,"ERROR",0) | C75: MAT16-0005 | D75: =_xlfn.XLOOKUP(C75,'IKARIA TECHO'!D:D,'IKARIA TECHO'!E:E,"ERROR",0) | E75: =SUMIF('IKARIA TECHO'!D:D,ANALISIS!C75,'IKARIA TECHO'!F:F) | F75: =_xlfn.XLOOKUP(C75,'IKARIA TECHO'!D:D,'IKARIA TECHO'!H:H,"ERROR",0) | G75: =E75*F75 | H75: =G75/$G$289
B76: =_xlfn.XLOOKUP(C76,'INSUMOS MAT '!B:B,'INSUMOS MAT '!C:C,"ERROR",0) | C76: MAT06-0110 | D76: =_xlfn.XLOOKUP(C76,'IKARIA TECHO'!D:D,'IKARIA TECHO'!E:E,"ERROR",0) | E76: =SUMIF('IKARIA TECHO'!D:D,ANALISIS!C76,'IKARIA TECHO'!F:F) | F76: =_xlfn.XLOOKUP(C76,'IKARIA TECHO'!D:D,'IKARIA TECHO'!H:H,"ERROR",0) | G76: =E76*F76 | H76: =G76/$G$289
B77: =_xlfn.XLOOKUP(C77,'INSUMOS MAT '!B:B,'INSUMOS MAT '!C:C,"ERROR",0) | C77: MAT19-0029 | D77: =_xlfn.XLOOKUP(C77,'IKARIA TECHO'!D:D,'IKARIA TECHO'!E:E,"ERROR",0) | E77: =SUMIF('IKARIA TECHO'!D:D,ANALISIS!C77,'IKARIA TECHO'!F:F) | F77: =_xlfn.XLOOKUP(C77,'IKARIA TECHO'!D:D,'IKARIA TECHO'!H:H,"ERROR",0) | G77: =E77*F77 | H77: =G77/$G$289
B78: =_xlfn.XLOOKUP(C78,'INSUMOS MAT '!B:B,'INSUMOS MAT '!C:C,"ERROR",0) | C78: MAT21-0029 | D78: =_xlfn.XLOOKUP(C78,'IKARIA TECHO'!D:D,'IKARIA TECHO'!E:E,"ERROR",0) | E78: =SUMIF('IKARIA TECHO'!D:D,ANALISIS!C78,'IKARIA TECHO'!F:F) | F78: =_xlfn.XLOOKUP(C78,'IKARIA TECHO'!D:D,'IKARIA TECHO'!H:H,"ERROR",0) | G78: =E78*F78 | H78: =G78/$G$289
B79: =_xlfn.XLOOKUP(C79,'INSUMOS MAT '!B:B,'INSUMOS MAT '!C:C,"ERROR",0) | C79: MAT04-0061 | D79: =_xlfn.XLOOKUP(C79,'IKARIA TECHO'!D:D,'IKARIA TECHO'!E:E,"ERROR",0) | E79: =SUMIF('IKARIA TECHO'!D:D,ANALISIS!C79,'IKARIA TECHO'!F:F) | F79: =_xlfn.XLOOKUP(C79,'IKARIA TECHO'!D:D,'IKARIA TECHO'!H:H,"ERROR",0) | G79: =E79*F79 | H79: =G79/$G$289
B80: =_xlfn.XLOOKUP(C80,'INSUMOS MAT '!B:B,'INSUMOS MAT '!C:C,"ERROR",0) | C80: MAT08-0046 | D80: =_xlfn.XLOOKUP(C80,'IKARIA TECHO'!D:D,'IKARIA TECHO'!E:E,"ERROR",0) | E80: =SUMIF('IKARIA TECHO'!D:D,ANALISIS!C80,'IKARIA TECHO'!F:F) | F80: =_xlfn.XLOOKUP(C80,'IKARIA TECHO'!D:D,'IKARIA TECHO'!H:H,"ERROR",0) | G80: =E80*F80 | H80: =G80/$G$289
... B111: =_xlfn.XLOOKUP(C111,'INSUMOS MAT '!B:B,'INSUMOS MAT '!C:C,"ERROR",0) | C111: MAT16-0056 | D111: =_xlfn.XLOOKUP(C111,'IKARIA TECHO'!D:D,'IKARIA TECHO'!E:E,"ERROR",0) | E111: =SUMIF('IKARIA TECHO'!D:D,ANALISIS!C111,'IKARIA TECHO'!F:F) | F111: =_xlfn.XLOOKUP(C111,'IKARIA TECHO'!D:D,'IKARIA TECHO'!H:H,"ERROR",0) | G111: =E111*F111 | H111: =G111/$G$289
C112: MAT08-0089 | D112: =_xlfn.XLOOKUP(C112,'IKARIA TECHO'!D:D,'IKARIA TECHO'!E:E,"ERROR",0) | E112: =SUMIF('IKARIA TECHO'!D:D,ANALISIS!C112,'IKARIA TECHO'!F:F) | F112: =_xlfn.XLOOKUP(C112,'IKARIA TECHO'!D:D,'IKARIA TECHO'!H:H,"ERROR",0) | G112: =E112*F112 | H112: =G112/$G$289
B113: =_xlfn.XLOOKUP(C113,'INSUMOS MAT '!B:B,'INSUMOS MAT '!C:C,"ERROR",0) | C113: MAT08-0092 | D113: =_xlfn.XLOOKUP(C113,'IKARIA TECHO'!D:D,'IKARIA TECHO'!E:E,"ERROR",0) | E113: =SUMIF('IKARIA TECHO'!D:D,ANALISIS!C113,'IKARIA TECHO'!F:F) | F113: =_xlfn.XLOOKUP(C113,'IKARIA TECHO'!D:D,'IKARIA TECHO'!H:H,"ERROR",0) | G113: =E113*F113 | H113: =G113/$G$289
B114: =_xlfn.XLOOKUP(C114,'INSUMOS MAT '!B:B,'INSUMOS MAT '!C:C,"ERROR",0) | C114: MAT16-0018 | D114: =_xlfn.XLOOKUP(C114,'IKARIA TECHO'!D:D,'IKARIA TECHO'!E:E,"ERROR",0) | E114: =SUMIF('IKARIA TECHO'!D:D,ANALISIS!C114,'IKARIA TECHO'!F:F) | F114: =_xlfn.XLOOKUP(C114,'IKARIA TECHO'!D:D,'IKARIA TECHO'!H:H,"ERROR",0) | G114: =E114*F114 | H114: =G114/$G$289
B115: =_xlfn.XLOOKUP(C115,'INSUMOS MAT '!B:B,'INSUMOS MAT '!C:C,"ERROR",0) | C115: MAT05-0063 | D115: =_xlfn.XLOOKUP(C115,'IKARIA TECHO'!D:D,'IKARIA TECHO'!E:E,"ERROR",0) | E115: =SUMIF('IKARIA TECHO'!D:D,ANALISIS!C115,'IKARIA TECHO'!F:F) | F115: =_xlfn.XLOOKUP(C115,'IKARIA TECHO'!D:D,'IKARIA TECHO'!H:H,"ERROR",0) | G115: =E115*F115 | H115: =G115/$G$289
B116: =_xlfn.XLOOKUP(C116,'INSUMOS MAT '!B:B,'INSUMOS MAT '!C:C,"ERROR",0) | C116: MAT05-0079 | D116: =_xlfn.XLOOKUP(C116,'IKARIA TECHO'!D:D,'IKARIA TECHO'!E:E,"ERROR",0) | E116: =SUMIF('IKARIA TECHO'!D:D,ANALISIS!C116,'IKARIA TECHO'!F:F) | F116: =_xlfn.XLOOKUP(C116,'IKARIA TECHO'!D:D,'IKARIA TECHO'!H:H,"ERROR",0) | G116: =E116*F116 | H116: =G116/$G$289
B117: =_xlfn.XLOOKUP(C117,'INSUMOS MAT '!B:B,'INSUMOS MAT '!C:C,"ERROR",0) | C117: MAT21-0005 | D117: =_xlfn.XLOOKUP(C117,'IKARIA TECHO'!D:D,'IKARIA TECHO'!E:E,"ERROR",0) | E117: =SUMIF('IKARIA TECHO'!D:D,ANALISIS!C117,'IKARIA TECHO'!F:F) | F117: =_xlfn.XLOOKUP(C117,'IKARIA TECHO'!D:D,'IKARIA TECHO'!H:H,"ERROR",0) | G117: =E117*F117 | H117: =G117/$G$289
B118: =_xlfn.XLOOKUP(C118,'INSUMOS MAT '!B:B,'INSUMOS MAT '!C:C,"ERROR",0) | C118: MAT05-0080 | D118: =_xlfn.XLOOKUP(C118,'IKARIA TECHO'!D:D,'IKARIA TECHO'!E:E,"ERROR",0) | E118: =SUMIF('IKARIA TECHO'!D:D,ANALISIS!C118,'IKARIA TECHO'!F:F) | F118: =_xlfn.XLOOKUP(C118,'IKARIA TECHO'!D:D,'IKARIA TECHO'!H:H,"ERROR",0) | G118: =E118*F118 | H118: =G118/$G$289
B119: =_xlfn.XLOOKUP(C119,'INSUMOS MAT '!B:B,'INSUMOS MAT '!C:C,"ERROR",0) | C119: MAT05-0032 | D119: =_xlfn.XLOOKUP(C119,'IKARIA TECHO'!D:D,'IKARIA TECHO'!E:E,"ERROR",0) | E119: =SUMIF('IKARIA TECHO'!D:D,ANALISIS!C119,'IKARIA TECHO'!F:F) | F119: =_xlfn.XLOOKUP(C119,'IKARIA TECHO'!D:D,'IKARIA TECHO'!H:H,"ERROR",0) | G119: =E119*F119 | H119: =G119/$G$289
B120: =_xlfn.XLOOKUP(C120,'INSUMOS MAT '!B:B,'INSUMOS MAT '!C:C,"ERROR",0) | C120: MAT05-0046 | D120: =_xlfn.XLOOKUP(C120,'IKARIA TECHO'!D:D,'IKARIA TECHO'!E:E,"ERROR",0) | E120: =SUMIF('IKARIA TECHO'!D:D,ANALISIS!C120,'IKARIA TECHO'!F:F) | F120: =_xlfn.XLOOKUP(C120,'IKARIA TECHO'!D:D,'IKARIA TECHO'!H:H,"ERROR",0) | G120: =E120*F120 | H120: =G120/$G$289
B121: =_xlfn.XLOOKUP(C121,'INSUMOS MAT '!B:B,'INSUMOS MAT '!C:C,"ERROR",0) | C121: MAT05-0068 | D121: =_xlfn.XLOOKUP(C121,'IKARIA TECHO'!D:D,'IKARIA TECHO'!E:E,"ERROR",0) | E121: =SUMIF('IKARIA TECHO'!D:D,ANALISIS!C121,'IKARIA TECHO'!F:F) | F121: =_xlfn.XLOOKUP(C121,'IKARIA TECHO'!D:D,'IKARIA TECHO'!H:H,"ERROR",0) | G121: =E121*F121 | H121: =G121/$G$289
B122: =_xlfn.XLOOKUP(C122,'INSUMOS MAT '!B:B,'INSUMOS MAT '!C:C,"ERROR",0) | C122: MAT05-0069 | D122: =_xlfn.XLOOKUP(C122,'IKARIA TECHO'!D:D,'IKARIA TECHO'!E:E,"ERROR",0) | E122: =SUMIF('IKARIA TECHO'!D:D,ANALISIS!C122,'IKARIA TECHO'!F:F) | F122: =_xlfn.XLOOKUP(C122,'IKARIA TECHO'!D:D,'IKARIA TECHO'!H:H,"ERROR",0) | G122: =E122*F122 | H122: =G122/$G$289
B123: =_xlfn.XLOOKUP(C123,'INSUMOS MAT '!B:B,'INSUMOS MAT '!C:C,"ERROR",0) | C123: MAT05-0072 | D123: =_xlfn.XLOOKUP(C123,'IKARIA TECHO'!D:D,'IKARIA TECHO'!E:E,"ERROR",0) | E123: =SUMIF('IKARIA TECHO'!D:D,ANALISIS!C123,'IKARIA TECHO'!F:F) | F123: =_xlfn.XLOOKUP(C123,'IKARIA TECHO'!D:D,'IKARIA TECHO'!H:H,"ERROR",0) | G123: =E123*F123 | H123: =G123/$G$289
B124: =_xlfn.XLOOKUP(C124,'INSUMOS MAT '!B:B,'INSUMOS MAT '!C:C,"ERROR",0) | C124: MAT05-0075 | D124: =_xlfn.XLOOKUP(C124,'IKARIA TECHO'!D:D,'IKARIA TECHO'!E:E,"ERROR",0) | E124: =SUMIF('IKARIA TECHO'!D:D,ANALISIS!C124,'IKARIA TECHO'!F:F) | F124: =_xlfn.XLOOKUP(C124,'IKARIA TECHO'!D:D,'IKARIA TECHO'!H:H,"ERROR",0) | G124: =E124*F124 | H124: =G124/$G$289
... B127: =_xlfn.XLOOKUP(C127,'INSUMOS MAT '!B:B,'INSUMOS MAT '!C:C,"ERROR",0) | C127: MAT08-0335 | D127: =_xlfn.XLOOKUP(C127,'IKARIA TECHO'!D:D,'IKARIA TECHO'!E:E,"ERROR",0) | E127: =SUMIF('IKARIA TECHO'!D:D,ANALISIS!C127,'IKARIA TECHO'!F:F) | F127: =_xlfn.XLOOKUP(C127,'IKARIA TECHO'!D:D,'IKARIA TECHO'!H:H,"ERROR",0) | G127: =E127*F127 | H127: =G127/$G$289
C128: CANOA | D128: =_xlfn.XLOOKUP(C128,'IKARIA TECHO'!D:D,'IKARIA TECHO'!E:E,"ERROR",0) | E128: =SUMIF('IKARIA TECHO'!D:D,ANALISIS!C128,'IKARIA TECHO'!F:F) | F128: =_xlfn.XLOOKUP(C128,'IKARIA TECHO'!D:D,'IKARIA TECHO'!H:H,"ERROR",0) | G128: =E128*F128 | H128: =G128/$G$289
C129: BOTAGUA | D129: =_xlfn.XLOOKUP(C129,'IKARIA TECHO'!D:D,'IKARIA TECHO'!E:E,"ERROR",0) | E129: =SUMIF('IKARIA TECHO'!D:D,ANALISIS!C129,'IKARIA TECHO'!F:F) | F129: =_xlfn.XLOOKUP(C129,'IKARIA TECHO'!D:D,'IKARIA TECHO'!H:H,"ERROR",0) | G129: =E129*F129 | H129: =G129/$G$289
C130: GANCHO CANOA | D130: =_xlfn.XLOOKUP(C130,'IKARIA TECHO'!D:D,'IKARIA TECHO'!E:E,"ERROR",0) | E130: =SUMIF('IKARIA TECHO'!D:D,ANALISIS!C130,'IKARIA TECHO'!F:F) | F130: =_xlfn.XLOOKUP(C130,'IKARIA TECHO'!D:D,'IKARIA TECHO'!H:H,"ERROR",0) | G130: =E130*F130 | H130: =G130/$G$289
B131: =_xlfn.XLOOKUP(C131,'INSUMOS MAT '!B:B,'INSUMOS MAT '!C:C,"ERROR",0) | C131: MAT07-0011 | D131: =_xlfn.XLOOKUP(C131,'IKARIA TECHO'!D:D,'IKARIA TECHO'!E:E,"ERROR",0) | E131: =SUMIF('IKARIA TECHO'!D:D,ANALISIS!C131,'IKARIA TECHO'!F:F) | F131: =_xlfn.XLOOKUP(C131,'IKARIA TECHO'!D:D,'IKARIA TECHO'!H:H,"ERROR",0) | G131: =E131*F131 | H131: =G131/$G$289
B132: =_xlfn.XLOOKUP(C132,'INSUMOS MAT '!B:B,'INSUMOS MAT '!C:C,"ERROR",0) | C132: MAT07-0025 | D132: =_xlfn.XLOOKUP(C132,'IKARIA TECHO'!D:D,'IKARIA TECHO'!E:E,"ERROR",0) | E132: =SUMIF('IKARIA TECHO'!D:D,ANALISIS!C132,'IKARIA TECHO'!F:F) | F132: =_xlfn.XLOOKUP(C132,'IKARIA TECHO'!D:D,'IKARIA TECHO'!H:H,"ERROR",0) | G132: =E132*F132 | H132: =G132/$G$289
C133: MAT04-79 | D133: =_xlfn.XLOOKUP(C133,'IKARIA TECHO'!D:D,'IKARIA TECHO'!E:E,"ERROR",0) | E133: =SUMIF('IKARIA TECHO'!D:D,ANALISIS!C133,'IKARIA TECHO'!F:F) | F133: =_xlfn.XLOOKUP(C133,'IKARIA TECHO'!D:D,'IKARIA TECHO'!H:H,"ERROR",0) | G133: =E133*F133 | H133: =G133/$G$289
B134: =_xlfn.XLOOKUP(C134,'INSUMOS MAT '!B:B,'INSUMOS MAT '!C:C,"ERROR",0) | C134: MAT04-0046 | D134: =_xlfn.XLOOKUP(C134,'IKARIA TECHO'!D:D,'IKARIA TECHO'!E:E,"ERROR",0) | E134: =SUMIF('IKARIA TECHO'!D:D,ANALISIS!C134,'IKARIA TECHO'!F:F) | F134: =_xlfn.XLOOKUP(C134,'IKARIA TECHO'!D:D,'IKARIA TECHO'!H:H,"ERROR",0) | G134: =E134*F134 | H134: =G134/$G$289
B135: =_xlfn.XLOOKUP(C135,'INSUMOS MAT '!B:B,'INSUMOS MAT '!C:C,"ERROR",0) | C135: MAT07-0018 | D135: =_xlfn.XLOOKUP(C135,'IKARIA TECHO'!D:D,'IKARIA TECHO'!E:E,"ERROR",0) | E135: =SUMIF('IKARIA TECHO'!D:D,ANALISIS!C135,'IKARIA TECHO'!F:F) | F135: =_xlfn.XLOOKUP(C135,'IKARIA TECHO'!D:D,'IKARIA TECHO'!H:H,"ERROR",0) | G135: =E135*F135 | H135: =G135/$G$289
B136: =_xlfn.XLOOKUP(C136,'INSUMOS MAT '!B:B,'INSUMOS MAT '!C:C,"ERROR",0) | C136: MAT07-0029 | D136: =_xlfn.XLOOKUP(C136,'IKARIA TECHO'!D:D,'IKARIA TECHO'!E:E,"ERROR",0) | E136: =SUMIF('IKARIA TECHO'!D:D,ANALISIS!C136,'IKARIA TECHO'!F:F) | F136: =_xlfn.XLOOKUP(C136,'IKARIA TECHO'!D:D,'IKARIA TECHO'!H:H,"ERROR",0) | G136: =E136*F136 | H136: =G136/$G$289
B137: =_xlfn.XLOOKUP(C137,'INSUMOS MAT '!B:B,'INSUMOS MAT '!C:C,"ERROR",0) | C137: MAT07-0027 | D137: =_xlfn.XLOOKUP(C137,'IKARIA TECHO'!D:D,'IKARIA TECHO'!E:E,"ERROR",0) | E137: =SUMIF('IKARIA TECHO'!D:D,ANALISIS!C137,'IKARIA TECHO'!F:F) | F137: =_xlfn.XLOOKUP(C137,'IKARIA TECHO'!D:D,'IKARIA TECHO'!H:H,"ERROR",0) | G137: =E137*F137 | H137: =G137/$G$289
B138: =_xlfn.XLOOKUP(C138,'INSUMOS MAT '!B:B,'INSUMOS MAT '!C:C,"ERROR",0) | C138: MAT07-0020 | D138: =_xlfn.XLOOKUP(C138,'IKARIA TECHO'!D:D,'IKARIA TECHO'!E:E,"ERROR",0) | E138: =SUMIF('IKARIA TECHO'!D:D,ANALISIS!C138,'IKARIA TECHO'!F:F) | F138: =_xlfn.XLOOKUP(C138,'IKARIA TECHO'!D:D,'IKARIA TECHO'!H:H,"ERROR",0) | G138: =E138*F138 | H138: =G138/$G$289
B139: =_xlfn.XLOOKUP(C139,'INSUMOS MAT '!B:B,'INSUMOS MAT '!C:C,"ERROR",0) | C139: MAT07-0007 | D139: =_xlfn.XLOOKUP(C139,'IKARIA TECHO'!D:D,'IKARIA TECHO'!E:E,"ERROR",0) | E139: =SUMIF('IKARIA TECHO'!D:D,ANALISIS!C139,'IKARIA TECHO'!F:F) | F139: =_xlfn.XLOOKUP(C139,'IKARIA TECHO'!D:D,'IKARIA TECHO'!H:H,"ERROR",0) | G139: =E139*F139 | H139: =G139/$G$289
B140: =_xlfn.XLOOKUP(C140,'INSUMOS MAT '!B:B,'INSUMOS MAT '!C:C,"ERROR",0) | C140: MAT07-0001 | D140: =_xlfn.XLOOKUP(C140,'IKARIA TECHO'!D:D,'IKARIA TECHO'!E:E,"ERROR",0) | E140: =SUMIF('IKARIA TECHO'!D:D,ANALISIS!C140,'IKARIA TECHO'!F:F) | F140: =_xlfn.XLOOKUP(C140,'IKARIA TECHO'!D:D,'IKARIA TECHO'!H:H,"ERROR",0) | G140: =E140*F140 | H140: =G140/$G$289
B141: =_xlfn.XLOOKUP(C141,'INSUMOS MAT '!B:B,'INSUMOS MAT '!C:C,"ERROR",0) | C141: MAT07-0003 | D141: =_xlfn.XLOOKUP(C141,'IKARIA TECHO'!D:D,'IKARIA TECHO'!E:E,"ERROR",0) | E141: =SUMIF('IKARIA TECHO'!D:D,ANALISIS!C141,'IKARIA TECHO'!F:F) | F141: =_xlfn.XLOOKUP(C141,'IKARIA TECHO'!D:D,'IKARIA TECHO'!H:H,"ERROR",0) | G141: =E141*F141 | H141: =G141/$G$289
B142: =_xlfn.XLOOKUP(C142,'INSUMOS MAT '!B:B,'INSUMOS MAT '!C:C,"ERROR",0) | C142: MAT07-0010 | D142: =_xlfn.XLOOKUP(C142,'IKARIA TECHO'!D:D,'IKARIA TECHO'!E:E,"ERROR",0) | E142: =SUMIF('IKARIA TECHO'!D:D,ANALISIS!C142,'IKARIA TECHO'!F:F) | F142: =_xlfn.XLOOKUP(C142,'IKARIA TECHO'!D:D,'IKARIA TECHO'!H:H,"ERROR",0) | G142: =E142*F142 | H142: =G142/$G$289
B143: =_xlfn.XLOOKUP(C143,'INSUMOS MAT '!B:B,'INSUMOS MAT '!C:C,"ERROR",0) | C143: MAT07-0024 | D143: =_xlfn.XLOOKUP(C143,'IKARIA TECHO'!D:D,'IKARIA TECHO'!E:E,"ERROR",0) | E143: =SUMIF('IKARIA TECHO'!D:D,ANALISIS!C143,'IKARIA TECHO'!F:F) | F143: =_xlfn.XLOOKUP(C143,'IKARIA TECHO'!D:D,'IKARIA TECHO'!H:H,"ERROR",0) | G143: =E143*F143 | H143: =G143/$G$289
B144: =_xlfn.XLOOKUP(C144,'INSUMOS MAT '!B:B,'INSUMOS MAT '!C:C,"ERROR",0) | C144: MAT08-0026 | D144: =_xlfn.XLOOKUP(C144,'IKARIA TECHO'!D:D,'IKARIA TECHO'!E:E,"ERROR",0) | E144: =SUMIF('IKARIA TECHO'!D:D,ANALISIS!C144,'IKARIA TECHO'!F:F) | F144: =_xlfn.XLOOKUP(C144,'IKARIA TECHO'!D:D,'IKARIA TECHO'!H:H,"ERROR",0) | G144: =E144*F144 | H144: =G144/$G$289
B145: =_xlfn.XLOOKUP(C145,'INSUMOS MAT '!B:B,'INSUMOS MAT '!C:C,"ERROR",0) | C145: MAT08-0120 | D145: =_xlfn.XLOOKUP(C145,'IKARIA TECHO'!D:D,'IKARIA TECHO'!E:E,"ERROR",0) | E145: =SUMIF('IKARIA TECHO'!D:D,ANALISIS!C145,'IKARIA TECHO'!F:F) | F145: =_xlfn.XLOOKUP(C145,'IKARIA TECHO'!D:D,'IKARIA TECHO'!H:H,"ERROR",0) | G145: =E145*F145 | H145: =G145/$G$289
... B160: =_xlfn.XLOOKUP(C160,'INSUMOS MAT '!B:B,'INSUMOS MAT '!C:C,"ERROR",0) | C160: MAT08-0039 | D160: =_xlfn.XLOOKUP(C160,'IKARIA TECHO'!D:D,'IKARIA TECHO'!E:E,"ERROR",0) | E160: =SUMIF('IKARIA TECHO'!D:D,ANALISIS!C160,'IKARIA TECHO'!F:F) | F160: =_xlfn.XLOOKUP(C160,'IKARIA TECHO'!D:D,'IKARIA TECHO'!H:H,"ERROR",0) | G160: =E160*F160 | H160: =G160/$G$289
C161: TABLATECK 1 | D161: =_xlfn.XLOOKUP(C161,'IKARIA TECHO'!D:D,'IKARIA TECHO'!E:E,"ERROR",0) | E161: =SUMIF('IKARIA TECHO'!D:D,ANALISIS!C161,'IKARIA TECHO'!F:F) | F161: =_xlfn.XLOOKUP(C161,'IKARIA TECHO'!D:D,'IKARIA TECHO'!H:H,"ERROR",0) | G161: =E161*F161 | H161: =G161/$G$289
C162: TABLATECK 2 | D162: =_xlfn.XLOOKUP(C162,'IKARIA TECHO'!D:D,'IKARIA TECHO'!E:E,"ERROR",0) | E162: =SUMIF('IKARIA TECHO'!D:D,ANALISIS!C162,'IKARIA TECHO'!F:F) | F162: =_xlfn.XLOOKUP(C162,'IKARIA TECHO'!D:D,'IKARIA TECHO'!H:H,"ERROR",0) | G162: =E162*F162 | H162: =G162/$G$289
C163: TABLATECK 3 | D163: =_xlfn.XLOOKUP(C163,'IKARIA TECHO'!D:D,'IKARIA TECHO'!E:E,"ERROR",0) | E163: =SUMIF('IKARIA TECHO'!D:D,ANALISIS!C163,'IKARIA TECHO'!F:F) | F163: =_xlfn.XLOOKUP(C163,'IKARIA TECHO'!D:D,'IKARIA TECHO'!H:H,"ERROR",0) | G163: =E163*F163 | H163: =G163/$G$289
B164: =_xlfn.XLOOKUP(C164,'INSUMOS MAT '!B:B,'INSUMOS MAT '!C:C,"ERROR",0) | C164: MAT17-0066 | D164: =_xlfn.XLOOKUP(C164,'IKARIA TECHO'!D:D,'IKARIA TECHO'!E:E,"ERROR",0) | E164: =SUMIF('IKARIA TECHO'!D:D,ANALISIS!C164,'IKARIA TECHO'!F:F) | F164: =_xlfn.XLOOKUP(C164,'IKARIA TECHO'!D:D,'IKARIA TECHO'!H:H,"ERROR",0) | G164: =E164*F164 | H164: =G164/$G$289
C165: TABLATECK 4 | D165: =_xlfn.XLOOKUP(C165,'IKARIA TECHO'!D:D,'IKARIA TECHO'!E:E,"ERROR",0) | E165: =SUMIF('IKARIA TECHO'!D:D,ANALISIS!C165,'IKARIA TECHO'!F:F) | F165: =_xlfn.XLOOKUP(C165,'IKARIA TECHO'!D:D,'IKARIA TECHO'!H:H,"ERROR",0) | G165: =E165*F165 | H165: =G165/$G$289
C166: TABLATECK 5 | D166: =_xlfn.XLOOKUP(C166,'IKARIA TECHO'!D:D,'IKARIA TECHO'!E:E,"ERROR",0) | E166: =SUMIF('IKARIA TECHO'!D:D,ANALISIS!C166,'IKARIA TECHO'!F:F) | F166: =_xlfn.XLOOKUP(C166,'IKARIA TECHO'!D:D,'IKARIA TECHO'!H:H,"ERROR",0) | G166: =E166*F166 | H166: =G166/$G$289
C167: TABLATECK 6 | D167: =_xlfn.XLOOKUP(C167,'IKARIA TECHO'!D:D,'IKARIA TECHO'!E:E,"ERROR",0) | E167: =SUMIF('IKARIA TECHO'!D:D,ANALISIS!C167,'IKARIA TECHO'!F:F) | F167: =_xlfn.XLOOKUP(C167,'IKARIA TECHO'!D:D,'IKARIA TECHO'!H:H,"ERROR",0) | G167: =E167*F167 | H167: =G167/$G$289
C168: MAT21-0015 | D168: =_xlfn.XLOOKUP(C168,'IKARIA TECHO'!D:D,'IKARIA TECHO'!E:E,"ERROR",0) | E168: =SUMIF('IKARIA TECHO'!D:D,ANALISIS!C168,'IKARIA TECHO'!F:F) | F168: =_xlfn.XLOOKUP(C168,'IKARIA TECHO'!D:D,'IKARIA TECHO'!H:H,"ERROR",0) | G168: =E168*F168 | H168: =G168/$G$289
C169: TABLATECK 7 | D169: =_xlfn.XLOOKUP(C169,'IKARIA TECHO'!D:D,'IKARIA TECHO'!E:E,"ERROR",0) | E169: =SUMIF('IKARIA TECHO'!D:D,ANALISIS!C169,'IKARIA TECHO'!F:F) | F169: =_xlfn.XLOOKUP(C169,'IKARIA TECHO'!D:D,'IKARIA TECHO'!H:H,"ERROR",0) | G169: =E169*F169 | H169: =G169/$G$289
C170: TABLATECK 8 | D170: =_xlfn.XLOOKUP(C170,'IKARIA TECHO'!D:D,'IKARIA TECHO'!E:E,"ERROR",0) | E170: =SUMIF('IKARIA TECHO'!D:D,ANALISIS!C170,'IKARIA TECHO'!F:F) | F170: =_xlfn.XLOOKUP(C170,'IKARIA TECHO'!D:D,'IKARIA TECHO'!H:H,"ERROR",0) | G170: =E170*F170 | H170: =G170/$G$289
B171: =_xlfn.XLOOKUP(C171,'INSUMOS MAT '!B:B,'INSUMOS MAT '!C:C,"ERROR",0) | C171: MAT14-0005 | D171: =_xlfn.XLOOKUP(C171,'IKARIA TECHO'!D:D,'IKARIA TECHO'!E:E,"ERROR",0) | E171: =SUMIF('IKARIA TECHO'!D:D,ANALISIS!C171,'IKARIA TECHO'!F:F) | F171: =_xlfn.XLOOKUP(C171,'IKARIA TECHO'!D:D,'IKARIA TECHO'!H:H,"ERROR",0) | G171: =E171*F171 | H171: =G171/$G$289
B172: =_xlfn.XLOOKUP(C172,'INSUMOS MAT '!B:B,'INSUMOS MAT '!C:C,"ERROR",0) | C172: MAT14-0016 | D172: =_xlfn.XLOOKUP(C172,'IKARIA TECHO'!D:D,'IKARIA TECHO'!E:E,"ERROR",0) | E172: =SUMIF('IKARIA TECHO'!D:D,ANALISIS!C172,'IKARIA TECHO'!F:F) | F172: =_xlfn.XLOOKUP(C172,'IKARIA TECHO'!D:D,'IKARIA TECHO'!H:H,"ERROR",0) | G172: =E172*F172 | H172: =G172/$G$289
C173: MAT14-0037 | D173: =_xlfn.XLOOKUP(C173,'IKARIA TECHO'!D:D,'IKARIA TECHO'!E:E,"ERROR",0) | E173: =SUMIF('IKARIA TECHO'!D:D,ANALISIS!C173,'IKARIA TECHO'!F:F) | F173: =_xlfn.XLOOKUP(C173,'IKARIA TECHO'!D:D,'IKARIA TECHO'!H:H,"ERROR",0) | G173: =E173*F173 | H173: =G173/$G$289
B174: =_xlfn.XLOOKUP(C174,'INSUMOS MAT '!B:B,'INSUMOS MAT '!C:C,"ERROR",0) | C174: MAT14-0022 | D174: =_xlfn.XLOOKUP(C174,'IKARIA TECHO'!D:D,'IKARIA TECHO'!E:E,"ERROR",0) | E174: =SUMIF('IKARIA TECHO'!D:D,ANALISIS!C174,'IKARIA TECHO'!F:F) | F174: =_xlfn.XLOOKUP(C174,'IKARIA TECHO'!D:D,'IKARIA TECHO'!H:H,"ERROR",0) | G174: =E174*F174 | H174: =G174/$G$289
B175: =_xlfn.XLOOKUP(C175,'INSUMOS MAT '!B:B,'INSUMOS MAT '!C:C,"ERROR",0) | C175: MAT14-0023 | D175: =_xlfn.XLOOKUP(C175,'IKARIA TECHO'!D:D,'IKARIA TECHO'!E:E,"ERROR",0) | E175: =SUMIF('IKARIA TECHO'!D:D,ANALISIS!C175,'IKARIA TECHO'!F:F) | F175: =_xlfn.XLOOKUP(C175,'IKARIA TECHO'!D:D,'IKARIA TECHO'!H:H,"ERROR",0) | G175: =E175*F175 | H175: =G175/$G$289
B176: =_xlfn.XLOOKUP(C176,'INSUMOS MAT '!B:B,'INSUMOS MAT '!C:C,"ERROR",0) | C176: MAT14-0035 | D176: =_xlfn.XLOOKUP(C176,'IKARIA TECHO'!D:D,'IKARIA TECHO'!E:E,"ERROR",0) | E176: =SUMIF('IKARIA TECHO'!D:D,ANALISIS!C176,'IKARIA TECHO'!F:F) | F176: =_xlfn.XLOOKUP(C176,'IKARIA TECHO'!D:D,'IKARIA TECHO'!H:H,"ERROR",0) | G176: =E176*F176 | H176: =G176/$G$289
B177: =_xlfn.XLOOKUP(C177,'INSUMOS MAT '!B:B,'INSUMOS MAT '!C:C,"ERROR",0) | C177: MAT14-0034 | D177: =_xlfn.XLOOKUP(C177,'IKARIA TECHO'!D:D,'IKARIA TECHO'!E:E,"ERROR",0) | E177: =SUMIF('IKARIA TECHO'!D:D,ANALISIS!C177,'IKARIA TECHO'!F:F) | F177: =_xlfn.XLOOKUP(C177,'IKARIA TECHO'!D:D,'IKARIA TECHO'!H:H,"ERROR",0) | G177: =E177*F177 | H177: =G177/$G$289
B178: =_xlfn.XLOOKUP(C178,'INSUMOS MAT '!B:B,'INSUMOS MAT '!C:C,"ERROR",0) | C178: MAT14-0018 | D178: =_xlfn.XLOOKUP(C178,'IKARIA TECHO'!D:D,'IKARIA TECHO'!E:E,"ERROR",0) | E178: =SUMIF('IKARIA TECHO'!D:D,ANALISIS!C178,'IKARIA TECHO'!F:F) | F178: =_xlfn.XLOOKUP(C178,'IKARIA TECHO'!D:D,'IKARIA TECHO'!H:H,"ERROR",0) | G178: =E178*F178 | H178: =G178/$G$289
B179: =_xlfn.XLOOKUP(C179,'INSUMOS MAT '!B:B,'INSUMOS MAT '!C:C,"ERROR",0) | C179: MAT14-0024 | D179: =_xlfn.XLOOKUP(C179,'IKARIA TECHO'!D:D,'IKARIA TECHO'!E:E,"ERROR",0) | E179: =SUMIF('IKARIA TECHO'!D:D,ANALISIS!C179,'IKARIA TECHO'!F:F) | F179: =_xlfn.XLOOKUP(C179,'IKARIA TECHO'!D:D,'IKARIA TECHO'!H:H,"ERROR",0) | G179: =E179*F179 | H179: =G179/$G$289
B180: =_xlfn.XLOOKUP(C180,'INSUMOS MAT '!B:B,'INSUMOS MAT '!C:C,"ERROR",0) | C180: MAT14-0021 | D180: =_xlfn.XLOOKUP(C180,'IKARIA TECHO'!D:D,'IKARIA TECHO'!E:E,"ERROR",0) | E180: =SUMIF('IKARIA TECHO'!D:D,ANALISIS!C180,'IKARIA TECHO'!F:F) | F180: =_xlfn.XLOOKUP(C180,'IKARIA TECHO'!D:D,'IKARIA TECHO'!H:H,"ERROR",0) | G180: =E180*F180 | H180: =G180/$G$289
B181: =_xlfn.XLOOKUP(C181,'INSUMOS MAT '!B:B,'INSUMOS MAT '!C:C,"ERROR",0) | C181: MAT14-0006 | D181: =_xlfn.XLOOKUP(C181,'IKARIA TECHO'!D:D,'IKARIA TECHO'!E:E,"ERROR",0) | E181: =SUMIF('IKARIA TECHO'!D:D,ANALISIS!C181,'IKARIA TECHO'!F:F) | F181: =_xlfn.XLOOKUP(C181,'IKARIA TECHO'!D:D,'IKARIA TECHO'!H:H,"ERROR",0) | G181: =E181*F181 | H181: =G181/$G$289
B182: =_xlfn.XLOOKUP(C182,'INSUMOS MAT '!B:B,'INSUMOS MAT '!C:C,"ERROR",0) | C182: MAT14-0013 | D182: =_xlfn.XLOOKUP(C182,'IKARIA TECHO'!D:D,'IKARIA TECHO'!E:E,"ERROR",0) | E182: =SUMIF('IKARIA TECHO'!D:D,ANALISIS!C182,'IKARIA TECHO'!F:F) | F182: =_xlfn.XLOOKUP(C182,'IKARIA TECHO'!D:D,'IKARIA TECHO'!H:H,"ERROR",0) | G182: =E182*F182 | H182: =G182/$G$289
B183: =_xlfn.XLOOKUP(C183,'INSUMOS MAT '!B:B,'INSUMOS MAT '!C:C,"ERROR",0) | C183: MAT14-0004 | D183: =_xlfn.XLOOKUP(C183,'IKARIA TECHO'!D:D,'IKARIA TECHO'!E:E,"ERROR",0) | E183: =SUMIF('IKARIA TECHO'!D:D,ANALISIS!C183,'IKARIA TECHO'!F:F) | F183: =_xlfn.XLOOKUP(C183,'IKARIA TECHO'!D:D,'IKARIA TECHO'!H:H,"ERROR",0) | G183: =E183*F183 | H183: =G183/$G$289
B184: =_xlfn.XLOOKUP(C184,'INSUMOS MAT '!B:B,'INSUMOS MAT '!C:C,"ERROR",0) | C184: MAT14-0053 | D184: =_xlfn.XLOOKUP(C184,'IKARIA TECHO'!D:D,'IKARIA TECHO'!E:E,"ERROR",0) | E184: =SUMIF('IKARIA TECHO'!D:D,ANALISIS!C184,'IKARIA TECHO'!F:F) | F184: =_xlfn.XLOOKUP(C184,'IKARIA TECHO'!D:D,'IKARIA TECHO'!H:H,"ERROR",0) | G184: =E184*F184 | H184: =G184/$G$289
B185: =_xlfn.XLOOKUP(C185,'INSUMOS MAT '!B:B,'INSUMOS MAT '!C:C,"ERROR",0) | C185: MAT14-0020 | D185: =_xlfn.XLOOKUP(C185,'IKARIA TECHO'!D:D,'IKARIA TECHO'!E:E,"ERROR",0) | E185: =SUMIF('IKARIA TECHO'!D:D,ANALISIS!C185,'IKARIA TECHO'!F:F) | F185: =_xlfn.XLOOKUP(C185,'IKARIA TECHO'!D:D,'IKARIA TECHO'!H:H,"ERROR",0) | G185: =E185*F185 | H185: =G185/$G$289
C186: GRANITO | D186: =_xlfn.XLOOKUP(C186,'IKARIA TECHO'!D:D,'IKARIA TECHO'!E:E,"ERROR",0) | E186: =SUMIF('IKARIA TECHO'!D:D,ANALISIS!C186,'IKARIA TECHO'!F:F) | F186: =_xlfn.XLOOKUP(C186,'IKARIA TECHO'!D:D,'IKARIA TECHO'!H:H,"ERROR",0) | G186: =E186*F186 | H186: =G186/$G$289
B187: =_xlfn.XLOOKUP(C187,'INSUMOS MAT '!B:B,'INSUMOS MAT '!C:C,"ERROR",0) | C187: MAT14-0068 | D187: =_xlfn.XLOOKUP(C187,'IKARIA TECHO'!D:D,'IKARIA TECHO'!E:E,"ERROR",0) | E187: =SUMIF('IKARIA TECHO'!D:D,ANALISIS!C187,'IKARIA TECHO'!F:F) | F187: =_xlfn.XLOOKUP(C187,'IKARIA TECHO'!D:D,'IKARIA TECHO'!H:H,"ERROR",0) | G187: =E187*F187 | H187: =G187/$G$289
B188: =_xlfn.XLOOKUP(C188,'INSUMOS MAT '!B:B,'INSUMOS MAT '!C:C,"ERROR",0) | C188: MAT14-0001 | D188: =_xlfn.XLOOKUP(C188,'IKARIA TECHO'!D:D,'IKARIA TECHO'!E:E,"ERROR",0) | E188: =SUMIF('IKARIA TECHO'!D:D,ANALISIS!C188,'IKARIA TECHO'!F:F) | F188: =_xlfn.XLOOKUP(C188,'IKARIA TECHO'!D:D,'IKARIA TECHO'!H:H,"ERROR",0) | G188: =E188*F188 | H188: =G188/$G$289
B189: =_xlfn.XLOOKUP(C189,'INSUMOS MAT '!B:B,'INSUMOS MAT '!C:C,"ERROR",0) | C189: MAT14-0033 | D189: =_xlfn.XLOOKUP(C189,'IKARIA TECHO'!D:D,'IKARIA TECHO'!E:E,"ERROR",0) | E189: =SUMIF('IKARIA TECHO'!D:D,ANALISIS!C189,'IKARIA TECHO'!F:F) | F189: =_xlfn.XLOOKUP(C189,'IKARIA TECHO'!D:D,'IKARIA TECHO'!H:H,"ERROR",0) | G189: =E189*F189 | H189: =G189/$G$289
B190: =_xlfn.XLOOKUP(C190,'INSUMOS MAT '!B:B,'INSUMOS MAT '!C:C,"ERROR",0) | C190: MAT07-0031 | D190: =_xlfn.XLOOKUP(C190,'IKARIA TECHO'!D:D,'IKARIA TECHO'!E:E,"ERROR",0) | E190: =SUMIF('IKARIA TECHO'!D:D,ANALISIS!C190,'IKARIA TECHO'!F:F) | F190: =_xlfn.XLOOKUP(C190,'IKARIA TECHO'!D:D,'IKARIA TECHO'!H:H,"ERROR",0) | G190: =E190*F190 | H190: =G190/$G$289
B191: =_xlfn.XLOOKUP(C191,'INSUMOS MAT '!B:B,'INSUMOS MAT '!C:C,"ERROR",0) | C191: MAT08-0307 | D191: =_xlfn.XLOOKUP(C191,'IKARIA TECHO'!D:D,'IKARIA TECHO'!E:E,"ERROR",0) | E191: =SUMIF('IKARIA TECHO'!D:D,ANALISIS!C191,'IKARIA TECHO'!F:F) | F191: =_xlfn.XLOOKUP(C191,'IKARIA TECHO'!D:D,'IKARIA TECHO'!H:H,"ERROR",0) | G191: =E191*F191 | H191: =G191/$G$289
B192: =_xlfn.XLOOKUP(C192,'INSUMOS MAT '!B:B,'INSUMOS MAT '!C:C,"ERROR",0) | C192: MAT21-0017 | D192: =_xlfn.XLOOKUP(C192,'IKARIA TECHO'!D:D,'IKARIA TECHO'!E:E,"ERROR",0) | E192: =SUMIF('IKARIA TECHO'!D:D,ANALISIS!C192,'IKARIA TECHO'!F:F) | F192: =_xlfn.XLOOKUP(C192,'IKARIA TECHO'!D:D,'IKARIA TECHO'!H:H,"ERROR",0) | G192: =E192*F192 | H192: =G192/$G$289
B193: =_xlfn.XLOOKUP(C193,'INSUMOS MAT '!B:B,'INSUMOS MAT '!C:C,"ERROR",0) | C193: MAT07-0039 | D193: =_xlfn.XLOOKUP(C193,'IKARIA TECHO'!D:D,'IKARIA TECHO'!E:E,"ERROR",0) | E193: =SUMIF('IKARIA TECHO'!D:D,ANALISIS!C193,'IKARIA TECHO'!F:F) | F193: =_xlfn.XLOOKUP(C193,'IKARIA TECHO'!D:D,'IKARIA TECHO'!H:H,"ERROR",0) | G193: =E193*F193 | H193: =G193/$G$289
B194: =_xlfn.XLOOKUP(C194,'INSUMOS MAT '!B:B,'INSUMOS MAT '!C:C,"ERROR",0) | C194: MAT18-0007 | D194: =_xlfn.XLOOKUP(C194,'IKARIA TECHO'!D:D,'IKARIA TECHO'!E:E,"ERROR",0) | E194: =SUMIF('IKARIA TECHO'!D:D,ANALISIS!C194,'IKARIA TECHO'!F:F) | F194: =_xlfn.XLOOKUP(C194,'IKARIA TECHO'!D:D,'IKARIA TECHO'!H:H,"ERROR",0) | G194: =E194*F194 | H194: =G194/$G$289
B195: =_xlfn.XLOOKUP(C195,'INSUMOS MAT '!B:B,'INSUMOS MAT '!C:C,"ERROR",0) | C195: MAT18-0008 | D195: =_xlfn.XLOOKUP(C195,'IKARIA TECHO'!D:D,'IKARIA TECHO'!E:E,"ERROR",0) | E195: =SUMIF('IKARIA TECHO'!D:D,ANALISIS!C195,'IKARIA TECHO'!F:F) | F195: =_xlfn.XLOOKUP(C195,'IKARIA TECHO'!D:D,'IKARIA TECHO'!H:H,"ERROR",0) | G195: =E195*F195 | H195: =G195/$G$289
C196: MAT08-0499 | D196: =_xlfn.XLOOKUP(C196,'IKARIA TECHO'!D:D,'IKARIA TECHO'!E:E,"ERROR",0) | E196: =SUMIF('IKARIA TECHO'!D:D,ANALISIS!C196,'IKARIA TECHO'!F:F) | F196: =_xlfn.XLOOKUP(C196,'IKARIA TECHO'!D:D,'IKARIA TECHO'!H:H,"ERROR",0) | G196: =E196*F196 | H196: =G196/$G$289
B197: =_xlfn.XLOOKUP(C197,'INSUMOS MAT '!B:B,'INSUMOS MAT '!C:C,"ERROR",0) | C197: MAT18-0083 | D197: =_xlfn.XLOOKUP(C197,'IKARIA TECHO'!D:D,'IKARIA TECHO'!E:E,"ERROR",0) | E197: =SUMIF('IKARIA TECHO'!D:D,ANALISIS!C197,'IKARIA TECHO'!F:F) | F197: =_xlfn.XLOOKUP(C197,'IKARIA TECHO'!D:D,'IKARIA TECHO'!H:H,"ERROR",0) | G197: =E197*F197 | H197: =G197/$G$289
B198: =_xlfn.XLOOKUP(C198,'INSUMOS MAT '!B:B,'INSUMOS MAT '!C:C,"ERROR",0) | C198: MAT08-0197 | D198: =_xlfn.XLOOKUP(C198,'IKARIA TECHO'!D:D,'IKARIA TECHO'!E:E,"ERROR",0) | E198: =SUMIF('IKARIA TECHO'!D:D,ANALISIS!C198,'IKARIA TECHO'!F:F) | F198: =_xlfn.XLOOKUP(C198,'IKARIA TECHO'!D:D,'IKARIA TECHO'!H:H,"ERROR",0) | G198: =E198*F198 | H198: =G198/$G$289
B199: =_xlfn.XLOOKUP(C199,'INSUMOS MAT '!B:B,'INSUMOS MAT '!C:C,"ERROR",0) | C199: MAT18-0032 | D199: =_xlfn.XLOOKUP(C199,'IKARIA TECHO'!D:D,'IKARIA TECHO'!E:E,"ERROR",0) | E199: =SUMIF('IKARIA TECHO'!D:D,ANALISIS!C199,'IKARIA TECHO'!F:F) | F199: =_xlfn.XLOOKUP(C199,'IKARIA TECHO'!D:D,'IKARIA TECHO'!H:H,"ERROR",0) | G199: =E199*F199 | H199: =G199/$G$289
...

Sheet Gastos generales
B1: Proyecto:
B3: Gastos Generales
B4: CIERRE DE PRESUPUESTOS | D4: m2 | J4: Indirectos
B5: TC | E5: Dias | F5: Meses | G5: Semanas | J5: Mat | K5: MO sin cargas | L5: SUB
B6: Plazo de xxxx a xxxx dias | E6: 0 | F6: =+E6/30 | G6: =+F6*4.33 | J6: =SUM(J15:J89) | K6: =SUM(K15:K75) | L6: =SUM(L15:L89)
G8: MAT. | H8: M.deO. | I8: S.C. | J8: MAT. | K8: M.deO. | L8: S.C.
B9: DESCRIPCION | C9: CANT. | D9: UNID. | E9: % | F9: TOTAL | G9: UNIT. | H9: UNIT. | I9: UNIT. | J9: TOTAL | K9: TOTAL | L9: TOTAL
B11: TOTAL COSTOS DIRECTOS
B12: Costo directo Total | C12: 0 | D12: u | E12: 0 | F12: =(C12*E12/100)+C12 | G12: 0 | H12: 0 | I12: 0 | J12: =+#REF! | K12: =+#REF! | L12: =+#REF! | M12: =+J12+K12+L12 | N12: =+M12*L104
B14: INDIRECTOS DE CAMPO | C14: 0 | D14: sem
B15: Pick up proveeduría | C15: 0 | D15: viajes | E15: 0 | F15: =(C15*E15/100)+C15 | H15: 0 | I15: 30000 | J15: =+C15*G15 | K15: =+C15*H15 | L15: =+C15*I15 | M15: =+SUM(J15:L15)
B16: Traslado agregados | C16: 0 | D16: m3 | E16: 0 | F16: =(C16*E16/100)+C16 | H16: 0 | I16: 4750 | J16: =+C16*G16 | K16: =+C16*H16 | L16: =+C16*I16 | M16: =+SUM(J16:L16)
B17: Traslado cemento | C17: 0 | D17: sacos | E17: 0 | F17: =(C17*E17/100)+C17 | H17: 0 | I17: 450 | J17: =+C17*G17 | K17: =+C17*H17 | L17: =+C17*I17 | M17: =+SUM(J17:L17)
B18: Traslado block 12 | C18: 0 | D18: block | E18: 0 | F18: =(C18*E18/100)+C18 | H18: 0 | I18: 30 | J18: =+C18*G18 | K18: =+C18*H18 | L18: =+C18*I18 | M18: =+SUM(J18:L18)
B19: Traslado block 15 | C19: 0 | D19: block | E19: 0 | F19: =(C19*E19/100)+C19 | H19: 0 | I19: 40 | J19: =+C19*G19 | K19: =+C19*H19 | L19: =+C19*I19 | M19: =+SUM(J19:L19)
B20: Traslado block 20 | C20: 0 | D20: block | E20: 0 | F20: =(C20*E20/100)+C20 | H20: 0 | I20: 50 | J20: =+C20*G20 | K20: =+C20*H20 | L20: =+C20*I20 | M20: =+SUM(J20:L20)
B21: Traslado varillas | C21: 0 | D21: kg. | E21: 0 | F21: =(C21*E21/100)+C21 | H21: 0 | I21: 30 | J21: =+C21*G21 | K21: =+C21*H21 | L21: =+C21*I21 | M21: =+SUM(J21:L21)
B22: Transporte de personal en bus 10 personas | C22: 0 | D22: hora | E22: 0 | F22: =(C22*E22/100)+C22 | H22: 0 | I22: 25000 | J22: =+C22*G22 | K22: =+C22*H22 | L22: =+C22*I22 | M22: =+SUM(J22:L22)
B23: Maestro de obras | C23: 0 | D23: gb | E23: 1 | F23: =+C23*E23 | I23: 3600000 | J23: =+C23*G23 | K23: =+C23*H23 | L23: =+C23*I23 | M23: =+SUM(J23:L23)
B24: Bonificacion | C24: 0 | D24: gb | E24: 0 | F24: =(C24*E24/100)+C24 | G24: 0 | I24: 900000 | J24: =+C24*G24 | K24: =+C24*H24 | L24: =+C24*I24 | M24: =+SUM(J24:L24)
B25: Guarda (1) | C25: 0 | D25: mes | E25: 0 | F25: =(C25*E25/100)+C25 | G25: 0 | I25: 0 | J25: =+C25*G25 | K25: =+C25*H25 | L25: =+C25*I25 | M25: =+SUM(J25:L25)
B26: Limpieza | C26: 0 | D26: hr. | E26: 0 | F26: =+C26 | G26: 0 | I26: 500000 | J26: =+C26*G26 | K26: =+C26*H26 | L26: =+C26*I26 | M26: =+SUM(J26:L26)
B27: Topografo 1 hr/día | C27: 0 | D27: hr. | E27: 0 | F27: =+C27 | I27: 5830 | J27: =+C27*G27 | K27: =+C27*H27 | L27: =+C27*I27 | M27: =+SUM(J27:L27)
B28: Ayudante de Topografo 2 hr/día | C28: 0 | D28: hr. | E28: 0 | F28: =+C28 | I28: 2450 | J28: =+C28*G28 | K28: =+C28*H28 | L28: =+C28*I28 | M28: =+SUM(J28:L28)
B29: Bodeguero | C29: 0 | D29: mes | E29: 1 | F29: =+C29*E29 | H29: =1500*58*4.33 | I29: 0 | J29: =+C29*G29 | K29: =+C29*H29 | L29: =+C29*I29 | M29: =+SUM(J29:L29)
B30: Ingeniero Director | C30: 0 | D30: mes | E30: 1 | F30: =+C30*E30 | G30: 0 | H30: 0 | I30: 2350000 | J30: =+C30*G30 | K30: =+C30*H30 | L30: =+C30*I30 | M30: =+SUM(J30:L30) | N30: Salarios ingeniero
B31: Ingeniero o Arquitecto | C31: 0 | D31: mes | E31: 1 | F31: =+C31*E31 | H31: 800000 | I31: 0 | J31: =+C31*G31 | K31: =+C31*H31 | L31: =+C31*I31 | M31: =+SUM(J31:L31)
B32: Ingeniero electromecanico | C32: 0 | D32: mes | E32: 1 | F32: =+C32*E32 | H32: 95000 | I32: 0 | J32: =+C32*G32 | K32: =+C32*H32 | L32: =+C32*I32 | M32: =+SUM(J32:L32)
B33: Ingeniero electromecanico | C33: 0 | D33: mes | E33: 1 | F33: =+C33*E33 | H33: 95000 | I33: 0 | J33: =+C33*G33 | K33: =+C33*H33 | L33: =+C33*I33 | M33: =+SUM(J33:L33)
B34: Ingeniero Regente ambiental | C34: 0 | D34: mes | E34: 1 | F34: =+C34*E34 | H34: =+(1500*tc) | I34: 0 | J34: =+C34*G34 | K34: =+C34*H34 | L34: =+C34*I34 | M34: =+SUM(J34:L34)
B35: Agua | C35: 0 | D35: mes | E35: 0 | F35: =(C35*E35/100)+C35 | I35: 45000 | J35: =+C35*G35 | K35: =+C35*H35 | L35: =+C35*I35 | M35: =+SUM(J35:L35)
B36: Energía eléctrica | C36: 0 | D36: mes | E36: 0 | F36: =(C36*E36/100)+C36 | I36: 45000 | J36: =+C36*G36 | K36: =+C36*H36 | L36: =+C36*I36 | M36: =+SUM(J36:L36)
B37: Rotulacion | C37: 0 | D37: un | E37: 0 | F37: =(C37*E37/100)+C37 | I37: 150000 | J37: =+C37*G37 | K37: =+C37*H37 | L37: =+C37*I37 | M37: =+SUM(J37:L37)
B38: ZONAJE
B39: Traslados Quin. personal SJ | C39: 0 | D39: viaje | E39: 0 | F39: 1 | I39: 1000 | J39: =+C39*G39 | K39: =+C39*H39 | L39: =+C39*I39 | M39: =+SUM(J39:L39)
B40: Alquiler casa | C40: 0 | D40: mes | E40: 0 | F40: =(C40*E40/100)+C40 | I40: 350000 | J40: =+C40*G40 | K40: =+C40*H40 | L40: =+C40*I40 | M40: =+SUM(J40:L40)
B41: Traslados ingenieros 2 ingenieros | C41: 0 | D41: mes | E41: 0 | F41: =(C41*E41/100)+C41 | I41: 85000 | J41: =+C41*G41 | K41: =+C41*H41 | L41: =+C41*I41 | M41: =+SUM(J41:L41)
B42: Otros rendimiento | C42: 0 | D42: gl | E42: 0 | F42: =(C42*E42/100)+C42 | I42: 100000 | J42: =+C42*G42 | K42: =+C42*H42 | L42: =+C42*I42 | M42: =+SUM(J42:L42)
B43: Alimentación personal | C43: 0 | D43: comidas | E43: 0 | F43: =(C43*E43/100)+C43 | I43: 0 | J43: =+C43*G43 | K43: =+C43*H43 | L43: =+C43*I43 | M43: =+SUM(J43:L43)
B44: Acarreos especiales | C44: 0 | D44: viaje | E44: 0 | F44: =(C44*E44/100)+C44 | I44: 25000 | J44: =+C44*G44 | K44: =+C44*H44 | L44: =+C44*I44 | M44: =+SUM(J44:L44)
B45: INSTALACIONES PROVISIONALES
B46: Bodega | C46: 0 | D46: gl | E46: 0 | F46: =(C46*E46/100)+C46 | G46: 10000 | H46: 25000 | J46: =+C46*G46 | K46: =+C46*H46 | L46: =+C46*I46 | M46: =+SUM(J46:L46)
B47: prevista elèctrica prov | C47: 0 | D47: gl | E47: 0 | F47: =(C47*E47/100)+C47 | G47: 30000 | H47: 20000 | J47: =+C47*G47 | K47: =+C47*H47 | L47: =+C47*I47 | M47: =+SUM(J47:L47)
B48: Comedor-cocina | C48: 0 | D48: gl | E48: 0 | F48: =(C48*E48/100)+C48 | G48: 70000 | H48: 30000 | J48: =+C48*G48 | K48: =+C48*H48 | L48: =+C48*I48 | M48: =+SUM(J48:L48)
B49: Oficinas inspección | C49: 0 | D49: gl | E49: 0 | F49: =(C49*E49/100)+C49 | G49: 100000 | H49: 50000 | J49: =+C49*G49 | K49: =+C49*H49 | L49: =+C49*I49 | M49: =+SUM(J49:L49)
B50: Cerramientos provisionales | C50: 0 | D50: gl | E50: 0 | F50: =(C50*E50/100)+C50 | G50: 400000 | H50: 25000 | J50: =+C50*G50 | K50: =+C50*H50 | L50: =+C50*I50 | M50: =+SUM(J50:L50)
B51: Cabaña sanitaria | C51: 0 | D51: gl | E51: 0 | F51: =(C51*E51/100)+C51 | G51: 0 | H51: 0 | I51: 175000 | J51: =+C51*G51 | K51: =+C51*H51 | L51: =+C51*I51 | M51: =+SUM(J51:L51)
B52: Vigilancia | C52: 0 | D52: mes | E52: 0 | F52: =(C52*E52/100)+C52 | G52: 0 | H52: 0 | I52: 175000 | J52: =+C52*G52 | K52: =+C52*H52 | L52: =+C52*I52 | M52: =+SUM(J52:L52)
B53: HERRAMIENTAS Y ALQUILERES
B54: Andamios 10un | C54: 0 | D54: mes | E54: 0 | F54: 1 | G54: =30*10*610 | J54: =+C54*G54 | K54: =+C54*H54 | L54: =+C54*I54 | M54: =+SUM(J54:L54)
B55: Hidrolavadora | C55: 0 | D55: mes | E55: 0 | F55: 1 | G55: 250000 | J55: =+C55*G55 | K55: =+C55*H55 | L55: =+C55*I55 | M55: =+SUM(J55:L55)
B56: Alquiler de Grua p/entrepiso | C56: 0 | D56: dia | E56: 0 | F56: 1 | G56: 300000 | J56: =+C56*G56 | K56: =+C56*H56 | L56: =+C56*I56 | M56: =+SUM(J56:L56)
B57: Herramientas, Taladros, Cierras | C57: 0 | D57: mes | E57: 0 | F57: 1 | G57: 150000 | J57: =+C57*G57 | K57: =+C57*H57 | L57: =+C57*I57 | M57: =+SUM(J57:L57)
B58: Cascos | C58: 0 | D58: u | E58: 0 | F58: =+C58 | G58: 1800 | J58: =+C58*G58 | K58: =+C58*H58 | L58: =+C58*I58 | M58: =+SUM(J58:L58)
B59: Chalecos | C59: 0 | D59: u | E59: 0 | F59: =+C59 | G59: 1650 | J59: =+C59*G59 | K59: =+C59*H59 | L59: =+C59*I59 | M59: =+SUM(J59:L59)
B60: Protectores de ojos | C60: 0 | D60: u | E60: 0 | F60: =+C60 | G60: 526 | J60: =+C60*G60 | K60: =+C60*H60 | L60: =+C60*I60 | M60: =+SUM(J60:L60)
B61: Orejeras - Tapones | C61: 0 | D61: u | E61: 0 | F61: =+C61 | G61: 330 | J61: =+C61*G61 | K61: =+C61*H61 | L61: =+C61*I61 | M61: =+SUM(J61:L61)
B62: Guantes de Cuero | C62: 0 | D62: u | E62: 0 | F62: =+C62 | G62: 2250 | J62: =+C62*G62 | K62: =+C62*H62 | L62: =+C62*I62 | M62: =+SUM(J62:L62)
B63: Cintas para Señalización | C63: 0 | D63: rollos | E63: 0 | F63: =+C63 | G63: 5378 | J63: =+C63*G63 | K63: =+C63*H63 | L63: =+C63*I63 | M63: =+SUM(J63:L63)
B64: Rotulos | C64: =+C59 | D64: u | E64: 0 | F64: =+C64 | G64: 8500 | J64: =+C64*G64 | K64: =+C64*H64 | L64: =+C64*I64 | M64: =+SUM(J64:L64)
B65: Estañones | C65: 0 | D65: u | E65: 0 | F65: =(C65*E65/100)+C65 | G65: 5000 | J65: =+C65*G65 | K65: =+C65*H65 | L65: =+C65*I65 | M65: =+SUM(J65:L65)
B66: Carretillos | C66: 0 | D66: u | E66: 0 | F66: =(C66*E66/100)+C66 | G66: 29500 | J66: =+C66*G66 | K66: =+C66*H66 | L66: =+C66*I66 | M66: =+SUM(J66:L66)
B67: Baldes de Agua | C67: 0 | D67: u | E67: 0 | F67: =(C67*E67/100)+C67 | G67: 2100 | J67: =+C67*G67 | K67: =+C67*H67 | L67: =+C67*I67 | M67: =+SUM(J67:L67)
B68: Palas | C68: 0 | D68: u | E68: 0 | F68: =(C68*E68/100)+C68 | G68: 4827 | J68: =+C68*G68 | K68: =+C68*H68 | L68: =+C68*I68 | M68: =+SUM(J68:L68)
B69: Picos | C69: 0 | D69: u | E69: 0 | F69: =(C69*E69/100)+C69 | G69: 9930 | J69: =+C69*G69 | K69: =+C69*H69 | L69: =+C69*I69 | M69: =+SUM(J69:L69)
B70: Macanas | C70: 0 | D70: u | E70: 0 | F70: 0 | G70: 9380 | J70: =+C70*G70 | K70: =+C70*H70 | L70: =+C70*I70 | M70: =+SUM(J70:L70)
B71: Mazos | C71: 0 | D71: u | E71: 0 | F71: 0 | G71: 6891 | J71: =+C71*G71 | K71: =+C71*H71 | L71: =+C71*I71 | M71: =+SUM(J71:L71)
B72: Barras | C72: 0 | D72: u | E72: 0 | F72: 0 | G72: 15400 | J72: =+C72*G72 | K72: =+C72*H72 | L72: =+C72*I72 | M72: =+SUM(J72:L72)
B73: Vibrador 65mm | C73: 0 | D73: mes | E73: 0 | F73: 0 | G73: 76650 | J73: =+C73*G73 | K73: =+C73*H73 | L73: =+C73*I73 | M73: =+SUM(J73:L73)
B74: Batidora | C74: 0 | D74: =+D73 | E74: 0 | F74: 0 | G74: 65000 | J74: =+C74*G74 | K74: =+C74*H74 | L74: =+C74*I74 | M74: =+SUM(J74:L74)
B75: Compactadores (Brincon) | C75: 0 | D75: =+D74 | E75: 0 | F75: =(C75*E75/100)+C75 | G75: 160000 | J75: =+C75*G75 | K75: =+C75*H75 | L75: =+C75*I75 | M75: =+SUM(J75:L75)
B76: PERMISOS, C SOCIALES, POLIZAS
B77: Pòliza INS | C77: 0 | D77: gl | E77: 0 | F77: 0 | H77: =SUM(K12:K37) | I77: 0 | J77: =+C77*G77 | K77: =+C77*H77 | L77: =+C77*I77 | M77: =+SUM(J77:L77)
B78: • Certificado de Seguro de Responsabilidad Civil por lesión o muerte de terceras personas, con un monto mínimo de ¢100.000.000 (Cien millones de colones) por persona y ¢100.000.000 (Cien millones de colones) por accidente.
B79: • Certificado de Seguro de Responsabilidad Civil por daños a la propiedad de terceros, con un monto mínimo de ¢100.000.000 (Cien millones de colones).
B80: • Una póliza que proteja las obras de todo riesgo de construcción y montaje, por el monto total del Contrato.
B81: Cuotas del Instituto Nacional de Aprendizaje, del Instituto Mixto de Ayuda Social y del Banco Popular
B82: Setena | C82: 0 | D82: gl | E82: 0 | F82: 1 | I82: =2160*C5 | J82: =+C82*G82 | K82: =+C82*H82 | L82: =+C82*I82 | M82: =+SUM(J82:L82)
B83: Especies Fiscales 0,25% | C83: 0 | D83: gl | E83: 0 | F83: 1 | I83: =1645606094*0.25% | J83: =+C83*G83 | K83: =+C83*H83 | L83: =+C83*I83 | M83: =+SUM(J83:L83)
B84: Planos y presupuesto preliminar | C84: 0 | D84: gl | E84: 0 | F84: 1 | I84: 250000 | J84: =+C84*G84 | K84: =+C84*H84 | L84: =+C84*I84 | M84: =+SUM(J84:L84)
B85: Planos Constructivos 133 laminas | C85: 0 | D85: gl | E85: 0 | F85: 1 | I85: =133*1000*2 | J85: =+C85*G85 | K85: =+C85*H85 | L85: =+C85*I85 | M85: =+SUM(J85:L85)
B86: Supervisión (especializada) | C86: 0 | D86: gl | E86: 0 | F86: 0.03 | I86: =+I85 | J86: =+C86*G86 | K86: =+C86*H86 | L86: =+C86*I86 | M86: =+SUM(J86:L86)
B87: Supervisión (especializada) | C87: 0 | D87: gl | E87: 0 | F87: 0.03 | I87: =+I86 | J87: =+C87*G87 | K87: =+C87*H87 | L87: =+C87*I87 | M87: =+SUM(J87:L87)
B88: Permisos | C88: 0 | D88: gl | E88: 0 | F88: 0.0125 | I88: =+I87 | J88: =+C88*G88 | K88: =+C88*H88 | L88: =+C88*I88 | M88: =+SUM(J88:L88)
B89: Cargas Sociales cierre | C89: 0 | D89: gl | E89: 0 | F89: =0.37+0.08+0.08 | H89: =SUM(K12:K44) | J89: =+F89*G89 | K89: =+F89*H89*C89 | L89: =+F89*I89 | M89: =+SUM(J89:L89)
G91: SUB-TOTAL ACUMULADO: | J91: =SUM(J10:J90) | K91: =SUM(K10:K90) | L91: =SUM(L10:L90) | M91: =SUM(M11:M90)
L92: =+L91+K91+J91 | M92: =+L92/$C$5
G94: IMPREVISTOS 1% | K94: 0 | L94: =+$L$92*K94 | M94: =+L94/$C$5
G95: OTROS | K95: 0 | L95: =+$L$92*K95 | M95: =+L95/$C$5
G96: ADMINISTRACION 10 % | K96: 0 | L96: =+$L$92*K96 | M96: =+L96/$C$5
G97: UTILIDAD DEL CONTRATISTA 3 % | K97: 0 | L97: =+$L$92*K97 | M97: =+L97/$C$5 | N97: =+L97/plazo
G98: SEGURIDAD OCUPACIONAL 0,25% | K98: 0 | L98: =+$L$92*K98 | M98: =+L98/$C$5
G100: TOTAL | L100: =+L94+L97+L92+L98+L96 | M100: =+L100/$C$5
G102: COSTO/m2 | L102: 0 | M102: =+L102/$C$5
G104: Factor | L104: =+L100/M12

Sheet Unitarios
B2: Precios unitarios
B4: Descripcion | C4: Costo | D4: unidad
B5: Grado 40
B6: Varilla #2 | C6: 808 | D6: Var
B7: Varilla #3 Grado 40 | C7: 2175.61 | D7: Var
B8: Varilla #4 Grado 40 | C8: 3859.12 | D8: Var
B9: Varilla #5 Grado 40 | C9: 6670 | D9: Var
B10: Grado 60
B11: Varilla #2 Grado 60 | C11: =+C6 | D11: Var
B12: Varilla #3 Grado 60 | C12: 2175.61 | D12: Var
B13: Varilla #4 Grado 60 | C13: 3859.12 | D13: Var
B14: Varilla #5 Grado 60 | C14: 6740 | D14: Var
B15: Varilla #6 Grado 60 | C15: 9700 | D15: Var
B16: Varilla #7 Grado 60 | C16: 14100 | D16: Var
B17: Varilla #8 Grado 60 | C17: 18400 | D17: Var
B18: Varilla #9 Grado 60 | C18: 22000 | D18: Var
B19: Varilla #10 Grado 60 | C19: 0 | D19: Var

Sheet Electromecanico
C2: INSTALACIÓN MECÁNICA- AGUA POTABLE
C4: TUBO PVC 1/2 P/GRUESA | D4: 14 | E4: uni | G4: 3985 | I4: =F4*D4 | J4: =G4*D4 | K4: =H4*D4 | L4: =K4+J4+I4
C5: CODO 90 LISO PVC 1/2 | D5: 51 | E5: uni | G5: 220 | I5: =F5*D5 | J5: =G5*D5 | K5: =H5*D5 | L5: =K5+J5+I5
C6: CODO 45 LISO PVC 1/2 | D6: 8 | E6: uni | G6: 410 | I6: =F6*D6 | J6: =G6*D6 | K6: =H6*D6 | L6: =K6+J6+I6
C7: TEE LISA PVC 1/2 | D7: 20 | E7: uni | G7: 230 | I7: =F7*D7 | J7: =G7*D7 | K7: =H7*D7 | L7: =K7+J7+I7
C8: TAPON MACHO CON ROSCA | D8: 10 | E8: UNI | G8: 770 | I8: =F8*D8 | J8: =G8*D8 | K8: =H8*D8 | L8: =K8+J8+I8
C9: TAPON HEMBRA PVC LISO 1/2 | D9: 10 | E9: uni | G9: 140 | I9: =F9*D9 | J9: =G9*D9 | K9: =H9*D9 | L9: =K9+J9+I9
C10: TAPON HEMBRA PVC LISO 1 1/2 | D10: 30 | E10: uni | G10: 160 | I10: =F10*D10 | J10: =G10*D10 | K10: =H10*D10 | L10: =K10+J10+I10
C11: ADAPTADOR MACHO PVC 1/2 | D11: 39 | E11: uni | G11: 1140 | I11: =F11*D11 | J11: =G11*D11 | K11: =H11*D11 | L11: =K11+J11+I11
C12: UNION LISA PVC 1/2 | D12: 8 | E12: uni | G12: 254 | I12: =F12*D12 | J12: =G12*D12 | K12: =H12*D12 | L12: =K12+J12+I12
C13: TUBO CPVC 1/2 | D13: 10 | E13: uni | G13: 196 | I13: =F13*D13 | J13: =G13*D13 | K13: =H13*D13 | L13: =K13+J13+I13
C14: CODO 90 CPVC 1/2 | D14: 41 | E14: uni | G14: 357.75 | I14: =F14*D14 | J14: =G14*D14 | K14: =H14*D14 | L14: =K14+J14+I14
C15: CODO 45 CPVC 1/2 | D15: 18 | E15: uni | G15: 824 | I15: =F15*D15 | J15: =G15*D15 | K15: =H15*D15 | L15: =K15+J15+I15
C16: TEE CPVC 1/2 | D16: 15 | E16: uni | G16: 1350 | I16: =F16*D16 | J16: =G16*D16 | K16: =H16*D16 | L16: =K16+J16+I16 | O16: Mecanico | P16: Eledtrico
C17: TAPON LISO CPVC 1/2 | D17: 24 | E17: uni | G17: 1090 | I17: =F17*D17 | J17: =G17*D17 | K17: =H17*D17 | L17: =K17+J17+I17 | N17: Materiales | O17: =+J35+J64+J77 | P17: =+J115+J161
C18: ADAPTADOR MACHO CPVC 1/2 | D18: 24 | E18: uni | G18: 809 | I18: =F18*D18 | J18: =G18*D18 | K18: =H18*D18 | L18: =K18+J18+I18 | N18: MO | O18: =+I35+I64+I77 | P18: =+I115+I161
C19: ADAPTADOR HEMBRA CPVC 1/2 | D19: 5 | E19: uni | G19: 880 | I19: =F19*D19 | J19: =G19*D19 | K19: =H19*D19 | L19: =K19+J19+I19 | O19: =SUM(O17:O18) | P19: =SUM(P17:P18)
C20: UNION LISA CPVC 1/2 | D20: 6 | E20: uni | G20: 3534 | I20: =F20*D20 | J20: =G20*D20 | K20: =H20*D20 | L20: =K20+J20+I20
C21: LLAVE DE CONTROL ESCUADRA 1/2 A 1/2 | D21: 6 | E21: uni | G21: 595 | I21: =F21*D21 | J21: =G21*D21 | K21: =H21*D21 | L21: =K21+J21+I21
C22: LLAVE DE CHORRO PVC 1/2 | D22: 2 | E22: uni | G22: 2850.29 | I22: =F22*D22 | J22: =G22*D22 | K22: =H22*D22 | L22: =K22+J22+I22
C23: GRIFERIA DUCHA BREZZA MONO S/LAVAPIES EZ4015551 SSB | D23: 2 | E23: uni | G23: 4656.73 | I23: =F23*D23 | J23: =G23*D23 | K23: =H23*D23 | L23: =K23+J23+I23
C24: HIDROMETRO DE 1/2Q (12MM) ENCAPSULADO ROSCADO ARAD | D24: 1 | E24: uni | G24: 34182.5 | I24: =F24*D24 | J24: =G24*D24 | K24: =H24*D24 | L24: =K24+J24+I24
C25: PEGAMENTO PVC AZUL WETBONDING (DOBLE PROPOSITO) | D25: 1 | E25: uni | G25: 18180.15 | I25: =F25*D25 | J25: =G25*D25 | K25: =H25*D25 | L25: =K25+J25+I25
C26: CODO 1/2X90 HG | D26: 3 | E26: uni | G26: 13601 | I26: =F26*D26 | J26: =G26*D26 | K26: =H26*D26 | L26: =K26+J26+I26
C27: UNION HG 1/2 | D27: 6 | E27: uni | G27: 383.57 | I27: =F27*D27 | J27: =G27*D27 | K27: =H27*D27 | L27: =K27+J27+I27
C28: NIPLE 1/2X3 H.G. | D28: 5 | E28: uni | G28: 481.26 | I28: =F28*D28 | J28: =G28*D28 | K28: =H28*D28 | L28: =K28+J28+I28
C29: NIPLE 1/2X4 HG | D29: 15 | E29: uni | G29: 282.26 | I29: =F29*D29 | J29: =G29*D29 | K29: =H29*D29 | L29: =K29+J29+I29
C30: TEFLON CINTA 1/2 (10M) | D30: 2 | E30: uni | G30: 302.21 | I30: =F30*D30 | J30: =G30*D30 | K30: =H30*D30 | L30: =K30+J30+I30
C31: M.O. MEDIDOR DE AGUA | D31: 1 | E31: uni | F31: 25000 | I31: =F31*D31 | J31: =G31*D31 | K31: =H31*D31 | L31: =K31+J31+I31
C32: MANO DE OBRA GENERAL | D32: 1 | E32: uni | F32: 198000 | I32: =F32*D32 | J32: =G32*D32 | K32: =H32*D32 | L32: =K32+J32+I32
C33: M.O. MONTAJE MONOCOMANDOS | D33: 1 | E33: uni | F33: 27000 | I33: =F33*D33 | J33: =G33*D33 | K33: =H33*D33 | L33: =K33+J33+I33
I34: =F34*D34 | J34: =G34*D34 | K34: =H34*D34 | L34: =K34+J34+I34
C35: SUB TOTAL | I35: =SUM(I13:I34) | J35: =SUM(J4:J30) | K35: =H35*D35 | L35: =SUM(I35:K35)
C37: INSTALACIÓN MECANICA AGUAS SERVIDAS | I37: =F37*D37 | J37: =G37*D37 | K37: =H37*D37 | L37: =K37+J37+I37
I38: =F38*D38 | J38: =G38*D38 | K38: =H38*D38 | L38: =K38+J38+I38
C39: TUBO SANITARIO PVC 4 | D39: 6 | E39: uni | G39: 23000 | I39: =F39*D39 | J39: =G39*D39 | K39: =H39*D39 | L39: =K39+J39+I39
C40: CODO 90 PARED DELGADA 4 | D40: 12 | E40: uni | G40: 2780 | I40: =F40*D40 | J40: =G40*D40 | K40: =H40*D40 | L40: =K40+J40+I40
C41: CODO 45 PARED DELGADA 4 | D41: 17 | E41: uni | G41: 4501.05 | I41: =F41*D41 | J41: =G41*D41 | K41: =H41*D41 | L41: =K41+J41+I41
C42: TEE PVC 4" SANITARIA PD | D42: 7 | E42: uni | G42: 3730 | I42: =F42*D42 | J42: =G42*D42 | K42: =H42*D42 | L42: =K42+J42+I42
C43: TAPON HEMBRA PVC SANITARIO 4 | D43: 12 | E43: uni | G43: 1881.75 | I43: =F43*D43 | J43: =G43*D43 | K43: =H43*D43 | L43: =K43+J43+I43
C44: ADAPTADOR MACHO PVC 4 | D44: 12 | E44: uni | G44: 6962.48 | I44: =F44*D44 | J44: =G44*D44 | K44: =H44*D44 | L44: =K44+J44+I44
C45: UNION LISA PVC 4 | D45: 12 | E45: uni | G45: 3924 | I45: =F45*D45 | J45: =G45*D45 | K45: =H45*D45 | L45: =K45+J45+I45
C46: YEE PARED DELGADA 4 | D46: 9 | E46: uni | G46: 5020 | I46: =F46*D46 | J46: =G46*D46 | K46: =H46*D46 | L46: =K46+J46+I46
C47: REDUCCION LISA P.D. 2 A 4 | D47: 9 | E47: uni | G47: 6921 | I47: =F47*D47 | J47: =G47*D47 | K47: =H47*D47 | L47: =K47+J47+I47
C48: REDUCCION LISA P.D. 3 A 4 | D48: 7 | E48: uni | G48: 6958 | I48: =F48*D48 | J48: =G48*D48 | K48: =H48*D48 | L48: =K48+J48+I48
C49: TUBO SANITARIO PVC 2 | D49: 6 | E49: uni | G49: 4700 | I49: =F49*D49 | J49: =G49*D49 | K49: =H49*D49 | L49: =K49+J49+I49
C50: CODO 90 PARED DELGADA 2 | D50: 14 | E50: uni | G50: 1861 | I50: =F50*D50 | J50: =G50*D50 | K50: =H50*D50 | L50: =K50+J50+I50
... C59: PEGAMENTO PVC AZUL WETBONDING (DOBLE PROPOSITO) | D59: 1 | E59: uni | G59: 13716.81 | I59: =F59*D59 | J59: =G59*D59 | K59: =H59*D59 | L59: =K59+J59+I59
C60: M.O. INSTALACION SANITARIA EXTERIOR Y CAJAS REGISTRO | D60: 1 | E60: global | F60: 90000 | I60: =F60*D60 | J60: =G60*D60 | K60: =H60*D60 | L60: =K60+J60+I60
C61: M.O. INSTALACION SANITARIA LOSA | D61: 1 | E61: global | F61: 80600 | I61: =F61*D61 | J61: =G61*D61 | K61: =H61*D61 | L61: =K61+J61+I61
C62: M.O. GENERAL | D62: 1 | E62: global | F62: 286250 | I62: =F62*D62 | J62: =G62*D62 | K62: =H62*D62 | L62: =K62+J62+I62
I63: =F63*D63 | J63: =G63*D63 | K63: =H63*D63 | L63: =K63+J63+I63
C64: SUB TOTAL | I64: =SUM(I39:I63) | J64: =SUM(J39:J63) | K64: =SUM(K39:K63) | L64: =SUM(I64:K64)
C66: INSTALACIÓN MECÁNICA - PLUVIALES | I66: =F66*D66 | J66: =G66*D66 | K66: =H66*D66 | L66: =K66+J66+I66
C68: PEGAMENTO PVC AZUL WETBONDING (DOBLE PROPOSITO) | D68: 1 | E68: uni | G68: 8500 | I68: =F68*D68 | J68: =G68*D68 | K68: =H68*D68 | L68: =K68+J68+I68
C69: TUBO SANITARIO PVC 4 | D69: 2 | E69: uni | G69: 20100 | I69: =F69*D69 | J69: =G69*D69 | K69: =H69*D69 | L69: =K69+J69+I69
C70: CODO 45 PARED DELGADA 4 | D70: 6 | E70: uni | G70: 5500 | I70: =F70*D70 | J70: =G70*D70 | K70: =H70*D70 | L70: =K70+J70+I70
C71: REDUCCION LISA P.D. 3 A 4 | D71: 7 | E71: uni | G71: 5000 | I71: =F71*D71 | J71: =G71*D71 | K71: =H71*D71 | L71: =K71+J71+I71
C72: TUBO SANITARIO PVC 3 | D72: 7 | E72: uni | G72: 17700 | I72: =F72*D72 | J72: =G72*D72 | K72: =H72*D72 | L72: =K72+J72+I72
C73: CENICERO DE CONCRETO 4" | D73: 1 | E73: uni | G73: 10000 | I73: =F73*D73 | J73: =G73*D73 | K73: =H73*D73 | L73: =K73+J73+I73
C74: M.O. GENERAL | D74: 1 | E74: global | F74: 125000 | I74: =F74*D74 | J74: =G74*D74 | K74: =H74*D74 | L74: =K74+J74+I74
C75: M.O. CAJAS DE REGISTRO PLUVIAL | D75: 5 | E75: uni | F75: 12630 | I75: =F75*D75 | J75: =G75*D75 | K75: =H75*D75 | L75: =K75+J75+I75
C77: SUB TOTAL | I77: =SUM(I68:I76) | J77: =SUM(J68:J76) | K77: =SUM(K52:K76) | L77: =SUM(I77:K77)
C79: INSTALACIÓN ELECTRICA-ACOMETIDAS / TELECOMUNICACIONES
C81: CENTRO DE CARGA QO124L125PG | D81: 1 | E81: uni | G81: 56402.44 | I81: =F81*D81 | J81: =G81*D81 | K81: =H81*D81 | L81: =K81+J81+I81
C82: BREAKER 2/100AMP QOM100VH CENTRO CARGA | D82: 1 | E82: uni | G82: 23521.88 | I82: =F82*D82 | J82: =G82*D82 | K82: =H82*D82 | L82: =K82+J82+I82
C83: BREAKER QO120PDF DUAL 20AMP | D83: 8 | E83: uni | G83: 21800 | I83: =F83*D83 | J83: =G83*D83 | K83: =H83*D83 | L83: =K83+J83+I83
C84: BREAKER QO230 2P/30AMP | D84: 2 | E84: uni | G84: 11290.5 | I84: =F84*D84 | J84: =G84*D84 | K84: =H84*D84 | L84: =K84+J84+I84
C85: BREAKER QO240 2P/40AMP | D85: 1 | E85: uni | G85: 15054 | I85: =F85*D85 | J85: =G85*D85 | K85: =H85*D85 | L85: =K85+J85+I85
C86: Calentador | D86: 1 | E86: uni | G86: =160000+30000 | I86: =F86*D86 | J86: =G86*D86 | K86: =H86*D86 | L86: =K86+J86+I86
C87: Mo Calentador | D87: 1 | E87: uni | F87: 65000 | I87: =F87*D87 | J87: =G87*D87 | K87: =H87*D87 | L87: =K87+J87+I87
C88: TUBO CONDUIT 1 1/2 UL | D88: 10 | E88: uni | G88: 5043 | I88: =F88*D88 | J88: =G88*D88 | K88: =H88*D88 | L88: =K88+J88+I88
C89: CONECTOR CONDUIT 1 1/2 UL | D89: 4 | E89: uni | G89: 1327 | I89: =F89*D89 | J89: =G89*D89 | K89: =H89*D89 | L89: =K89+J89+I89
C90: CURVA CONDUIT 1 1/2 UL | D90: 6 | E90: uni | G90: 5103 | I90: =F90*D90 | J90: =G90*D90 | K90: =H90*D90 | L90: =K90+J90+I90
C91: UNION CONDUIT 1 1/2 UL | D91: 6 | E91: uni | G91: 1122 | I91: =F91*D91 | J91: =G91*D91 | K91: =H91*D91 | L91: =K91+J91+I91
C92: CABLE ALUMINIO 1/0 SERIE 8000 | D92: 60 | E92: mts | G92: 893.83 | I92: =F92*D92 | J92: =G92*D92 | K92: =H92*D92 | L92: =K92+J92+I92
C93: CABLE DE ALUMINIO #4 SERIE 8000 | D93: 20 | E93: mts | G93: 470.44 | I93: =F93*D93 | J93: =G93*D93 | K93: =H93*D93 | L93: =K93+J93+I93
C94: ROLLO DE PIOLA | D94: 1 | E94: uni | G94: 2100 | I94: =F94*D94 | J94: =G94*D94 | K94: =H94*D94 | L94: =K94+J94+I94
C95: BASE MEDIDOR MS1254JCBM+A125+QO2100 | D95: 1 | E95: uni | G95: 61156.88 | I95: =F95*D95 | J95: =G95*D95 | K95: =H95*D95 | L95: =K95+J95+I95
C96: VARILLA COOPERWELL 5/8 3M | D96: 1 | E96: uni | G96: 11760.94 | I96: =F96*D96 | J96: =G96*D96 | K96: =H96*D96 | L96: =K96+J96+I96
C97: CAJA DE REGISTRO 30X30 PARA VARILLA COPERWELL | D97: 1 | E97: uni | G97: 4233.94 | I97: =F97*D97 | J97: =G97*D97 | K97: =H97*D97 | L97: =K97+J97+I97
C98: CONDULETA BOTAGUA 1-1/4 | D98: 1 | E98: uni | G98: 1411.31 | I98: =F98*D98 | J98: =G98*D98 | K98: =H98*D98 | L98: =K98+J98+I98
C99: TUBO EMT 11/4 | D99: 1 | E99: uni | G99: 12000 | I99: =F99*D99 | J99: =G99*D99 | K99: =H99*D99 | L99: =K99+J99+I99
... C106: CABLE THHN 6 VERDE | D106: 6 | E106: mts | G106: 1200 | I106: =F106*D106 | J106: =G106*D106 | K106: =H106*D106 | L106: =K106+J106+I106
C107: MANO DE OBRA GENERAL | D107: 1 | E107: global | F107: 55000 | I107: =F107*D107 | J107: =G107*D107 | K107: =H107*D107 | L107: =K107+J107+I107
C108: GABINETE 14" PLASTICO UL | D108: 1 | E108: uni | G108: 41600 | I108: =F108*D108 | J108: =G108*D108 | K108: =H108*D108 | L108: =K108+J108+I108
C109: TUBO CONDUIT 1 UL | D109: 8 | E109: uni | G109: 3392.9 | I109: =F109*D109 | J109: =G109*D109 | K109: =H109*D109 | L109: =K109+J109+I109
C110: CONECTOR CONDUIT 1" UL | D110: 6 | E110: uni | G110: 1194 | I110: =F110*D110 | J110: =G110*D110 | K110: =H110*D110 | L110: =K110+J110+I110
C111: CURVA CONDUIT 1 UL | D111: 2 | E111: uni | G111: 1757 | I111: =F111*D111 | J111: =G111*D111 | K111: =H111*D111 | L111: =K111+J111+I111
C112: UNION CONDUIT 1 UL | D112: 1 | E112: uni | G112: 612 | I112: =F112*D112 | J112: =G112*D112 | K112: =H112*D112 | L112: =K112+J112+I112
C113: M.O. ARMADO DE CAJA INTELIGENTE | D113: 1 | E113: global | F113: 26000 | I113: =F113*D113 | J113: =G113*D113 | K113: =H113*D113 | L113: =K113+J113+I113
C115: SUB TOTAL | I115: =SUM(I106:I114) | J115: =SUM(J81:J114) | K115: =SUM(K90:K114) | L115: =SUM(I115:K115)
C117: INSTALACIÓN ELÉCTRICA | I117: =F117*D117 | J117: =G117*D117 | K117: =H117*D117 | L117: =K117+J117+I117
I118: =F118*D118 | J118: =G118*D118 | K118: =H118*D118 | L118: =K118+J118+I118
C119: CAJA OCTAGONAL 1/2 EMT PESADAS (8 SALIDAS ) | D119: 24 | E119: uni | G119: 535.92 | I119: =F119*D119 | J119: =G119*D119 | K119: =H119*D119 | L119: =K119+J119+I119
C120: CAJA CUADRADA EMT CON HUECO DE 1/2 Y 3/4 | D120: 5 | E120: uni | G120: 752.7 | I120: =F120*D120 | J120: =G120*D120 | K120: =H120*D120 | L120: =K120+J120+I120
C121: CAJA CUADRADA EMT 4X4 DOBLE FONDO CON HUECO DE 1 | D121: 2 | E121: uni | G121: 613.8 | I121: =F121*D121 | J121: =G121*D121 | K121: =H121*D121 | L121: =K121+J121+I121
C122: CAJA CUADRADA EMT 4X4 DOBLE FONDO CON HUECO DE 3/4 | D122: 1 | E122: uni | G122: 613.8 | I122: =F122*D122 | J122: =G122*D122 | K122: =H122*D122 | L122: =K122+J122+I122
C123: TAPA CIEGA PARA CAJA OCTAGONAL | D123: 24 | E123: uni | G123: 216.4 | I123: =F123*D123 | J123: =G123*D123 | K123: =H123*D123 | L123: =K123+J123+I123
C124: TAPA CIEGA CUADRADA 4X4 EMT | D124: 3 | E124: uni | G124: 216.4 | I124: =F124*D124 | J124: =G124*D124 | K124: =H124*D124 | L124: =K124+J124+I124
...

Sheet Ventaneria
B2: Ventaneria
B3: Tipo | C3: Longitud | D3: Alto | E3: Area
B4: v1 | C4: 1.4 | D4: 1.85 | E4: =+C4*D4
B5: v2 | C5: 1.4 | D5: 1.85 | E5: =+C5*D5
B6: v3 | C6: 0.65 | D6: 0.55 | E6: =+C6*D6
B7: v4 | C7: 0.65 | D7: 0.55 | E7: =+C7*D7
B8: v4 | C8: 1.25 | D8: 0.45 | E8: =+C8*D8
D9: Area | E9: =SUM(E4:E8) | F9: =+K14 | G9: =+E9*F9
B11: Puertas
B12: Tipo | C12: Longitud | D12: Alto | E12: Area
B13: P05 | C13: 1.7 | D13: 2.15 | E13: =+C13*D13
B14: P08 | C14: 1.7 | D14: 2.1 | E14: =+C14*D14 | K14: =1072000/(E9+E17)
B15: P09 | C15: 0.8 | D15: 2.1 | E15: =+C15*D15
B16: P09 | C16: 1.45 | D16: 2.13 | E16: =+C16*D16
D17: Area | E17: =SUM(E12:E16) | F17: =+K14 | G17: =+E17*F17
F19: Hoy | G19: =+G9+G17
F21: Año 2021 | G21: 696000
F23: Diferencia | G23: =+G19-G21
G24: =+G23/G21

Sheet Puertas
B2: Puertas
B3: 2021
B4: Descripcion | C4: Cantidad | D4: Costo | E4: Total
B5: Puertas | C5: 7 | D5: 97000 | E5: =+C5*D5
D6: total | E6: =SUM(E5)
B8: 44574
B9: Descripcion | C9: Cantidad | D9: Costo | E9: Total
B10: Puertas | C10: 7 | D10: 116000 | E10: =+C10*D10
D11: total | E11: =SUM(E10)
D13: 44574 | E13: =+E11
D15: Año 2021 | E15: =+E6
D17: Diferencia | E17: =+E13-E15
E18: =+E17/E15

Sheet Enchapes
B2: Muy poco disponible
B4: Descripcion | C4: Antes | D4: Real | E4: Diferencia
B5: Enchape pisos | C5: 403000 | D5: =+#REF! | E5: =+C5-D5
B6: Enchape baños | C6: 175500 | D6: =+#REF! | E6: =+C6-D6
B7: Enchape fachadas | C7: 65000 | D7: =+#REF! | E7: =+C7-D7
E8: =SUM(E5:E7)

Sheet Hojalateria
B2: Canoa | C2: =1.15+5.45+2.7+0.91 | D2: 12000 | E2: =+C2*D2
B3: Botaguas | C3: =6.55+0.5+5.3+3.7+2.05+2.85+6.45+14.9 | D3: 8000 | E3: =+C3*D3
E4: =SUM(E2:E3)
