Workbook

Sheet ANALISIS
A1: CODIGO | B1: DESCRIPCION | C1: CANTIDAD | D1: UNIDAD | E1: PRECIO UNITARIO | F1: PRECIO TOTAL
A2: MAT01-0001 | B2: Concreto f'c 200 kg/cm2 | C2: 25.5 | D2: m³ | E2: 45000 | F2: =C2*E2
A3: MAT01-0002 | B3: Acero de refuerzo #4 | C3: 1500 | D3: kg | E3: 35 | F3: =C3*E3
A4: MAT01-0003 | B4: Bloque concreto 6" | C4: 3000 | D4: pza | E4: 12 | F4: =C4*E4
A5: MAT01-0004 | B5: Arena lavada | C5: 50 | D5: m³ | E5: 8500 | F5: =C5*E5
A6: MO01-0001 | B6: Albañilería | C6: 50 | D6: jornada | E6: 15000 | F6: =C6*E6
A7: MO01-0002 | B7: Enfierrado | C7: 30 | D7: jornada | E7: 18000 | F7: =C7*E7
E9: TOTAL: | F9: =SUM(F2:F7)

Sheet DESGLOSE
A3: N° | B3: DESCRIPCION | C3: CANTIDAD | D3: UNIDAD | E3: TOTAL MATERIAL | F3: TOTAL MANO OBRA | G3: TOTAL SUB/EQUIPOS | H3: TOTAL DIRECTO | I3: TOTAL DOLARES | J3: COSTO/M2
A4: 1 | B4: Concreto f'c 200 kg/cm2 | C4: 25.5 | D4: m³ | E4: =25.5*45000*0.6 | F4: =25.5*45000*0.35 | G4: =25.5*45000*0.05 | H4: =E4+F4+G4 | I4: =H4/505 | J4: =H4/73.7
A5: 2 | B5: Acero de refuerzo #4 | C5: 1500 | D5: kg | E5: =1500*35*0.6 | F5: =1500*35*0.35 | G5: =1500*35*0.05 | H5: =E5+F5+G5 | I5: =H5/505 | J5: =H5/73.7
A6: 3 | B6: Bloque concreto 6" | C6: 3000 | D6: pza | E6: =3000*12*0.6 | F6: =3000*12*0.35 | G6: =3000*12*0.05 | H6: =E6+F6+G6 | I6: =H6/505 | J6: =H6/73.7
A7: 4 | B7: Arena lavada | C7: 50 | D7: m³ | E7: =50*8500*0.6 | F7: =50*8500*0.35 | G7: =50*8500*0.05 | H7: =E7+F7+G7 | I7: =H7/505 | J7: =H7/73.7
A8: 5 | B8: Albañilería | C8: 50 | D8: jornada | E8: =50*15000*0.6 | F8: =50*15000*0.35 | G8: =50*15000*0.05 | H8: =E8+F8+G8 | I8: =H8/505 | J8: =H8/73.7
A9: 6 | B9: Enfierrado | C9: 30 | D9: jornada | E9: =30*18000*0.6 | F9: =30*18000*0.35 | G9: =30*18000*0.05 | H9: =E9+F9+G9 | I9: =H9/505 | J9: =H9/73.7
B11: TOTALES: | E11: =SUM(E4:E9) | F11: =SUM(F4:F9) | G11: =SUM(G4:G9) | H11: =SUM(H4:H9) | I11: =SUM(I4:I9)

Sheet Resumen Presupuesto
B1: ESTIMADO ZANTE AZOTEA | F1: TIPO CAMBIO | G1: 505
F2: AREA BASE | G2: 73.7 m²
A3: N° | B3: Actividad | C3: Cantidad | D3: Unidad | E3: COSTO M2 | F3: TOTAL
A4: 1 | B4: OBRA GRIS
A5: 1.7 | B5: MATERIALES | E5: =1661000.0/73.7 | F5: =DESGLOSE!H11
A6: 1.8 | B6: MANO DE OBRA | E6: =1290000/73.7 | F6: =DESGLOSE!H11
A8: 2 | B8: COSTOS INDIRECTOS
B9: Administración (10%) | F9: =DESGLOSE!H11*10/100
B10: Imprevistos (5%) | F10: =DESGLOSE!H11*5/100
B11: Utilidad (15%) | F11: =DESGLOSE!H11*15/100
B12: Subtotal Indirectos: | F12: =SUM(F9:F11)
B13: COSTO DE VENTA
B14: Costo de Venta (3%) | F14: =(DESGLOSE!H11+F12)*3/100
A16: 4 | B16: RUBROS FIJOS (No escalan con área)
B17: Pago Brenes | F17: 500000
B18: Total Rubros Fijos: | F18: =SUM(F17:F17)
B20: TOTAL PRESUPUESTO: | F20: =DESGLOSE!H11+F12+F14+F18
B22: COSTO POR M²: | F22: =F20/73.7 | G22: colones/m²
B24: NOTA: Sistema de Pesos (Scaling)
B25: Para escalar a otra área: nuevo_costo = peso × (nueva_area / 73.7 m²)

Sheet Gastos generales
B1: Proyecto: | C1: PRESUPUESTO INMOBILIARIO L.32
B3: Descripción | C3: % | D3: Base | E3: Total
B4: Administración | C4: 10% | D4: =DESGLOSE!H11 | E4: =D4*C4/100
B5: Imprevistos | C5: 5% | D5: =DESGLOSE!H11 | E5: =D5*C5/100
B6: Utilidad | C6: 15% | D6: =DESGLOSE!H11 | E6: =D6*C6/100
D7: TOTAL: | E7: =SUM(E4:E6)

Sheet 1_OG y 2_ACA
A1: 1_OG y 2_ACA

Sheet 3.2_MEC
A1: 3.2_MEC

Sheet 3.1_ELEC
A1: 3.1_ELEC

Sheet Descompuesto
A1: Descompuesto

Sheet Detallado
A1: Detallado

Sheet HORAS MANO DE OBRA
A1: HORAS MANO DE OBRA

Sheet ELEC
A1: ELEC

Sheet BaseDatosMuebles
A1: BaseDatosMuebles

Sheet Subc. Vent.
A1: Subc. Vent.

Sheet BASE DATOS EQUIPOS Y SUBCONTRAT
A1: BASE DATOS EQUIPOS Y SUBCONTRAT

Sheet BASE DATOS MANO DE OBRA
A1: BASE DATOS MANO DE OBRA

Sheet Unitarios
A1: Unitarios

Sheet Electromecanico
A1: Electromecanico

Sheet Ventaneria
A1: Ventaneria

Sheet Puertas
A1: Puertas

Sheet Enchapes
A1: Enchapes

Sheet Hojalateria
A1: Hojalateria

Sheet BASE DATOS PRECIOS 
A1: BASE DATOS PRECIOS

Sheet COSTOS MO CUADRILLA
A1: COSTOS MO CUADRILLA
