Workbook

Sheet ANALISIS
A1: CODIGO | B1: DESCRIPCION | C1: CANTIDAD | D1: UNIDAD | E1: PRECIO UNITARIO | F1: PRECIO TOTAL
A2: MAT01-0001 | B2: Concreto f'c 200 kg/cm2 | C2: 25.5 | D2: m³ | E2: 45000 | F2: =C2*E2
A3: MAT01-0002 | B3: Acero de refuerzo #4 | C3: 1500 | D3: kg | E3: 35 | F3: =C3*E3
A4: MAT01-0003 | B4: Bloque concreto 6" | C4: 3000 | D4: pza | E4: 12 | F4: =C4*E4
A5: MAT01-0004 | B5: Arena lavada | C5: 50 | D5: m³ | E5: 8500 | F5: =C5*E5
A6: MAT01-0005 | B6: Grava | C6: 40 | D6: m³ | E6: 9500 | F6: =C6*E6
A7: MAT01-0006 | B7: Acero #3 | C7: 800 | D7: kg | E7: 32 | F7: =C7*E7
A8: MAT01-0007 | B8: Ladrillo block 12cm | C8: 2500 | D8: pza | E8: 15 | F8: =C8*E8
A9: MAT01-0008 | B9: Cemento Portland | C9: 200 | D9: bolsa | E9: 2800 | F9: =C9*E9
A10: MO01-0001 | B10: Albañilería | C10: 60 | D10: jornada | E10: 15000 | F10: =C10*E10
A11: MO01-0002 | B11: Enfierrado | C11: 30 | D11: jornada | E11: 18000 | F11: =C11*E11
A12: MO01-0003 | B12: Formaleta | C12: 25 | D12: jornada | E12: 16000 | F12: =C12*E12
A13: MO01-0004 | B13: Fundición | C13: 20 | D13: jornada | E13: 17000 | F13: =C13*E13
... A16: FIX01 | B16: Pago Brenes | C16: 85000 | D16: global | E16: 1 | F16: =C16*E16
E18: TOTAL COSTO DIRECTO: | F18: =SUM(F2:F16)

Sheet DESGLOSE
A3: N° | B3: DESCRIPCION | C3: CANTIDAD | D3: UNIDAD | E3: TOTAL MATERIAL | F3: TOTAL MANO OBRA | G3: TOTAL SUB/EQUIPOS | H3: TOTAL DIRECTO | I3: TOTAL DOLARES
A4: 1 | B4: Concreto f'c 200 kg/cm2 | C4: 25.5 | D4: m³ | E4: =25.5*45000*0.6 | F4: =25.5*45000*0.35 | G4: =25.5*45000*0.05 | H4: =E4+F4+G4 | I4: =H4/505
A5: 2 | B5: Acero de refuerzo #4 | C5: 1500 | D5: kg | E5: =1500*35*0.6 | F5: =1500*35*0.35 | G5: =1500*35*0.05 | H5: =E5+F5+G5 | I5: =H5/505
A6: 3 | B6: Bloque concreto 6" | C6: 3000 | D6: pza | E6: =3000*12*0.6 | F6: =3000*12*0.35 | G6: =3000*12*0.05 | H6: =E6+F6+G6 | I6: =H6/505
A7: 4 | B7: Arena lavada | C7: 50 | D7: m³ | E7: =50*8500*0.6 | F7: =50*8500*0.35 | G7: =50*8500*0.05 | H7: =E7+F7+G7 | I7: =H7/505
A8: 5 | B8: Grava | C8: 40 | D8: m³ | E8: =40*9500*0.6 | F8: =40*9500*0.35 | G8: =40*9500*0.05 | H8: =E8+F8+G8 | I8: =H8/505
A9: 6 | B9: Acero #3 | C9: 800 | D9: kg | E9: =800*32*0.6 | F9: =800*32*0.35 | G9: =800*32*0.05 | H9: =E9+F9+G9 | I9: =H9/505
A10: 7 | B10: Ladrillo block 12cm | C10: 2500 | D10: pza | E10: =2500*15*0.6 | F10: =2500*15*0.35 | G10: =2500*15*0.05 | H10: =E10+F10+G10 | I10: =H10/505
A11: 8 | B11: Cemento Portland | C11: 200 | D11: bolsa | E11: =200*2800*0.6 | F11: =200*2800*0.35 | G11: =200*2800*0.05 | H11: =E11+F11+G11 | I11: =H11/505
A12: 9 | B12: Albañilería | C12: 60 | D12: jornada | E12: =60*15000*0.6 | F12: =60*15000*0.35 | G12: =60*15000*0.05 | H12: =E12+F12+G12 | I12: =H12/505
A13: 10 | B13: Enfierrado | C13: 30 | D13: jornada | E13: =30*18000*0.6 | F13: =30*18000*0.35 | G13: =30*18000*0.05 | H13: =E13+F13+G13 | I13: =H13/505
A14: 11 | B14: Formaleta | C14: 25 | D14: jornada | E14: =25*16000*0.6 | F14: =25*16000*0.35 | G14: =25*16000*0.05 | H14: =E14+F14+G14 | I14: =H14/505
A15: 12 | B15: Fundición | C15: 20 | D15: jornada | E15: =20*17000*0.6 | F15: =20*17000*0.35 | G15: =20*17000*0.05 | H15: =E15+F15+G15 | I15: =H15/505
A16: 13 | B16: Mezcladora | C16: 15 | D16: día | E16: =15*8500*0.6 | F16: =15*8500*0.35 | G16: =15*8500*0.05 | H16: =E16+F16+G16 | I16: =H16/505
A17: 14 | B17: Vibrador | C17: 10 | D17: día | E17: =10*5000*0.6 | F17: =10*5000*0.35 | G17: =10*5000*0.05 | H17: =E17+F17+G17 | I17: =H17/505
A18: 15 | B18: Pago Brenes | C18: - | D18: - | E18: - | F18: - | G18: - | H18: =85000
B20: TOTALES: | E20: =SUM(E4:E18) | F20: =SUM(F4:F18) | G20: =SUM(G4:G18) | H20: =SUM(H4:H18) | I20: =SUM(I4:I18)

Sheet Resumen Presupuesto
B1: PRESUPUESTO INMOBILIARIO L.32 | F1: TIPO CAMBIO: | G1: 505
F2: AREA BASE (m²): | G2: 73.7
F3: AREA ACTUAL (m²): | G3: 204
F4: FACTOR ESCALA: | G4: =204.0/73.7
A6: N° | B6: DESCRIPCION | C6: MONTO
A7: 1 | B7: COSTO DIRECTO | C7: =DESGLOSE!H20
A8: 2 | B8: COSTOS INDIRECTOS
A9: 2.1 | B9: Administración (10.0%) | C9: =DESGLOSE!H20*0.1
A10: 2.2 | B10: Imprevistos (5.0%) | C10: =DESGLOSE!H20*0.05
A11: 2.3 | B11: Utilidad (15.0%) | C11: =DESGLOSE!H20*0.15
B12: TOTAL INDIRECTOS: | C12: =SUM(C9:C11)
B13: SUBTOTAL (Directo + Indirectos): | C13: =C7+C12
A14: 3 | B14: Costo de Venta (10.0%) | C14: =C13*0.1
B15: TOTAL PRESUPUESTO: | C15: =C13+C14
A16: 4 | B16: Pago Brenes (FIJO) | C16: 85000
B17: GRAN TOTAL: | C17: =C15+C16
B19: COSTO POR M²: | C19: =C17/204.0 | D19: colones/m²
B20: TOTAL EN DÓLARES: | C20: =C17/505

Sheet Gastos generales
B1: COSTOS INDIRECTOS
B3: Descripción | C3: % | D3: Base (Directo) | E3: Total
B4: Administración | C4: 10.0% | D4: =DESGLOSE!H20 | E4: =D4*C4/100
B5: Imprevistos | C5: 5.0% | D5: =DESGLOSE!H20 | E5: =D5*C5/100
B6: Utilidad | C6: 15.0% | D6: =DESGLOSE!H20 | E6: =D6*C6/100
D7: TOTAL: | E7: =SUM(E4:E6)

Sheet 1_OG y 2_ACA
A1: 1_OG y 2_ACA

Sheet 3.2_MEC
A1: 3.2_MEC

Sheet 3.1_ELEC
A1: 3.1_ELEC

Sheet Descompuesto
A1: Descompuesto

Sheet Detallado
A1: Detallado

Sheet HORAS MANO DE OBRA
A1: HORAS MANO DE OBRA

Sheet ELEC
A1: ELEC

Sheet BaseDatosMuebles
A1: BaseDatosMuebles

Sheet Subc. Vent.
A1: Subc. Vent.

Sheet BASE DATOS EQUIPOS Y SUBCONTRAT
A1: BASE DATOS EQUIPOS Y SUBCONTRAT

Sheet BASE DATOS MANO DE OBRA
A1: BASE DATOS MANO DE OBRA

Sheet Unitarios
A1: Unitarios

Sheet Electromecanico
A1: Electromecanico

Sheet Ventaneria
A1: Ventaneria

Sheet Puertas
A1: Puertas

Sheet Enchapes
A1: Enchapes

Sheet Hojalateria
A1: Hojalateria

Sheet BASE DATOS PRECIOS 
A1: BASE DATOS PRECIOS

Sheet COSTOS MO CUADRILLA
A1: COSTOS MO CUADRILLA
