Workbook
Name _Fill: #REF!
Name _Key1: #REF!
Name _Sort: #REF!
Name AR: #REF!
Name area: #REF!
Name Beginning_Balance: -FV(interest_rate/12,payment_number-1,-monthly_payment,loan_amount)
Name Beginning_Balance: -FV(interest_rate/12,payment_number-1,-monthly_payment,loan_amount)
Name Beginning_Balance: -FV(interest_rate/12,payment_number-1,-monthly_payment,loan_amount)
Name Beginning_Balance: -FV(interest_rate/12,payment_number-1,-monthly_payment,loan_amount)
Name CE: #REF!
Name cellbimuser3312070200E1100905702600: 1667853438554
Name CodigoProyecto: Descompuesto!$L$3
Name ds: Detallado!$Q$4
Name ETR: #REF!
Name FAN: '3.1_ELEC'!#REF!
Name FAN: '3.2_MEC'!#REF!
Name FAN: '1_OG y 2_ACA'!$D$112
Name FCL: '3.1_ELEC'!#REF!
Name FCL: '3.2_MEC'!#REF!
Name FCL: '1_OG y 2_ACA'!$D$95
Name FDG: '3.1_ELEC'!#REF!
Name FDG: '3.2_MEC'!#REF!
Name FDG: '1_OG y 2_ACA'!$D$96
Name FILTRAR__Cant_E__D5_D126__Cant_E__F5_F126__0: #REF!
Name KH: 'BASE DATOS EQUIPOS Y SUBCONTRAT'!$P$6
Name ListaObra: #REF!
Name ListaSubTareas: #REF!
Name losaa: '3.1_ELEC'!#REF!
Name losaa: '3.2_MEC'!#REF!
Name losaa: '1_OG y 2_ACA'!$D$102
Name losaac: '1_OG y 2_ACA'!$D$281
Name losaad: '3.1_ELEC'!#REF!
Name losaad: '3.2_MEC'!#REF!
Name losaad: '1_OG y 2_ACA'!$D$105
Name losac: '3.1_ELEC'!#REF!
Name losac: '3.2_MEC'!#REF!
Name losac: '1_OG y 2_ACA'!$D$104
Name losap: '3.1_ELEC'!#REF!
Name losap: '3.2_MEC'!#REF!
Name losap: '1_OG y 2_ACA'!$D$103
Name muroa: '3.1_ELEC'!#REF!
Name muroa: '3.2_MEC'!#REF!
Name muroa: '1_OG y 2_ACA'!$D$106
Name muroad: '3.1_ELEC'!#REF!
Name muroad: '3.2_MEC'!#REF!
Name muroad: '1_OG y 2_ACA'!$D$109
Name muroc: '3.1_ELEC'!#REF!
Name muroc: '3.2_MEC'!#REF!
Name muroc: '1_OG y 2_ACA'!$D$108
Name murof: '3.1_ELEC'!#REF!
Name murof: '3.2_MEC'!#REF!
Name murof: '1_OG y 2_ACA'!$D$110
Name murop: '3.1_ELEC'!#REF!
Name murop: '3.2_MEC'!#REF!
Name murop: '1_OG y 2_ACA'!$D$107
Name PARED_LIV_2P: #REF!
Name PARED_LIV_2P: #REF!
Name PI: #REF!
Name plazo: 'Gastos generales'!$F$6
Name plazo: #REF!

Sheet ANALISIS
C1: CODIGO | D1: DESCRIPCION | E1: CANTIDAD | F1: PRECIO UNITARIO | G1: PRECIO TOTAL | H1: % PORCENTAJE
C2: MAT01-0001 | D2: =_xlfn.XLOOKUP(C2,Detallado!C:C,Detallado!E:E,"ERROR",0) -> ERROR | E2: =SUMIF(Detallado!C:C,ANALISIS!C2,Detallado!F:F) -> 0 | F2: =_xlfn.XLOOKUP(C2,Detallado!C:C,Detallado!H:H,"ERROR",0) -> ERROR | G2: =E2*F2 -> #VALUE! | H2: =G2/$G$313 -> #VALUE! | J2: 35867.2 | K2: 35867.2 | M2: =+K2-G2 -> #VALUE!
C3: MAT01-0002 | D3: =_xlfn.XLOOKUP(C3,Detallado!C:C,Detallado!E:E,"ERROR",0) -> ERROR | E3: =SUMIF(Detallado!C:C,ANALISIS!C3,Detallado!F:F) -> 0 | F3: =_xlfn.XLOOKUP(C3,Detallado!C:C,Detallado!H:H,"ERROR",0) -> ERROR | G3: =E3*F3 -> #VALUE! | H3: =G3/$G$313 -> #VALUE! | J3: 42456 | K3: 42456 | M3: =+K3-G3 -> #VALUE!
C4: MAT01-0005 | D4: =_xlfn.XLOOKUP(C4,Detallado!C:C,Detallado!E:E,"ERROR",0) -> ERROR | E4: =SUMIF(Detallado!C:C,ANALISIS!C4,Detallado!F:F) -> 0 | F4: =_xlfn.XLOOKUP(C4,Detallado!C:C,Detallado!H:H,"ERROR",0) -> ERROR | G4: =E4*F4 -> #VALUE! | H4: =G4/$G$313 -> #VALUE! | J4: 25198.68 | K4: 0 | M4: =+K4-G4 -> #VALUE!
C5: MAT01-0006 | D5: =_xlfn.XLOOKUP(C5,Detallado!C:C,Detallado!E:E,"ERROR",0) -> ERROR | E5: =SUMIF(Detallado!C:C,ANALISIS!C5,Detallado!F:F) -> 0 | F5: =_xlfn.XLOOKUP(C5,Detallado!C:C,Detallado!H:H,"ERROR",0) -> ERROR | G5: =E5*F5 -> #VALUE! | H5: =G5/$G$313 -> #VALUE! | J5: 64593.335 | K5: 64593.335 | M5: =+K5-G5 -> #VALUE!
C6: MAT01-0007 | D6: =_xlfn.XLOOKUP(C6,Detallado!C:C,Detallado!E:E,"ERROR",0) -> ERROR | E6: =SUMIF(Detallado!C:C,ANALISIS!C6,Detallado!F:F) -> 0 | F6: =_xlfn.XLOOKUP(C6,Detallado!C:C,Detallado!H:H,"ERROR",0) -> ERROR | G6: =E6*F6 -> #VALUE! | H6: =G6/$G$313 -> #VALUE! | J6: 33640 | K6: 0 | M6: =+K6-G6 -> #VALUE!
C7: MAT01-0008 | D7: =_xlfn.XLOOKUP(C7,Detallado!C:C,Detallado!E:E,"ERROR",0) -> ERROR | E7: =SUMIF(Detallado!C:C,ANALISIS!C7,Detallado!F:F) -> 0 | F7: =_xlfn.XLOOKUP(C7,Detallado!C:C,Detallado!H:H,"ERROR",0) -> ERROR | G7: =E7*F7 -> #VALUE! | H7: =G7/$G$313 -> #VALUE! | J7: 83520 | K7: 83520 | M7: =+K7-G7 -> #VALUE!
C8: MAT01-0010 | D8: =_xlfn.XLOOKUP(C8,Detallado!C:C,Detallado!E:E,"ERROR",0) -> ERROR | E8: =SUMIF(Detallado!C:C,ANALISIS!C8,Detallado!F:F) -> 0 | F8: =_xlfn.XLOOKUP(C8,Detallado!C:C,Detallado!H:H,"ERROR",0) -> ERROR | G8: =E8*F8 -> #VALUE! | H8: =G8/$G$313 -> #VALUE! | J8: 25520 | K8: 25520 | M8: =+K8-G8 -> #VALUE!
C9: MAT01-0011 | D9: =_xlfn.XLOOKUP(C9,Detallado!C:C,Detallado!E:E,"ERROR",0) -> ERROR | E9: =SUMIF(Detallado!C:C,ANALISIS!C9,Detallado!F:F) -> 0 | F9: =_xlfn.XLOOKUP(C9,Detallado!C:C,Detallado!H:H,"ERROR",0) -> ERROR | G9: =E9*F9 -> #VALUE! | H9: =G9/$G$313 -> #VALUE! | J9: 26100 | K9: 0 | M9: =+K9-G9 -> #VALUE!
C10: MAT01-0012 | D10: =_xlfn.XLOOKUP(C10,Detallado!C:C,Detallado!E:E,"ERROR",0) -> ERROR | E10: =SUMIF(Detallado!C:C,ANALISIS!C10,Detallado!F:F) -> 0 | F10: =_xlfn.XLOOKUP(C10,Detallado!C:C,Detallado!H:H,"ERROR",0) -> ERROR | G10: =E10*F10 -> #VALUE! | H10: =G10/$G$313 -> #VALUE! | J10: 40426 | K10: 0 | M10: =+K10-G10 -> #VALUE!
C11: MAT01-0025 | D11: =_xlfn.XLOOKUP(C11,Detallado!C:C,Detallado!E:E,"ERROR",0) -> ERROR | E11: =SUMIF(Detallado!C:C,ANALISIS!C11,Detallado!F:F) -> 0 | F11: =_xlfn.XLOOKUP(C11,Detallado!C:C,Detallado!H:H,"ERROR",0) -> ERROR | G11: =E11*F11 -> #VALUE! | H11: =G11/$G$313 -> #VALUE! | J11: 102654.87 | K11: 102654.87 | M11: =+K11-G11 -> #VALUE!
C12: MAT02-0001 | D12: =_xlfn.XLOOKUP(C12,Detallado!C:C,Detallado!E:E,"ERROR",0) -> ERROR | E12: =SUMIF(Detallado!C:C,ANALISIS!C12,Detallado!F:F) -> 0 | F12: =_xlfn.XLOOKUP(C12,Detallado!C:C,Detallado!H:H,"ERROR",0) -> ERROR | G12: =E12*F12 -> #VALUE! | H12: =G12/$G$313 -> #VALUE! | J12: 866.02808 | K12: 54559.769 | M12: =+K12-G12 -> #VALUE!
C13: MAT02-0010 | D13: =_xlfn.XLOOKUP(C13,Detallado!C:C,Detallado!E:E,"ERROR",0) -> ERROR | E13: =SUMIF(Detallado!C:C,ANALISIS!C13,Detallado!F:F) -> 0 | F13: =_xlfn.XLOOKUP(C13,Detallado!C:C,Detallado!H:H,"ERROR",0) -> ERROR | G13: =E13*F13 -> #VALUE! | H13: =G13/$G$313 -> #VALUE! | J13: 27221.952 | K13: 299441.47 | M13: =+K13-G13 -> #VALUE!
... C309: TABLATECK 8 | D309: =_xlfn.XLOOKUP(C309,Detallado!C:C,Detallado!E:E,"ERROR",0) -> ERROR | E309: =SUMIF(Detallado!C:C,ANALISIS!C309,Detallado!F:F) -> 0 | F309: =_xlfn.XLOOKUP(C309,Detallado!C:C,Detallado!H:H,"ERROR",0) -> ERROR | G309: =E309*F309 -> #VALUE! | H309: =G309/$G$313 -> #VALUE! | J309: 1172.5664 | K309: 4690.2655 | M309: =+K309-G309 -> #VALUE!
D310: =_xlfn.XLOOKUP(C310,Detallado!C:C,Detallado!E:E,"ERROR",0) -> TOTAL PRESUPUESTO | E310: =SUMIF(Detallado!C:C,ANALISIS!C310,Detallado!F:F) -> 0 | F310: =_xlfn.XLOOKUP(C310,Detallado!C:C,Detallado!H:H,"ERROR",0) -> 0 | G310: =E310*F310 -> 0 | H310: =G310/$G$313 -> #VALUE!
F313: Total | G313: =SUM(G2:G312) -> #VALUE! | H313: =SUM(H2:H312) -> #VALUE!
F315: Verificacion | G315: =Detallado!K8 -> 23471758
F316: Diferencia | G316: =G313-G315 -> #VALUE!
G318: 15693774

Sheet DESGLOSE
A3: N° | B3: DESCRIPCION | C3: CANTIDAD | D3: UNIDAD | E3: TOTAL MATERIAL | F3: TOTAL MANO DE OBRA | G3: TOTAL SUB/EQUIPOS | H3: TOTAL DIRECTO COLONES | I3: TOTAL DÓLARES | J3: COSTO/M2
A4: 1 | B4: FUNDACIONES | C4: =+'1_OG y 2_ACA'!D12 -> 48.12 | D4: m2 | E4: =SUM(E5:E8) -> 1835286.7 | F4: =SUM(F5:F8) -> 1179900 | G4: =SUM(G5:G8) -> 151000 | H4: =SUM(H5:H8) -> 3166186.7 | I4: =SUM(I5:I8) -> 6147.9354 | J4: =H4/C4 -> 65797.729
A5: 1.1 | B5: OBRAS PRELIMINARES Y RELLENOS | C5: =+C4 -> 48.12 | D5: m2 | E5: =Detallado!K11 -> 276899.83 | F5: =Detallado!L11 -> 168187.5 | G5: =Detallado!M11 -> 151000 | H5: =Detallado!N11 -> 596087.33 | I5: =Detallado!O11 -> 1157.4511 | J5: =H5/C5 -> 12387.517
A6: 1.2 | B6: EXCAVACIÓN Y TUBERÍAS MECÁNICAS (INCLUYE ACOMETIDA) | C6: =+C4 -> 48.12 | D6: m2 | E6: =Detallado!K21 -> 13982.942 | F6: =Detallado!L21 -> 131962.5 | G6: =Detallado!M21 -> 0 | H6: =Detallado!N21 -> 145945.44 | I6: =Detallado!O21 -> 283.38921 | J6: =H6/C6 -> 3032.9477
A7: 1.3 | B7: SELLO DE CONCRETO | C7: =+C4 -> 48.12 | D7: m2 | E7: =Detallado!K28 -> 157774.98 | F7: =Detallado!L28 -> 23287.5 | G7: =Detallado!M28 -> 0 | H7: =Detallado!N28 -> 181062.48 | I7: =Detallado!O28 -> 351.57762 | J7: =H7/C7 -> 3762.7281
A8: 1.4 | B8: LOSA FLOTANTE (ACERO, ELECTROMECANICOS, CONCRETO) | C8: =+C4 -> 48.12 | D8: m2 | E8: =Detallado!K37 -> 1386629 | F8: =Detallado!L37 -> 856462.5 | G8: =Detallado!M37 -> 0 | H8: =Detallado!N37 -> 2243091.5 | I8: =Detallado!O37 -> 4355.5174 | J8: =H8/C8 -> 46614.536 | L8: MAT | M8: M.O
A9: 2 | B9: SUPERESTRUCTURA PRIMER NIVEL | C9: =C10 -> 129.48 | D9: m2 | E9: =SUM(E10:E12) -> 2432321.8 | F9: =SUM(F10:F12) -> 2093287.5 | G9: =SUM(G10:G12) -> 276815.7 | H9: =SUM(H10:H12) -> 4802425 | I9: =SUM(I10:I12) -> 9325.097 | J9: =H9/C9 -> 37090.091 | L9: 2702858.3 | M9: 959962.5
A10: 2.1 | B10: ACERO EN PAREDES MUROS N1 (ELECTROMECANICO) | C10: =+'1_OG y 2_ACA'!D343 -> 129.48 | D10: m2 | E10: =Detallado!K55 -> 704662.5 | F10: =Detallado!L55 -> 1112625 | G10: =Detallado!M55 -> 0 | H10: =Detallado!N55 -> 1817287.5 | I10: =Detallado!O55 -> 3528.7136 | J10: =H10/C10 -> 14035.276 | K10: ACERO Y CONCRETO | L10: =+L9-E9 -> 270536.54 | M10: =+M9-F9 -> -1133325
A11: 2.2 | B11: PAREDES, MUROS, ENTREPISO N1 (FORMALETA, CONCRETO, DESENCOFRADO) | C11: =+C10 -> 129.48 | D11: m2 | E11: =Detallado!K68 -> 1727659.3 | F11: =Detallado!L68 -> 980662.5 | G11: =Detallado!M68 -> 276815.7 | H11: =Detallado!N68 -> 2985137.5 | I11: =Detallado!O68 -> 5796.3834 | J11: =H11/C11 -> 23054.815 | K11: ACABADO AZOTEA
A12: 2.3 | B12: MAMPOSTERIA | C12: 1 | D12: Global | E12: =Detallado!K84 -> 0 | F12: =Detallado!L84 -> 0 | G12: =Detallado!M84 -> 0 | H12: =Detallado!N84 -> 0 | I12: =Detallado!O84 -> 0 | J12: =H12/C12 -> 0
A13: 3 | B13: SUPERESTRUCTURA SEGUNDO NIVEL | C13: 1 | D13: Global | E13: =SUM(E14:E15) -> 1979575 | F13: =SUM(F14:F15) -> 1283400 | G13: =SUM(G14:G15) -> 254144.45 | H13: =SUM(H14:H15) -> 3570907.5 | I13: =SUM(I14:I15) -> 6829.3582 | J13: =H13/C13 -> 3570907.5
A14: 3.1 | B14: ACERO EN PAREDES MUROS N2 (ELECTROMECANICO) | C14: 1 | D14: Global | E14: =Detallado!K89 -> 423822.75 | F14: =Detallado!L89 -> 859050 | G14: =Detallado!M89 -> 0 | H14: =Detallado!N89 -> 1336660.7 | I14: =Detallado!O89 -> 2491.015 | J14: =H14/C14 -> 1336660.7
A15: 3.2 | B15: PAREDES, MUROS, ENTREPISO N2 (FORMALETA, CONCRETO, DESENCOFRADO) | C15: 1 | D15: Global | E15: =Detallado!K101 -> 1555752.3 | F15: =Detallado!L101 -> 424350 | G15: =Detallado!M101 -> 254144.45 | H15: =Detallado!N101 -> 2234246.7 | I15: =Detallado!O101 -> 4338.3432 | J15: =H15/C15 -> 2234246.7
A16: 4 | B16: OTROS GRIS | C16: 1 | D16: Global | E16: =SUM(E17:E19) -> 1212110.7 | F16: =SUM(F17:F19) -> 1304100 | G16: =SUM(G17:G19) -> 59260.2 | H16: =SUM(H17:H19) -> 2575470.9 | I16: =SUM(I17:I19) -> 5000.9143 | J16: =H16/C16 -> 2575470.9
A17: 4.1 | B17: GRADAS EN CONCRETO | C17: 1 | D17: Global | E17: =Detallado!K254 -> 341339.46 | F17: =Detallado!L254 -> 543375 | G17: =Detallado!M254 -> 44260.2 | H17: =Detallado!N254 -> 928974.66 | I17: =Detallado!O254 -> 1803.8343 | J17: =H17/C17 -> 928974.66
A18: 4.2 | B18: COLUMNAS (MEDIDOR) | C18: 1 | D18: Global | E18: =Detallado!K269 -> 89072.417 | F18: =Detallado!L269 -> 152662.5 | G18: =Detallado!M269 -> 0 | H18: =Detallado!N269 -> 241734.92 | I18: =Detallado!O269 -> 469.38819 | J18: =H18/C18 -> 241734.92
A19: 4.3 | B19: CHORREA DE COCHERAS Y PILAS | C19: 33.01 | D19: m2 | E19: =Detallado!K282 -> 781698.78 | F19: =Detallado!L282 -> 608062.5 | G19: =Detallado!M282 -> 15000 | H19: =Detallado!N282 -> 1404761.3 | I19: =Detallado!O282 -> 2727.6918 | J19: =H19/C19 -> 42555.628
A20: 5 | B20: ESTRUCTURA METÁLICA Y CUBIERTAS | C20: =C21+C22 -> 60.8 | D20: m2 | E20: =SUM(E21:E28) -> 1467743.8 | F20: =SUM(F21:F28) -> 2632312.5 | G20: =SUM(G21:G28) -> 0 | H20: =SUM(H21:H28) -> 4100056.3 | I20: =SUM(I21:I28) -> 7961.2743 | J20: =H20/C20 -> 67435.136
A21: 5.1 | B21: ESTRUCTURA TECHO CASA | C21: =+'1_OG y 2_ACA'!E724 -> 44.8 | D21: m2 | E21: =Detallado!K116 -> 729007.47 | F21: =Detallado!L116 -> 1047000 | G21: =Detallado!M116 -> 0 | H21: =Detallado!N116 -> 1776007.5 | I21: =Detallado!O116 -> 3448.5582 | J21: =H21/C21 -> 39643.024
A22: 5.2 | B22: ESTRUCTURA TECHO COCHERA | C22: =+'1_OG y 2_ACA'!E797 -> 16 | D22: m2 | E22: =Detallado!K144 -> 263802.06 | F22: =Detallado!L144 -> 408000 | G22: =Detallado!M144 -> 0 | H22: =Detallado!N144 -> 671802.06 | I22: =Detallado!O144 -> 1304.47 | J22: =H22/C22 -> 41987.629
A23: 5.3 | B23: CUBIERTA TECHO CASA | C23: =+C21 -> 44.8 | D23: m2 | E23: =Detallado!K168 -> 150159.27 | F23: =Detallado!L168 -> 403650 | G23: =Detallado!M168 -> 0 | H23: =Detallado!N168 -> 553809.27 | I23: =Detallado!O168 -> 1075.3578 | J23: =H23/C23 -> 12361.814
A24: 5.4 | B24: CUBIERTA TECHO COCHERA | C24: =+C22 -> 16 | D24: Global | E24: =Detallado!K175 -> 0 | F24: =Detallado!L175 -> 0 | G24: =Detallado!M175 -> 0 | H24: =Detallado!N175 -> 0 | I24: =Detallado!O175 -> 0 | J24: =H24/C24 -> 0
A25: 5.5 | B25: HOJALATERIA Y CANOAS | C25: 1 | D25: Global | E25: =Detallado!K237 -> 143392.11 | F25: =Detallado!L237 -> 553725 | G25: =Detallado!M237 -> 0 | H25: =Detallado!N237 -> 697117.11 | I25: =Detallado!O237 -> 1353.6255 | J25: =H25/C25 -> 697117.11
A26: 5.6 | B26: GRADAS ESTRUCTURA, PINTADO Y ACABADO | C26: 1 | D26: Global | E26: =Detallado!K187 -> 0 | F26: =Detallado!L187 -> 0 | G26: =Detallado!M187 -> 0 | H26: =Detallado!N187 -> 0 | I26: =Detallado!O187 -> 0 | J26: =H26/C26 -> 0
A27: 5.7 | B27: BARANDA DE GRADAS (N2) | C27: 1 | D27: Global | E27: =Detallado!K213 -> 181382.87 | F27: =Detallado!L213 -> 219937.5 | G27: =Detallado!M213 -> 0 | H27: =Detallado!N213 -> 401320.37 | I27: =Detallado!O213 -> 779.26286 | J27: =H27/C27 -> 401320.37
A28: 5.8 | B28: ESTRUCTURA METÁLICA INTERNA | C28: 1 | D28: Global | E28: =Detallado!K229 -> 0 | F28: =Detallado!L229 -> 0 | G28: =Detallado!M229 -> 0 | H28: =Detallado!N229 -> 0 | I28: =Detallado!O229 -> 0 | J28: =H28/C28 -> 0
A29: 6 | B29: LIVIANO | C29: =C30+C31 -> 105.45 | D29: m2 | E29: =SUM(E30:E31) -> 1635299.4 | F29: =SUM(F30:F31) -> 540787.5 | G29: =SUM(G30:G31) -> 0 | H29: =SUM(H30:H31) -> 2176086.9 | I29: =SUM(I30:I31) -> 4225.4114 | J29: =H29/C29 -> 20636.196
A30: 6.1 | B30: LIVIANO EXTERIORES | C30: =+'1_OG y 2_ACA'!D1299+'1_OG y 2_ACA'!D1318+'1_OG y 2_ACA'!D1341 -> 52.55 | D30: m2 | E30: =Detallado!K323 -> 514909.4 | F30: =Detallado!L323 -> 243225 | G30: =Detallado!M323 -> 0 | H30: =Detallado!N323 -> 758134.4 | I30: =Detallado!O323 -> 1472.1056 | J30: =H30/C30 -> 14426.915
A31: 6.2 | B31: LIVIANO INTERIORES ( PAREDES LIVIANAS Y CIELOS) | C31: =+'1_OG y 2_ACA'!D1366+'1_OG y 2_ACA'!E1390 -> 52.9 | D31: m2 | E31: =Detallado!K361 -> 1120390 | F31: =Detallado!L361 -> 297562.5 | G31: =Detallado!M361 -> 0 | H31: =Detallado!N361 -> 1417952.5 | I31: =Detallado!O361 -> 2753.3058 | J31: =H31/C31 -> 26804.395
A32: 7 | B32: REPELLOS | C32: =C33 -> 474.2825 | D32: m2 | E32: =SUM(E33:E34) -> 1229814.6 | F32: =SUM(F33:F34) -> 1278225 | G32: =SUM(G33:G34) -> 0 | H32: =SUM(H33:H34) -> 2508039.6 | I32: =SUM(I33:I34) -> 4869.9797 | J32: =H32/C32 -> 5288.0711
A33: 7.1 | B33: REPELLOS INTERNO Y EXTERNO | C33: =+'1_OG y 2_ACA'!D1453 -> 474.2825 | D33: m2 | E33: =Detallado!K395 -> 960861.6 | F33: =Detallado!L395 -> 1014300 | G33: =Detallado!M395 -> 0 | H33: =Detallado!N395 -> 1975161.6 | I33: =Detallado!O395 -> 3835.2652 | J33: =H33/C33 -> 4164.5256
A34: 7.2 | B34: EMPASTE | C34: =+'1_OG y 2_ACA'!D1465 -> 225.0125 | D34: m2 | E34: =Detallado!K399 -> 268952.96 | F34: =Detallado!L399 -> 263925 | G34: =Detallado!M399 -> 0 | H34: =Detallado!N399 -> 532877.96 | I34: =Detallado!O399 -> 1034.7145 | J34: =H34/C34 -> 2368.2149
A35: 8 | B35: ENCHAPES | C35: 1 | D35: Global | E35: =E36 -> 844081.25 | F35: =F36 -> 626175 | G35: =G36 -> 0 | H35: =H36 -> 1470256.3 | I35: =I36 -> 2854.8665 | J35: =H35/C35 -> 1470256.3
A36: 8.1 | B36: ENCHAPES (INTERNO Y EXTERNO) | C36: =+'1_OG y 2_ACA'!D1489+'1_OG y 2_ACA'!D1550+'1_OG y 2_ACA'!D1509+'1_OG y 2_ACA'!#REF! -> #REF! | D36: m2 | E36: =Detallado!K407 -> 844081.25 | F36: =Detallado!L407 -> 626175 | G36: =Detallado!M407 -> 0 | H36: =Detallado!N407 -> 1470256.3 | I36: =Detallado!O407 -> 2854.8665 | J36: =H36/C36 -> #REF!
A37: 9 | B37: MUEBLES Y PUERTAS | C37: 1 | D37: Global | E37: =SUM(E38:E39) -> 3664782.7 | F37: =SUM(F38:F39) -> 618262.5 | G37: =SUM(G38:G39) -> 268000 | H37: =SUM(H38:H39) -> 4551045.2 | I37: =SUM(I38:I39) -> 8836.9809 | J37: =H37/C37 -> 4551045.2
A38: 9.1 | B38: MUEBLES | C38: 5 | D38: un | E38: =Detallado!K477 -> 1806677.9 | F38: =Detallado!L477 -> 300000 | G38: =Detallado!M477 -> 268000 | H38: =Detallado!N477 -> 2374677.9 | I38: =Detallado!O477 -> 4611.025 | J38: =H38/C38 -> 474935.57
A39: 9.2 | B39: PUERTAS Y RODAPIE | C39: 1 | D39: Global | E39: =Detallado!K513 -> 1858104.8 | F39: =Detallado!L513 -> 318262.5 | G39: =Detallado!M513 -> 0 | H39: =Detallado!N513 -> 2176367.3 | I39: =Detallado!O513 -> 4225.956 | J39: =H39/C39 -> 2176367.3
A40: 10 | B40: OBRAS ADICIONALES | C40: 1 | D40: Global | E40: =SUM(E41:E43) -> 670539.01 | F40: =SUM(F41:F43) -> 455400 | G40: =SUM(G41:G43) -> 0 | H40: =SUM(H41:H43) -> 1125939 | I40: =SUM(I41:I43) -> 2186.2893 | J40: =H40/C40 -> 1125939
A41: 10.1 | B41: ZACATE | C41: =+Detallado!F549 -> 36.34 | D41: m2 | E41: =Detallado!K549 -> 195691.58 | F41: =Detallado!L549 -> 150075 | G41: =Detallado!M549 -> 0 | H41: =Detallado!N549 -> 345766.58 | I41: =Detallado!O549 -> 671.39142 | J41: =H41/C41 -> 9514.7656
A42: 10.2 | B42: TAPIAS PREFABRICADAS | C42: =+Detallado!#REF! -> #REF! | D42: m | E42: =Detallado!K299 -> 277853.73 | F42: =Detallado!L299 -> 144900 | G42: =Detallado!M299 -> 0 | H42: =Detallado!N299 -> 422753.73 | I42: =Detallado!O299 -> 820.88103 | J42: =H42/C42 -> #REF!
A43: 10.3 | B43: ACERAS | C43: =+Detallado!F312 -> 12.24 | D43: m2 | E43: =Detallado!K312 -> 196993.7 | F43: =Detallado!L312 -> 160425 | G43: =Detallado!M312 -> 0 | H43: =Detallado!N312 -> 357418.7 | I43: =Detallado!O312 -> 694.01689 | J43: =H43/C43 -> 29200.874
A44: 11 | B44: ACABADOS | C44: 1 | D44: Global | E44: =SUM(E45:E48) -> #REF! | F44: =SUM(F45:F48) -> #REF! | G44: =SUM(G45:G48) -> #REF! | H44: =SUM(H45:H48) -> #REF! | I44: =SUM(I45:I48) -> #REF! | J44: =H44/C44 -> #REF!
A45: 11.1 | B45: PINTURA | C45: =+'1_OG y 2_ACA'!D1572 -> 538.3825 | D45: m2 | E45: =Detallado!#REF! -> #REF! | F45: =Detallado!#REF! -> #REF! | G45: =Detallado!#REF! -> #REF! | H45: =Detallado!#REF! -> #REF! | I45: =Detallado!#REF! -> #REF! | J45: =H45/C45 -> #REF!
A46: 11.2 | B46: LOSA SANITARIA, GRIFERIA | C46: =+'1_OG y 2_ACA'!#REF!+'1_OG y 2_ACA'!#REF!+'1_OG y 2_ACA'!#REF!+'1_OG y 2_ACA'!#REF!+'1_OG y 2_ACA'!#REF! -> #REF! | D46: un | E46: =Detallado!K526 -> 669316.46 | F46: =Detallado!L526 -> 77625 | G46: =Detallado!M526 -> 0 | H46: =Detallado!N526 -> 746941.46 | I46: =Detallado!O526 -> 1450.3718 | J46: =H46/C46 -> #REF!
A47: 11.3 | B47: ACABADOS DE AZOTEA | C47: 1 | D47: Global | E47: =Detallado!K452 -> 964895.08 | F47: =Detallado!L452 -> 113850 | G47: =Detallado!M452 -> 0 | H47: =Detallado!N452 -> 1078745.1 | I47: =Detallado!O452 -> 2094.6506 | J47: =H47/C47 -> 1078745.1
A48: 11.4 | B48: PONCHEO FINAL | C48: 1 | D48: Global | E48: =Detallado!K462 -> 0 | F48: =Detallado!L462 -> 310500 | G48: =Detallado!M462 -> 0 | H48: =Detallado!N462 -> 310500 | I48: =Detallado!O462 -> 602.91262 | J48: =H48/C48 -> 310500
A49: 12 | B49: VENTANERIA | C49: =C50 -> 21.005 | D49: m2 | E49: =E50 -> 0 | F49: =F50 -> 0 | G49: =G50 -> 1151015.2 | H49: =H50 -> 1151015.2 | I49: =I50 -> 2234.9809 | J49: =H49/C49 -> 54797.199
A50: 12.1 | B50: VENTANERIA | C50: =+'1_OG y 2_ACA'!G1666 -> 21.005 | D50: m2 | E50: =Detallado!K472 -> 0 | F50: =Detallado!L472 -> 0 | G50: =Detallado!M472 -> 1151015.2 | H50: =Detallado!N472 -> 1151015.2 | I50: =Detallado!O472 -> 2234.9809 | J50: =H50/C50 -> 54797.199
A51: 13 | B51: ELÉCTRICO | C51: 1 | D51: Global | E51: =SUM(E52:E60) -> #REF! | F51: =SUM(F52:F60) -> #REF! | G51: =SUM(G52:G60) -> #REF! | H51: =SUM(H52:H60) -> #REF! | I51: =SUM(I52:I60) -> #REF! | J51: =H51/C51 -> #REF!
A52: 13.1 | B52: ACOMETIDA | C52: 1 | D52: Global | E52: =Detallado!K559 -> 141132.47 | F52: =Detallado!L559 -> 0 | G52: =Detallado!M559 -> 211250 | H52: =Detallado!N559 -> 352382.47 | I52: =Detallado!O559 -> 684.23781 | J52: =H52/C52 -> 352382.47
A53: 13.2 | B53: ELÉCTRICO LOSA | C53: 1 | D53: Global | E53: =Detallado!#REF! -> #REF! | F53: =Detallado!#REF! -> #REF! | G53: =Detallado!#REF! -> #REF! | H53: =Detallado!#REF! -> #REF! | I53: =Detallado!#REF! -> #REF! | J53: =H53/C53 -> #REF!
A54: 13.3 | B54: ELÉCTRICO MUROS | C54: 1 | D54: Global | E54: =Detallado!K583 -> 133305.7 | F54: =Detallado!L583 -> 0 | G54: =Detallado!M583 -> 71250 | H54: =Detallado!N583 -> 204555.7 | I54: =Detallado!O583 -> 397.19554 | J54: =H54/C54 -> 204555.7
A55: 13.4 | B55: BASE MEDIDOR | C55: 1 | D55: Global | E55: =Detallado!K696 -> 115787.24 | F55: =Detallado!L696 -> 0 | G55: =Detallado!M696 -> 25000 | H55: =Detallado!N696 -> 140787.24 | I55: =Detallado!O696 -> 273.37327 | J55: =H55/C55 -> 140787.24
A56: 13.5 | B56: ELÉCTRICO ILUMINACIÓN | C56: 1 | D56: Global | E56: =Detallado!#REF! -> #REF! | F56: =Detallado!#REF! -> #REF! | G56: =Detallado!#REF! -> #REF! | H56: =Detallado!#REF! -> #REF! | I56: =Detallado!#REF! -> #REF! | J56: =H56/C56 -> #REF!
A57: 13.6 | B57: TABLERO ELÉCTRICO | C57: 1 | D57: Global | E57: =Detallado!K729 -> 140431.52 | F57: =Detallado!L729 -> 0 | G57: =Detallado!M729 -> 32500 | H57: =Detallado!N729 -> 172931.52 | I57: =Detallado!O729 -> 335.78935 | J57: =H57/C57 -> 172931.52
A58: 13.7 | B58: CABLEADO ELÉCTRICO | C58: 1 | D58: Global | E58: =Detallado!K747 -> 399790.97 | F58: =Detallado!L747 -> 0 | G58: =Detallado!M747 -> 442468 | H58: =Detallado!N747 -> 842258.97 | I58: =Detallado!O747 -> 1635.4543 | J58: =H58/C58 -> 842258.97
A59: 13.8 | B59: PLAQUERIA | C59: 1 | D59: Global | E59: =Detallado!K769 -> 556820.39 | F59: =Detallado!L769 -> 0 | G59: =Detallado!M769 -> 123750 | H59: =Detallado!N769 -> 680570.39 | I59: =Detallado!O769 -> 1321.4959 | J59: =H59/C59 -> 680570.39
A60: 13.9 | B60: ACABADOS FINALES Y BREAKERS | C60: 1 | D60: Global | E60: =Detallado!K800 -> 1350272.5 | F60: =Detallado!L800 -> 0 | G60: =Detallado!M800 -> 156250 | H60: =Detallado!N800 -> 1506522.5 | I60: =Detallado!O800 -> 2925.2863 | J60: =H60/C60 -> 1506522.5
A61: 14 | B61: MECÁNICO | C61: 1 | D61: Global | E61: =SUM(E62:E64) -> 314588.41 | F61: =SUM(F62:F64) -> 411412.5 | G61: =SUM(G62:G64) -> 0 | H61: =SUM(H62:H64) -> 726000.91 | I61: =SUM(I62:I64) -> 1409.7105 | J61: =H61/C61 -> 726000.91
A62: 14.03 | B62: CAJAS Y TUBERIAS MECÁNICAS | C62: 1 | D62: Global | E62: =Detallado!K911 -> 192838.28 | F62: =Detallado!L911 -> 181125 | G62: =Detallado!M911 -> 0 | H62: =Detallado!N911 -> 373963.28 | I62: =Detallado!O911 -> 726.14229 | J62: =H62/C62 -> 373963.28
A63: 14.04 | B63: BAJANTES | C63: 1 | D63: Global | E63: =Detallado!K248 -> 17251.518 | F63: =Detallado!L248 -> 160425 | G63: =Detallado!M248 -> 0 | H63: =Detallado!N248 -> 177676.52 | I63: =Detallado!O248 -> 345.00295 | J63: =H63/C63 -> 177676.52
A64: 14.05 | B64: ACABADOS MECÁNICOS | C64: 1 | D64: Global | E64: =Detallado!K930 -> 104498.61 | F64: =Detallado!L930 -> 69862.5 | G64: =Detallado!M930 -> 0 | H64: =Detallado!N930 -> 174361.11 | I64: =Detallado!O930 -> 338.56527 | J64: =H64/C64 -> 174361.11
A65: 15 | B65: ALQUILERES | C65: 1 | D65: Global | E65: =E66 -> #REF! | F65: =F66 -> #REF! | G65: =G66 -> #REF! | H65: =H66 -> #REF! | I65: =I66 -> #REF! | J65: =H65/C65 -> #REF!
A66: 15.1 | B66: ALQUILERES | C66: 1 | D66: Global | E66: =Detallado!#REF! -> #REF! | F66: =Detallado!#REF! -> #REF! | G66: =Detallado!#REF! -> #REF! | H66: =Detallado!#REF! -> #REF! | I66: =Detallado!#REF! -> #REF! | J66: =H66/C66 -> #REF!
A67: 16 | B67: MANO DE OBRA | C67: 1 | D67: Global | E67: =Detallado!#REF! -> #REF! | F67: =F68 -> #REF! | G67: =G68 -> #REF! | H67: =H68 -> #REF! | I67: =I68 -> #REF! | J67: =H67/C67 -> #REF!
A68: 16.1 | B68: MANO DE OBRA | C68: 1 | D68: Global | E68: =Detallado!#REF! -> #REF! | F68: =Detallado!#REF! -> #REF! | G68: =Detallado!#REF! -> #REF! | H68: =Detallado!#REF! -> #REF! | I68: =Detallado!#REF! -> #REF! | J68: =H68/C68 -> #REF! | K68: VERFICACION | L68: =H70-Detallado!N951 -> #REF!
D70: TOTAL | E70: =SUM(E4:E68)/2 -> #REF! | F70: =SUM(F4:F68)/2 -> #REF! | G70: =SUM(G4:G68)/2 -> #REF! | H70: =SUM(H4:H68)/2 -> #REF! | I70: =SUM(I4:I68)/2 -> #REF!
F71: =F70/E70 -> #REF!
G72: Hechura concreto | H72: ='1_OG y 2_ACA'!D1843*E82 -> 813170.01
G73: Alquiler Bomba | H73: ='1_OG y 2_ACA'!D1844*C86 -> 367887.81
G74: Hechura muebles | H74: 150000
G75: Hechura cubierta | H75: =+E78 -> 152320 | J75: =+H75+H74+H73+H72 -> 1483377.8
H76: =SUM(H70:H75) -> #REF!
B77: Hechura cubierta techo | C77: m2 | D77: Costo/m2 | E77: Costo Total
C78: =+Detallado!F168 -> 44.8 | D78: 3400 | E78: =C78*D78 -> 152320 | H78: =+F70+G51 -> #REF! | L78: 18627702
G79: BACK-HOE | H79: 63500 | J79: =+H79+88000 -> 151500 | L79: 7577636
C80: FC=210 kg/cm2 REGULAR | G80: LASTRE | H80: =+Detallado!K12+Detallado!K283 -> 488749.88 | L80: =SUM(L78:L79) -> 26205338
B81: Hechura concreto | C81: Costo adelante (m3) | D81: Costo Orosi (m3) | E81: Hechura (m3) | H81: =+H76-H78-H79-H80 -> #REF! | J81: =+H81+H78 -> #REF!
C82: 61339.064 | D82: 75000 | E82: =D82-C82 -> 13660.936
G83: FORMALETA | H83: =('1_OG y 2_ACA'!D521+'1_OG y 2_ACA'!D706)*1150 -> 684756
J84: =+J81-L80 -> #REF!
B85: Bomba de concreto | C85: Costo Orosi costo/(m3) | G85: CON TODO | H85: =+H76+H79-H80+H83 -> #REF!
C86: =(129807.75*1.04)/15 -> 9000.004
H87: 21026676
H89: =+H87-H85 -> #REF!
G91: BACK HOE | H91: =+SUMIF(Detallado!E7:E818,DESGLOSE!G91,Detallado!M7:M818) -> 105000
G92: COMPACTADOR | H92: =+SUMIF(Detallado!E7:E818,DESGLOSE!G92,Detallado!M7:M818) -> 13000
H93: =SUM(H91:H92) -> 118000
G95: MATERIALES | H95: =+(E70+G70)-H80-H93 -> #REF!
G96: MANO+INCAPACIDADES | H96: =+F70*1.04 -> #REF!
G97: HECHURAS | H97: =+J75 -> 1483377.8
G98: LASTRE | H98: =+H80 -> 488749.88
G99: FORMALETA-MAQUINARIA | H99: =+H83+H93 -> 802756
G100: CON TODO | H100: =SUM(H95:H99) -> #REF!

Sheet Resumen Presupuesto
A1: , | B1: ESTIMADO ZANTE AZOTEA | G1: TIPO CAMBIO | H1: 505
A3: N° | B3: Actividad | C3: Cantidad | D3: Unidad | E3: COSTO M2 | F3: TOTAL
A5: 1 | B5: OBRA GRIS
A6: 1.1 | B6: FUNDACIONES
A7: 1.1.1 | B7: TRAZADO Y RELLENOS | C7: =+Detallado!F11 -> 57.62 | D7: m2 | E7: =F7/C7 -> 10345.146 | F7: =Detallado!N11 -> 596087.33 | I7: N11
A8: 1.1.2 | B8: EXCAVACIÓN | C8: =+Detallado!F21 -> 57.62 | D8: m2 | E8: =F8/C8 -> 2532.8956 | F8: =Detallado!N21 -> 145945.44 | I8: N20
A9: 1.1.3 | B9: SELLO DE CONCRETO | C9: =+Detallado!F28 -> 48.12 | D9: m2 | E9: =F9/C9 -> 3762.7281 | F9: =Detallado!N28 -> 181062.48 | I9: N29
A10: 1.1.4 | B10: LOSA FLOTANTE (ACERO, CONCRETO, FORMALETA) | C10: =+Detallado!F37 -> 48.12 | D10: m2 | E10: =F10/C10 -> 46614.536 | F10: =Detallado!N37 -> 2243091.5 | I10: N40
B12: TOTAL LOSAS | C12: =+C8 -> 57.62 | D12: m2 | E12: =+F12/C12 -> 54949.44 | F12: =+SUBTOTAL(9,F7:F10) -> 3166186.7
A14: 1.2 | B14: MUROS N1 Y N2, ENTREPISO
A15: 1.2.1 | B15: ACERO EN PAREDES MUROS N1 | C15: =+Detallado!F55 -> 129.48 | D15: m2 | E15: =F15/C15 -> 14035.276 | F15: =Detallado!N55 -> 1817287.5 | I15: N60
A16: 1.2.2 | B16: PAREDES, MUROS, ENTREPISO N1 | C16: =+Detallado!F68 -> 129.48 | D16: m2 | E16: =F16/C16 -> 23054.815 | F16: =Detallado!N68 -> 2985137.5 | I16: N72
A17: 1.2.3 | B17: MAMPOSTERIA | C17: =+Detallado!F84 -> 1 | D17: Global | E17: =F17/C17 -> 0 | F17: =Detallado!N84 -> 0 | I17: N85
A18: 1.2.4 | B18: ACERO EN PAREDES MUROS N2 | C18: =+Detallado!F89 -> 132.88 | D18: Global | E18: =F18/C18 -> 10059.157 | F18: =Detallado!N89 -> 1336660.7 | I18: N90
A19: 1.2.5 | B19: PAREDES, MUROS, ENTREPISO N2 | C19: =+Detallado!F101 -> 132.88 | D19: Global | E19: =F19/C19 -> 16814.018 | F19: =Detallado!N101 -> 2234246.7 | I19: N102
B21: TOTAL MUROS PRIMER Y SEGUNDO NIVEL | C21: =C15 -> 129.48 | D21: m2 | E21: =+F21/C21 -> 64668.925 | F21: =+SUBTOTAL(9,F15:F19) -> 8373332.4
A23: 1.3 | B23: ESTRUCTURA METÁLICA Y CUBIERTAS
A24: 1.3.1 | B24: ESTRUCTURA TECHO CASA | C24: =+Detallado!F116 -> 44.8 | D24: m2 | E24: =F24/C24 -> 39643.024 | F24: =Detallado!N116 -> 1776007.5 | I24: N118
A25: 1.3.2 | B25: ESTRUCTURA TECHO COCHERA | C25: =+Detallado!F144 -> 16 | D25: m2 | E25: =F25/C25 -> 41987.629 | F25: =Detallado!N144 -> 671802.06 | I25: N138
A26: 1.3.3 | B26: CUBIERTA TECHO CASA | C26: =+Detallado!F168 -> 44.8 | D26: m2 | E26: =F26/C26 -> 12361.814 | F26: =Detallado!N168 -> 553809.27 | I26: N158
A27: 1.3.4 | B27: CUBIERTA TECHO COCHERA | C27: =+Detallado!F175 -> 16 | D27: m2 | E27: =F27/C27 -> 0 | F27: =Detallado!N175 -> 0 | I27: N165
A28: 1.3.5 | B28: GRADAS ESTRUCTURA, PINTADO Y ACABADO | C28: =+Detallado!F187 -> 1 | D28: Global | E28: =F28/C28 -> 0 | F28: =Detallado!N187 -> 0 | I28: N177
A29: 1.3.6 | B29: BARANDA DE GRADAS (N2) | C29: =+Detallado!F213 -> 1 | D29: Global | E29: =F29/C29 -> 401320.37 | F29: =Detallado!N213 -> 401320.37 | I29: N203
A30: 1.3.7 | B30: ESTRUCTURA METÁLICA INTERNA | C30: =+Detallado!F229 -> 1 | D30: Global | E30: =F30/C30 -> 0 | F30: =Detallado!N229 -> 0 | I30: N219
B32: TOTAL ESTRUCT METÁLICA Y CUBIERTAS | C32: =C24+C25 -> 60.8 | D32: m2 | E32: =+F32/C32 -> 55969.394 | F32: =+SUBTOTAL(9,F24:F30) -> 3402939.2
A34: 1.4 | B34: HOJALATERIA
A35: 1.4.1 | B35: CANOAS Y BOTAGUAS | C35: =+Detallado!F237 -> 1 | D35: Global | E35: =F35/C35 -> 697117.11 | F35: =Detallado!N237 -> 697117.11 | I35: N228
A36: 1.4.2 | B36: BAJANTES | C36: =+Detallado!F248 -> 1 | D36: Global | E36: =F36/C36 -> 177676.52 | F36: =Detallado!N248 -> 177676.52 | I36: N240
B38: TOTAL HOJALATERIA | C38: =C35+C36 -> 2 | D38: m2 | E38: =+F38/C38 -> 437396.81 | F38: =+SUBTOTAL(9,F35:F36) -> 874793.63
A40: 1.5 | B40: OBRAS COMPLEMENTARIAS
A41: 1.5.1 | B41: GRADAS EN CONCRETO | C41: =+Detallado!F253 -> 1 | D41: Global | E41: =F41/C41 -> 928974.66 | F41: =Detallado!N254 -> 928974.66 | I41: N247
A42: 1.5.2 | B42: COLUMNAS (MEDIDOR) | C42: =+Detallado!F269 -> 1 | D42: Global | E42: =F42/C42 -> 241734.92 | F42: =Detallado!N269 -> 241734.92
A43: 1.5.3 | B43: CHORREA DE COCHERAS Y PILAS | C43: =+Detallado!F282 -> 39.3 | D43: m2 | E43: =F43/C43 -> 35744.562 | F43: =Detallado!N282 -> 1404761.3
A44: 1.5.4 | B44: TAPIAS PREFABRICADAS | C44: =+Detallado!F299 -> 8.5 | D44: m | E44: =F44/C44 -> 49735.733 | F44: =Detallado!N299 -> 422753.73
A45: 1.5.5 | B45: ACERAS | C45: =+Detallado!F312 -> 12.24 | D45: m2 | E45: =F45/C45 -> 29200.874 | F45: =Detallado!N312 -> 357418.7
B47: TOTAL OBRAS COMPLEMENTARIAS | C47: 1 | D47: Global | E47: =+F47/C47 -> 3355643.3 | F47: =+SUBTOTAL(9,F41:F45) -> 3355643.3
A49: 1.6 | B49: LIVIANO
A50: 1.6.1 | B50: LIVIANO EXTERIORES (PRECINTA Y TAPICHELES, ALEROS) | C50: =+Detallado!F324+Detallado!F334+Detallado!F345 -> 52.55 | D50: m2 | E50: =F50/C50 -> 14426.915 | F50: =Detallado!N323 -> 758134.4
A51: 1.6.2 | B51: LIVIANO INTERIORES ( PAREDES LIVIANAS Y CIELOS) | C51: =+Detallado!F362+Detallado!F375 -> 52.9 | D51: m2 | E51: =F51/C51 -> 26804.395 | F51: =Detallado!N361 -> 1417952.5
B53: TOTAL LIVIANO | C53: =C50+C51 -> 105.45 | D53: m2 | E53: =+F53/C53 -> 20636.196 | F53: =+SUBTOTAL(9,F50:F51) -> 2176086.9
A55: 2 | B55: ACABADOS
A56: 2.1 | B56: REPELLOS Y EMPASTE
A57: 2.1.1 | B57: REPELLOS INTERNO Y EXTERNO | C57: =+Detallado!F395 -> 474.2825 | D57: m2 | E57: =F57/C57 -> 4164.5256 | F57: =Detallado!N395 -> 1975161.6
A58: 2.1.2 | B58: EMPASTE | C58: =+Detallado!F399 -> 225.0125 | D58: m2 | E58: =F58/C58 -> 2368.2149 | F58: =Detallado!N399 -> 532877.96
B60: TOTAL REPELLOS | C60: =C57 -> 474.2825 | D60: m2 | E60: =+F60/C60 -> 5288.0711 | F60: =+SUBTOTAL(9,F57:F58) -> 2508039.6
A62: 2.2 | B62: ENCHAPES
A63: 2.2.1 | B63: ENCHAPES PAREDES, PISOS Y FACHADA | C63: =+Detallado!F407 -> 121.6 | D63: m2 | E63: =F63/C63 -> 12090.923 | F63: =Detallado!N407 -> 1470256.3
B65: TOTAL ENCHAPES | C65: =C63 -> 121.6 | D65: m2 | E65: =+F65/C65 -> 12090.923 | F65: =+SUBTOTAL(9,F63) -> 1470256.3
A67: 2.3 | B67: PINTURA/ IMPERMEABILIZANTE
A68: 2.3.1 | B68: PINTURA PAREDES Y CIELOS | C68: =+Detallado!F429 -> 538.3825 | D68: m2 | E68: =F68/C68 -> 2826.3317 | F68: =+Detallado!N429 -> 1521647.5
A69: 2.3.2 | B69: ACABADOS DE AZOTEA | C69: =+Detallado!F452 -> 55.7 | D69: Global | E69: =F69/C69 -> 19367.057 | F69: =Detallado!N452 -> 1078745.1
A70: 2.3.3 | B70: PONCHEO FINAL | C70: =+Detallado!F462 -> 1 | D70: Global | E70: =F70/C70 -> 310500 | F70: =Detallado!N462 -> 310500
B72: PINTURA | C72: 1 | D72: Global | E72: =+F72/C72 -> 2910892.6 | F72: =+SUBTOTAL(9,F68:F70) -> 2910892.6
A74: 2.4 | B74: MADERAS
A75: 2.4.1 | B75: CIELOS | C75: =+Detallado!F466 -> 1 | D75: m2 | E75: =F75/C75 -> 0
A76: 2.4.2 | B76: PANEL ACANALADO | C76: =+Detallado!F466 -> 1 | D76: m2 | E76: =F76/C76 -> 0
B78: TOTAL MADERAS | C78: 1 | D78: Global | E78: =+F78/C78 -> 0 | F78: =+SUBTOTAL(9,F75:F76) -> 0
A80: 2.5 | B80: VENTANERIA
A81: 2.5.1 | B81: VENTANERIA | C81: =+Detallado!F471 -> 21.005 | D81: m2 | E81: =F81/C81 -> 54797.199 | F81: =Detallado!N471 -> 1151015.2
B83: TOTAL VENTANERIA | C83: =C81 -> 21.005 | D83: m2 | E83: =+F83/C83 -> 54797.199 | F83: =+SUBTOTAL(9,F81) -> 1151015.2
A85: 2.6 | B85: MUEBLES Y PUERTAS
A86: 2.6.1 | B86: MUEBLES | C86: =+Detallado!F477 -> 1 | D86: un | E86: =F86/C86 -> 2374677.9 | F86: =Detallado!N477 -> 2374677.9
A87: 2.6.2 | B87: PUERTAS Y RODAPIE | C87: =+Detallado!F513 -> 1 | D87: Global | E87: =F87/C87 -> 2176367.3 | F87: =Detallado!N513 -> 2176367.3
B89: TOTAL MUEBLES Y PUERTAS | C89: 1 | D89: Global | E89: =+F89/C89 -> 4551045.2 | F89: =+SUBTOTAL(9,F86:F87) -> 4551045.2
A91: 2.7 | B91: LOZA SANITARIA
A92: 2.7.1 | B92: LOSA SANITARIA, GRIFERIA | C92: =+Detallado!F525 -> 1 | D92: un | E92: =F92/C92 -> 746941.46 | F92: =Detallado!N526 -> 746941.46
B94: TOTAL ACABADOS | C94: 1 | D94: Global | E94: =+F94/C94 -> 746941.46 | F94: =+SUBTOTAL(9,F92) -> 746941.46
A96: 2.8 | B96: ZACATE
A97: 2.8.1 | B97: ZACATE | C97: =+Detallado!F549 -> 36.34 | D97: m2 | E97: =F97/C97 -> 9514.7656 | F97: =Detallado!N549 -> 345766.58
B99: TOTAL OBRAS ADICIONALES | C99: 1 | D99: Global | E99: =+F99/C99 -> 345766.58 | F99: =+SUBTOTAL(9,F97:F98) -> 345766.58
A101: 3 | B101: ELECTROMECANICO
A102: 3.1 | B102: ELÉCTRICO
A103: 3.1.1 | B103: ACOMETIDA | C103: =+Detallado!F559 -> 1 | D103: Global | E103: =F103/C103 -> 352382.47 | F103: =Detallado!N559 -> 352382.47
A104: 3.1.2 | B104: ELÉCTRICO MUROS | C104: =+Detallado!F583 -> 1 | D104: Global | E104: =F104/C104 -> 204555.7 | F104: =+Detallado!N583 -> 204555.7
A105: 3.1.3 | B105: ELECTRICO ENTREPISO | C105: =+Detallado!F609 -> 1 | D105: Global | E105: =F105/C105 -> 105474.43 | F105: =+Detallado!N609 -> 105474.43
A106: 3.1.4 | B106: ELECTRICO AZOTEA | C106: =+Detallado!F635 -> 1 | D106: Global | E106: =F106/C106 -> 64967.907 | F106: =+Detallado!N635 -> 64967.907
A107: 3.1.5 | B107: ELÉCTRICO ILUMINACIÓN | C107: =+Detallado!F662 -> 1 | D107: Global | E107: =F107/C107 -> 408311.25 | F107: =+Detallado!N662 -> 408311.25 | H107: Costo Partidas
A108: 3.1.6 | B108: BASE MEDIDOR | C108: =+Detallado!F696 -> 1 | D108: Global | E108: =F108/C108 -> 140787.24 | F108: =+Detallado!N696 -> 140787.24 | H108: =F12 -> 3166186.7
A109: 3.1.7 | B109: TABLERO ELÉCTRICO | C109: =+Detallado!F729 -> 1 | D109: Global | E109: =F109/C109 -> 172931.52 | F109: =+Detallado!N729 -> 172931.52 | H109: =F21 -> 8373332.4
A110: 3.1.8 | B110: CABLEADO ELÉCTRICO | C110: =+Detallado!F747 -> 1 | D110: Global | E110: =F110/C110 -> 842258.97 | F110: =+Detallado!N747 -> 842258.97 | H110: =F32 -> 3402939.2
A111: 3.1.9 | B111: PLAQUERIA | C111: =+Detallado!F769 -> 1 | D111: Global | E111: =F111/C111 -> 680570.39 | F111: =+Detallado!N769 -> 680570.39 | H111: =F38 -> 874793.63
A112: 3.1.10 | B112: ACABADOS FINALES Y BREAKERS | C112: =+Detallado!F800 -> 1 | D112: Global | E112: =F112/C112 -> 1506522.5 | F112: =+Detallado!N800 -> 1506522.5 | H112: =F47 -> 3355643.3
H113: =F53 -> 2176086.9
B114: TOTAL ELÉCTRICO | C114: 1 | D114: Global | E114: =+F114/C114 -> 4478762.3 | F114: =+SUBTOTAL(9,F103:F113) -> 4478762.3
H115: =F60 -> 2508039.6
A116: 3.2 | B116: MECÁNICO | H116: =F65 -> 1470256.3
A117: 3.2.1 | B117: EXCAVACION TUBERIA SANITARIA | C117: =+Detallado!F822 -> 1 | D117: Global | E117: =F117/C117 -> 338833.9 | F117: =+Detallado!N822 -> 338833.9 | H117: =F72 -> 2910892.6
A118: 3.2.2 | B118: POTABLE DE LOSA | C118: =+Detallado!F843 -> 1 | D118: Global | E118: =F118/C118 -> 150804.51 | F118: =+Detallado!N843 -> 150804.51 | H118: =F78 -> 0
A119: 3.2.2.1 | B119: POTABLE DE ENTREPISO | C119: =+Detallado!F860 -> 1 | D119: Global | E119: =F119/C119 -> 0 | F119: =+Detallado!N860 -> 0 | H119: =F83 -> 1151015.2
A120: 3.2.2.2 | B120: SANITARIO DE ENTREPISO | C120: =+Detallado!F875 -> 1 | D120: Global | E120: =F120/C120 -> 0 | F120: =+Detallado!N875 -> 0 | H120: =F89 -> 4551045.2
A121: 3.2.3 | B121: TUBERÍA MECÁNICA MUROS | C121: =+Detallado!F891 -> 1 | D121: Global | E121: =F121/C121 -> 41226.479 | F121: =+Detallado!N891 -> 41226.479 | H121: =F94 -> 746941.46
A122: 3.2.4 | B122: CAJAS Y TUBERIAS MECÁNICAS | C122: =+Detallado!F822 -> 1 | D122: Global | E122: =F122/C122 -> 373963.28 | F122: =+Detallado!N911 -> 373963.28 | H122: =F99 -> 345766.58
A123: 3.2.5 | B123: ACABADOS MECÁNICOS | C123: =+Detallado!F930 -> 1 | D123: Global | E123: =F123/C123 -> 174361.11 | F123: =+Detallado!N930 -> 174361.11
A124: 3.2.6 | B124: MEDIDOR | C124: =+Detallado!F943 -> 1 | D124: Global | E124: =F124/C124 -> 151045.53 | F124: =+Detallado!N943 -> 151045.53 | H124: =F114 -> 4478762.3
H125: =F126 -> 1230234.8
B126: TOTAL OBRAS MECÁNICO | C126: 1 | D126: Global | E126: =+F126/C126 -> 1230234.8 | F126: =+SUBTOTAL(9,F117:F125) -> 1230234.8
G128: ÁREA TOTAL | H128: =Detallado!E6 -> 126.79 | I128: m2 | J128: m2
G130: Costo/m2
A131: SUBTOTAL | F131: =SUBTOTAL(9,F6:F127) -> 40741936 | G131: =+F131/H128 -> 321333.99 | H131: =+Detallado!F960-'Resumen Presupuesto'!F131 -> 0
F132: Verficacion | G132: =F131-Detallado!N8 -> 0
...

Sheet Descompuesto
A1: N Obra | B1: N Linea | C1: N Actividad | D1: Descripcion actividad | E1: Tipo Tarea | F1: Tipo | G1: N° | H1: Cantidad | I1: Unit Mat | J1: Variante
A2: VN-L.32 | B2: 1 | C2: 1.1 | D2: LASTRE FINO | E2: Auxiliar | F2: Artículo | G2: M10-0023 | H2: 19 | I2: 14166.663 | L2: PROYECTO
A3: VN-L.32 | B3: 2 | C3: 1.1 | D3: BOLSA CAL | E3: Auxiliar | F3: Artículo | G3: M06-0163 | H3: 2 | I3: 1627.2 | L3: ='1_OG y 2_ACA'!E3 -> VN-L.32
A4: VN-L.32 | B4: 3 | C4: 1.1 | D4: CRAYON LYRA AMARILLO | E4: Auxiliar | F4: Artículo | G4: M06-0179 | H4: 6 | I4: 340.017
A5: VN-L.32 | B5: 4 | C5: 1.1 | D5: CUERDA ALBAÑIL BLANCA | E5: Auxiliar | F5: Artículo | G5: M06-0180 | H5: 7 | I5: 812.9107
A6: VN-L.32 | B6: 5 | C6: 1.1 | D6: ARENA LAVADA | E6: Auxiliar | F6: Artículo | G6: M10-0010 | H6: 0.5 | I6: 12044.501
A7: VN-L.32 | B7: 6 | C7: 1.1 | D7: MECHA BLANCA | E7: Auxiliar | F7: Artículo | G7: M06-0231 | H7: 1 | I7: 4338.0022
A8: VN-L.32 | B8: 7 | C8: 1.1 | D8: ACETONA | E8: Auxiliar | F8: Artículo | G8: M06-0123 | H8: 1 | I8: 2809.7789
A9: VN-L.32 | B9: 8 | C9: 1.1 | D9: TUBO 1X2X1.5MM HN | E9: Auxiliar | F9: Artículo | G9: M01-0067 | H9: 1 | I9: 14238
A10: VN-L.32 | B10: 9 | C10: 1.1 | D10: VARILLA DEFORME #4 | E10: Auxiliar | F10: Artículo | G10: M01-0148 | H10: 1 | I10: 2395.6
A11: VN-L.32 | B11: 10 | C11: 1.1 | D11: REGLA SEMIDURO 1X3X4 SIN CEPILLAR | E11: Auxiliar | F11: Artículo | G11: M09-0042 | H11: 5 | I11: 1524.9915
A12: VN-L.32 | B12: 11 | C12: 1.1 | D12: CONCRETO FC 120 CM2 (Concreto Pobre, Sello) | E12: Auxiliar | F12: Artículo | G12: M10-0091 | H12: 2.406 | I12: 54479.503
A13: VN-L.32 | B13: 12 | C13: 1.1 | D13: ADITIVO ERGO 4000 PG50 | E13: Auxiliar | F13: Artículo | G13: M10-0009 | H13: 8 | I13: 748.625
A14: VN-L.32 | B14: 13 | C14: 1.1 | D14: VARILLA DEFORME #2 | E14: Auxiliar | F14: Artículo | G14: M01-0146 | H14: 53 | I14: 569.8025
A15: VN-L.32 | B15: 14 | C15: 1.1 | D15: VARILLA DEFORME #3 | E15: Auxiliar | F15: Artículo | G15: M01-0147 | H15: 361 | I15: 1344.7 | J15: 02
A16: VN-L.32 | B16: 16 | C16: 1.1 | D16: ALAMBRE NEGRO #16 (1.68MM) | E16: Auxiliar | F16: Artículo | G16: M01-0001 | H16: 58 | I16: 586.8542
A17: VN-L.32 | B17: 17 | C17: 1.1 | D17: SEPARADOR TIPO CONO 2.5CM (1") SP125 | E17: Auxiliar | F17: Artículo | G17: M06-0261 | H17: 49 | I17: 56.5
A18: VN-L.32 | B18: 18 | C18: 1.1 | D18: SEPARADORES TIPO CONO 12CM SP450 | E18: Auxiliar | F18: Artículo | G18: M06-0264 | H18: 49 | I18: 203.4
A19: VN-L.32 | B19: 19 | C19: 1.1 | D19: DISCO CORTE METAL FINO 9" | E19: Auxiliar | F19: Artículo | G19: M08-0037 | H19: 7 | I19: 3037.6321
A20: VN-L.32 | B20: 20 | C20: 1.1 | D20: CONCRETO FC 210 KG/CM2 NORMAL | E20: Auxiliar | F20: Artículo | G20: M10-0065 | H20: 10.1052 | I20: 78867.084
A21: VN-L.32 | B21: 21 | C21: 1.2 | D21: VARILLA DEFORME #2 | E21: Auxiliar | F21: Artículo | G21: M01-0146 | H21: 6 | I21: 569.8025
A22: VN-L.32 | B22: 22 | C22: 1.2 | D22: VARILLA DEFORME #3 | E22: Auxiliar | F22: Artículo | G22: M01-0147 | H22: 146 | I22: 1344.7 | J22: 01
A23: VN-L.32 | B23: 23 | C23: 1.2 | D23: VARILLA DEFORME #3 | E23: Auxiliar | F23: Artículo | G23: M01-0147 | H23: 323 | I23: 1344.7 | J23: 02
A24: VN-L.32 | B24: 24 | C24: 1.2 | D24: VARILLA DEFORME #4 | E24: Auxiliar | F24: Artículo | G24: M01-0148 | H24: 78.5 | I24: 2395.6
A25: VN-L.32 | B25: 25 | C25: 1.2 | D25: MALLA ELECTROSOLDADA #2 (5.3 MM) | E25: Auxiliar | F25: Artículo | G25: M01-0145 | H25: 13.317175 | I25: 18762.497
A26: VN-L.32 | B26: 26 | C26: 1.2 | D26: ALAMBRE NEGRO #16 (1.68MM) | E26: Auxiliar | F26: Artículo | G26: M01-0001 | H26: 108 | I26: 586.8542
A27: VN-L.32 | B27: 27 | C27: 1.2 | D27: DISCO CORTE FINO METAL 4-1/2 | E27: Auxiliar | F27: Artículo | G27: M08-0051 | H27: 7 | I27: 3661.2
A28: VN-L.32 | B28: 28 | C28: 1.2 | D28: DISCO CORTE METAL FINO 9" | E28: Auxiliar | F28: Artículo | G28: M08-0037 | H28: 7 | I28: 3037.6321
A29: VN-L.32 | B29: 29 | C29: 1.2 | D29: ESPUMA EXPANSIVA 750ML | E29: Auxiliar | F29: Artículo | G29: M06-0193 | H29: 4 | I29: 6420.0046
A30: VN-L.32 | B30: 30 | C30: 1.2 | D30: FUNDAS DE 10CM | E30: Auxiliar | F30: Artículo | G30: M06-0195 | H30: 1200 | I30: 29.553229
A31: VN-L.32 | B31: 31 | C31: 1.2 | D31: REGLA SEMIDURO 1X3X4 SIN CEPILLAR | E31: Auxiliar | F31: Artículo | G31: M09-0042 | H31: 10 | I31: 1524.9915
A32: VN-L.32 | B32: 32 | C32: 1.2 | D32: CLAVO ACERO 2 X 3.8MM CAJA (250) | E32: Auxiliar | F32: Artículo | G32: M06-0040 | H32: 2 | I32: 6370.375
A33: VN-L.32 | B33: 33 | C33: 1.2 | D33: REPEMAX CAPA GRUESA 80XA-W2 (40KG) | E33: Auxiliar | F33: Artículo | G33: M10-0090 | H33: 6 | I33: 5527.4967
A34: VN-L.32 | B34: 34 | C34: 1.2 | D34: PERNO ANCLAJE 3/8X3-1/2 | E34: Auxiliar | F34: Artículo | G34: M06-0240 | H34: 60 | I34: 156.8101
A35: VN-L.32 | B35: 35 | C35: 1.2 | D35: CRAYON LYRA AMARILLO | E35: Auxiliar | F35: Artículo | G35: M06-0179 | H35: 10 | I35: 340.017
... A43: VN-L.32 | B43: 45 | C43: 1.3 | D43: ANGULAR HN 1"X1/8 | E43: Auxiliar | F43: Artículo | G43: M01-0018 | H43: 1 | I43: 4081.0741
A44: VN-L.32 | B44: 46 | C44: 1.3 | D44: VARILLA DEFORME #3 | E44: Auxiliar | F44: Artículo | G44: M01-0147 | H44: 6 | I44: 1344.7 | J44: 01
A45: VN-L.32 | B45: 47 | C45: 1.3 | D45: VARILLA DEFORME #4 | E45: Auxiliar | F45: Artículo | G45: M01-0148 | H45: 4 | I45: 2395.6
A46: VN-L.32 | B46: 48 | C46: 1.3 | D46: SOLDADURA 3/32 (6013) | E46: Auxiliar | F46: Artículo | G46: M01-0055 | H46: 5 | I46: 3600.0331
A47: VN-L.32 | B47: 49 | C47: 1.3 | D47: DISCO CORTE METAL FINO 9" | E47: Auxiliar | F47: Artículo | G47: M08-0037 | H47: 17 | I47: 3037.6321
A48: VN-L.32 | B48: 50 | C48: 1.3 | D48: DISCO ESMERILAR 4-1/2 | E48: Auxiliar | F48: Artículo | G48: M08-0043 | H48: 17 | I48: 1519.85
A49: VN-L.32 | B49: 51 | C49: 1.3 | D49: DISCO FLAP G60 4-1/2" | E49: Auxiliar | F49: Artículo | G49: M08-0044 | H49: 17 | I49: 1672.6034
A50: VN-L.32 | B50: 52 | C50: 1.3 | D50: DISCO CORTE FINO METAL 4-1/2 | E50: Auxiliar | F50: Artículo | G50: M08-0051 | H50: 17 | I50: 3661.2
A51: VN-L.32 | B51: 53 | C51: 1.3 | D51: THINNER INDUSTRIAL | E51: Auxiliar | F51: Artículo | G51: M11-0019 | H51: 4 | I51: 6465
A52: VN-L.32 | B52: 54 | C52: 1.3 | D52: MECHA BLANCA | E52: Auxiliar | F52: Artículo | G52: M06-0231 | H52: 4 | I52: 4338.0022
A53: VN-L.32 | B53: 55 | C53: 1.3 | D53: BROCHA CORRIENTE 3" | E53: Auxiliar | F53: Artículo | G53: M11-0002 | H53: 8 | I53: 2060.0013
A54: VN-L.32 | B54: 56 | C54: 1.3 | D54: ANTICORROSIVO MINIO GALON | E54: Auxiliar | F54: Artículo | G54: M11-0066 | H54: 3.5 | I54: 17605.004
A55: VN-L.32 | B55: 57 | C55: 1.3 | D55: STONE GRIP EPOXICO | E55: Auxiliar | F55: Artículo | G55: M06-0526 | H55: 2 | I55: 12244.505
A56: VN-L.32 | B56: 58 | C56: 1.3 | D56: LIJA DE AGUA #120 | E56: Auxiliar | F56: Artículo | G56: M08-0062 | H56: 10 | I56: 369.9959
... A78: VN-L.32 | B78: 95 | C78: 1.4 | D78: HOJALATERIA 30cm | E78: Auxiliar | F78: Artículo | G78: M15-0056 | H78: 12 | I78: 1120.96
A79: VN-L.32 | B79: 96 | C79: 1.5 | D79: VARILLA DEFORME #3 | E79: Auxiliar | F79: Artículo | G79: M01-0147 | H79: 87 | I79: 1344.7 | J79: 02
A80: VN-L.32 | B80: 97 | C80: 1.5 | D80: ALAMBRE NEGRO #16 (1.68MM) | E80: Auxiliar | F80: Artículo | G80: M01-0001 | H80: 27.1 | I80: 586.8542
A81: VN-L.32 | B81: 98 | C81: 1.5 | D81: DISCO CORTE FINO METAL 4-1/2 | E81: Auxiliar | F81: Artículo | G81: M08-0051 | H81: 1 | I81: 3661.2
A82: VN-L.32 | B82: 99 | C82: 1.5 | D82: DISCO CORTE METAL FINO 9" | E82: Auxiliar | F82: Artículo | G82: M08-0037 | H82: 1 | I82: 3037.6321
A83: VN-L.32 | B83: 100 | C83: 1.5 | D83: CONCRETO FC 210 KG/CM2 NORMAL | E83: Auxiliar | F83: Artículo | G83: M10-0065 | H83: 9.08828 | I83: 78867.084
A84: VN-L.32 | B84: 101 | C84: 1.5 | D84: VARILLA DEFORME #2 | E84: Auxiliar | F84: Artículo | G84: M01-0146 | H84: 15 | I84: 569.8025
A85: VN-L.32 | B85: 102 | C85: 1.5 | D85: LASTRE FINO | E85: Auxiliar | F85: Artículo | G85: M10-0023 | H85: 15.5 | I85: 14166.663
A86: VN-L.32 | B86: 103 | C86: 1.5 | D86: MALLA ELECTROSOLDADA #2 (5.3 MM) | E86: Auxiliar | F86: Artículo | G86: M01-0145 | H86: 9.5 | I86: 18762.497
A87: VN-L.32 | B87: 104 | C87: 1.5 | D87: ROLLO PLASTICO NEGRO 3,6MX100M | E87: Auxiliar | F87: Artículo | G87: M06-0242 | H87: 0.08646 | I87: 65407.055
A88: VN-L.32 | B88: 105 | C88: 1.5 | D88: PIEDRA P/LAVADO GRUESA GRIS CON VERDE | E88: Auxiliar | F88: Artículo | G88: M10-0021 | H88: 10 | I88: 4520
A89: VN-L.32 | B89: 106 | C89: 1.5 | D89: MAXICLEAR BRILLANTE | E89: Auxiliar | F89: Artículo | G89: M11-0111 | H89: 1 | I89: 29260.005
A90: VN-L.32 | B90: 108 | C90: 1.5 | D90: BALDOSA LISA 1,5M LARGO (140x50x4) | E90: Auxiliar | F90: Artículo | G90: M10-0094 | H90: 30 | I90: 6988.62
A91: VN-L.32 | B91: 111 | C91: 1.5 | D91: COLUMNA EN T PREFA 3,30x12x12 | E91: Auxiliar | F91: Artículo | G91: M10-0095 | H91: 1 | I91: 6115.08
... A135: VN-L.32 | B135: 155 | C135: 2.3 | D135: PINTURA INTERIOR FIBROCENTRO | E135: Auxiliar | F135: Artículo | G135: M11-0076 | H135: 5 | I135: 44999.994
A136: VN-L.32 | B136: 156 | C136: 2.3 | D136: PINTURA SEAL COAT CUBETA | E136: Auxiliar | F136: Artículo | G136: M11-0115 | H136: 4 | I136: 73043.2 | J136: 05
A137: VN-L.32 | B137: 159 | C137: 2.3 | D137: PINTURA SUPER COAT CUBETA | E137: Auxiliar | F137: Artículo | G137: M11-0121 | H137: 1 | I137: 79640.004
A138: VN-L.32 | B138: 160 | C138: 2.3 | D138: LIJA DE AGUA #180 | E138: Auxiliar | F138: Artículo | G138: M08-0064 | H138: 9 | I138: 324.9993
A139: VN-L.32 | B139: 161 | C139: 2.3 | D139: DURETAN BLANCO | E139: Auxiliar | F139: Artículo | G139: M06-0003 | H139: 1 | I139: 4746.8136
A140: VN-L.32 | B140: 162 | C140: 2.3 | D140: SILICON PINTABLE | E140: Auxiliar | F140: Artículo | G140: M06-0025 | H140: 2 | I140: 2839.4979
A141: VN-L.32 | B141: 163 | C141: 2.3 | D141: MECHA BLANCA | E141: Auxiliar | F141: Artículo | G141: M06-0231 | H141: 2 | I141: 4338.0022
A142: VN-L.32 | B142: 164 | C142: 2.3 | D142: THINNER INDUSTRIAL | E142: Auxiliar | F142: Artículo | G142: M11-0019 | H142: 3 | I142: 6465
A143: VN-L.32 | B143: 165 | C143: 2.3 | D143: PINTURA SUPER DRY GALON | E143: Auxiliar | F143: Artículo | G143: M11-0073 | H143: 1 | I143: 24555.996
A144: VN-L.32 | B144: 166 | C144: 2.3 | D144: BROCHA CORRIENTE 2" | E144: Auxiliar | F144: Artículo | G144: M11-0001 | H144: 3 | I144: 1425.0091
A145: VN-L.32 | B145: 167 | C145: 2.3 | D145: BROCHA CORRIENTE 3" | E145: Auxiliar | F145: Artículo | G145: M11-0002 | H145: 6 | I145: 2060.0013
A146: VN-L.32 | B146: 168 | C146: 2.3 | D146: FELPA 3/4 | E146: Auxiliar | F146: Artículo | G146: M11-0004 | H146: 6 | I146: 1739.9966
A147: VN-L.32 | B147: 169 | C147: 2.3 | D147: RODILLO PARA FELPA | E147: Auxiliar | F147: Artículo | G147: M11-0009 | H147: 6 | I147: 2410.29
A148: VN-L.32 | B148: 170 | C148: 2.3 | D148: MASKING BLANCO 2" | E148: Auxiliar | F148: Artículo | G148: M06-0226 | H148: 3 | I148: 2885.003
... A236: VN-L.32 | B236: 262 | C236: 3.1 | D236: ARO REPELLO EMT 4X4 1GANG | E236: Auxiliar | F236: Artículo | G236: M05-0386 | H236: 4 | I236: 159.0814
A237: VN-L.32 | B237: 263 | C237: 3.1 | D237: VARILLA DEFORME #3 | E237: Auxiliar | F237: Artículo | G237: M01-0147 | H237: 6 | I237: 1344.7 | J237: 01
A238: VN-L.32 | B238: 264 | C238: 3.1 | D238: CAJA RECTANGULAR INTEMPERIE B5V 3HUECOS 1/2" (UL) | E238: Auxiliar | F238: Artículo | G238: M05-0160 | H238: 2 | I238: 1408.9179
A239: VN-L.32 | B239: 265 | C239: 3.1 | D239: CABLE TGP 3X12 | E239: Auxiliar | F239: Artículo | G239: M05-0264 | H239: 25 | I239: 1344.1915
A240: VN-L.32 | B240: 266 | C240: 3.1 | D240: GAZA EMT 1 OREJAS 3/4" | E240: Auxiliar | F240: Artículo | G240: M05-0407 | H240: 25 | I240: 18.306
A241: VN-L.32 | B241: 267 | C241: 3.1 | D241: TAPA CIEGA PARA CAJA OCTAGONAL | E241: Auxiliar | F241: Artículo | G241: M05-0015 | H241: 9 | I241: 156.0191
A242: VN-L.32 | B242: 268 | C242: 3.1 | D242: TAPA CIEGA CUADRADA 4X4 EMT | E242: Auxiliar | F242: Artículo | G242: M05-0410 | H242: 3 | I242: 154.4823
A243: VN-L.32 | B243: 269 | C243: 3.1 | D243: CONECTOR DERIVADOR 12-10 AWG IDC 562 562 AMARILLO | E243: Auxiliar | F243: Artículo | G243: M05-0007 | H243: 100 | I243: 116.6951
A244: VN-L.32 | B244: 270 | C244: 3.1 | D244: CONECTOR RESORTE ROJO | E244: Auxiliar | F244: Artículo | G244: M05-0008 | H244: 25 | I244: 108.0054
A245: VN-L.32 | B245: 271 | C245: 3.1 | D245: TAPE NEGRO SUPER 33+3M 19MM | E245: Auxiliar | F245: Artículo | G245: M05-0019 | H245: 3 | I245: 2530.8045
A246: VN-L.32 | B246: 272 | C246: 3.1 | D246: CABLE #12 | E246: Auxiliar | F246: Artículo | G246: M05-0259 | H246: 200 | I246: 265.55 | J246: 01
A247: VN-L.32 | B247: 273 | C247: 3.1 | D247: CABLE #12 | E247: Auxiliar | F247: Artículo | G247: M05-0259 | H247: 430 | I247: 265.55 | J247: 02
A248: VN-L.32 | B248: 274 | C248: 3.1 | D248: CABLE #12 | E248: Auxiliar | F248: Artículo | G248: M05-0259 | H248: 200 | I248: 265.55 | J248: 03
A249: VN-L.32 | B249: 275 | C249: 3.1 | D249: CABLE #12 | E249: Auxiliar | F249: Artículo | G249: M05-0259 | H249: 430 | I249: 265.55 | J249: 05
A250: VN-L.32 | B250: 276 | C250: 3.1 | D250: CONECTOR TSJ 1/2-3/8 EMT | E250: Auxiliar | F250: Artículo | G250: M05-0399 | H250: 10 | I250: 91.53
A251: VN-L.32 | B251: 277 | C251: 3.1 | D251: CONECTOR RESORTE AMARILLO | E251: Auxiliar | F251: Artículo | G251: M05-0011 | H251: 100 | I251: 89.6994
A252: VN-L.32 | B252: 278 | C252: 3.1 | D252: REGLA SEMIDURO 1X3X4 SIN CEPILLAR | E252: Auxiliar | F252: Artículo | G252: M09-0042 | H252: 1 | I252: 1524.9915
A253: VN-L.32 | B253: 279 | C253: 3.1 | D253: TORNILLO 8X1 1/4 P/BROCA | E253: Auxiliar | F253: Artículo | G253: M06-0061 | H253: 100 | I253: 14.5
A254: VN-L.32 | B254: 280 | C254: 3.1 | D254: TORNILLO GYPSUM 1 1/4" | E254: Auxiliar | F254: Artículo | G254: M06-0496 | H254: 200 | I254: 5.5
A255: VN-L.32 | B255: 281 | C255: 3.1 | D255: CABLE #10 | E255: Auxiliar | F255: Artículo | G255: M05-0258 | H255: 35 | I255: 463.3 | J255: 04
A256: VN-L.32 | B256: 282 | C256: 3.1 | D256: CONDULETA BOTAGUA 1-1/4 | E256: Auxiliar | F256: Artículo | G256: M05-0392 | H256: 1 | I256: 1006.83
A257: VN-L.32 | B257: 283 | C257: 3.1 | D257: CONDULETA BOTAGUA 1 | E257: Auxiliar | F257: Artículo | G257: M05-0393 | H257: 1 | I257: 824.9
A258: VN-L.32 | B258: 285 | C258: 3.1 | D258: CONECTOR TORNILLO EMT 1 | E258: Auxiliar | F258: Artículo | G258: M05-0396 | H258: 1 | I258: 172.4606
...

Sheet Detallado
C1: Desglose de Presupuesto
C2: Proyecto: | E2: =+'1_OG y 2_ACA'!D3 -> Modelo Casa
C3: Cliente: | E3: ADELANTE DESARROLLOS | R3: Actualizacion
C4: Fecha: | E4: 45995 | P4: TC | Q4: 515 | R4: 45727
C5: Ubicación: | E5: Cartago
C6: Area: | E6: ='1_OG y 2_ACA'!D9 -> 126.79
A7: DESCRIPCION DE HORAS M.O. | B7: N Tarea | C7: N° | D7: Variante | E7: Descripcion actividad | F7: Cantidad | G7: Unidad | H7: Unit mater | I7: Unit MO | J7: Unit Sub/ Equipos | K7: Total Mater | L7: Total MO | M7: Total Sub/Equipos | N7: Total Directo Colones | O7: Total Directo Dólares | X7: m.o | Y7: =+X50/'1_OG y 2_ACA'!D11 -> 107706.74 | Z7: =+'1_OG y 2_ACA'!D11 -> 116.57
E8: TOTAL PRESUPUESTO | K8: =+SUBTOTAL(9,K9:K950) -> 23471758 | L8: =+SUBTOTAL(9,L9:L950) -> 13952475 | M8: =+SUBTOTAL(9,M9:M950) -> 3317703.5 | N8: =+SUBTOTAL(9,N9:N950) -> 40741936 | O8: =+SUBTOTAL(9,O9:O950) -> 79110.556 | V8: =+C11 -> 1.1.1 | W8: =+E11 -> TRAZADO Y RELLENOS | X8: =+L11 -> 168187.5 | Y8: =+X8/$X$50 -> 0.013395657 | Z8: =+X8/$Z$7 -> 1442.8026
C9: 1 | E9: OBRA GRIS | K9: =+SUBTOTAL(9,K10:K392) -> 11108224 | L9: =+SUBTOTAL(9,L10:L392) -> 9499537.5 | M9: =+SUBTOTAL(9,M10:M392) -> 741220.35 | N9: =+SUBTOTAL(9,N10:N392) -> 21348982 | O9: =+SUBTOTAL(9,O10:O392) -> 41454.334 | V9: =+C21 -> 1.1.2 | W9: =+E21 -> EXCAVACIÓN | X9: =+L21 -> 131962.5 | Y9: =+X9/$X$50 -> 0.010510439 | Z9: =+X9/$Z$7 -> 1132.0451
B10: =VALUE(IF(AND(LEN(TRIM(C10))-LEN(SUBSTITUTE(TRIM(C10),".",""))=1,ISNUMBER(VALUE(SUBSTITUTE(TRIM(C10),".","")))),TRIM(C10),B9)) -> 1.1 | C10: 1.1 | E10: FUNDACIONES | F10: 1 | G10: UND | K10: =+SUBTOTAL(9,K11:K53) -> 1835286.7 | L10: =+SUBTOTAL(9,L11:L53) -> 1179900 | M10: =+SUBTOTAL(9,M11:M53) -> 151000 | N10: =+SUBTOTAL(9,N11:N53) -> 3166186.7 | O10: =+SUBTOTAL(9,O11:O53) -> 6147.9354 | V10: =+C28 -> 1.1.3 | W10: =+E28 -> SELLO DE CONCRETO | X10: =+L28 -> 23287.5 | Y10: =+X10/$X$50 -> 0.0018547833 | Z10: =+X10/$Z$7 -> 199.77267
B11: =VALUE(IF(AND(LEN(TRIM(C11))-LEN(SUBSTITUTE(TRIM(C11),".",""))=1,ISNUMBER(VALUE(SUBSTITUTE(TRIM(C11),".","")))),TRIM(C11),B10)) -> 1.1 | C11: 1.1.1 | E11: TRAZADO Y RELLENOS | F11: =+'1_OG y 2_ACA'!D219 -> 57.62 | G11: m2 | K11: =+SUBTOTAL(9,K12:K20) -> 276899.83 | L11: =+SUBTOTAL(9,L12:L20) -> 168187.5 | M11: =+SUBTOTAL(9,M12:M20) -> 151000 | N11: =+SUBTOTAL(9,N12:N20) -> 596087.33 | O11: =+SUBTOTAL(9,O12:O20) -> 1157.4511 | V11: =+C37 -> 1.1.4 | W11: =+E37 -> LOSA FLOTANTE (ACERO, CONCRETO) | X11: =+L37 -> 856462.5 | Y11: =+X11/$X$50 -> 0.068214808 | Z11: =+X11/$Z$7 -> 7347.1948 | AA11: =+AVERAGE(Z8:Z11) -> 2530.4538
B12: =VALUE(IF(AND(LEN(TRIM(C12))-LEN(SUBSTITUTE(TRIM(C12),".",""))=1,ISNUMBER(VALUE(SUBSTITUTE(TRIM(C12),".","")))),TRIM(C12),B11)) -> 1.1 | C12: M10-0023 | E12: =_xlfn.XLOOKUP(C12,'BASE DATOS PRECIOS '!B:B,'BASE DATOS PRECIOS '!E:E) -> LASTRE FINO | F12: =ROUNDUP('1_OG y 2_ACA'!D222,0) -> 19 | G12: =+_xlfn.XLOOKUP(C12,'BASE DATOS PRECIOS '!B:B,'BASE DATOS PRECIOS '!F:F) -> M3 | H12: =+_xlfn.XLOOKUP(E12,'BASE DATOS PRECIOS '!E:E,'BASE DATOS PRECIOS '!H:H) -> 14166.663 | K12: =+F12*H12 -> 269166.6 | L12: =+F12*I12 -> 0 | M12: =+F12*J12 -> 0 | N12: =SUM(K12:M12) -> 269166.6 | O12: =SUM(K12:M12)/tc -> 522.65359 | V12: =+C55 -> 1.2.1 | W12: =+E55 -> ACERO EN PAREDES MUROS N1 | X12: =+L55 -> 1112625 | Y12: =+X12/$X$50 -> 0.088617425 | Z12: =+X12/$Z$7 -> 9544.6942
B13: =VALUE(IF(AND(LEN(TRIM(C13))-LEN(SUBSTITUTE(TRIM(C13),".",""))=1,ISNUMBER(VALUE(SUBSTITUTE(TRIM(C13),".","")))),TRIM(C13),B12)) -> 1.1 | C13: M06-0163 | E13: =_xlfn.XLOOKUP(C13,'BASE DATOS PRECIOS '!B:B,'BASE DATOS PRECIOS '!E:E) -> BOLSA CAL | F13: =+'1_OG y 2_ACA'!D223 -> 2 | G13: =+_xlfn.XLOOKUP(C13,'BASE DATOS PRECIOS '!B:B,'BASE DATOS PRECIOS '!F:F) -> BOLSA | H13: =+_xlfn.XLOOKUP(E13,'BASE DATOS PRECIOS '!E:E,'BASE DATOS PRECIOS '!H:H) -> 1627.2 | K13: =+F13*H13 -> 3254.4 | L13: =+F13*I13 -> 0 | M13: =+F13*J13 -> 0 | N13: =SUM(K13:M13) -> 3254.4 | O13: =SUM(K13:M13)/tc -> 6.3192233 | V13: =+C68 -> 1.2.2 | W13: =+E68 -> PAREDES, MUROS N1 (FORMALETA, CONCRETO, DESENCOFRADO) | X13: =+L68 -> 980662.5 | Y13: =+X13/$X$50 -> 0.078106986 | Z13: =+X13/$Z$7 -> 8412.6491
B14: =VALUE(IF(AND(LEN(TRIM(C14))-LEN(SUBSTITUTE(TRIM(C14),".",""))=1,ISNUMBER(VALUE(SUBSTITUTE(TRIM(C14),".","")))),TRIM(C14),B13)) -> 1.1 | C14: M06-0179 | E14: =_xlfn.XLOOKUP(C14,'BASE DATOS PRECIOS '!B:B,'BASE DATOS PRECIOS '!E:E) -> CRAYON LYRA AMARILLO | F14: =+'1_OG y 2_ACA'!D224 -> 6 | G14: =+_xlfn.XLOOKUP(C14,'BASE DATOS PRECIOS '!B:B,'BASE DATOS PRECIOS '!F:F) -> UND | H14: =+_xlfn.XLOOKUP(E14,'BASE DATOS PRECIOS '!E:E,'BASE DATOS PRECIOS '!H:H) -> 340.017 | K14: =+F14*H14 -> 2040.102 | L14: =+F14*I14 -> 0 | M14: =+F14*J14 -> 0 | N14: =SUM(K14:M14) -> 2040.102 | O14: =SUM(K14:M14)/tc -> 3.9613631 | V14: =+C84 -> 1.2.3 | W14: =+E84 -> MAMPOSTERIA | X14: =+L84 -> 0 | Y14: =+X14/$X$50 -> 0 | Z14: =+X14/$Z$7 -> 0
B15: =VALUE(IF(AND(LEN(TRIM(C15))-LEN(SUBSTITUTE(TRIM(C15),".",""))=1,ISNUMBER(VALUE(SUBSTITUTE(TRIM(C15),".","")))),TRIM(C15),B14)) -> 1.1 | C15: M06-0180 | E15: =_xlfn.XLOOKUP(C15,'BASE DATOS PRECIOS '!B:B,'BASE DATOS PRECIOS '!E:E) -> CUERDA ALBAÑIL BLANCA | F15: =+'1_OG y 2_ACA'!D225 -> 3 | G15: =+_xlfn.XLOOKUP(C15,'BASE DATOS PRECIOS '!B:B,'BASE DATOS PRECIOS '!F:F) -> UND | H15: =+_xlfn.XLOOKUP(E15,'BASE DATOS PRECIOS '!E:E,'BASE DATOS PRECIOS '!H:H) -> 812.9107 | K15: =+F15*H15 -> 2438.7321 | L15: =+F15*I15 -> 0 | M15: =+F15*J15 -> 0 | N15: =SUM(K15:M15) -> 2438.7321 | O15: =SUM(K15:M15)/tc -> 4.7354021 | V15: =+C89 -> 1.2.4 | W15: =+E89 -> ACERO EN PAREDES MUROS N2 | X15: =+L89 -> 859050 | Y15: =+X15/$X$50 -> 0.068420895 | Z15: =+X15/$Z$7 -> 7369.3918
B16: =VALUE(IF(AND(LEN(TRIM(C16))-LEN(SUBSTITUTE(TRIM(C16),".",""))=1,ISNUMBER(VALUE(SUBSTITUTE(TRIM(C16),".","")))),TRIM(C16),B15)) -> 1.1 | C16: BACK HOE | E16: =+_xlfn.XLOOKUP(C16,'BASE DATOS EQUIPOS Y SUBCONTRAT'!A:A,'BASE DATOS EQUIPOS Y SUBCONTRAT'!B:B) -> BACK HOE | F16: =+'1_OG y 2_ACA'!F233 -> 6 | G16: =+_xlfn.XLOOKUP(C16,'BASE DATOS EQUIPOS Y SUBCONTRAT'!A:A,'BASE DATOS EQUIPOS Y SUBCONTRAT'!C:C) -> HORA | H16: 0 | J16: =+_xlfn.XLOOKUP(C16,'BASE DATOS EQUIPOS Y SUBCONTRAT'!A:A,'BASE DATOS EQUIPOS Y SUBCONTRAT'!E:E) -> 15000 | K16: =+F16*H16 -> 0 | L16: =+F16*I16 -> 0 | M16: =+F16*J16 -> 90000 | N16: =SUM(K16:M16) -> 90000 | O16: =SUM(K16:M16)/tc -> 174.75728 | V16: =+C101 -> 1.2.5 | W16: =+E101 -> PAREDES, MUROS N2 (FORMALETA, CONCRETO, DESENCOFRADO) | X16: =+L101 -> 424350 | Y16: =+X16/$X$50 -> 0.033798274 | Z16: =+X16/$Z$7 -> 3640.302 | AA16: =+AVERAGE(Z12:Z16) -> 5793.4074
B17: =VALUE(IF(AND(LEN(TRIM(C17))-LEN(SUBSTITUTE(TRIM(C17),".",""))=1,ISNUMBER(VALUE(SUBSTITUTE(TRIM(C17),".","")))),TRIM(C17),B16)) -> 1.1 | C17: COMPACTADOR | E17: =+_xlfn.XLOOKUP(C17,'BASE DATOS EQUIPOS Y SUBCONTRAT'!A:A,'BASE DATOS EQUIPOS Y SUBCONTRAT'!B:B) -> COMPACTADOR | F17: =+'1_OG y 2_ACA'!F234 -> 1 | G17: =+_xlfn.XLOOKUP(C17,'BASE DATOS EQUIPOS Y SUBCONTRAT'!A:A,'BASE DATOS EQUIPOS Y SUBCONTRAT'!C:C) -> HORA | H17: 0 | J17: =+_xlfn.XLOOKUP(C17,'BASE DATOS EQUIPOS Y SUBCONTRAT'!A:A,'BASE DATOS EQUIPOS Y SUBCONTRAT'!E:E) -> 13000 | K17: =+F17*H17 -> 0 | L17: =+F17*I17 -> 0 | M17: =+F17*J17 -> 13000 | N17: =SUM(K17:M17) -> 13000 | O17: =SUM(K17:M17)/tc -> 25.242718 | V17: =+C116 -> 1.3.1 | W17: =+E116 -> ESTRUCTURA TECHO CASA | X17: =+L116 -> 1047000 | Y17: =+X17/$X$50 -> 0.08339058 | Z17: =+X17/$Z$7 -> 8981.7277
B18: =VALUE(IF(AND(LEN(TRIM(C18))-LEN(SUBSTITUTE(TRIM(C18),".",""))=1,ISNUMBER(VALUE(SUBSTITUTE(TRIM(C18),".","")))),TRIM(C18),B17)) -> 1.1 | C18: VAGONETA | E18: =+_xlfn.XLOOKUP(C18,'BASE DATOS EQUIPOS Y SUBCONTRAT'!A:A,'BASE DATOS EQUIPOS Y SUBCONTRAT'!B:B) -> VAGONETA | F18: =+'1_OG y 2_ACA'!F235 -> 2 | G18: =+_xlfn.XLOOKUP(C18,'BASE DATOS EQUIPOS Y SUBCONTRAT'!A:A,'BASE DATOS EQUIPOS Y SUBCONTRAT'!C:C) -> HORA | J18: =+_xlfn.XLOOKUP(C18,'BASE DATOS EQUIPOS Y SUBCONTRAT'!A:A,'BASE DATOS EQUIPOS Y SUBCONTRAT'!E:E) -> 24000 | K18: =+F18*H18 -> 0 | L18: =+F18*I18 -> 0 | M18: =+F18*J18 -> 48000 | N18: =SUM(K18:M18) -> 48000 | O18: =SUM(K18:M18)/tc -> 93.203883 | V18: =+C144 -> 1.3.2 | W18: =+E144 -> ESTRUCTURA TECHO COCHERA | X18: =+L144 -> 408000 | Y18: =+X18/$X$50 -> 0.032496043 | Z18: =+X18/$Z$7 -> 3500.0429
A19: Losa Flotante (Formaleta trazo) | B19: =VALUE(IF(AND(LEN(TRIM(C19))-LEN(SUBSTITUTE(TRIM(C19),".",""))=1,ISNUMBER(VALUE(SUBSTITUTE(TRIM(C19),".","")))),TRIM(C19),B18)) -> 1.1 | C19: OPERARIO | E19: =+_xlfn.XLOOKUP(C19,'BASE DATOS MANO DE OBRA'!A:A,'BASE DATOS MANO DE OBRA'!B:B) -> OPERARIO PLUS | F19: =ROUND('1_OG y 2_ACA'!F230,0)/2 -> 32.5 | G19: =+_xlfn.XLOOKUP(C19,'BASE DATOS MANO DE OBRA'!A:A,'BASE DATOS MANO DE OBRA'!C:C) -> hora | H19: 0 | I19: =+_xlfn.XLOOKUP(C19,'BASE DATOS MANO DE OBRA'!A:A,'BASE DATOS MANO DE OBRA'!E:E) -> 2850 | J19: 0 | K19: =+F19*H19 -> 0 | L19: =+F19*I19 -> 92625 | M19: =+F19*J19 -> 0 | N19: =SUM(K19:M19) -> 92625 | O19: =SUM(K19:M19)/tc -> 179.85437 | V19: =+C168 -> 1.3.3 | W19: =+E168 -> CUBIERTA TECHO CASA | X19: =+L168 -> 403650 | Y19: =+X19/$X$50 -> 0.032149577 | Z19: =+X19/$Z$7 -> 3462.7263
A20: Losa Flotante (Formaleta trazo) | B20: =VALUE(IF(AND(LEN(TRIM(C20))-LEN(SUBSTITUTE(TRIM(C20),".",""))=1,ISNUMBER(VALUE(SUBSTITUTE(TRIM(C20),".","")))),TRIM(C20),B19)) -> 1.1 | C20: AYUDANTE | E20: =+_xlfn.XLOOKUP(C20,'BASE DATOS MANO DE OBRA'!A:A,'BASE DATOS MANO DE OBRA'!B:B) -> AYUDANTE PLUS | F20: =+F19 -> 32.5 | G20: =+_xlfn.XLOOKUP(C20,'BASE DATOS MANO DE OBRA'!A:A,'BASE DATOS MANO DE OBRA'!C:C) -> hora | H20: 0 | I20: =+_xlfn.XLOOKUP(C20,'BASE DATOS MANO DE OBRA'!A:A,'BASE DATOS MANO DE OBRA'!E:E) -> 2325 | J20: 0 | K20: =+F20*H20 -> 0 | L20: =+F20*I20 -> 75562.5 | M20: =+F20*J20 -> 0 | N20: =SUM(K20:M20) -> 75562.5 | O20: =SUM(K20:M20)/tc -> 146.7233 | V20: =+C175 -> 1.3.4 | W20: =+E175 -> CUBIERTA TECHO COCHERA | X20: =+L175 -> 0 | Y20: =+X20/$X$50 -> 0 | Z20: =+X20/$Z$7 -> 0
B21: =VALUE(IF(AND(LEN(TRIM(C21))-LEN(SUBSTITUTE(TRIM(C21),".",""))=1,ISNUMBER(VALUE(SUBSTITUTE(TRIM(C21),".","")))),TRIM(C21),B20)) -> 1.1 | C21: 1.1.2 | E21: EXCAVACIÓN | F21: =+'1_OG y 2_ACA'!D219 -> 57.62 | G21: m2 | K21: =+SUBTOTAL(9,K22:K27) -> 13982.942 | L21: =+SUBTOTAL(9,L22:L27) -> 131962.5 | M21: =+SUBTOTAL(9,M22:M27) -> 0 | N21: =+SUBTOTAL(9,N22:N27) -> 145945.44 | O21: =+SUBTOTAL(9,O22:O27) -> 283.38921 | V21: =+C187 -> 1.3.5 | W21: =+E187 -> GRADAS ESTRUCTURA, PINTADO Y ACABADO | X21: =+L187 -> 0 | Y21: =+X21/$X$50 -> 0 | Z21: =+X21/$Z$7 -> 0
B22: =VALUE(IF(AND(LEN(TRIM(C22))-LEN(SUBSTITUTE(TRIM(C22),".",""))=1,ISNUMBER(VALUE(SUBSTITUTE(TRIM(C22),".","")))),TRIM(C22),B21)) -> 1.1 | C22: M10-0010 | E22: =+_xlfn.XLOOKUP(C22,'BASE DATOS PRECIOS '!B:B,'BASE DATOS PRECIOS '!E:E) -> ARENA LAVADA | F22: =+'1_OG y 2_ACA'!D241 -> 0.5 | G22: =+_xlfn.XLOOKUP(C22,'BASE DATOS PRECIOS '!B:B,'BASE DATOS PRECIOS '!F:F) -> M3 | H22: =+_xlfn.XLOOKUP(E22,'BASE DATOS PRECIOS '!E:E,'BASE DATOS PRECIOS '!H:H) -> 12044.501 | K22: =+F22*H22 -> 6022.2503 | L22: =+F22*I22 -> 0 | M22: =+F22*J22 -> 0 | N22: =SUM(K22:M22) -> 6022.2503 | O22: =SUM(K22:M22)/tc -> 11.69369 | V22: =+C213 -> 1.3.6 | W22: =+E213 -> BARANDA DE GRADAS (N2) | X22: =+L213 -> 219937.5 | Y22: =+X22/$X$50 -> 0.017517398 | Z22: =+X22/$Z$7 -> 1886.7419
B23: =VALUE(IF(AND(LEN(TRIM(C23))-LEN(SUBSTITUTE(TRIM(C23),".",""))=1,ISNUMBER(VALUE(SUBSTITUTE(TRIM(C23),".","")))),TRIM(C23),B22)) -> 1.1 | C23: M06-0231 | E23: =+_xlfn.XLOOKUP(C23,'BASE DATOS PRECIOS '!B:B,'BASE DATOS PRECIOS '!E:E) -> MECHA BLANCA | F23: =+'1_OG y 2_ACA'!D242 -> 1 | G23: =+_xlfn.XLOOKUP(C23,'BASE DATOS PRECIOS '!B:B,'BASE DATOS PRECIOS '!F:F) -> KG | H23: =+_xlfn.XLOOKUP(E23,'BASE DATOS PRECIOS '!E:E,'BASE DATOS PRECIOS '!H:H) -> 4338.0022 | K23: =+F23*H23 -> 4338.0022 | L23: =+F23*I23 -> 0 | M23: =+F23*J23 -> 0 | N23: =SUM(K23:M23) -> 4338.0022 | O23: =SUM(K23:M23)/tc -> 8.4233052 | V23: =+C229 -> 1.3.7 | W23: =+E229 -> ESTRUCTURA METÁLICA INTERNA | X23: =+L229 -> 0 | Y23: =+X23/$X$50 -> 0 | Z23: =+X23/$Z$7 -> 0 | AA23: =+AVERAGE(Z17:Z23) -> 2547.3198
B24: =VALUE(IF(AND(LEN(TRIM(C24))-LEN(SUBSTITUTE(TRIM(C24),".",""))=1,ISNUMBER(VALUE(SUBSTITUTE(TRIM(C24),".","")))),TRIM(C24),B23)) -> 1.1 | C24: M06-0180 | E24: =+_xlfn.XLOOKUP(C24,'BASE DATOS PRECIOS '!B:B,'BASE DATOS PRECIOS '!E:E) -> CUERDA ALBAÑIL BLANCA | F24: =+'1_OG y 2_ACA'!D243 -> 1 | G24: =+_xlfn.XLOOKUP(C24,'BASE DATOS PRECIOS '!B:B,'BASE DATOS PRECIOS '!F:F) -> UND | H24: =+_xlfn.XLOOKUP(E24,'BASE DATOS PRECIOS '!E:E,'BASE DATOS PRECIOS '!H:H) -> 812.9107 | K24: =+F24*H24 -> 812.9107 | L24: =+F24*I24 -> 0 | M24: =+F24*J24 -> 0 | N24: =SUM(K24:M24) -> 812.9107 | O24: =SUM(K24:M24)/tc -> 1.5784674 | V24: =+C237 -> 1.4.1 | W24: =+E237 -> BOTAGUAS Y CANOAS | X24: =+L237 -> 553725 | Y24: =+X24/$X$50 -> 0.044102625 | Z24: =+X24/$Z$7 -> 4750.1501
B25: =VALUE(IF(AND(LEN(TRIM(C25))-LEN(SUBSTITUTE(TRIM(C25),".",""))=1,ISNUMBER(VALUE(SUBSTITUTE(TRIM(C25),".","")))),TRIM(C25),B24)) -> 1.1 | C25: M06-0123 | E25: =+_xlfn.XLOOKUP(C25,'BASE DATOS PRECIOS '!B:B,'BASE DATOS PRECIOS '!E:E) -> ACETONA | F25: =+'1_OG y 2_ACA'!D244 -> 1 | G25: =+_xlfn.XLOOKUP(C25,'BASE DATOS PRECIOS '!B:B,'BASE DATOS PRECIOS '!F:F) -> LITRO | H25: =+_xlfn.XLOOKUP(E25,'BASE DATOS PRECIOS '!E:E,'BASE DATOS PRECIOS '!H:H) -> 2809.7789 | K25: =+F25*H25 -> 2809.7789 | L25: =+F25*I25 -> 0 | M25: =+F25*J25 -> 0 | N25: =SUM(K25:M25) -> 2809.7789 | O25: =SUM(K25:M25)/tc -> 5.4558814 | V25: =+C248 -> 1.4.2 | W25: =+E248 -> BAJANTES | X25: =+L248 -> 160425 | Y25: =+X25/$X$50 -> 0.012777396 | Z25: =+X25/$Z$7 -> 1376.2117 | AA25: =+AVERAGE(Z24:Z25) -> 3063.1809
A26: Losa Flotante (Formaleta trazo) | B26: =VALUE(IF(AND(LEN(TRIM(C26))-LEN(SUBSTITUTE(TRIM(C26),".",""))=1,ISNUMBER(VALUE(SUBSTITUTE(TRIM(C26),".","")))),TRIM(C26),B25)) -> 1.1 | C26: OPERARIO | E26: =+_xlfn.XLOOKUP(C26,'BASE DATOS MANO DE OBRA'!A:A,'BASE DATOS MANO DE OBRA'!B:B) -> OPERARIO PLUS | F26: =ROUND('1_OG y 2_ACA'!F248,0)/2 -> 25.5 | G26: =+_xlfn.XLOOKUP(C26,'BASE DATOS MANO DE OBRA'!A:A,'BASE DATOS MANO DE OBRA'!C:C) -> hora | H26: 0 | I26: =+_xlfn.XLOOKUP(C26,'BASE DATOS MANO DE OBRA'!A:A,'BASE DATOS MANO DE OBRA'!E:E) -> 2850 | J26: 0 | K26: =+F26*H26 -> 0 | L26: =+F26*I26 -> 72675 | M26: =+F26*J26 -> 0 | N26: =SUM(K26:M26) -> 72675 | O26: =SUM(K26:M26)/tc -> 141.1165 | V26: =+C254 -> 1.5.1 | W26: =+E254 -> GRADAS EN CONCRETO | X26: =+L254 -> 543375 | Y26: =+X26/$X$50 -> 0.043278277 | Z26: =+X26/$Z$7 -> 4661.3623
A27: Losa Flotante (Formaleta trazo) | B27: =VALUE(IF(AND(LEN(TRIM(C27))-LEN(SUBSTITUTE(TRIM(C27),".",""))=1,ISNUMBER(VALUE(SUBSTITUTE(TRIM(C27),".","")))),TRIM(C27),B26)) -> 1.1 | C27: AYUDANTE | E27: =+_xlfn.XLOOKUP(C27,'BASE DATOS MANO DE OBRA'!A:A,'BASE DATOS MANO DE OBRA'!B:B) -> AYUDANTE PLUS | F27: =+F26 -> 25.5 | G27: =+_xlfn.XLOOKUP(C27,'BASE DATOS MANO DE OBRA'!A:A,'BASE DATOS MANO DE OBRA'!C:C) -> hora | H27: 0 | I27: =+_xlfn.XLOOKUP(C27,'BASE DATOS MANO DE OBRA'!A:A,'BASE DATOS MANO DE OBRA'!E:E) -> 2325 | J27: 0 | K27: =+F27*H27 -> 0 | L27: =+F27*I27 -> 59287.5 | M27: =+F27*J27 -> 0 | N27: =SUM(K27:M27) -> 59287.5 | O27: =SUM(K27:M27)/tc -> 115.12136 | V27: =+C269 -> 1.5.2 | W27: =+E269 -> COLUMNAS (MEDIDOR) | X27: =+L269 -> 152662.5 | Y27: =+X27/$X$50 -> 0.012159135 | Z27: =+X27/$Z$7 -> 1309.6208
B28: =VALUE(IF(AND(LEN(TRIM(C28))-LEN(SUBSTITUTE(TRIM(C28),".",""))=1,ISNUMBER(VALUE(SUBSTITUTE(TRIM(C28),".","")))),TRIM(C28),B27)) -> 1.1 | C28: 1.1.3 | E28: SELLO DE CONCRETO | F28: =+'1_OG y 2_ACA'!D253 -> 48.12 | G28: m2 | K28: =+SUBTOTAL(9,K29:K36) -> 157774.98 | L28: =+SUBTOTAL(9,L29:L36) -> 23287.5 | M28: =+SUBTOTAL(9,M29:M36) -> 0 | N28: =+SUBTOTAL(9,N29:N36) -> 181062.48 | O28: =+SUBTOTAL(9,O29:O36) -> 351.57762 | V28: =+C282 -> 1.5.3 | W28: =+E282 -> CHORREA DE COCHERAS Y PILAS | X28: =+L282 -> 608062.5 | Y28: =+X28/$X$50 -> 0.048430453 | Z28: =+X28/$Z$7 -> 5216.2864
B29: =VALUE(IF(AND(LEN(TRIM(C29))-LEN(SUBSTITUTE(TRIM(C29),".",""))=1,ISNUMBER(VALUE(SUBSTITUTE(TRIM(C29),".","")))),TRIM(C29),B28)) -> 1.1 | E29: CONCRETO | V29: =+C299 -> 1.5.4 | W29: =+E299 -> TAPIAS PREFABRICADAS | X29: =+L299 -> 144900 | Y29: =+X29/$X$50 -> 0.011540874 | Z29: =+X29/$Z$7 -> 1243.0299
B30: =VALUE(IF(AND(LEN(TRIM(C30))-LEN(SUBSTITUTE(TRIM(C30),".",""))=1,ISNUMBER(VALUE(SUBSTITUTE(TRIM(C30),".","")))),TRIM(C30),B29)) -> 1.1 | C30: M01-0067 | E30: =+_xlfn.XLOOKUP(C30,'BASE DATOS PRECIOS '!B:B,'BASE DATOS PRECIOS '!E:E) -> TUBO 1X2X1.5MM HN | F30: =+'1_OG y 2_ACA'!D261 -> 1 | G30: =+_xlfn.XLOOKUP(C30,'BASE DATOS PRECIOS '!B:B,'BASE DATOS PRECIOS '!F:F) -> UND | H30: =+_xlfn.XLOOKUP(E30,'BASE DATOS PRECIOS '!E:E,'BASE DATOS PRECIOS '!H:H) -> 14238 | K30: =+F30*H30 -> 14238 | L30: =+F30*I30 -> 0 | M30: =+F30*J30 -> 0 | N30: =SUM(K30:M30) -> 14238 | O30: =SUM(K30:M30)/tc -> 27.646602 | V30: =+C395 -> 2.1.1 | W30: =+E395 -> REPELLOS INTERNO Y EXTERNO | X30: =+L395 -> 1014300 | Y30: =+X30/$X$50 -> 0.080786117 | Z30: =+X30/$Z$7 -> 8701.2096
B31: =VALUE(IF(AND(LEN(TRIM(C31))-LEN(SUBSTITUTE(TRIM(C31),".",""))=1,ISNUMBER(VALUE(SUBSTITUTE(TRIM(C31),".","")))),TRIM(C31),B30)) -> 1.1 | C31: M01-0148 | E31: =+_xlfn.XLOOKUP(C31,'BASE DATOS PRECIOS '!B:B,'BASE DATOS PRECIOS '!E:E) -> VARILLA DEFORME #4 | F31: =+'1_OG y 2_ACA'!D262 -> 1 | G31: =+_xlfn.XLOOKUP(C31,'BASE DATOS PRECIOS '!B:B,'BASE DATOS PRECIOS '!F:F) -> UND | H31: =+_xlfn.XLOOKUP(E31,'BASE DATOS PRECIOS '!E:E,'BASE DATOS PRECIOS '!H:H) -> 2395.6 | K31: =+F31*H31 -> 2395.6 | L31: =+F31*I31 -> 0 | M31: =+F31*J31 -> 0 | N31: =SUM(K31:M31) -> 2395.6 | O31: =SUM(K31:M31)/tc -> 4.6516505 | V31: =+C399 -> 2.1.2 | W31: =+E399 -> EMPASTE | X31: =+L399 -> 263925 | Y31: =+X31/$X$50 -> 0.021020878 | Z31: =+X31/$Z$7 -> 2264.0902 | AA31: =+AVERAGE(Z30:Z31) -> 5482.6499
B32: =VALUE(IF(AND(LEN(TRIM(C32))-LEN(SUBSTITUTE(TRIM(C32),".",""))=1,ISNUMBER(VALUE(SUBSTITUTE(TRIM(C32),".","")))),TRIM(C32),B31)) -> 1.1 | C32: M06-0180 | E32: =+_xlfn.XLOOKUP(C32,'BASE DATOS PRECIOS '!B:B,'BASE DATOS PRECIOS '!E:E) -> CUERDA ALBAÑIL BLANCA | F32: =+'1_OG y 2_ACA'!D263 -> 3 | G32: =+_xlfn.XLOOKUP(C32,'BASE DATOS PRECIOS '!B:B,'BASE DATOS PRECIOS '!F:F) -> UND | H32: =+_xlfn.XLOOKUP(E32,'BASE DATOS PRECIOS '!E:E,'BASE DATOS PRECIOS '!H:H) -> 812.9107 | K32: =+F32*H32 -> 2438.7321 | L32: =+F32*I32 -> 0 | M32: =+F32*J32 -> 0 | N32: =SUM(K32:M32) -> 2438.7321 | O32: =SUM(K32:M32)/tc -> 4.7354021 | V32: =+C407 -> 2.2.1 | W32: =+E407 -> ENCHAPES (INTERNO Y EXTERNO) | X32: =+L407 -> 626175 | Y32: =+X32/$X$50 -> 0.049873062 | Z32: =+X32/$Z$7 -> 5371.6651 | AA32: =+AVERAGE(Z32) -> 5371.6651
B33: =VALUE(IF(AND(LEN(TRIM(C33))-LEN(SUBSTITUTE(TRIM(C33),".",""))=1,ISNUMBER(VALUE(SUBSTITUTE(TRIM(C33),".","")))),TRIM(C33),B32)) -> 1.1 | C33: M09-0042 | E33: =+_xlfn.XLOOKUP(C33,'BASE DATOS PRECIOS '!B:B,'BASE DATOS PRECIOS '!E:E) -> REGLA SEMIDURO 1X3X4 SIN CEPILLAR | F33: =+'1_OG y 2_ACA'!D264 -> 5 | G33: =+_xlfn.XLOOKUP(C33,'BASE DATOS PRECIOS '!B:B,'BASE DATOS PRECIOS '!F:F) -> UND | H33: =+_xlfn.XLOOKUP(E33,'BASE DATOS PRECIOS '!E:E,'BASE DATOS PRECIOS '!H:H) -> 1524.9915 | K33: =+F33*H33 -> 7624.9575 | L33: =+F33*I33 -> 0 | M33: =+F33*J33 -> 0 | N33: =SUM(K33:M33) -> 7624.9575 | O33: =SUM(K33:M33)/tc -> 14.805743 | V33: =+C429 -> 2.3.1 | W33: =+E429 -> PINTURA PAREDES Y CIELOS | X33: =+L429 -> 773662.5 | Y33: =+X33/$X$50 -> 0.061620023 | Z33: =+X33/$Z$7 -> 6636.892
B34: =VALUE(IF(AND(LEN(TRIM(C34))-LEN(SUBSTITUTE(TRIM(C34),".",""))=1,ISNUMBER(VALUE(SUBSTITUTE(TRIM(C34),".","")))),TRIM(C34),B33)) -> 1.1 | C34: M10-0091 | E34: =+_xlfn.XLOOKUP(C34,'BASE DATOS PRECIOS '!B:B,'BASE DATOS PRECIOS '!E:E) -> CONCRETO FC 120 CM2 (Concreto Pobre, Sello) | F34: ='1_OG y 2_ACA'!D255 -> 2.406 | G34: =+_xlfn.XLOOKUP(C34,'BASE DATOS PRECIOS '!B:B,'BASE DATOS PRECIOS '!F:F) -> M3 | H34: =+_xlfn.XLOOKUP(E34,'BASE DATOS PRECIOS '!E:E,'BASE DATOS PRECIOS '!H:H) -> 54479.503 | K34: =+F34*H34 -> 131077.69 | L34: =+F34*I34 -> 0 | M34: =+F34*J34 -> 0 | N34: =SUM(K34:M34) -> 131077.69 | O34: =SUM(K34:M34)/tc -> 254.51978 | V34: =+C431 -> M11-0115 | W34: =+E431 -> PINTURA SEAL COAT CUBETA | X34: =+L431 -> 0 | Y34: =+X34/$X$50 -> 0 | Z34: =+X34/$Z$7 -> 0
A35: Sello Losa | B35: =VALUE(IF(AND(LEN(TRIM(C35))-LEN(SUBSTITUTE(TRIM(C35),".",""))=1,ISNUMBER(VALUE(SUBSTITUTE(TRIM(C35),".","")))),TRIM(C35),B34)) -> 1.1 | C35: OPERARIO | E35: =+_xlfn.XLOOKUP(C35,'BASE DATOS MANO DE OBRA'!A:A,'BASE DATOS MANO DE OBRA'!B:B) -> OPERARIO PLUS | F35: =ROUND('1_OG y 2_ACA'!F267,0)/2 -> 4.5 | G35: =+_xlfn.XLOOKUP(C35,'BASE DATOS MANO DE OBRA'!A:A,'BASE DATOS MANO DE OBRA'!C:C) -> hora | H35: 0 | I35: =+_xlfn.XLOOKUP(C35,'BASE DATOS MANO DE OBRA'!A:A,'BASE DATOS MANO DE OBRA'!E:E) -> 2850 | J35: 0 | K35: =+F35*H35 -> 0 | L35: =+F35*I35 -> 12825 | M35: =+F35*J35 -> 0 | N35: =SUM(K35:M35) -> 12825 | O35: =SUM(K35:M35)/tc -> 24.902913 | V35: =+C452 -> 2.3.2 | W35: =+E452 -> ACABADOS DE AZOTEA | X35: =+L452 -> 113850 | Y35: =+X35/$X$50 -> 0.0090678295 | Z35: =+X35/$Z$7 -> 976.66638
A36: Sello Losa | B36: =VALUE(IF(AND(LEN(TRIM(C36))-LEN(SUBSTITUTE(TRIM(C36),".",""))=1,ISNUMBER(VALUE(SUBSTITUTE(TRIM(C36),".","")))),TRIM(C36),B35)) -> 1.1 | C36: AYUDANTE | E36: =+_xlfn.XLOOKUP(C36,'BASE DATOS MANO DE OBRA'!A:A,'BASE DATOS MANO DE OBRA'!B:B) -> AYUDANTE PLUS | F36: =+F35 -> 4.5 | G36: =+_xlfn.XLOOKUP(C36,'BASE DATOS MANO DE OBRA'!A:A,'BASE DATOS MANO DE OBRA'!C:C) -> hora | H36: 0 | I36: =+_xlfn.XLOOKUP(C36,'BASE DATOS MANO DE OBRA'!A:A,'BASE DATOS MANO DE OBRA'!E:E) -> 2325 | J36: 0 | K36: =+F36*H36 -> 0 | L36: =+F36*I36 -> 10462.5 | M36: =+F36*J36 -> 0 | N36: =SUM(K36:M36) -> 10462.5 | O36: =SUM(K36:M36)/tc -> 20.315534 | V36: =+C462 -> 2.3.3 | W36: =+E462 -> PONCHEO FINAL | X36: =+L462 -> 310500 | Y36: =+X36/$X$50 -> 0.024730444 | Z36: =+X36/$Z$7 -> 2663.6356 | AA36: =+AVERAGE(Z33:Z36) -> 2569.2985
B37: =VALUE(IF(AND(LEN(TRIM(C37))-LEN(SUBSTITUTE(TRIM(C37),".",""))=1,ISNUMBER(VALUE(SUBSTITUTE(TRIM(C37),".","")))),TRIM(C37),B36)) -> 1.1 | C37: 1.1.4 | E37: LOSA FLOTANTE (ACERO, CONCRETO) | F37: =+'1_OG y 2_ACA'!D12 -> 48.12 | G37: m2 | K37: =+SUBTOTAL(9,K38:K53) -> 1386629 | L37: =+SUBTOTAL(9,L38:L53) -> 856462.5 | M37: =+SUBTOTAL(9,M38:M53) -> 0 | N37: =+SUBTOTAL(9,N38:N53) -> 2243091.5 | O37: =+SUBTOTAL(9,O38:O53) -> 4355.5174 | V37: =+C466 -> 2.4.1 | W37: =+E466 -> MUEBLES | X37: =+L466 -> 0 | Y37: =+X37/$X$50 -> 0 | Z37: =+X37/$Z$7 -> 0
B38: =VALUE(IF(AND(LEN(TRIM(C38))-LEN(SUBSTITUTE(TRIM(C38),".",""))=1,ISNUMBER(VALUE(SUBSTITUTE(TRIM(C38),".","")))),TRIM(C38),B37)) -> 1.1 | E38: CONCRETO Y ACERO | V38: =+C472 -> 2.5.1 | W38: =+E472 -> VENTANERIA (INCLUYE PUERTAS DE ALUMINIO) | X38: =+L472 -> 0 | Y38: =+X38/$X$50 -> 0 | Z38: =+X38/$Z$7 -> 0
B39: =VALUE(IF(AND(LEN(TRIM(C39))-LEN(SUBSTITUTE(TRIM(C39),".",""))=1,ISNUMBER(VALUE(SUBSTITUTE(TRIM(C39),".","")))),TRIM(C39),B38)) -> 1.1 | C39: M10-0009 | E39: =+_xlfn.XLOOKUP(C39,'BASE DATOS PRECIOS '!B:B,'BASE DATOS PRECIOS '!E:E) -> ADITIVO ERGO 4000 PG50 | F39: =+'1_OG y 2_ACA'!D283 -> 8 | G39: =+_xlfn.XLOOKUP(C39,'BASE DATOS PRECIOS '!B:B,'BASE DATOS PRECIOS '!F:F) -> LITRO | H39: =(+_xlfn.XLOOKUP(E39,'BASE DATOS PRECIOS '!E:E,'BASE DATOS PRECIOS '!H:H)) -> 748.625 | K39: =+F39*H39 -> 5989 | L39: =+F39*I39 -> 0 | M39: =+F39*J39 -> 0 | N39: =SUM(K39:M39) -> 5989 | O39: =SUM(K39:M39)/tc -> 11.629126 | V39: =+C549 -> 2.8.1 | W39: =+E549 -> ZACATE | X39: =+L549 -> 150075 | Y39: =+X39/$X$50 -> 0.011953048 | Z39: =+X39/$Z$7 -> 1287.4239 | AA39: =+AVERAGE(Z39) -> 1287.4239
B40: =VALUE(IF(AND(LEN(TRIM(C40))-LEN(SUBSTITUTE(TRIM(C40),".",""))=1,ISNUMBER(VALUE(SUBSTITUTE(TRIM(C40),".","")))),TRIM(C40),B39)) -> 1.1 | C40: M01-0146 | E40: =+_xlfn.XLOOKUP(C40,'BASE DATOS PRECIOS '!B:B,'BASE DATOS PRECIOS '!E:E) -> VARILLA DEFORME #2 | F40: =+'1_OG y 2_ACA'!D313 -> 53 | G40: UND | H40: =+_xlfn.XLOOKUP(E40,'BASE DATOS PRECIOS '!E:E,'BASE DATOS PRECIOS '!H:H) -> 569.8025 | K40: =+F40*H40 -> 30199.532 | L40: =+F40*I40 -> 0 | M40: =+F40*J40 -> 0 | N40: =SUM(K40:M40) -> 30199.532 | O40: =SUM(K40:M40)/tc -> 58.639869 | V40: =+C558 -> 3.1 | W40: =+E558 -> ELÉCTRICO | X40: =+L558 -> 0 | Y40: =+X40/$X$50 -> 0 | Z40: =+X40/$Z$7 -> 0
B41: =VALUE(IF(AND(LEN(TRIM(C41))-LEN(SUBSTITUTE(TRIM(C41),".",""))=1,ISNUMBER(VALUE(SUBSTITUTE(TRIM(C41),".","")))),TRIM(C41),B40)) -> 1.1 | C41: M01-0147 | D41: 02 | E41: VARILLA DEFORME #3 | F41: ='1_OG y 2_ACA'!D314 -> 361 | G41: UND | H41: =+_xlfn.XLOOKUP(E41,'BASE DATOS PRECIOS '!E:E,'BASE DATOS PRECIOS '!H:H) -> 1344.7 | K41: =+F41*H41 -> 485436.7 | L41: =+F41*I41 -> 0 | M41: =+F41*J41 -> 0 | N41: =SUM(K41:M41) -> 485436.7 | O41: =SUM(K41:M41)/tc -> 942.59553 | V41: =+C822 -> 3.2.1 | W41: =+E822 -> EXCAVACION TUBERIA SANITARIA | X41: =+L822 -> 80212.5 | Y41: =+X41/$X$50 -> 0.0063886981 | Z41: =+X41/$Z$7 -> 688.10586
B42: =VALUE(IF(AND(LEN(TRIM(C42))-LEN(SUBSTITUTE(TRIM(C42),".",""))=1,ISNUMBER(VALUE(SUBSTITUTE(TRIM(C42),".","")))),TRIM(C42),B41)) -> 1.1 | C42: M01-0145 | E42: =+_xlfn.XLOOKUP(C42,'BASE DATOS PRECIOS '!B:B,'BASE DATOS PRECIOS '!E:E) -> MALLA ELECTROSOLDADA #2 (5.3 MM) | F42: =+'1_OG y 2_ACA'!D315 -> 0 | G42: UND | H42: =+_xlfn.XLOOKUP(E42,'BASE DATOS PRECIOS '!E:E,'BASE DATOS PRECIOS '!H:H) -> 18762.497 | K42: =+F42*H42 -> 0 | L42: =+F42*I42 -> 0 | M42: =+F42*J42 -> 0 | N42: =SUM(K42:M42) -> 0 | O42: =SUM(K42:M42)/tc -> 0 | V42: =+C843 -> 3.2.2 | W42: =+E843 -> POTABLE DE LOSA | X42: =+L843 -> 75037.5 | Y42: =+X42/$X$50 -> 0.005976524 | Z42: =+X42/$Z$7 -> 643.71193
B43: =VALUE(IF(AND(LEN(TRIM(C43))-LEN(SUBSTITUTE(TRIM(C43),".",""))=1,ISNUMBER(VALUE(SUBSTITUTE(TRIM(C43),".","")))),TRIM(C43),B42)) -> 1.1 | C43: M01-0001 | E43: =+_xlfn.XLOOKUP(C43,'BASE DATOS PRECIOS '!B:B,'BASE DATOS PRECIOS '!E:E) -> ALAMBRE NEGRO #16 (1.68MM) | F43: =+'1_OG y 2_ACA'!D316 -> 58 | G43: KG | H43: =+_xlfn.XLOOKUP(E43,'BASE DATOS PRECIOS '!E:E,'BASE DATOS PRECIOS '!H:H) -> 586.8542 | K43: =+F43*H43 -> 34037.544 | L43: =+F43*I43 -> 0 | M43: =+F43*J43 -> 0 | N43: =SUM(K43:M43) -> 34037.544 | O43: =SUM(K43:M43)/tc -> 66.092318 | V43: =+C860 -> 3.2.2.1 | W43: =+E860 -> POTABLE DE ENTREPISO | X43: =+L860 -> 0 | Y43: =+X43/$X$50 -> 0 | Z43: =+X43/$Z$7 -> 0
B44: =VALUE(IF(AND(LEN(TRIM(C44))-LEN(SUBSTITUTE(TRIM(C44),".",""))=1,ISNUMBER(VALUE(SUBSTITUTE(TRIM(C44),".","")))),TRIM(C44),B43)) -> 1.1 | C44: M06-0261 | E44: =+_xlfn.XLOOKUP(C44,'BASE DATOS PRECIOS '!B:B,'BASE DATOS PRECIOS '!E:E) -> SEPARADOR TIPO CONO 2.5CM (1") SP125 | F44: =ROUNDUP('1_OG y 2_ACA'!D317,0) -> 49 | G44: UND | H44: =+_xlfn.XLOOKUP(E44,'BASE DATOS PRECIOS '!E:E,'BASE DATOS PRECIOS '!H:H) -> 56.5 | K44: =+F44*H44 -> 2768.5 | L44: =+F44*I44 -> 0 | M44: =+F44*J44 -> 0 | N44: =SUM(K44:M44) -> 2768.5 | O44: =SUM(K44:M44)/tc -> 5.3757282 | V44: =+C875 -> 3.2.2.2 | W44: =+E875 -> SANITARIO DE ENTREPISO | X44: =+L875 -> 0 | Y44: =+X44/$X$50 -> 0 | Z44: =+X44/$Z$7 -> 0
B45: =VALUE(IF(AND(LEN(TRIM(C45))-LEN(SUBSTITUTE(TRIM(C45),".",""))=1,ISNUMBER(VALUE(SUBSTITUTE(TRIM(C45),".","")))),TRIM(C45),B44)) -> 1.1 | C45: M06-0264 | E45: =+_xlfn.XLOOKUP(C45,'BASE DATOS PRECIOS '!B:B,'BASE DATOS PRECIOS '!E:E) -> SEPARADORES TIPO CONO 12CM SP450 | F45: =+F44 -> 49 | G45: UND | H45: =+_xlfn.XLOOKUP(E45,'BASE DATOS PRECIOS '!E:E,'BASE DATOS PRECIOS '!H:H) -> 203.4 | K45: =+F45*H45 -> 9966.6 | L45: =+F45*I45 -> 0 | M45: =+F45*J45 -> 0 | N45: =SUM(K45:M45) -> 9966.6 | O45: =SUM(K45:M45)/tc -> 19.352621 | V45: =+C891 -> 3.2.3 | W45: =+E891 -> TUBERÍA MECÁNICA MUROS | X45: =+L891 -> 0 | Y45: =+X45/$X$50 -> 0 | Z45: =+X45/$Z$7 -> 0
B46: =VALUE(IF(AND(LEN(TRIM(C46))-LEN(SUBSTITUTE(TRIM(C46),".",""))=1,ISNUMBER(VALUE(SUBSTITUTE(TRIM(C46),".","")))),TRIM(C46),B45)) -> 1.1 | C46: M08-0037 | E46: =+_xlfn.XLOOKUP(C46,'BASE DATOS PRECIOS '!B:B,'BASE DATOS PRECIOS '!E:E) -> DISCO CORTE METAL FINO 9" | F46: =+'1_OG y 2_ACA'!D319 -> 7 | G46: UND | H46: =+_xlfn.XLOOKUP(E46,'BASE DATOS PRECIOS '!E:E,'BASE DATOS PRECIOS '!H:H) -> 3037.6321 | K46: =+F46*H46 -> 21263.425 | L46: =+F46*I46 -> 0 | M46: =+F46*J46 -> 0 | N46: =SUM(K46:M46) -> 21263.425 | O46: =SUM(K46:M46)/tc -> 41.288203 | V46: =+C911 -> 3.2.4 | W46: =+E911 -> CAJAS Y TUBERIAS MECÁNICAS | X46: =+L911 -> 181125 | Y46: =+X46/$X$50 -> 0.014426092 | Z46: =+X46/$Z$7 -> 1553.7874
B47: =VALUE(IF(AND(LEN(TRIM(C47))-LEN(SUBSTITUTE(TRIM(C47),".",""))=1,ISNUMBER(VALUE(SUBSTITUTE(TRIM(C47),".","")))),TRIM(C47),B46)) -> 1.1 | C47: M10-0065 | E47: =+_xlfn.XLOOKUP(C47,'BASE DATOS PRECIOS '!B:B,'BASE DATOS PRECIOS '!E:E) -> CONCRETO FC 210 KG/CM2 NORMAL | F47: ='1_OG y 2_ACA'!D277 -> 10.1052 | G47: =+_xlfn.XLOOKUP(C47,'BASE DATOS PRECIOS '!B:B,'BASE DATOS PRECIOS '!F:F) -> M3 | H47: =+_xlfn.XLOOKUP(E47,'BASE DATOS PRECIOS '!E:E,'BASE DATOS PRECIOS '!H:H) -> 78867.084 | K47: =+F47*H47 -> 796967.66 | L47: =+F47*I47 -> 0 | M47: =+F47*J47 -> 0 | N47: =SUM(K47:M47) -> 796967.66 | O47: =SUM(K47:M47)/tc -> 1547.51 | V47: =+C912 -> M13-0060 | W47: =+E912 -> TRAMPA PARA GRASA 4" | X47: =+L912 -> 0 | Y47: =+X47/$X$50 -> 0 | Z47: =+X47/$Z$7 -> 0
A48: Acero Losa | B48: =VALUE(IF(AND(LEN(TRIM(C48))-LEN(SUBSTITUTE(TRIM(C48),".",""))=1,ISNUMBER(VALUE(SUBSTITUTE(TRIM(C48),".","")))),TRIM(C48),B47)) -> 1.1 | C48: OPERARIO | E48: =+_xlfn.XLOOKUP(C48,'BASE DATOS MANO DE OBRA'!A:A,'BASE DATOS MANO DE OBRA'!B:B) -> OPERARIO PLUS | F48: =ROUND('1_OG y 2_ACA'!F330,0)/2 -> 138 | G48: =+_xlfn.XLOOKUP(C48,'BASE DATOS MANO DE OBRA'!A:A,'BASE DATOS MANO DE OBRA'!C:C) -> hora | H48: 0 | I48: =+_xlfn.XLOOKUP(C48,'BASE DATOS MANO DE OBRA'!A:A,'BASE DATOS MANO DE OBRA'!E:E) -> 2850 | J48: 0 | K48: =+F48*H48 -> 0 | L48: =+F48*I48 -> 393300 | M48: =+F48*J48 -> 0 | N48: =SUM(K48:M48) -> 393300 | O48: =SUM(K48:M48)/tc -> 763.68932 | V48: =+C930 -> 3.2.5 | W48: =+E930 -> ACABADOS MECÁNICOS | X48: =+L930 -> 69862.5 | Y48: =+X48/$X$50 -> 0.0055643499 | Z48: =+X48/$Z$7 -> 599.31801
A49: Acero Losa | B49: =VALUE(IF(AND(LEN(TRIM(C49))-LEN(SUBSTITUTE(TRIM(C49),".",""))=1,ISNUMBER(VALUE(SUBSTITUTE(TRIM(C49),".","")))),TRIM(C49),B48)) -> 1.1 | C49: AYUDANTE | E49: =+_xlfn.XLOOKUP(C49,'BASE DATOS MANO DE OBRA'!A:A,'BASE DATOS MANO DE OBRA'!B:B) -> AYUDANTE PLUS | F49: =+F48 -> 138 | G49: =+_xlfn.XLOOKUP(C49,'BASE DATOS MANO DE OBRA'!A:A,'BASE DATOS MANO DE OBRA'!C:C) -> hora | H49: 0 | I49: =+_xlfn.XLOOKUP(C49,'BASE DATOS MANO DE OBRA'!A:A,'BASE DATOS MANO DE OBRA'!E:E) -> 2325 | J49: 0 | K49: =+F49*H49 -> 0 | L49: =+F49*I49 -> 320850 | M49: =+F49*J49 -> 0 | N49: =SUM(K49:M49) -> 320850 | O49: =SUM(K49:M49)/tc -> 623.00971 | V49: =+C943 -> 3.2.6 | W49: =+E943 -> MEDIDOR | X49: =+L943 -> 98325 | Y49: =+X49/$X$50 -> 0.0078313073 | Z49: =+X49/$Z$7 -> 843.4846 | AA49: =+AVERAGE(Z41:Z49) -> 480.9342
A50: Losa Flotante (Formaleta trazo) | B50: =VALUE(IF(AND(LEN(TRIM(C50))-LEN(SUBSTITUTE(TRIM(C50),".",""))=1,ISNUMBER(VALUE(SUBSTITUTE(TRIM(C50),".","")))),TRIM(C50),B49)) -> 1.1 | C50: OPERARIO | E50: =+_xlfn.XLOOKUP(C50,'BASE DATOS MANO DE OBRA'!A:A,'BASE DATOS MANO DE OBRA'!B:B) -> OPERARIO PLUS | F50: =ROUND('1_OG y 2_ACA'!F331,0)/2 -> 7.5 | G50: =+_xlfn.XLOOKUP(C50,'BASE DATOS MANO DE OBRA'!A:A,'BASE DATOS MANO DE OBRA'!C:C) -> hora | H50: 0 | I50: =+_xlfn.XLOOKUP(C50,'BASE DATOS MANO DE OBRA'!A:A,'BASE DATOS MANO DE OBRA'!E:E) -> 2850 | J50: 0 | K50: =+F50*H50 -> 0 | L50: =+F50*I50 -> 21375 | M50: =+F50*J50 -> 0 | N50: =SUM(K50:M50) -> 21375 | O50: =SUM(K50:M50)/tc -> 41.504854 | X50: =SUM(X8:X49) -> 12555375 | Y50: =SUM(Y8:Y49) -> 1 | Z50: =+X50/$Z$7 -> 107706.74
A51: Losa Flotante (Formaleta trazo) | B51: =VALUE(IF(AND(LEN(TRIM(C51))-LEN(SUBSTITUTE(TRIM(C51),".",""))=1,ISNUMBER(VALUE(SUBSTITUTE(TRIM(C51),".","")))),TRIM(C51),B50)) -> 1.1 | C51: AYUDANTE | E51: =+_xlfn.XLOOKUP(C51,'BASE DATOS MANO DE OBRA'!A:A,'BASE DATOS MANO DE OBRA'!B:B) -> AYUDANTE PLUS | F51: =+F50 -> 7.5 | G51: =+_xlfn.XLOOKUP(C51,'BASE DATOS MANO DE OBRA'!A:A,'BASE DATOS MANO DE OBRA'!C:C) -> hora | H51: 0 | I51: =+_xlfn.XLOOKUP(C51,'BASE DATOS MANO DE OBRA'!A:A,'BASE DATOS MANO DE OBRA'!E:E) -> 2325 | J51: 0 | K51: =+F51*H51 -> 0 | L51: =+F51*I51 -> 17437.5 | M51: =+F51*J51 -> 0 | N51: =SUM(K51:M51) -> 17437.5 | O51: =SUM(K51:M51)/tc -> 33.859223 | X51: =+X50-L951 -> -1397100
A52: Colado de Losa | B52: =VALUE(IF(AND(LEN(TRIM(C52))-LEN(SUBSTITUTE(TRIM(C52),".",""))=1,ISNUMBER(VALUE(SUBSTITUTE(TRIM(C52),".","")))),TRIM(C52),B51)) -> 1.1 | C52: OPERARIO | E52: =+_xlfn.XLOOKUP(C52,'BASE DATOS MANO DE OBRA'!A:A,'BASE DATOS MANO DE OBRA'!B:B) -> OPERARIO PLUS | F52: =ROUND('1_OG y 2_ACA'!F329,0)/2 -> 20 | G52: =+_xlfn.XLOOKUP(C52,'BASE DATOS MANO DE OBRA'!A:A,'BASE DATOS MANO DE OBRA'!C:C) -> hora | H52: 0 | I52: =+_xlfn.XLOOKUP(C52,'BASE DATOS MANO DE OBRA'!A:A,'BASE DATOS MANO DE OBRA'!E:E) -> 2850 | J52: 0 | K52: =+F52*H52 -> 0 | L52: =+F52*I52 -> 57000 | M52: =+F52*J52 -> 0 | N52: =SUM(K52:M52) -> 57000 | O52: =SUM(K52:M52)/tc -> 110.67961
A53: Colado de Losa | B53: =VALUE(IF(AND(LEN(TRIM(C53))-LEN(SUBSTITUTE(TRIM(C53),".",""))=1,ISNUMBER(VALUE(SUBSTITUTE(TRIM(C53),".","")))),TRIM(C53),B52)) -> 1.1 | C53: AYUDANTE | E53: =+_xlfn.XLOOKUP(C53,'BASE DATOS MANO DE OBRA'!A:A,'BASE DATOS MANO DE OBRA'!B:B) -> AYUDANTE PLUS | F53: =+F52 -> 20 | G53: =+_xlfn.XLOOKUP(C53,'BASE DATOS MANO DE OBRA'!A:A,'BASE DATOS MANO DE OBRA'!C:C) -> hora | H53: 0 | I53: =+_xlfn.XLOOKUP(C53,'BASE DATOS MANO DE OBRA'!A:A,'BASE DATOS MANO DE OBRA'!E:E) -> 2325 | J53: 0 | K53: =+F53*H53 -> 0 | L53: =+F53*I53 -> 46500 | M53: =+F53*J53 -> 0 | N53: =SUM(K53:M53) -> 46500 | O53: =SUM(K53:M53)/tc -> 90.291262
B54: =VALUE(IF(AND(LEN(TRIM(C54))-LEN(SUBSTITUTE(TRIM(C54),".",""))=1,ISNUMBER(VALUE(SUBSTITUTE(TRIM(C54),".","")))),TRIM(C54),B53)) -> 1.2 | C54: 1.2 | E54: MUROS N1 & N2, ENTREPISO & AZOTEA | F54: 1 | G54: UND | K54: =+SUBTOTAL(9,K55:K114) -> 4465684.8 | L54: =+SUBTOTAL(9,L55:L114) -> 3376687.5 | M54: =+SUBTOTAL(9,M55:M114) -> 530960.15 | N54: =+SUBTOTAL(9,N55:N114) -> 8373332.4 | O54: =+SUBTOTAL(9,O55:O114) -> 16258.898
B55: =VALUE(IF(AND(LEN(TRIM(C55))-LEN(SUBSTITUTE(TRIM(C55),".",""))=1,ISNUMBER(VALUE(SUBSTITUTE(TRIM(C55),".","")))),TRIM(C55),B54)) -> 1.2 | C55: 1.2.1 | E55: ACERO EN PAREDES MUROS N1 | F55: =+'1_OG y 2_ACA'!D462 -> 129.48 | G55: m2 | K55: =+SUBTOTAL(9,K56:K67) -> 704662.5 | L55: =+SUBTOTAL(9,L56:L67) -> 1112625 | M55: =+SUBTOTAL(9,M56:M67) -> 0 | N55: =+SUBTOTAL(9,N56:N67) -> 1817287.5 | O55: =+SUBTOTAL(9,O56:O67) -> 3528.7136
B56: =VALUE(IF(AND(LEN(TRIM(C56))-LEN(SUBSTITUTE(TRIM(C56),".",""))=1,ISNUMBER(VALUE(SUBSTITUTE(TRIM(C56),".","")))),TRIM(C56),B55)) -> 1.2 | C56: M01-0146 | E56: =+_xlfn.XLOOKUP(C56,'BASE DATOS PRECIOS '!B:B,'BASE DATOS PRECIOS '!E:E) -> VARILLA DEFORME #2 | F56: =+'1_OG y 2_ACA'!D445 -> 6 | G56: =+_xlfn.XLOOKUP(C56,'BASE DATOS PRECIOS '!B:B,'BASE DATOS PRECIOS '!F:F) -> UND | H56: =+_xlfn.XLOOKUP(E56,'BASE DATOS PRECIOS '!E:E,'BASE DATOS PRECIOS '!H:H) -> 569.8025 | K56: =+F56*H56 -> 3418.815 | L56: =+F56*I56 -> 0 | M56: =+F56*J56 -> 0 | N56: =SUM(K56:M56) -> 3418.815 | O56: =SUM(K56:M56)/tc -> 6.6384757
B57: =VALUE(IF(AND(LEN(TRIM(C57))-LEN(SUBSTITUTE(TRIM(C57),".",""))=1,ISNUMBER(VALUE(SUBSTITUTE(TRIM(C57),".","")))),TRIM(C57),B56)) -> 1.2 | C57: M01-0147 | D57: 01 | E57: VARILLA DEFORME #3 | F57: ='1_OG y 2_ACA'!D446 -> 106 | G57: =+_xlfn.XLOOKUP(C57,'BASE DATOS PRECIOS '!B:B,'BASE DATOS PRECIOS '!F:F) -> UND | H57: =+_xlfn.XLOOKUP(E57,'BASE DATOS PRECIOS '!E:E,'BASE DATOS PRECIOS '!H:H) -> 1344.7 | K57: =+F57*H57 -> 142538.2 | L57: =+F57*I57 -> 0 | M57: =+F57*J57 -> 0 | N57: =SUM(K57:M57) -> 142538.2 | O57: =SUM(K57:M57)/tc -> 276.7732
B58: =VALUE(IF(AND(LEN(TRIM(C58))-LEN(SUBSTITUTE(TRIM(C58),".",""))=1,ISNUMBER(VALUE(SUBSTITUTE(TRIM(C58),".","")))),TRIM(C58),B57)) -> 1.2 | C58: M01-0147 | D58: 02 | E58: VARILLA DEFORME #3 | F58: ='1_OG y 2_ACA'!D447 -> 161 | G58: =+_xlfn.XLOOKUP(C58,'BASE DATOS PRECIOS '!B:B,'BASE DATOS PRECIOS '!F:F) -> UND | H58: =+_xlfn.XLOOKUP(E58,'BASE DATOS PRECIOS '!E:E,'BASE DATOS PRECIOS '!H:H) -> 1344.7 | K58: =+F58*H58 -> 216496.7 | L58: =+F58*I58 -> 0 | M58: =+F58*J58 -> 0 | N58: =SUM(K58:M58) -> 216496.7 | O58: =SUM(K58:M58)/tc -> 420.38194
B59: =VALUE(IF(AND(LEN(TRIM(C59))-LEN(SUBSTITUTE(TRIM(C59),".",""))=1,ISNUMBER(VALUE(SUBSTITUTE(TRIM(C59),".","")))),TRIM(C59),B58)) -> 1.2 | C59: M01-0148 | E59: =+_xlfn.XLOOKUP(C59,'BASE DATOS PRECIOS '!B:B,'BASE DATOS PRECIOS '!E:E) -> VARILLA DEFORME #4 | F59: =+'1_OG y 2_ACA'!D448 -> 57 | G59: =+_xlfn.XLOOKUP(C59,'BASE DATOS PRECIOS '!B:B,'BASE DATOS PRECIOS '!F:F) -> UND | H59: =+_xlfn.XLOOKUP(E59,'BASE DATOS PRECIOS '!E:E,'BASE DATOS PRECIOS '!H:H) -> 2395.6 | K59: =+F59*H59 -> 136549.2 | L59: =+F59*I59 -> 0 | M59: =+F59*J59 -> 0 | N59: =SUM(K59:M59) -> 136549.2 | O59: =SUM(K59:M59)/tc -> 265.14408
B60: =VALUE(IF(AND(LEN(TRIM(C60))-LEN(SUBSTITUTE(TRIM(C60),".",""))=1,ISNUMBER(VALUE(SUBSTITUTE(TRIM(C60),".","")))),TRIM(C60),B59)) -> 1.2 | C60: M01-0145 | E60: =+_xlfn.XLOOKUP(C60,'BASE DATOS PRECIOS '!B:B,'BASE DATOS PRECIOS '!E:E) -> MALLA ELECTROSOLDADA #2 (5.3 MM) | F60: =+'1_OG y 2_ACA'!D449 -> 7.5 | G60: =+_xlfn.XLOOKUP(C60,'BASE DATOS PRECIOS '!B:B,'BASE DATOS PRECIOS '!F:F) -> UND | H60: =+_xlfn.XLOOKUP(E60,'BASE DATOS PRECIOS '!E:E,'BASE DATOS PRECIOS '!H:H) -> 18762.497 | K60: =+F60*H60 -> 140718.73 | L60: =+F60*I60 -> 0 | M60: =+F60*J60 -> 0 | N60: =SUM(K60:M60) -> 140718.73 | O60: =SUM(K60:M60)/tc -> 273.24025
B61: =VALUE(IF(AND(LEN(TRIM(C61))-LEN(SUBSTITUTE(TRIM(C61),".",""))=1,ISNUMBER(VALUE(SUBSTITUTE(TRIM(C61),".","")))),TRIM(C61),B60)) -> 1.2 | C61: M01-0001 | E61: =+_xlfn.XLOOKUP(C61,'BASE DATOS PRECIOS '!B:B,'BASE DATOS PRECIOS '!E:E) -> ALAMBRE NEGRO #16 (1.68MM) | F61: =+'1_OG y 2_ACA'!D450 -> 65 | G61: =+_xlfn.XLOOKUP(C61,'BASE DATOS PRECIOS '!B:B,'BASE DATOS PRECIOS '!F:F) -> KG | H61: =+_xlfn.XLOOKUP(E61,'BASE DATOS PRECIOS '!E:E,'BASE DATOS PRECIOS '!H:H) -> 586.8542 | K61: =+F61*H61 -> 38145.523 | L61: =+F61*I61 -> 0 | M61: =+F61*J61 -> 0 | N61: =SUM(K61:M61) -> 38145.523 | O61: =SUM(K61:M61)/tc -> 74.068977
B62: =VALUE(IF(AND(LEN(TRIM(C62))-LEN(SUBSTITUTE(TRIM(C62),".",""))=1,ISNUMBER(VALUE(SUBSTITUTE(TRIM(C62),".","")))),TRIM(C62),B61)) -> 1.2 | C62: M08-0051 | E62: =+_xlfn.XLOOKUP(C62,'BASE DATOS PRECIOS '!B:B,'BASE DATOS PRECIOS '!E:E) -> DISCO CORTE FINO METAL 4-1/2 | F62: =+'1_OG y 2_ACA'!D451 -> 4 | G62: =+_xlfn.XLOOKUP(C62,'BASE DATOS PRECIOS '!B:B,'BASE DATOS PRECIOS '!F:F) -> UND | H62: =+_xlfn.XLOOKUP(E62,'BASE DATOS PRECIOS '!E:E,'BASE DATOS PRECIOS '!H:H) -> 3661.2 | K62: =+F62*H62 -> 14644.8 | L62: =+F62*I62 -> 0 | M62: =+F62*J62 -> 0 | N62: =SUM(K62:M62) -> 14644.8 | O62: =SUM(K62:M62)/tc -> 28.436505
B63: =VALUE(IF(AND(LEN(TRIM(C63))-LEN(SUBSTITUTE(TRIM(C63),".",""))=1,ISNUMBER(VALUE(SUBSTITUTE(TRIM(C63),".","")))),TRIM(C63),B62)) -> 1.2 | C63: M08-0037 | E63: =+_xlfn.XLOOKUP(C63,'BASE DATOS PRECIOS '!B:B,'BASE DATOS PRECIOS '!E:E) -> DISCO CORTE METAL FINO 9" | F63: =+F62 -> 4 | G63: =+_xlfn.XLOOKUP(C63,'BASE DATOS PRECIOS '!B:B,'BASE DATOS PRECIOS '!F:F) -> UND | H63: =+_xlfn.XLOOKUP(E63,'BASE DATOS PRECIOS '!E:E,'BASE DATOS PRECIOS '!H:H) -> 3037.6321 | K63: =+F63*H63 -> 12150.528 | L63: =+F63*I63 -> 0 | M63: =+F63*J63 -> 0 | N63: =SUM(K63:M63) -> 12150.528 | O63: =SUM(K63:M63)/tc -> 23.593259
A64: Acero Muros y Entrepiso | B64: =VALUE(IF(AND(LEN(TRIM(C64))-LEN(SUBSTITUTE(TRIM(C64),".",""))=1,ISNUMBER(VALUE(SUBSTITUTE(TRIM(C64),".","")))),TRIM(C64),B63)) -> 1.2 | C64: OPERARIO | E64: =+_xlfn.XLOOKUP(C64,'BASE DATOS MANO DE OBRA'!A:A,'BASE DATOS MANO DE OBRA'!B:B) -> OPERARIO PLUS | F64: =+ROUNDUP('1_OG y 2_ACA'!F455,0)/2 -> 145 | G64: =+_xlfn.XLOOKUP(C64,'BASE DATOS MANO DE OBRA'!A:A,'BASE DATOS MANO DE OBRA'!C:C) -> hora | H64: 0 | I64: =+_xlfn.XLOOKUP(C64,'BASE DATOS MANO DE OBRA'!A:A,'BASE DATOS MANO DE OBRA'!E:E) -> 2850 | J64: 0 | K64: =+F64*H64 -> 0 | L64: =+F64*I64 -> 413250 | M64: =+F64*J64 -> 0 | N64: =SUM(K64:M64) -> 413250 | O64: =SUM(K64:M64)/tc -> 802.42718
A65: Acero Muros y Entrepiso | B65: =VALUE(IF(AND(LEN(TRIM(C65))-LEN(SUBSTITUTE(TRIM(C65),".",""))=1,ISNUMBER(VALUE(SUBSTITUTE(TRIM(C65),".","")))),TRIM(C65),B64)) -> 1.2 | C65: AYUDANTE | E65: =+_xlfn.XLOOKUP(C65,'BASE DATOS MANO DE OBRA'!A:A,'BASE DATOS MANO DE OBRA'!B:B) -> AYUDANTE PLUS | F65: =+F64 -> 145 | G65: =+_xlfn.XLOOKUP(C65,'BASE DATOS MANO DE OBRA'!A:A,'BASE DATOS MANO DE OBRA'!C:C) -> hora | H65: 0 | I65: =+_xlfn.XLOOKUP(C65,'BASE DATOS MANO DE OBRA'!A:A,'BASE DATOS MANO DE OBRA'!E:E) -> 2325 | J65: 0 | K65: =+F65*H65 -> 0 | L65: =+F65*I65 -> 337125 | M65: =+F65*J65 -> 0 | N65: =SUM(K65:M65) -> 337125 | O65: =SUM(K65:M65)/tc -> 654.61165
A66: Muros y Entrepiso (Formaleta, Concreto) | B66: =VALUE(IF(AND(LEN(TRIM(C66))-LEN(SUBSTITUTE(TRIM(C66),".",""))=1,ISNUMBER(VALUE(SUBSTITUTE(TRIM(C66),".","")))),TRIM(C66),B65)) -> 1.2 | C66: OPERARIO | E66: =+_xlfn.XLOOKUP(C66,'BASE DATOS MANO DE OBRA'!A:A,'BASE DATOS MANO DE OBRA'!B:B) -> OPERARIO PLUS | F66: =+ROUNDUP('1_OG y 2_ACA'!F531,0)/2 -> 70 | G66: =+_xlfn.XLOOKUP(C66,'BASE DATOS MANO DE OBRA'!A:A,'BASE DATOS MANO DE OBRA'!C:C) -> hora | H66: 0 | I66: =+_xlfn.XLOOKUP(C66,'BASE DATOS MANO DE OBRA'!A:A,'BASE DATOS MANO DE OBRA'!E:E) -> 2850 | J66: 0 | K66: =+F66*H66 -> 0 | L66: =+F66*I66 -> 199500 | M66: =+F66*J66 -> 0 | N66: =SUM(K66:M66) -> 199500 | O66: =SUM(K66:M66)/tc -> 387.37864
A67: Muros y Entrepiso (Formaleta, Concreto) | B67: =VALUE(IF(AND(LEN(TRIM(C67))-LEN(SUBSTITUTE(TRIM(C67),".",""))=1,ISNUMBER(VALUE(SUBSTITUTE(TRIM(C67),".","")))),TRIM(C67),B66)) -> 1.2 | C67: AYUDANTE | E67: =+_xlfn.XLOOKUP(C67,'BASE DATOS MANO DE OBRA'!A:A,'BASE DATOS MANO DE OBRA'!B:B) -> AYUDANTE PLUS | F67: =+F66 -> 70 | G67: =+_xlfn.XLOOKUP(C67,'BASE DATOS MANO DE OBRA'!A:A,'BASE DATOS MANO DE OBRA'!C:C) -> hora | H67: 0 | I67: =+_xlfn.XLOOKUP(C67,'BASE DATOS MANO DE OBRA'!A:A,'BASE DATOS MANO DE OBRA'!E:E) -> 2325 | J67: 0 | K67: =+F67*H67 -> 0 | L67: =+F67*I67 -> 162750 | M67: =+F67*J67 -> 0 | N67: =SUM(K67:M67) -> 162750 | O67: =SUM(K67:M67)/tc -> 316.01942
B68: =VALUE(IF(AND(LEN(TRIM(C68))-LEN(SUBSTITUTE(TRIM(C68),".",""))=1,ISNUMBER(VALUE(SUBSTITUTE(TRIM(C68),".","")))),TRIM(C68),B67)) -> 1.2 | C68: 1.2.2 | E68: PAREDES, MUROS N1 (FORMALETA, CONCRETO, DESENCOFRADO) | F68: =+'1_OG y 2_ACA'!D462 -> 129.48 | G68: m2 | K68: =+SUBTOTAL(9,K69:K83) -> 1727659.3 | L68: =+SUBTOTAL(9,L69:L83) -> 980662.5 | M68: =+SUBTOTAL(9,M69:M83) -> 276815.7 | N68: =+SUBTOTAL(9,N69:N83) -> 2985137.5 | O68: =+SUBTOTAL(9,O69:O83) -> 5796.3834
B69: =VALUE(IF(AND(LEN(TRIM(C69))-LEN(SUBSTITUTE(TRIM(C69),".",""))=1,ISNUMBER(VALUE(SUBSTITUTE(TRIM(C69),".","")))),TRIM(C69),B68)) -> 1.2 | C69: M06-0193 | E69: =+_xlfn.XLOOKUP(C69,'BASE DATOS PRECIOS '!B:B,'BASE DATOS PRECIOS '!E:E) -> ESPUMA EXPANSIVA 750ML | F69: =+'1_OG y 2_ACA'!D499 -> 4 | G69: =+_xlfn.XLOOKUP(C69,'BASE DATOS PRECIOS '!B:B,'BASE DATOS PRECIOS '!F:F) -> UND | H69: =+_xlfn.XLOOKUP(E69,'BASE DATOS PRECIOS '!E:E,'BASE DATOS PRECIOS '!H:H) -> 6420.0046 | K69: =+F69*H69 -> 25680.018 | L69: =+F69*I69 -> 0 | M69: =+F69*J69 -> 0 | N69: =SUM(K69:M69) -> 25680.018 | O69: =SUM(K69:M69)/tc -> 49.864113
B70: =VALUE(IF(AND(LEN(TRIM(C70))-LEN(SUBSTITUTE(TRIM(C70),".",""))=1,ISNUMBER(VALUE(SUBSTITUTE(TRIM(C70),".","")))),TRIM(C70),B69)) -> 1.2 | C70: M06-0195 | E70: =+_xlfn.XLOOKUP(C70,'BASE DATOS PRECIOS '!B:B,'BASE DATOS PRECIOS '!E:E) -> FUNDAS DE 10CM | F70: ='1_OG y 2_ACA'!D523 -> 600 | G70: =+_xlfn.XLOOKUP(C70,'BASE DATOS PRECIOS '!B:B,'BASE DATOS PRECIOS '!F:F) -> UND | H70: =+_xlfn.XLOOKUP(E70,'BASE DATOS PRECIOS '!E:E,'BASE DATOS PRECIOS '!H:H) -> 29.553229 | K70: =+F70*H70 -> 17731.937 | L70: =+F70*I70 -> 0 | M70: =+F70*J70 -> 0 | N70: =SUM(K70:M70) -> 17731.937 | O70: =SUM(K70:M70)/tc -> 34.430946
B71: =VALUE(IF(AND(LEN(TRIM(C71))-LEN(SUBSTITUTE(TRIM(C71),".",""))=1,ISNUMBER(VALUE(SUBSTITUTE(TRIM(C71),".","")))),TRIM(C71),B70)) -> 1.2 | C71: M09-0042 | E71: =+_xlfn.XLOOKUP(C71,'BASE DATOS PRECIOS '!B:B,'BASE DATOS PRECIOS '!E:E) -> REGLA SEMIDURO 1X3X4 SIN CEPILLAR | F71: ='1_OG y 2_ACA'!D524 -> 10 | G71: =+_xlfn.XLOOKUP(C71,'BASE DATOS PRECIOS '!B:B,'BASE DATOS PRECIOS '!F:F) -> UND | H71: =+_xlfn.XLOOKUP(E71,'BASE DATOS PRECIOS '!E:E,'BASE DATOS PRECIOS '!H:H) -> 1524.9915 | K71: =+F71*H71 -> 15249.915 | L71: =+F71*I71 -> 0 | M71: =+F71*J71 -> 0 | N71: =SUM(K71:M71) -> 15249.915 | O71: =SUM(K71:M71)/tc -> 29.611485
B72: =VALUE(IF(AND(LEN(TRIM(C72))-LEN(SUBSTITUTE(TRIM(C72),".",""))=1,ISNUMBER(VALUE(SUBSTITUTE(TRIM(C72),".","")))),TRIM(C72),B71)) -> 1.2 | C72: M06-0040 | E72: =+_xlfn.XLOOKUP(C72,'BASE DATOS PRECIOS '!B:B,'BASE DATOS PRECIOS '!E:E) -> CLAVO ACERO 2 X 3.8MM CAJA (250) | F72: ='1_OG y 2_ACA'!D525 -> 1 | G72: =+_xlfn.XLOOKUP(C72,'BASE DATOS PRECIOS '!B:B,'BASE DATOS PRECIOS '!F:F) -> CJ | H72: =+_xlfn.XLOOKUP(E72,'BASE DATOS PRECIOS '!E:E,'BASE DATOS PRECIOS '!H:H) -> 6370.375 | K72: =+F72*H72 -> 6370.375 | L72: =+F72*I72 -> 0 | M72: =+F72*J72 -> 0 | N72: =SUM(K72:M72) -> 6370.375 | O72: =SUM(K72:M72)/tc -> 12.36966
B73: =VALUE(IF(AND(LEN(TRIM(C73))-LEN(SUBSTITUTE(TRIM(C73),".",""))=1,ISNUMBER(VALUE(SUBSTITUTE(TRIM(C73),".","")))),TRIM(C73),B72)) -> 1.2 | C73: M10-0090 | E73: =+_xlfn.XLOOKUP(C73,'BASE DATOS PRECIOS '!B:B,'BASE DATOS PRECIOS '!E:E) -> REPEMAX CAPA GRUESA 80XA-W2 (40KG) | F73: ='1_OG y 2_ACA'!D526 -> 3 | G73: =+_xlfn.XLOOKUP(C73,'BASE DATOS PRECIOS '!B:B,'BASE DATOS PRECIOS '!F:F) -> SACO | H73: =+_xlfn.XLOOKUP(E73,'BASE DATOS PRECIOS '!E:E,'BASE DATOS PRECIOS '!H:H) -> 5527.4967 | K73: =+F73*H73 -> 16582.49 | L73: =+F73*I73 -> 0 | M73: =+F73*J73 -> 0 | N73: =SUM(K73:M73) -> 16582.49 | O73: =SUM(K73:M73)/tc -> 32.19901
B74: =VALUE(IF(AND(LEN(TRIM(C74))-LEN(SUBSTITUTE(TRIM(C74),".",""))=1,ISNUMBER(VALUE(SUBSTITUTE(TRIM(C74),".","")))),TRIM(C74),B73)) -> 1.2 | C74: M06-0240 | E74: =+_xlfn.XLOOKUP(C74,'BASE DATOS PRECIOS '!B:B,'BASE DATOS PRECIOS '!E:E) -> PERNO ANCLAJE 3/8X3-1/2 | F74: ='1_OG y 2_ACA'!D527 -> 60 | G74: =+_xlfn.XLOOKUP(C74,'BASE DATOS PRECIOS '!B:B,'BASE DATOS PRECIOS '!F:F) -> UND | H74: =+_xlfn.XLOOKUP(E74,'BASE DATOS PRECIOS '!E:E,'BASE DATOS PRECIOS '!H:H) -> 156.8101 | K74: =+F74*H74 -> 9408.606 | L74: =+F74*I74 -> 0 | M74: =+F74*J74 -> 0 | N74: =SUM(K74:M74) -> 9408.606 | O74: =SUM(K74:M74)/tc -> 18.269138
B75: =VALUE(IF(AND(LEN(TRIM(C75))-LEN(SUBSTITUTE(TRIM(C75),".",""))=1,ISNUMBER(VALUE(SUBSTITUTE(TRIM(C75),".","")))),TRIM(C75),B74)) -> 1.2 | C75: M06-0179 | E75: =+_xlfn.XLOOKUP(C75,'BASE DATOS PRECIOS '!B:B,'BASE DATOS PRECIOS '!E:E) -> CRAYON LYRA AMARILLO | F75: ='1_OG y 2_ACA'!D528 -> 10 | G75: =+_xlfn.XLOOKUP(C75,'BASE DATOS PRECIOS '!B:B,'BASE DATOS PRECIOS '!F:F) -> UND | H75: =+_xlfn.XLOOKUP(E75,'BASE DATOS PRECIOS '!E:E,'BASE DATOS PRECIOS '!H:H) -> 340.017 | K75: =+F75*H75 -> 3400.17 | L75: =+F75*I75 -> 0 | M75: =+F75*J75 -> 0 | N75: =SUM(K75:M75) -> 3400.17 | O75: =SUM(K75:M75)/tc -> 6.6022718
B76: =VALUE(IF(AND(LEN(TRIM(C76))-LEN(SUBSTITUTE(TRIM(C76),".",""))=1,ISNUMBER(VALUE(SUBSTITUTE(TRIM(C76),".","")))),TRIM(C76),B75)) -> 1.2 | C76: M10-0063 | E76: =+_xlfn.XLOOKUP(C76,'BASE DATOS PRECIOS '!B:B,'BASE DATOS PRECIOS '!E:E) -> CONCRETO FC 210 KG/CM2 AUTOCOMPACTABLE | F76: ='1_OG y 2_ACA'!D491 -> 19.77255 | G76: =+_xlfn.XLOOKUP(C76,'BASE DATOS PRECIOS '!B:B,'BASE DATOS PRECIOS '!F:F) -> M3 | H76: =+_xlfn.XLOOKUP(E76,'BASE DATOS PRECIOS '!E:E,'BASE DATOS PRECIOS '!H:H) -> 82601.169 | K76: =+F76*H76 -> 1633235.8 | L76: =+F76*I76 -> 0 | M76: =+F76*J76 -> 0 | N76: =SUM(K76:M76) -> 1633235.8 | O76: =SUM(K76:M76)/tc -> 3171.3316
B77: =VALUE(IF(AND(LEN(TRIM(C77))-LEN(SUBSTITUTE(TRIM(C77),".",""))=1,ISNUMBER(VALUE(SUBSTITUTE(TRIM(C77),".","")))),TRIM(C77),B76)) -> 1.2 | C77: BOMBA | E77: =+_xlfn.XLOOKUP(C77,'BASE DATOS EQUIPOS Y SUBCONTRAT'!A:A,'BASE DATOS EQUIPOS Y SUBCONTRAT'!B:B) -> BOMBA DE CONCRETO | F77: =F76 -> 19.77255 | G77: =+_xlfn.XLOOKUP(C77,'BASE DATOS EQUIPOS Y SUBCONTRAT'!A:A,'BASE DATOS EQUIPOS Y SUBCONTRAT'!C:C) -> M3 | H77: 0 | J77: 14000 | K77: =+F77*H77 -> 0 | L77: =+F77*I77 -> 0 | M77: =+F77*J77 -> 276815.7 | N77: =SUM(K77:M77) -> 276815.7 | O77: =SUM(K77:M77)/tc -> 537.50621 | V77: =+C179 -> M15-0001 | W77: =+E179 -> BASE ALUMINIO NEGRA PARA TAPA DE POLYCARBONATO 6.40 | X77: =+L179 -> 0 | Y77: =+X77/$X$50 -> 0 | Z77: =+X77/$Z$7 -> 0
A78: Muros y Entrepiso (Formaleta, Concreto) | B78: =VALUE(IF(AND(LEN(TRIM(C78))-LEN(SUBSTITUTE(TRIM(C78),".",""))=1,ISNUMBER(VALUE(SUBSTITUTE(TRIM(C78),".","")))),TRIM(C78),B77)) -> 1.2 | C78: OPERARIO | E78: =+_xlfn.XLOOKUP(C78,'BASE DATOS MANO DE OBRA'!A:A,'BASE DATOS MANO DE OBRA'!B:B) -> OPERARIO PLUS | F78: =+ROUNDUP('1_OG y 2_ACA'!F532,0)/2 -> 38.5 | G78: =+_xlfn.XLOOKUP(C78,'BASE DATOS MANO DE OBRA'!A:A,'BASE DATOS MANO DE OBRA'!C:C) -> hora | H78: 0 | I78: =+_xlfn.XLOOKUP(C78,'BASE DATOS MANO DE OBRA'!A:A,'BASE DATOS MANO DE OBRA'!E:E) -> 2850 | J78: 0 | K78: =+F78*H78 -> 0 | L78: =+F78*I78 -> 109725 | M78: =+F78*J78 -> 0 | N78: =SUM(K78:M78) -> 109725 | O78: =SUM(K78:M78)/tc -> 213.05825
A79: Muros y Entrepiso (Formaleta, Concreto) | B79: =VALUE(IF(AND(LEN(TRIM(C79))-LEN(SUBSTITUTE(TRIM(C79),".",""))=1,ISNUMBER(VALUE(SUBSTITUTE(TRIM(C79),".","")))),TRIM(C79),B78)) -> 1.2 | C79: AYUDANTE | E79: =+_xlfn.XLOOKUP(C79,'BASE DATOS MANO DE OBRA'!A:A,'BASE DATOS MANO DE OBRA'!B:B) -> AYUDANTE PLUS | F79: =+F78 -> 38.5 | G79: =+_xlfn.XLOOKUP(C79,'BASE DATOS MANO DE OBRA'!A:A,'BASE DATOS MANO DE OBRA'!C:C) -> hora | H79: 0 | I79: =+_xlfn.XLOOKUP(C79,'BASE DATOS MANO DE OBRA'!A:A,'BASE DATOS MANO DE OBRA'!E:E) -> 2325 | J79: 0 | K79: =+F79*H79 -> 0 | L79: =+F79*I79 -> 89512.5 | M79: =+F79*J79 -> 0 | N79: =SUM(K79:M79) -> 89512.5 | O79: =SUM(K79:M79)/tc -> 173.81068
A80: Muros y Entrepiso (Formaleta, Concreto) | B80: =VALUE(IF(AND(LEN(TRIM(C80))-LEN(SUBSTITUTE(TRIM(C80),".",""))=1,ISNUMBER(VALUE(SUBSTITUTE(TRIM(C80),".","")))),TRIM(C80),B79)) -> 1.2 | C80: OPERARIO | E80: =+_xlfn.XLOOKUP(C80,'BASE DATOS MANO DE OBRA'!A:A,'BASE DATOS MANO DE OBRA'!B:B) -> OPERARIO PLUS | F80: =+ROUNDUP(('1_OG y 2_ACA'!F533+'1_OG y 2_ACA'!F531),0)/2 -> 87.5 | G80: =+_xlfn.XLOOKUP(C80,'BASE DATOS MANO DE OBRA'!A:A,'BASE DATOS MANO DE OBRA'!C:C) -> hora | H80: 0 | I80: =+_xlfn.XLOOKUP(C80,'BASE DATOS MANO DE OBRA'!A:A,'BASE DATOS MANO DE OBRA'!E:E) -> 2850 | J80: 0 | K80: =+F80*H80 -> 0 | L80: =+F80*I80 -> 249375 | M80: =+F80*J80 -> 0 | N80: =SUM(K80:M80) -> 249375 | O80: =SUM(K80:M80)/tc -> 484.2233
A81: Muros y Entrepiso (Formaleta, Concreto) | B81: =VALUE(IF(AND(LEN(TRIM(C81))-LEN(SUBSTITUTE(TRIM(C81),".",""))=1,ISNUMBER(VALUE(SUBSTITUTE(TRIM(C81),".","")))),TRIM(C81),B80)) -> 1.2 | C81: AYUDANTE | E81: =+_xlfn.XLOOKUP(C81,'BASE DATOS MANO DE OBRA'!A:A,'BASE DATOS MANO DE OBRA'!B:B) -> AYUDANTE PLUS | F81: =+F80 -> 87.5 | G81: =+_xlfn.XLOOKUP(C81,'BASE DATOS MANO DE OBRA'!A:A,'BASE DATOS MANO DE OBRA'!C:C) -> hora | H81: 0 | I81: =+_xlfn.XLOOKUP(C81,'BASE DATOS MANO DE OBRA'!A:A,'BASE DATOS MANO DE OBRA'!E:E) -> 2325 | J81: 0 | K81: =+F81*H81 -> 0 | L81: =+F81*I81 -> 203437.5 | M81: =+F81*J81 -> 0 | N81: =SUM(K81:M81) -> 203437.5 | O81: =SUM(K81:M81)/tc -> 395.02427
A82: Desencofre y Resane | B82: =VALUE(IF(AND(LEN(TRIM(C82))-LEN(SUBSTITUTE(TRIM(C82),".",""))=1,ISNUMBER(VALUE(SUBSTITUTE(TRIM(C82),".","")))),TRIM(C82),B81)) -> 1.2 | C82: OPERARIO | E82: =+_xlfn.XLOOKUP(C82,'BASE DATOS MANO DE OBRA'!A:A,'BASE DATOS MANO DE OBRA'!B:B) -> OPERARIO PLUS | F82: =+ROUNDUP(('1_OG y 2_ACA'!F534+'1_OG y 2_ACA'!F535),0)/2 -> 63.5 | G82: =+_xlfn.XLOOKUP(C82,'BASE DATOS MANO DE OBRA'!A:A,'BASE DATOS MANO DE OBRA'!C:C) -> hora | H82: 0 | I82: =+_xlfn.XLOOKUP(C82,'BASE DATOS MANO DE OBRA'!A:A,'BASE DATOS MANO DE OBRA'!E:E) -> 2850 | J82: 0 | K82: =+F82*H82 -> 0 | L82: =+F82*I82 -> 180975 | M82: =+F82*J82 -> 0 | N82: =SUM(K82:M82) -> 180975 | O82: =SUM(K82:M82)/tc -> 351.40777
A83: Desencofre y Resane | B83: =VALUE(IF(AND(LEN(TRIM(C83))-LEN(SUBSTITUTE(TRIM(C83),".",""))=1,ISNUMBER(VALUE(SUBSTITUTE(TRIM(C83),".","")))),TRIM(C83),B82)) -> 1.2 | C83: AYUDANTE | E83: =+_xlfn.XLOOKUP(C83,'BASE DATOS MANO DE OBRA'!A:A,'BASE DATOS MANO DE OBRA'!B:B) -> AYUDANTE PLUS | F83: =+F82 -> 63.5 | G83: =+_xlfn.XLOOKUP(C83,'BASE DATOS MANO DE OBRA'!A:A,'BASE DATOS MANO DE OBRA'!C:C) -> hora | H83: 0 | I83: =+_xlfn.XLOOKUP(C83,'BASE DATOS MANO DE OBRA'!A:A,'BASE DATOS MANO DE OBRA'!E:E) -> 2325 | J83: 0 | K83: =+F83*H83 -> 0 | L83: =+F83*I83 -> 147637.5 | M83: =+F83*J83 -> 0 | N83: =SUM(K83:M83) -> 147637.5 | O83: =SUM(K83:M83)/tc -> 286.67476
B84: =VALUE(IF(AND(LEN(TRIM(C84))-LEN(SUBSTITUTE(TRIM(C84),".",""))=1,ISNUMBER(VALUE(SUBSTITUTE(TRIM(C84),".","")))),TRIM(C84),B83)) -> 1.2 | C84: 1.2.3 | E84: MAMPOSTERIA | F84: 1 | G84: gb | K84: =+SUBTOTAL(9,K85:K88) -> 0 | L84: =+SUBTOTAL(9,L85:L88) -> 0 | M84: =+SUBTOTAL(9,M85:M88) -> 0 | N84: =+SUBTOTAL(9,N85:N88) -> 0 | O84: =+SUBTOTAL(9,O85:O88) -> 0
B85: =VALUE(IF(AND(LEN(TRIM(C85))-LEN(SUBSTITUTE(TRIM(C85),".",""))=1,ISNUMBER(VALUE(SUBSTITUTE(TRIM(C85),".","")))),TRIM(C85),B84)) -> 1.2
B86: =VALUE(IF(AND(LEN(TRIM(C86))-LEN(SUBSTITUTE(TRIM(C86),".",""))=1,ISNUMBER(VALUE(SUBSTITUTE(TRIM(C86),".","")))),TRIM(C86),B85)) -> 1.2
B87: =VALUE(IF(AND(LEN(TRIM(C87))-LEN(SUBSTITUTE(TRIM(C87),".",""))=1,ISNUMBER(VALUE(SUBSTITUTE(TRIM(C87),".","")))),TRIM(C87),B86)) -> 1.2 | C87: OPERARIO | E87: =+_xlfn.XLOOKUP(C87,'BASE DATOS MANO DE OBRA'!A:A,'BASE DATOS MANO DE OBRA'!B:B) -> OPERARIO PLUS | F87: 0 | G87: =+_xlfn.XLOOKUP(C87,'BASE DATOS MANO DE OBRA'!A:A,'BASE DATOS MANO DE OBRA'!C:C) -> hora | H87: 0 | I87: =+_xlfn.XLOOKUP(C87,'BASE DATOS MANO DE OBRA'!A:A,'BASE DATOS MANO DE OBRA'!E:E) -> 2850 | J87: 0 | K87: =+F87*H87 -> 0 | L87: =+F87*I87 -> 0 | M87: =+F87*J87 -> 0 | N87: =SUM(K87:M87) -> 0 | O87: =SUM(K87:M87)/tc -> 0
B88: =VALUE(IF(AND(LEN(TRIM(C88))-LEN(SUBSTITUTE(TRIM(C88),".",""))=1,ISNUMBER(VALUE(SUBSTITUTE(TRIM(C88),".","")))),TRIM(C88),B87)) -> 1.2 | C88: AYUDANTE | E88: =+_xlfn.XLOOKUP(C88,'BASE DATOS MANO DE OBRA'!A:A,'BASE DATOS MANO DE OBRA'!B:B) -> AYUDANTE PLUS | F88: 0 | G88: =+_xlfn.XLOOKUP(C88,'BASE DATOS MANO DE OBRA'!A:A,'BASE DATOS MANO DE OBRA'!C:C) -> hora | H88: 0 | I88: =+_xlfn.XLOOKUP(C88,'BASE DATOS MANO DE OBRA'!A:A,'BASE DATOS MANO DE OBRA'!E:E) -> 2325 | J88: 0 | K88: =+F88*H88 -> 0 | L88: =+F88*I88 -> 0 | M88: =+F88*J88 -> 0 | N88: =SUM(K88:M88) -> 0 | O88: =SUM(K88:M88)/tc -> 0
B89: =VALUE(IF(AND(LEN(TRIM(C89))-LEN(SUBSTITUTE(TRIM(C89),".",""))=1,ISNUMBER(VALUE(SUBSTITUTE(TRIM(C89),".","")))),TRIM(C89),B88)) -> 1.2 | C89: 1.2.4 | E89: ACERO EN PAREDES MUROS N2 | F89: =+'1_OG y 2_ACA'!D647 -> 132.88 | G89: m2 | K89: =+SUBTOTAL(9,K91:K100) -> 423822.75 | L89: =+SUBTOTAL(9,L91:L100) -> 859050 | M89: =+SUBTOTAL(9,M91:M100) -> 0 | N89: =+SUBTOTAL(9,N90:N100) -> 1336660.7 | O89: =+SUBTOTAL(9,O91:O100) -> 2491.015
B90: =VALUE(IF(AND(LEN(TRIM(C90))-LEN(SUBSTITUTE(TRIM(C90),".",""))=1,ISNUMBER(VALUE(SUBSTITUTE(TRIM(C90),".","")))),TRIM(C90),B89)) -> 1.2 | C90: M01-0147 | D90: 01 | E90: VARILLA DEFORME #3 | F90: ='1_OG y 2_ACA'!D630 -> 40 | G90: =+_xlfn.XLOOKUP(C90,'BASE DATOS PRECIOS '!B:B,'BASE DATOS PRECIOS '!F:F) -> UND | H90: =+_xlfn.XLOOKUP(E90,'BASE DATOS PRECIOS '!E:E,'BASE DATOS PRECIOS '!H:H) -> 1344.7 | K90: =+F90*H90 -> 53788 | L90: =+F90*I90 -> 0 | M90: =+F90*J90 -> 0 | N90: =SUM(K90:M90) -> 53788 | O90: =SUM(K90:M90)/tc -> 104.44272
B91: =VALUE(IF(AND(LEN(TRIM(C91))-LEN(SUBSTITUTE(TRIM(C91),".",""))=1,ISNUMBER(VALUE(SUBSTITUTE(TRIM(C91),".","")))),TRIM(C91),B90)) -> 1.2 | C91: M01-0147 | D91: 02 | E91: VARILLA DEFORME #3 | F91: ='1_OG y 2_ACA'!D631 -> 162 | G91: =+_xlfn.XLOOKUP(C91,'BASE DATOS PRECIOS '!B:B,'BASE DATOS PRECIOS '!F:F) -> UND | H91: =+_xlfn.XLOOKUP(E91,'BASE DATOS PRECIOS '!E:E,'BASE DATOS PRECIOS '!H:H) -> 1344.7 | K91: =+F91*H91 -> 217841.4 | L91: =+F91*I91 -> 0 | M91: =+F91*J91 -> 0 | N91: =SUM(K91:M91) -> 217841.4 | O91: =SUM(K91:M91)/tc -> 422.99301
B92: =VALUE(IF(AND(LEN(TRIM(C92))-LEN(SUBSTITUTE(TRIM(C92),".",""))=1,ISNUMBER(VALUE(SUBSTITUTE(TRIM(C92),".","")))),TRIM(C92),B91)) -> 1.2 | C92: M01-0148 | E92: =+_xlfn.XLOOKUP(C92,'BASE DATOS PRECIOS '!B:B,'BASE DATOS PRECIOS '!E:E) -> VARILLA DEFORME #4 | F92: =+'1_OG y 2_ACA'!D632 -> 21.5 | G92: =+_xlfn.XLOOKUP(C92,'BASE DATOS PRECIOS '!B:B,'BASE DATOS PRECIOS '!F:F) -> UND | H92: =+_xlfn.XLOOKUP(E92,'BASE DATOS PRECIOS '!E:E,'BASE DATOS PRECIOS '!H:H) -> 2395.6 | K92: =+F92*H92 -> 51505.4 | L92: =+F92*I92 -> 0 | M92: =+F92*J92 -> 0 | N92: =SUM(K92:M92) -> 51505.4 | O92: =SUM(K92:M92)/tc -> 100.01049
B93: =VALUE(IF(AND(LEN(TRIM(C93))-LEN(SUBSTITUTE(TRIM(C93),".",""))=1,ISNUMBER(VALUE(SUBSTITUTE(TRIM(C93),".","")))),TRIM(C93),B92)) -> 1.2 | C93: M01-0145 | E93: =+_xlfn.XLOOKUP(C93,'BASE DATOS PRECIOS '!B:B,'BASE DATOS PRECIOS '!E:E) -> MALLA ELECTROSOLDADA #2 (5.3 MM) | F93: =+'1_OG y 2_ACA'!D633 -> 5.8171745 | G93: =+_xlfn.XLOOKUP(C93,'BASE DATOS PRECIOS '!B:B,'BASE DATOS PRECIOS '!F:F) -> UND | H93: =+_xlfn.XLOOKUP(E93,'BASE DATOS PRECIOS '!E:E,'BASE DATOS PRECIOS '!H:H) -> 18762.497 | K93: =+F93*H93 -> 109144.72 | L93: =+F93*I93 -> 0 | M93: =+F93*J93 -> 0 | N93: =SUM(K93:M93) -> 109144.72 | O93: =SUM(K93:M93)/tc -> 211.9315
B94: =VALUE(IF(AND(LEN(TRIM(C94))-LEN(SUBSTITUTE(TRIM(C94),".",""))=1,ISNUMBER(VALUE(SUBSTITUTE(TRIM(C94),".","")))),TRIM(C94),B93)) -> 1.2 | C94: M01-0001 | E94: =+_xlfn.XLOOKUP(C94,'BASE DATOS PRECIOS '!B:B,'BASE DATOS PRECIOS '!E:E) -> ALAMBRE NEGRO #16 (1.68MM) | F94: =+'1_OG y 2_ACA'!D634 -> 43 | G94: =+_xlfn.XLOOKUP(C94,'BASE DATOS PRECIOS '!B:B,'BASE DATOS PRECIOS '!F:F) -> KG | H94: =+_xlfn.XLOOKUP(E94,'BASE DATOS PRECIOS '!E:E,'BASE DATOS PRECIOS '!H:H) -> 586.8542 | K94: =+F94*H94 -> 25234.731 | L94: =+F94*I94 -> 0 | M94: =+F94*J94 -> 0 | N94: =SUM(K94:M94) -> 25234.731 | O94: =SUM(K94:M94)/tc -> 48.999477
B95: =VALUE(IF(AND(LEN(TRIM(C95))-LEN(SUBSTITUTE(TRIM(C95),".",""))=1,ISNUMBER(VALUE(SUBSTITUTE(TRIM(C95),".","")))),TRIM(C95),B94)) -> 1.2 | C95: M08-0051 | E95: =+_xlfn.XLOOKUP(C95,'BASE DATOS PRECIOS '!B:B,'BASE DATOS PRECIOS '!E:E) -> DISCO CORTE FINO METAL 4-1/2 | F95: =+'1_OG y 2_ACA'!D635 -> 3 | G95: =+_xlfn.XLOOKUP(C95,'BASE DATOS PRECIOS '!B:B,'BASE DATOS PRECIOS '!F:F) -> UND | H95: =+_xlfn.XLOOKUP(E95,'BASE DATOS PRECIOS '!E:E,'BASE DATOS PRECIOS '!H:H) -> 3661.2 | K95: =+F95*H95 -> 10983.6 | L95: =+F95*I95 -> 0 | M95: =+F95*J95 -> 0 | N95: =SUM(K95:M95) -> 10983.6 | O95: =SUM(K95:M95)/tc -> 21.327379
B96: =VALUE(IF(AND(LEN(TRIM(C96))-LEN(SUBSTITUTE(TRIM(C96),".",""))=1,ISNUMBER(VALUE(SUBSTITUTE(TRIM(C96),".","")))),TRIM(C96),B95)) -> 1.2 | C96: M08-0037 | E96: =+_xlfn.XLOOKUP(C96,'BASE DATOS PRECIOS '!B:B,'BASE DATOS PRECIOS '!E:E) -> DISCO CORTE METAL FINO 9" | F96: =+'1_OG y 2_ACA'!D636 -> 3 | G96: =+_xlfn.XLOOKUP(C96,'BASE DATOS PRECIOS '!B:B,'BASE DATOS PRECIOS '!F:F) -> UND | H96: =+_xlfn.XLOOKUP(E96,'BASE DATOS PRECIOS '!E:E,'BASE DATOS PRECIOS '!H:H) -> 3037.6321 | K96: =+F96*H96 -> 9112.8963 | L96: =+F96*I96 -> 0 | M96: =+F96*J96 -> 0 | N96: =SUM(K96:M96) -> 9112.8963 | O96: =SUM(K96:M96)/tc -> 17.694944
A97: Acero Muros y Entrepiso | B97: =VALUE(IF(AND(LEN(TRIM(C97))-LEN(SUBSTITUTE(TRIM(C97),".",""))=1,ISNUMBER(VALUE(SUBSTITUTE(TRIM(C97),".","")))),TRIM(C97),B96)) -> 1.2 | C97: OPERARIO | E97: =+_xlfn.XLOOKUP(C97,'BASE DATOS MANO DE OBRA'!A:A,'BASE DATOS MANO DE OBRA'!B:B) -> OPERARIO PLUS | F97: =+ROUNDUP('1_OG y 2_ACA'!F639,0)/2 -> 96 | G97: =+_xlfn.XLOOKUP(C97,'BASE DATOS MANO DE OBRA'!A:A,'BASE DATOS MANO DE OBRA'!C:C) -> hora | H97: 0 | I97: =+_xlfn.XLOOKUP(C97,'BASE DATOS MANO DE OBRA'!A:A,'BASE DATOS MANO DE OBRA'!E:E) -> 2850 | J97: 0 | K97: =+F97*H97 -> 0 | L97: =+F97*I97 -> 273600 | M97: =+F97*J97 -> 0 | N97: =SUM(K97:M97) -> 273600 | O97: =SUM(K97:M97)/tc -> 531.26214
A98: Acero Muros y Entrepiso | B98: =VALUE(IF(AND(LEN(TRIM(C98))-LEN(SUBSTITUTE(TRIM(C98),".",""))=1,ISNUMBER(VALUE(SUBSTITUTE(TRIM(C98),".","")))),TRIM(C98),B97)) -> 1.2 | C98: AYUDANTE | E98: =+_xlfn.XLOOKUP(C98,'BASE DATOS MANO DE OBRA'!A:A,'BASE DATOS MANO DE OBRA'!B:B) -> AYUDANTE PLUS | F98: =+F97 -> 96 | G98: =+_xlfn.XLOOKUP(C98,'BASE DATOS MANO DE OBRA'!A:A,'BASE DATOS MANO DE OBRA'!C:C) -> hora | H98: 0 | I98: =+_xlfn.XLOOKUP(C98,'BASE DATOS MANO DE OBRA'!A:A,'BASE DATOS MANO DE OBRA'!E:E) -> 2325 | J98: 0 | K98: =+F98*H98 -> 0 | L98: =+F98*I98 -> 223200 | M98: =+F98*J98 -> 0 | N98: =SUM(K98:M98) -> 223200 | O98: =SUM(K98:M98)/tc -> 433.39806
A99: Muros y Entrepiso (Formaleta, Concreto) | B99: =VALUE(IF(AND(LEN(TRIM(C99))-LEN(SUBSTITUTE(TRIM(C99),".",""))=1,ISNUMBER(VALUE(SUBSTITUTE(TRIM(C99),".","")))),TRIM(C99),B98)) -> 1.2 | C99: OPERARIO | E99: =+_xlfn.XLOOKUP(C99,'BASE DATOS MANO DE OBRA'!A:A,'BASE DATOS MANO DE OBRA'!B:B) -> OPERARIO PLUS | F99: =+ROUNDUP('1_OG y 2_ACA'!F715,0)/2 -> 70 | G99: =+_xlfn.XLOOKUP(C99,'BASE DATOS MANO DE OBRA'!A:A,'BASE DATOS MANO DE OBRA'!C:C) -> hora | H99: 0 | I99: =+_xlfn.XLOOKUP(C99,'BASE DATOS MANO DE OBRA'!A:A,'BASE DATOS MANO DE OBRA'!E:E) -> 2850 | J99: 0 | K99: =+F99*H99 -> 0 | L99: =+F99*I99 -> 199500 | M99: =+F99*J99 -> 0 | N99: =SUM(K99:M99) -> 199500 | O99: =SUM(K99:M99)/tc -> 387.37864
A100: Muros y Entrepiso (Formaleta, Concreto) | B100: =VALUE(IF(AND(LEN(TRIM(C100))-LEN(SUBSTITUTE(TRIM(C100),".",""))=1,ISNUMBER(VALUE(SUBSTITUTE(TRIM(C100),".","")))),TRIM(C100),B99)) -> 1.2 | C100: AYUDANTE | E100: =+_xlfn.XLOOKUP(C100,'BASE DATOS MANO DE OBRA'!A:A,'BASE DATOS MANO DE OBRA'!B:B) -> AYUDANTE PLUS | F100: =+F99 -> 70 | G100: =+_xlfn.XLOOKUP(C100,'BASE DATOS MANO DE OBRA'!A:A,'BASE DATOS MANO DE OBRA'!C:C) -> hora | H100: 0 | I100: =+_xlfn.XLOOKUP(C100,'BASE DATOS MANO DE OBRA'!A:A,'BASE DATOS MANO DE OBRA'!E:E) -> 2325 | J100: 0 | K100: =+F100*H100 -> 0 | L100: =+F100*I100 -> 162750 | M100: =+F100*J100 -> 0 | N100: =SUM(K100:M100) -> 162750 | O100: =SUM(K100:M100)/tc -> 316.01942
...

Sheet 1_OG y 2_ACA
C3: Modelo | D3: Modelo Casa | E3: VN-L.32
C6: MODELO DE CASA | D6: DATOS GENERALES
C8: DIMENSIONES
C9: Área total de casa | D9: =87.57+39.22 -> 126.79 | E9: m2 | F9: Incluye: Area total N1 y N2 interna, pilas, terrazas, ducto de escaleras SIN AZOTEA
C10: Área interna de casa | D10: =48.12+39.22+(3.5+2.15) -> 92.99 | E10: m2 | F10: Incluye: Area N1 y N2 sin garage, azotea, pilas ni terraza. Sí se debe incluir area de ducto de escalera (monitor de azotea)
C11: Área prorrateada | D11: =+D10+0.6*(D13+D14) -> 116.57 | E11: m2 | F11: Incluye: area total + area cochera * 60% + pila * 60% + terraza * 60%
C12: Área losa de fundación | D12: 48.12 | E12: m2 | F12: *medida a borde externo
C13: Áreas de pilas+terraza | D13: =4.13+5.37 -> 9.5 | E13: m2 | F13: *medida a borde externo
C14: Áreas externas de casa (cochera) | D14: 29.8 | E14: m2 | F14: *medida a borde externo
C15: Perímetro Losa flotante | D15: 34.36 | E15: m
C16: Área pilas mas losa de fundacion | D16: =+D13+D12 -> 57.62 | E16: m2
C17: Área total de nivel 1 | D17: =+D16+D14 -> 87.42 | E17: m2
C18: Área total de azotea | D18: 31.5 | E18: m2
C19: Área entrepiso de nivel 2 | D19: 39.22 | E19: m2
C20: Área total de la casa | D20: =+D19+D18+D17 -> 158.14 | E20: m2
C21: Área de techo de casa | D21: 44.8 | E21: m2
C22: Área de techo de cochera | D22: 16 | E22: m2
C23: Área de lote | D23: =6.8*18.2 -> 123.76 | E23: m2
C24: Niveles | D24: 2
C25: Azotea | D25: Sí
C26: Longitud de paredes nivel 1 | D26: 49.8 | E26: m
C27: Altura paredes nivel 1 | D27: 2.6 | E27: m
C28: Longitud de paredes nivel 2 | D28: 41.8 | E28: m
C29: Altura paredes nivel 2 | D29: 2.6 | E29: m
C30: Longitud de paredes nivel 3 azotea | D30: 24.2 | E30: m
C31: Altura paredes nivel 3 azotea | D31: 1 | E31: m
C32: Área de Muros | D32: =+D343+D547 -> 153.68 | E32: m2
C33: Cantidad de esquinas | D33: 35 | E33: u
C34: Area losa cenital | D34: 0 | E34: m2
C36: TOTAL PUERTAS Y VENTANAS
C37: Codigo | D37: Altura | E37: Ancho | F37: Cantidad
C38: Puertas Nivel 1
C39: P01 | D39: 2.15 | E39: 1 | F39: 1
C40: P02 | D40: 2.15 | E40: 0.8 | F40: 1
C41: P03 | D41: 1.15 | E41: 0.8 | F41: 1
C42: P05 | D42: 2.15 | E42: 1.8 | F42: 1
C43: P06 | D43: 2.15 | E43: 0.9 | F43: 1
C44: P07 | D44: 2.15 | E44: 1.5 | F44: 1
C45: P08 | D45: 2.15 | E45: 0.7 | F45: 1
C46: P08 | D46: 2.15 | E46: 0.8 | F46: 1
C47: P08 | D47: 2.15 | E47: 0.7 | F47: 1
C54: Puertas Nivel 2
C55: P11 | D55: 2.15 | E55: 0.9 | F55: 1
C56: P12 | D56: 2.15 | E56: 0.8 | F56: 1
C57: P13 | D57: 2.15 | E57: 0.9 | F57: 1
C58: P14 | D58: 2.15 | E58: 0.9 | F58: 1
C59: P15 | D59: 2.15 | E59: 0.9 | F59: 1
C70: Ventanas Nivel 1
D71: 2.15 | E71: 0.6 | F71: 1
D72: 0.55 | E72: 0.55 | F72: 1
D73: 0.55 | E73: 0.55 | F73: 1
C82: Ventanas Nivel 2
D83: 1.95 | E83: 1.35 | F83: 1
D84: 1.95 | E84: 1.2 | F84: 1
D85: 1.5 | E85: 1.5 | F85: 1
D86: 1.5 | E86: 1.5 | F86: 1
D87: 2.1 | E87: 1.2 | F87: 1
C94: FACTORES
C95: Factor de compactación | D95: 0.3
C96: Factor de desperdicio general | D96: 0.05
C97: Factor MO para muros de concreto | D97: =IF(D33/D32>0.2,1.1,1) -> 1.1
C98: DOSIFICACIONES /m3
C99: Sello Arena | D99: =ROUNDUP(1083*(1+FDG)/1600,2) -> 0.72 | E99: m3
C100: Sello Piedra cuartilla | D100: =ROUNDUP(852*(1+FDG)/1600,2) -> 0.56 | E100: m3
C101: Sello Cemento | D101: 180 | E101: kg
C102: Losas Arena | D102: =ROUNDUP(872*(1+FDG)/1600,2) -> 0.58 | E102: m3
C103: Losas Piedra cuartilla | D103: =ROUNDUP(952*(1+FDG)/1600,2) -> 0.63 | E103: m3
C104: Losas Cemento | D104: 333 | E104: kg
C105: Losas Aditivo | D105: 0.8 | E105: litros
C106: Muros Arena | D106: =ROUNDUP(1050*(1+FDG)/1600,2) -> 0.69 | E106: m3
C107: Muros Piedra quintilla | D107: =ROUNDUP(810*(1+FDG)/1600,2) -> 0.54 | E107: m3
C108: Muros Cemento | D108: 340 | E108: kg
C109: Muros Aditivo | D109: 2.4 | E109: litros
C110: Muros Fibra | D110: 1 | E110: kg
C111: ACEROS
C112: Alambre negro | D112: 0.045
C113: Soldadura | D113: =2.2/550 -> 0.004
C114: Thinner | D114: =+D113 -> 0.004
C115: Disco corte metal | D115: =+D114 -> 0.004
C116: Mecha | D116: =+D115 -> 0.004
C117: CIELOS DE GYPSUM
C118: Láminas (a una cara) | D118: =1.1/1.22/2.44 -> 0.36952432 | E118: /m2
C119: Perfil omega | D119: =1.1/0.4/3.5 -> 0.78571429 | E119: /m2
C120: Canal para cielo | D120: =1.1/1.2/4.5 -> 0.2037037 | E120: /m2
C121: Angular de metal | D121: 0.25 | E121: /m2
C122: Cinta papel de 2"x76m | D122: =+D118*3.66/76*1.1 -> 0.019575065 | E122: /m2
C123: Pasta para cielo (cubeta) | D123: 0.066666667 | E123: /m2
C124: Tornillo frijolillo | D124: 25 | E124: /m2
C125: Tornillo de forro | D125: 12 | E125: /m2
C126: MURO SECO
C127: Láminas (a dos caras) | D127: =2*1.1/1.22/2.44 -> 0.73904864 | E127: /m2
C128: Stud | D128: =1.1/0.4/3 -> 0.91666667 | E128: /m2
C129: Track | D129: =1.1*2/D27/3 -> 0.28205128 | E129: /m2
C130: Clavo de impacto | D130: =+D129*3/0.2 -> 4.2307692 | E130: /m2
C131: Tiro verde | D131: =+D130 -> 4.2307692 | E131: /m2
C132: Cinta malla | D132: =+D118*2*3.66/45*1.1 -> 0.066120219 | E132: /m2
C133: Jota de plástico | D133: =1.1/3.05 -> 0.36065574 | E133: /m2
C134: Esquinero de plástico | D134: =1.1/3.05 -> 0.36065574 | E134: /m2
C135: Tornillo frijolillo | D135: 25 | E135: /m2
C136: Tornillo de forro | D136: 24 | E136: /m2
...

Sheet 3.2_MEC
C3: Modelo | D3: ='1_OG y 2_ACA'!D3 -> Modelo Casa | E3: ='1_OG y 2_ACA'!E3 -> VN-L.32
C5: 3 | D5: ELECTROMECANICO
C7: 3.2 | D7: MECÁNICO
C10: Elemento | D10: Cantidad | E10: Unidad
C11: Baño Principal | D11: 1 | E11: u
C12: Baño Secundario | D12: 1 | E12: u
C13: Medio baño | D13: 1 | E13: u
C15: 3.2.1 | D15: EXCAVACION TUBERIA SANITARIA
C17: SANITARIO EN LOSA
C18: Tubería
B19: M13-0179 | C19: Tubo PVC 4" | D19: =29.8+10 -> 39.8 | E19: =ROUNDUP(D19/6,0) -> 7
B20: M13-0190 | C20: Tubo PVC 3" | D20: 0 | E20: =ROUNDUP(D20/6,0) -> 0
B21: M13-0173 | C21: Tubo PVC 2" | D21: =12.1+10 -> 22.1 | E21: =ROUNDUP(D21/6,0) -> 4
C22: Accesorios
B23: M13-0096 | C23: Codo 90 PVC 4" | D23: 6 | E23: =ROUNDUP(D23,0) -> 6
B24: M13-0118 | C24: Codo 45 PVC 4" | E24: =ROUNDUP(D24,0) -> 0
B25: M13-0124 | C25: Codo 90 PVC 3" | E25: =ROUNDUP(D25,0) -> 0
B26: M13-0117 | C26: Codo 45 PVC 3" | E26: =ROUNDUP(D26,0) -> 0
B27: M13-0211 | C27: Codo 90 PVC 2" | D27: 9 | E27: =ROUNDUP(D27,0) -> 9
B28: M13-0119 | C28: Codo 45 PVC 2" | D28: 2 | E28: =ROUNDUP(D28,0) -> 2
B29: M13-0193 | C29: Yee PVC 4" | D29: 3 | E29: =ROUNDUP(D29,0) -> 3
B30: M13-0192 | C30: Yee PVC 3" | E30: =ROUNDUP(D30,0) -> 0
B31: M13-0191 | C31: Yee PVC 2" | D31: 3 | E31: =ROUNDUP(D31,0) -> 3
B32: M13-0132 | C32: Reducción 3" a 4" | D32: 2 | E32: =ROUNDUP(D32,0) -> 2
B33: M13-0134 | C33: Reducción 2" a 3" | E33: =ROUNDUP(D33,0) -> 0
D35: Costo | E35: Costo Total | F35: Horas
C36: Mano de obra ml de tuberia | D36: =+'1_OG y 2_ACA'!D154 -> 1200 | E36: =+SUM(D19:D21)*D36 -> 74280 | F36: =+E36/'COSTOS MO CUADRILLA'!K70 -> 26.260606
C37: Mano de obra accesorios | D37: =+'1_OG y 2_ACA'!D155 -> 500 | E37: =+SUM(D23:D33)*D37 -> 12500 | F37: =+E37/'COSTOS MO CUADRILLA'!K70 -> 4.4191919
D38: Total | E38: =SUM(E36:E37) -> 86780 | F38: =+E38/'COSTOS MO CUADRILLA'!K70 -> 30.679798
C41: 3.2.2 | D41: POTABLE DE LOSA
C43: POTABLE EN LOSA
C44: Tubería
B45: M13-0170 | C45: Tubo PVC 1/2 | D45: =39.4+10 -> 49.4 | E45: =ROUNDUP(D45/6,0) -> 9
B46: M13-0166 | C46: Tubo CPVC 1/2 | D46: =26.2+12 -> 38.2 | E46: =ROUNDUP(D46/6,0) -> 7
C47: Accesorios
B48: M13-0120 | C48: Codo 90 PVC 1/2 | D48: 18 | E48: =ROUNDUP(D48,0) -> 18
B49: M13-0094 | C49: Codo 90 CPVC 1/2 | D49: 15 | E49: =ROUNDUP(D49,0) -> 15
B50: M13-0159 | C50: Tee PVC 1/2 | D50: 12 | E50: =ROUNDUP(D50,0) -> 12
B51: M13-0157 | C51: Tee CPVC 1/2 | D51: 5 | E51: =ROUNDUP(D51,0) -> 5
B52: M13-0091 | C52: Adaptador macho PVC 1/2 | D52: 1 | E52: =ROUNDUP(D52,0) -> 1
B53: M13-0090 | C53: Adaptador macho CPVC 1/2 | D53: 1 | E53: =ROUNDUP(D53,0) -> 1
B54: M13-0255 | C54: Llave de paso 1/2 | D54: 1 | E54: =ROUNDUP(D54,0) -> 1
B55: M13-0245 | C55: Llave de chorro 1/2 | D55: 1 | E55: =ROUNDUP(D55,0) -> 1
D57: Costo | E57: Costo Total | F57: Horas
C58: Mano de obra ml de tuberia | D58: =+'1_OG y 2_ACA'!D158 -> 600 | E58: =+SUM(D45:D46)*D58 -> 52560 | F58: =+E58/'COSTOS MO CUADRILLA'!K71 -> 18.581818
C59: Mano de obra accesorios | D59: =+'1_OG y 2_ACA'!D159 -> 485 | E59: =+SUM(D48:D55)*D59 -> 26190 | F59: =+E59/'COSTOS MO CUADRILLA'!K71 -> 9.2590909
D60: Total | E60: =SUM(E58:E59) -> 78750 | F60: =+E60/'COSTOS MO CUADRILLA'!K71 -> 27.840909
C63: 3.2.2.1 | D63: POTABLE DE ENTREPISO
C65: POTABLE DE ENTREPISO
C66: Tubería | D66: ml
B67: M13-0170 | C67: Tubo PVC 1/2 | D67: 0 | E67: =ROUNDUP(D67/6,0) -> 0
B68: M13-0166 | C68: Tubo CPVC 1/2 | D68: 0 | E68: =ROUNDUP(D68/6,0) -> 0
C69: Accesorios
B70: M13-0120 | C70: Codo 90 PVC 1/2 | D70: 0 | E70: =ROUNDUP(D70,0) -> 0
B71: M13-0094 | C71: Codo 90 CPVC 1/2 | D71: 0 | E71: =ROUNDUP(D71,0) -> 0
B72: M13-0159 | C72: Tee PVC 1/2 | D72: 0 | E72: =ROUNDUP(D72,0) -> 0
B73: M13-0157 | C73: Tee CPVC 1/2 | D73: 0 | E73: =ROUNDUP(D73,0) -> 0
B74: M13-0091 | C74: Adaptador macho PVC 1/2 | D74: 0 | E74: =ROUNDUP(D74,0) -> 0
B75: M13-0090 | C75: Adaptador macho CPVC 1/2 | D75: 0 | E75: =ROUNDUP(D75,0) -> 0
D77: Costo | E77: Costo Total | F77: Horas
C78: Mano de obra ml de tuberia | D78: =+'1_OG y 2_ACA'!D158 -> 600 | E78: =+SUM(D67:D68)*D78 -> 0 | F78: =+E78/'COSTOS MO CUADRILLA'!K72 -> 0
C79: Mano de obra accesorios | D79: =+'1_OG y 2_ACA'!D159 -> 485 | E79: =+SUM(D70:D75)*D79 -> 0 | F79: =+E79/'COSTOS MO CUADRILLA'!K72 -> 0
D80: Total | E80: =SUM(E78:E79) -> 0 | F80: =+E80/'COSTOS MO CUADRILLA'!K72 -> 0
C83: 3.2.2.2 | D83: SANITARIO DE ENTREPISO
C85: SANITARIO DE ENTREPISO
C86: Tubería
B87: M13-0190 | C87: Tubo PVC 3" | D87: 0 | E87: =ROUNDUP(D87/6,0) -> 0
B88: M13-0173 | C88: Tubo PVC 2" | D88: 0 | E88: =ROUNDUP(D88/6,0) -> 0
C89: Accesorios
B90: M13-0124 | C90: Codo 90 PVC 3" | D90: 0 | E90: =ROUNDUP(D90,0) -> 0
B91: M13-0117 | C91: Codo 45 PVC 3" | D91: 0 | E91: =ROUNDUP(D91,0) -> 0
B92: M13-0211 | C92: Codo 90 PVC 2" | D92: 0 | E92: =ROUNDUP(D92,0) -> 0
B93: M13-0119 | C93: Codo 45 PVC 2" | D93: 0 | E93: =ROUNDUP(D93,0) -> 0
B94: M13-0192 | C94: Yee PVC 3" | D94: 0 | E94: =ROUNDUP(D94,0) -> 0
B95: M13-0191 | C95: Yee PVC 2" | D95: 0 | E95: =ROUNDUP(D95,0) -> 0
B96: M13-0134 | C96: Reducción 2" a 3" | D96: 0 | E96: =ROUNDUP(D96,0) -> 0
D98: Costo | E98: Costo Total | F98: Horas
C99: Mano de obra ml de tuberia | D99: =+'1_OG y 2_ACA'!D156 -> 1200 | E99: =+SUM(D87:D88)*D99 -> 0 | F99: =+E99/'COSTOS MO CUADRILLA'!K72 -> 0
C100: Mano de obra accesorios | D100: =+'1_OG y 2_ACA'!D157 -> 400 | E100: =+SUM(D90:D96)*D100 -> 0 | F100: =+E100/'COSTOS MO CUADRILLA'!K72 -> 0
D101: Total | E101: =SUM(E99:E100) -> 0 | F101: =+E101/'COSTOS MO CUADRILLA'!K72 -> 0
C104: 3.2.3 | D104: TUBERÍA MECÁNICA MUROS
C106: MECANICO MUROS 1NIVEL
C107: Tubería | D107: (m)
B108: M13-0172 | C108: Tubo SDR41 PVC 1 1/4 | D108: 0 | E108: =ROUNDUP(D108,0) -> 0
B109: M13-0170 | C109: Tubo PVC 1/2 p/gruesa | D109: =+H114/6 -> 0 | E109: =ROUNDUP(D109,0) -> 0
B110: M13-0166 | C110: Tubo CPVC 1/2 | D110: =+I114/6 -> 0 | E110: =ROUNDUP(D110,0) -> 0
C111: Accesorios
B112: M13-0120 | C112: Codo 90 PVC liso 1/2" | D112: 0 | E112: =ROUNDUP(D112,0) -> 0
B113: M13-0094 | C113: Codo 90 CPVC 1/2" | D113: 0 | E113: =ROUNDUP(D113,0) -> 0
B114: M13-0091 | C114: Adaptador macho PVC 1/2 | D114: 0 | E114: =ROUNDUP(D114,0) -> 0
B115: M13-0090 | C115: Adaptador macho CPVC 1/2 | D115: 0 | E115: =ROUNDUP(D115,0) -> 0
B116: M13-0147 | C116: Tapon hembra liso PVC 1/2 | D116: 0 | E116: =ROUNDUP(D116,0) -> 0
B117: M13-0100 | C117: Tapon liso CPVC 1/2 | D117: 0 | E117: =ROUNDUP(D117,0) -> 0
B118: M13-0199 | C118: Tapon liso PVC sanitario 11/4 | D118: 0 | E118: =ROUNDUP(D118,0) -> 0
C120: MECANICO MUROS 2NIVEL
C121: Tubería
B122: M13-0172 | C122: Tubo SDR41 pvc 1 1/4 | D122: 0 | E122: =ROUNDUP(D122,0) -> 0
B123: M13-0170 | C123: Tubo PVC 1/2 p/gruesa | D123: 0 | E123: =ROUNDUP(D123,0) -> 0
B124: M13-0166 | C124: Tubo CPVC 1/2 | D124: 0 | E124: =ROUNDUP(D124,0) -> 0
C125: Accesorios
...

Sheet 3.1_ELEC
C3: Modelo | D3: ='1_OG y 2_ACA'!D3 -> Modelo Casa | E3: ='1_OG y 2_ACA'!E3 -> VN-L.32
C5: 3 | D5: ELECTROMECANICO
C7: 3.1 | D7: ELÉCTRICO
C9: 3.1.1 | D9: ACOMETIDA & ELECTRICO LOSA
C11: Seleccionar modelo: | D11: Zante / Azotea
C13: Tuberia acometida electrica
B14: M05-0362 | C14: Curva 38mm 1 1/2" | D14: =IFERROR(_xlfn.XLOOKUP($D$11,ELEC!$F$5:$AV$5,ELEC!F6:AV6,0,0,1),0) -> 1 | E14: =ROUNDUP(D14,0) -> 1
B15: M05-0366 | C15: Curva 25mm 1" | D15: =IFERROR(_xlfn.XLOOKUP($D$11,ELEC!$F$5:$AV$5,ELEC!F7:AV7,0,0,1),0) -> 3 | E15: =ROUNDUP(D15,0) -> 3
B16: M05-0361 | C16: Curva 13mm 1/2" | D16: =IFERROR(_xlfn.XLOOKUP($D$11,ELEC!$F$5:$AV$5,ELEC!F8:AV8,0,0,1),0) -> 45 | E16: =ROUNDUP(D16,0) -> 45
B17: M05-0367 | C17: Curva 19mm 3/4" | D17: =IFERROR(_xlfn.XLOOKUP($D$11,ELEC!$F$5:$AV$5,ELEC!F9:AV9,0,0,1),0) -> 15 | E17: =ROUNDUP(D17,0) -> 15
B18: M05-0368 | C18: Tubo 38mm 1 1/2" | D18: =IFERROR(_xlfn.XLOOKUP($D$11,ELEC!$F$5:$AV$5,ELEC!F10:AV10,0,0,1),0) -> 4 | E18: =ROUNDUP(D18,0) -> 4 | H18: Ikaria / Techo
B19: M05-0369 | C19: Tubo 25mm 1" | D19: =IFERROR(_xlfn.XLOOKUP($D$11,ELEC!$F$5:$AV$5,ELEC!F11:AV11,0,0,1),0) -> 7 | E19: =ROUNDUP(D19,0) -> 7 | H19: Ikaria Especial / Techo
B20: M05-0370 | C20: Tubo 13mm 1/2" | D20: =IFERROR(_xlfn.XLOOKUP($D$11,ELEC!$F$5:$AV$5,ELEC!F12:AV12,0,0,1),0) -> 45 | E20: =ROUNDUP(D20,0) -> 45 | H20: Ikaria / Azotea
B21: M05-0371 | C21: Tubo 19mm 3/4" | D21: =IFERROR(_xlfn.XLOOKUP($D$11,ELEC!$F$5:$AV$5,ELEC!F13:AV13,0,0,1),0) -> 25 | E21: =ROUNDUP(D21,0) -> 25 | H21: Milo / Azotea
B22: M05-0372 | C22: Union 38mm 1 1/2" | D22: =IFERROR(_xlfn.XLOOKUP($D$11,ELEC!$F$5:$AV$5,ELEC!F14:AV14,0,0,1),0) -> 3 | E22: =ROUNDUP(D22,0) -> 3 | H22: Milo / Techo
B23: M05-0373 | C23: Union 25mm 1" | D23: =IFERROR(_xlfn.XLOOKUP($D$11,ELEC!$F$5:$AV$5,ELEC!F15:AV15,0,0,1),0) -> 3 | E23: =ROUNDUP(D23,0) -> 3 | H23: Milo 1,1 / Techo
B24: M05-0374 | C24: Union 13mm 1/2" | D24: =IFERROR(_xlfn.XLOOKUP($D$11,ELEC!$F$5:$AV$5,ELEC!F16:AV16,0,0,1),0) -> 18 | E24: =ROUNDUP(D24,0) -> 18 | H24: Neo Tripoli / Techo
B25: M05-0375 | C25: Union 19mm 3/4" | D25: =IFERROR(_xlfn.XLOOKUP($D$11,ELEC!$F$5:$AV$5,ELEC!F17:AV17,0,0,1),0) -> 15 | E25: =ROUNDUP(D25,0) -> 15 | H25: Neo Tripoli / Azotea
B26: M05-0476 | C26: Conector de 1/2" UL | D26: =IFERROR(_xlfn.XLOOKUP($D$11,ELEC!$F$5:$AV$5,ELEC!F18:AV18,0,0,1),0) -> 0 | E26: =ROUNDUP(D26,0) -> 0 | H26: Santorini / Azotea
B27: M11-0071 | C27: Spray | D27: =IFERROR(_xlfn.XLOOKUP($D$11,ELEC!$F$5:$AV$5,ELEC!F19:AV19,0,0,1),0) -> 1 | E27: =ROUNDUP(D27,0) -> 1 | H27: Santorini 4D / Azotea
B28: M06-0175 | C28: Cinta empaque | D28: =IFERROR(_xlfn.XLOOKUP($D$11,ELEC!$F$5:$AV$5,ELEC!F20:AV20,0,0,1),0) -> 1 | E28: =ROUNDUP(D28,0) -> 1 | H28: Santorini DA / Azotea
B29: M06-0013 | C29: Pegamento | D29: =IFERROR(_xlfn.XLOOKUP($D$11,ELEC!$F$5:$AV$5,ELEC!F21:AV21,0,0,1),0) -> 1 | E29: =ROUNDUP(D29,0) -> 1 | H29: Skyros / Techo
... B33: M06-0197 | C33: Cilindro de gas | D33: =IFERROR(_xlfn.XLOOKUP($D$11,ELEC!$F$5:$AV$5,ELEC!F25:AV25,0,0,1),0) -> 1 | E33: =ROUNDUP(D33,0) -> 1 | H33: Zante / Techo
H34: Zante / Azotea
C35: SUBCONTRATO | D35: =+E328+E329 -> 211250 | H35: Zante Crece / Techo
H36: Zante Crece / Azotea
H37: Zante Of / Techo
C38: 3.1.2 | D38: ELÉCTRICO MUROS | H38: Zante Of / Azotea
H39: Zante Mod. / Azotea
H40: Stella / Techo
C41: ELECTRICO MUROS | D41: Cantidad | E41: Unidad | H41: Stella / Azotea
B42: M05-0372 | C42: Union 1 1/2" | D42: =IFERROR(_xlfn.XLOOKUP($D$11,ELEC!$F$5:$AV$5,ELEC!F32:AV32,0,0,1),0)+IFERROR(_xlfn.XLOOKUP($D$11,ELEC!$F$5:$AV$5,ELEC!F84:AV84,0,0,1),0) -> 0 | E42: =ROUNDUP(D42,0) -> 0 | H42: Stella 1DA / Techo
B43: M05-0373 | C43: Union 1" | D43: =IFERROR(_xlfn.XLOOKUP($D$11,ELEC!$F$5:$AV$5,ELEC!F33:AV33,0,0,1),0)+IFERROR(_xlfn.XLOOKUP($D$11,ELEC!$F$5:$AV$5,ELEC!F85:AV85,0,0,1),0) -> 0 | E43: =ROUNDUP(D43,0) -> 0 | H43: Stella 1DA-1DA / Azotea
B44: M05-0374 | C44: Union 1/2" | D44: =IFERROR(_xlfn.XLOOKUP($D$11,ELEC!$F$5:$AV$5,ELEC!F34:AV34,0,0,1),0)+IFERROR(_xlfn.XLOOKUP($D$11,ELEC!$F$5:$AV$5,ELEC!F86:AV86,0,0,1),0) -> 20 | E44: =ROUNDUP(D44,0) -> 20 | H44: Stella L 1DA / Azotea
B45: M05-0375 | C45: Union 3/4" | D45: =IFERROR(_xlfn.XLOOKUP($D$11,ELEC!$F$5:$AV$5,ELEC!F35:AV35,0,0,1),0)+IFERROR(_xlfn.XLOOKUP($D$11,ELEC!$F$5:$AV$5,ELEC!F87:AV87,0,0,1),0) -> 12 | E45: =ROUNDUP(D45,0) -> 12 | H45: Stella L 1DA-1DA / Azotea
B46: M11-0071 | C46: Spray | D46: =IFERROR(_xlfn.XLOOKUP($D$11,ELEC!$F$5:$AV$5,ELEC!F36:AV36,0,0,1),0)+IFERROR(_xlfn.XLOOKUP($D$11,ELEC!$F$5:$AV$5,ELEC!F88:AV88,0,0,1),0) -> 2 | E46: =ROUNDUP(D46,0) -> 2 | H46: Stella L 1DA-2DA.1 / Azotea
B47: M06-0175 | C47: Cinta empaque | D47: =IFERROR(_xlfn.XLOOKUP($D$11,ELEC!$F$5:$AV$5,ELEC!F37:AV37,0,0,1),0)+IFERROR(_xlfn.XLOOKUP($D$11,ELEC!$F$5:$AV$5,ELEC!F89:AV89,0,0,1),0) -> 4 | E47: =ROUNDUP(D47,0) -> 4 | H47: Stella L 1DA-2DA.2 / Azotea
B48: M06-0013 | C48: Pegamento | D48: =IFERROR(_xlfn.XLOOKUP($D$11,ELEC!$F$5:$AV$5,ELEC!F38:AV38,0,0,1),0)+IFERROR(_xlfn.XLOOKUP($D$11,ELEC!$F$5:$AV$5,ELEC!F90:AV90,0,0,1),0) -> 3 | E48: =ROUNDUP(D48,0) -> 3 | H48: Stella L 2DA / Techo
B49: M06-0210 | C49: Cegueta | D49: =IFERROR(_xlfn.XLOOKUP($D$11,ELEC!$F$5:$AV$5,ELEC!F39:AV39,0,0,1),0)+IFERROR(_xlfn.XLOOKUP($D$11,ELEC!$F$5:$AV$5,ELEC!F91:AV91,0,0,1),0) -> 2 | E49: =ROUNDUP(D49,0) -> 2 | H49: Stella L 2DA / Azotea
B50: M04-0003 | C50: Lamina de estereofon | D50: =IFERROR(_xlfn.XLOOKUP($D$11,ELEC!$F$5:$AV$5,ELEC!F40:AV40,0,0,1),0)+IFERROR(_xlfn.XLOOKUP($D$11,ELEC!$F$5:$AV$5,ELEC!F92:AV92,0,0,1),0) -> 1 | E50: =ROUNDUP(D50,0) -> 1 | H50: Stellita / Azotea
B51: M06-0197 | C51: Cilindro gas | D51: =IFERROR(_xlfn.XLOOKUP($D$11,ELEC!$F$5:$AV$5,ELEC!F41:AV41,0,0,1),0)+IFERROR(_xlfn.XLOOKUP($D$11,ELEC!$F$5:$AV$5,ELEC!F93:AV93,0,0,1),0) -> 3 | E51: =ROUNDUP(D51,0) -> 3 | H51: Stella L 2DA Amp / Azotea
B52: M05-0388 | C52: Caja cuadrada 4x4 doble 1 | D52: =IFERROR(_xlfn.XLOOKUP($D$11,ELEC!$F$5:$AV$5,ELEC!F42:AV42,0,0,1),0)+IFERROR(_xlfn.XLOOKUP($D$11,ELEC!$F$5:$AV$5,ELEC!F94:AV94,0,0,1),0) -> 1 | E52: =ROUNDUP(D52,0) -> 1 | H52: Stella L 1DA Amp / Azotea
B53: M05-0385 | C53: Caja cuadrada 4x4 doble 1/2 | D53: =IFERROR(_xlfn.XLOOKUP($D$11,ELEC!$F$5:$AV$5,ELEC!F43:AV43,0,0,1),0)+IFERROR(_xlfn.XLOOKUP($D$11,ELEC!$F$5:$AV$5,ELEC!F95:AV95,0,0,1),0) -> 5 | E53: =ROUNDUP(D53,0) -> 5 | H53: Zante DA / Azotea
... B60: M05-0405 | C60: Tubo 1/2" | D60: =IFERROR(_xlfn.XLOOKUP($D$11,ELEC!$F$5:$AV$5,ELEC!F50:AV50,0,0,1),0)+IFERROR(_xlfn.XLOOKUP($D$11,ELEC!$F$5:$AV$5,ELEC!F102:AV102,0,0,1),0) -> 10 | E60: =ROUNDUP(D60,0) -> 10 | H60: Gyro / Azotea
B61: M05-0386 | C61: Aro de repello 1 Gang | D61: =IFERROR(_xlfn.XLOOKUP($D$11,ELEC!$F$5:$AV$5,ELEC!F51:AV51,0,0,1),0)+IFERROR(_xlfn.XLOOKUP($D$11,ELEC!$F$5:$AV$5,ELEC!F103:AV103,0,0,1),0) -> 4 | E61: =ROUNDUP(D61,0) -> 4
B62: M01-0147 | C62: Varilla #3 G40 | D62: =IFERROR(_xlfn.XLOOKUP($D$11,ELEC!$F$5:$AV$5,ELEC!F52:AV52,0,0,1),0)+IFERROR(_xlfn.XLOOKUP($D$11,ELEC!$F$5:$AV$5,ELEC!F104:AV104,0,0,1),0) -> 6 | E62: =ROUNDUP(D62,0) -> 6
B63: M05-0371 | C63: Tubo 19mm 3/4" | D63: =IFERROR(_xlfn.XLOOKUP($D$11,ELEC!$F$5:$AV$5,ELEC!F53:AV53,0,0,1),0)+IFERROR(_xlfn.XLOOKUP($D$11,ELEC!$F$5:$AV$5,ELEC!F105:AV105,0,0,1),0) -> 4 | E63: =ROUNDUP(D63,0) -> 4
C65: SUBCONTRATO | D65: =+E330 -> 71250
C68: 3.1.3 | D68: ELECTRICO ENTREPISO
C71: ELECTRICO ENTREPISO | D71: Cantidad | E71: Unidad
B72: M05-0362 | C72: Curva 38mm 1 1/2" | D72: =IFERROR(_xlfn.XLOOKUP($D$11,ELEC!$F$5:$AV$5,ELEC!F58:AV58,0,0,1),0) -> 0 | E72: =ROUNDUP(D72,0) -> 0
B73: M05-0366 | C73: Curva 25mm 1" | D73: =IFERROR(_xlfn.XLOOKUP($D$11,ELEC!$F$5:$AV$5,ELEC!F59:AV59,0,0,1),0) -> 0 | E73: =ROUNDUP(D73,0) -> 0
B74: M05-0361 | C74: Curva 13mm 1/2" | D74: =IFERROR(_xlfn.XLOOKUP($D$11,ELEC!$F$5:$AV$5,ELEC!F60:AV60,0,0,1),0) -> 45 | E74: =ROUNDUP(D74,0) -> 45
B75: M05-0367 | C75: Curva 19mm 3/4" | D75: =IFERROR(_xlfn.XLOOKUP($D$11,ELEC!$F$5:$AV$5,ELEC!F61:AV61,0,0,1),0) -> 15 | E75: =ROUNDUP(D75,0) -> 15
B76: M05-0368 | C76: Tubo 38mm 1 1/2" | D76: =IFERROR(_xlfn.XLOOKUP($D$11,ELEC!$F$5:$AV$5,ELEC!F62:AV62,0,0,1),0) -> 0 | E76: =ROUNDUP(D76,0) -> 0
B77: M05-0369 | C77: Tubo 25mm 1" | D77: =IFERROR(_xlfn.XLOOKUP($D$11,ELEC!$F$5:$AV$5,ELEC!F63:AV63,0,0,1),0) -> 0 | E77: =ROUNDUP(D77,0) -> 0
B78: M05-0370 | C78: Tubo 13mm 1/2" | D78: =IFERROR(_xlfn.XLOOKUP($D$11,ELEC!$F$5:$AV$5,ELEC!F64:AV64,0,0,1),0) -> 45 | E78: =ROUNDUP(D78,0) -> 45
B79: M05-0371 | C79: Tubo 19mm 3/4" | D79: =IFERROR(_xlfn.XLOOKUP($D$11,ELEC!$F$5:$AV$5,ELEC!F65:AV65,0,0,1),0) -> 12 | E79: =ROUNDUP(D79,0) -> 12
B80: M05-0372 | C80: Union 38mm 1 1/2" | D80: =IFERROR(_xlfn.XLOOKUP($D$11,ELEC!$F$5:$AV$5,ELEC!F66:AV66,0,0,1),0) -> 0 | E80: =ROUNDUP(D80,0) -> 0
B81: M05-0373 | C81: Union 25mm 1" | D81: =IFERROR(_xlfn.XLOOKUP($D$11,ELEC!$F$5:$AV$5,ELEC!F67:AV67,0,0,1),0) -> 0 | E81: =ROUNDUP(D81,0) -> 0
B82: M05-0374 | C82: Union 13mm 1/2" | D82: =IFERROR(_xlfn.XLOOKUP($D$11,ELEC!$F$5:$AV$5,ELEC!F68:AV68,0,0,1),0) -> 15 | E82: =ROUNDUP(D82,0) -> 15
B83: M05-0375 | C83: Union 19mm 3/4" | D83: =IFERROR(_xlfn.XLOOKUP($D$11,ELEC!$F$5:$AV$5,ELEC!F69:AV69,0,0,1),0) -> 10 | E83: =ROUNDUP(D83,0) -> 10
... B93: M05-0477 | C93: Conector de 3/4" UL | D93: =IFERROR(_xlfn.XLOOKUP($D$11,ELEC!$F$5:$AV$5,ELEC!F79:AV79,0,0,1),0) -> 10 | E93: =ROUNDUP(D93,0) -> 10
C97: 3.1.4 | D97: ELECTRICO AZOTEA
C100: ELECTRICO ENTREPISO | D100: Cantidad | E100: Unidad
B101: M05-0362 | C101: Curva 38mm 1 1/2" | D101: =IFERROR(_xlfn.XLOOKUP($D$11,ELEC!$F$5:$AV$5,ELEC!F110:AV110,0,0,1),0) -> 0 | E101: =ROUNDUP(D101,0) -> 0
B102: M05-0366 | C102: Curva 25mm 1" | D102: =IFERROR(_xlfn.XLOOKUP($D$11,ELEC!$F$5:$AV$5,ELEC!F111:AV111,0,0,1),0) -> 0 | E102: =ROUNDUP(D102,0) -> 0
B103: M05-0361 | C103: Curva 13mm 1/2" | D103: =IFERROR(_xlfn.XLOOKUP($D$11,ELEC!$F$5:$AV$5,ELEC!F112:AV112,0,0,1),0) -> 25 | E103: =ROUNDUP(D103,0) -> 25
B104: M05-0367 | C104: Curva 19mm 3/4" | D104: =IFERROR(_xlfn.XLOOKUP($D$11,ELEC!$F$5:$AV$5,ELEC!F113:AV113,0,0,1),0) -> 7 | E104: =ROUNDUP(D104,0) -> 7
B105: M05-0368 | C105: Tubo 38mm 1 1/2" | D105: =IFERROR(_xlfn.XLOOKUP($D$11,ELEC!$F$5:$AV$5,ELEC!F114:AV114,0,0,1),0) -> 0 | E105: =ROUNDUP(D105,0) -> 0
B106: M05-0369 | C106: Tubo 25mm 1" | D106: =IFERROR(_xlfn.XLOOKUP($D$11,ELEC!$F$5:$AV$5,ELEC!F115:AV115,0,0,1),0) -> 0 | E106: =ROUNDUP(D106,0) -> 0
B107: M05-0370 | C107: Tubo 13mm 1/2" | D107: =IFERROR(_xlfn.XLOOKUP($D$11,ELEC!$F$5:$AV$5,ELEC!F116:AV116,0,0,1),0) -> 25 | E107: =ROUNDUP(D107,0) -> 25
B108: M05-0371 | C108: Tubo 19mm 3/4" | D108: =IFERROR(_xlfn.XLOOKUP($D$11,ELEC!$F$5:$AV$5,ELEC!F117:AV117,0,0,1),0) -> 10 | E108: =ROUNDUP(D108,0) -> 10
B109: M05-0372 | C109: Union 38mm 1 1/2" | D109: =IFERROR(_xlfn.XLOOKUP($D$11,ELEC!$F$5:$AV$5,ELEC!F118:AV118,0,0,1),0) -> 0 | E109: =ROUNDUP(D109,0) -> 0
B110: M05-0373 | C110: Union 25mm 1" | D110: =IFERROR(_xlfn.XLOOKUP($D$11,ELEC!$F$5:$AV$5,ELEC!F119:AV119,0,0,1),0) -> 0 | E110: =ROUNDUP(D110,0) -> 0
B111: M05-0374 | C111: Union 13mm 1/2" | D111: =IFERROR(_xlfn.XLOOKUP($D$11,ELEC!$F$5:$AV$5,ELEC!F120:AV120,0,0,1),0) -> 10 | E111: =ROUNDUP(D111,0) -> 10
B112: M05-0375 | C112: Union 19mm 3/4" | D112: =IFERROR(_xlfn.XLOOKUP($D$11,ELEC!$F$5:$AV$5,ELEC!F121:AV121,0,0,1),0) -> 4 | E112: =ROUNDUP(D112,0) -> 4
... B123: M05-0477 | C123: Conector 3/4" UL | D123: =IFERROR(_xlfn.XLOOKUP($D$11,ELEC!$F$5:$AV$5,ELEC!F132:AV132,0,0,1),0) -> 2 | E123: =ROUNDUP(D123,0) -> 2
C126: 3.1.5 | D126: ELECTRICO ILUMINACION
C129: ELECTRICO ILUMINACION | D129: Cantidad | E129: Unidad
B130: M05-0361 | C130: Curva 1/2" | D130: =IFERROR(_xlfn.XLOOKUP($D$11,ELEC!$F$5:$AV$5,ELEC!F136:AV136,0,0,1),0) -> 20 | E130: =ROUNDUP(D130,0) -> 20
B131: M05-0370 | C131: Tubo 1/2" | D131: =IFERROR(_xlfn.XLOOKUP($D$11,ELEC!$F$5:$AV$5,ELEC!F137:AV137,0,0,1),0) -> 9 | E131: =ROUNDUP(D131,0) -> 9
B132: M05-0374 | C132: Union 1/2" | D132: =IFERROR(_xlfn.XLOOKUP($D$11,ELEC!$F$5:$AV$5,ELEC!F138:AV138,0,0,1),0) -> 8 | E132: =ROUNDUP(D132,0) -> 8
B133: M05-0476 | C133: Conector 1/2" | D133: =IFERROR(_xlfn.XLOOKUP($D$11,ELEC!$F$5:$AV$5,ELEC!F139:AV139,0,0,1),0) -> 30 | E133: =ROUNDUP(D133,0) -> 30
B134: M05-0264 | C134: TGP 3x12 | D134: =IFERROR(_xlfn.XLOOKUP($D$11,ELEC!$F$5:$AV$5,ELEC!F140:AV140,0,0,1),0) -> 25 | E134: =ROUNDUP(D134,0) -> 25
B135: M05-0389 | C135: Caja octagonal | D135: =IFERROR(_xlfn.XLOOKUP($D$11,ELEC!$F$5:$AV$5,ELEC!F141:AV141,0,0,1),0) -> 4 | E135: =ROUNDUP(D135,0) -> 4
B136: M05-0407 | C136: Gaza metaliza 3/4" | D136: =IFERROR(_xlfn.XLOOKUP($D$11,ELEC!$F$5:$AV$5,ELEC!F142:AV142,0,0,1),0) -> 25 | E136: =ROUNDUP(D136,0) -> 25
B137: M05-0223 | C137: Caja 4x4 sencilla | D137: =IFERROR(_xlfn.XLOOKUP($D$11,ELEC!$F$5:$AV$5,ELEC!F143:AV143,0,0,1),0) -> 0 | E137: =ROUNDUP(D137,0) -> 0
B138: M05-0015 | C138: Tapa ciega octagonal | D138: =IFERROR(_xlfn.XLOOKUP($D$11,ELEC!$F$5:$AV$5,ELEC!F144:AV144,0,0,1),0) -> 9 | E138: =ROUNDUP(D138,0) -> 9
B139: M05-0410 | C139: Tapa cuadrada ciega MT | D139: =IFERROR(_xlfn.XLOOKUP($D$11,ELEC!$F$5:$AV$5,ELEC!F145:AV145,0,0,1),0) -> 3 | E139: =ROUNDUP(D139,0) -> 3
B140: M05-0007 | C140: scotch plug amarillo | D140: =IFERROR(_xlfn.XLOOKUP($D$11,ELEC!$F$5:$AV$5,ELEC!F146:AV146,0,0,1),0) -> 50 | E140: =ROUNDUP(D140,0) -> 50
B141: M05-0008 | C141: conector empalme rojo | D141: =IFERROR(_xlfn.XLOOKUP($D$11,ELEC!$F$5:$AV$5,ELEC!F147:AV147,0,0,1),0) -> 25 | E141: =ROUNDUP(D141,0) -> 25
... B159: M05-0258 | C159: Cable thhn #12 rojo | D159: =IFERROR(_xlfn.XLOOKUP($D$11,ELEC!$F$5:$AV$5,ELEC!F165:AV165,0,0,1),0) -> 35 | E159: =ROUNDUP(D159,0) -> 35
C161: SUBCONTRATO | D161: =+E327 -> 95000
C164: 3.1.6 | D164: BASE MEDIDOR
C167: BASE MEDIDOR | D167: Cantidad | E167: Unidad
B168: M05-0362 | C168: Curva conduit 1-1/2 ul | D168: =IFERROR(_xlfn.XLOOKUP($D$11,ELEC!$F$5:$AV$5,ELEC!F282:AV282,0,0,1),0) -> 1 | E168: =ROUNDUP(D168,0) -> 1
B169: M05-0366 | C169: Curva conduit 1 ul | D169: =IFERROR(_xlfn.XLOOKUP($D$11,ELEC!$F$5:$AV$5,ELEC!F283:AV283,0,0,1),0) -> 1 | E169: =ROUNDUP(D169,0) -> 1
B170: M05-0361 | C170: Curva conduit 1/2 ul | D170: =IFERROR(_xlfn.XLOOKUP($D$11,ELEC!$F$5:$AV$5,ELEC!F284:AV284,0,0,1),0) -> 2 | E170: =ROUNDUP(D170,0) -> 2
B171: M05-0367 | C171: curva conduit 3/4 ul | D171: =IFERROR(_xlfn.XLOOKUP($D$11,ELEC!$F$5:$AV$5,ELEC!F285:AV285,0,0,1),0) -> 0 | E171: =ROUNDUP(D171,0) -> 0
...

Sheet BASE DATOS PRECIOS 
B1: CODIGO | C1: COD VARIANTE | D1: VARIANTE | E1: DESCRIPCION | F1: UNIDAD | G1: PRECIO | H1: PRECIO CON IVA | I1: ACTUALIZACION DE COSTOS MAY-2025 | J1: TIPO DE CAMBIO | K1: 530 | L1: ✓✓
A2: No se encuentra en la lista de productos | B2: ACA03-0001 | E2: FLETE AGREGADOS | F2: UND | G2: 5500 | H2: =+G2*1.13 -> 6215 | I2: ✓✓ | J2: IVA | K2: 1.13 | L2: GENERAL
A3: No se encuentra en la lista de productos | B3: ACA03-0001 | E3: FLETE AGREGADOS | F3: UND | G3: 5500 | H3: =+G3*1.13 -> 6215 | I3: ✓✓ | J3: IVA | K3: 1.1 | L3: MADERA
A4: No se encuentra en la lista de productos | B4: ACA15-0001 | E4: FLETE EQUIPO PESADO | F4: UND | G4: 58744.4 | H4: =+G4*1.13 -> 66381.172 | I4: ✓✓ | J4: IVA | K4: 1 | L4: SIN IVA
B5: BAJANTE | E5: BAJANTE DE HOJALATERIA 6M | F5: UND | G5: 12212.39 | H5: =+G5*1.13 -> 13800.001 | I5: ✓✓
B6: BOTAGUA | E6: BOTAGUA 10 CM X 10 CM X 1,83 M | F6: UND | G6: error | H6: 6844 | I6: ✓✓
B7: CANOA | E7: CANOA HG 10 CM | F7: YARDA | G7: error | H7: 11021.16 | I7: ✓✓
A8: No se encuentra en la lista de productos | B8: EQU15-0024 | E8: SERVICIO TRANSPORTE | F8: UND | G8: 64000 | H8: =+G8*1.13 -> 72320
A9: No se encuentra en la lista de productos | B9: EQU15-0024 | E9: SERVICIO TRANSPORTE | F9: UND | G9: 64000 | H9: =+G9*1.13 -> 72320
B10: EQU15-0024 | E10: SERVICIO TRANSPORTE | F10: UND | G10: 64000 | H10: =+G10*1.13 -> 72320 | I10: ✓✓
A11: No se encuentra en la lista de productos | B11: GANCHO CANOA | E11: GANCHO CANOA | F11: UND | G11: error | H11: 500 | I11: ✓✓
A12: No se encuentra en la lista de productos | B12: M01-0001 | E12: ALAMBRE NEGRO #16 (1.68MM) | F12: KG | G12: 519.34 | H12: =+G12*1.13 -> 586.8542 | I12: ✓✓
A13: No se encuentra en la lista de productos | B13: M01-0006 | E13: ANGULAR HN 1 1/4 X 1.8 | F13: UND | G13: 7422.828 | H13: =+G13*1.13 -> 8387.7956 | I13: ✓✓
B14: M01-0007 | E14: PLATINA HN 3X1/4 | F14: UND | G14: 13704.21 | H14: =+G14*1.13 -> 15485.757 | I14: ✓✓
A15: EQU20-0005 GAS JUMBO PARA SOPLETE TRUPPER | B15: M01-0007 | E15: PLATINA HN 3X1/4 | F15: UND | G15: 13704.21 | H15: =+G15*1.13 -> 15485.757
B16: M01-0008 | E16: PLATINA HN 3/4X1/8 | F16: UND | G16: 1546.78 | H16: =+G16*1.13 -> 1747.8614 | I16: ✓✓
B17: M01-0009 | E17: PLATINA HN 4X1/4 | F17: UND | G17: 14658.52 | H17: =+G17*1.13 -> 16564.128 | I17: ✓✓
B18: M01-0010 | E18: ANGULAR HN 2"X1/4 | F18: UND | G18: 14290.66 | H18: =+G18*1.13 -> 16148.446 | I18: ✓✓
B19: M01-0011 | E19: PLATINA ALUMINIO 2X3/8 | F19: UND | G19: 56702.74 | H19: =+G19*1.13 -> 64074.096 | I19: ✓✓
A20: No se encuentra en la lista de productos | B20: M01-0013 | E20: PLATINA HN 1/8"X 1 1/2 | F20: UND | G20: 3362.83 | H20: =+G20*1.13 -> 3799.9979
B21: M01-0018 | E21: ANGULAR HN 1"X1/8 | F21: UND | G21: 3611.57 | H21: =+G21*1.13 -> 4081.0741 | I21: ✓✓
B22: M01-0029 | E22: ANGULAR ALUMINIO 3/4"X1/8" | F22: UND | G22: 22600 | H22: =+G22*1.13 -> 25538 | I22: ✓✓
B23: M01-0037 | E23: LAMINA DE JORDOMEX #1 ACS 4X8X3MM | F23: UND | G23: 34633.4 | H23: =+G23*1.13 -> 39135.742 | I23: ✓✓
B24: M01-0038 | E24: LAMINA DE JORDOMEX #3 (1/2) ROMBO 13X32 3MM ESPESOR | F24: UND | G24: 13375 | H24: =+G24*1.13 -> 15113.75 | I24: ✓✓
B25: M01-0042 | E25: LAMINA 1.22X2.44 HN 1/8 | F25: UND | G25: 32103.67 | H25: =+G25*1.13 -> 36277.147 | I25: ✓✓
B26: M01-0048 | E26: LAMINA DIAMANTADA 1/8 HN | F26: UND | G26: 27299.7 | H26: =+G26*1.13 -> 30848.661 | I26: ✓✓
A27: MAT0044 ADAPTADOR MACHO CPVC 1/2" | B27: M01-0049 | E27: LAMINA DIAMANTADA 1/4 HN | F27: UND | G27: 98765.8 | H27: =+G27*1.13 -> 111605.35
A28: MAT0049 ADAPTADOR MACHO PVC 1/2" | B28: M01-0055 | E28: SOLDADURA 3/32 (6013) | F28: KG | G28: 3185.87 | H28: =+G28*1.13 -> 3600.0331
B29: M01-0063 | E29: SOLDADURA ALAMBRE MIG ECA 08 EN 5 KG | F29: UND | G29: 14296.22 | H29: =+G29*1.13 -> 16154.729 | I29: ✓✓
B30: M01-0066 | E30: TUBO 1X1X1.8MM H.N. | F30: UND | G30: 4879.2 | H30: =+G30*1.13 -> 5513.496 | I30: ✓✓
B31: M01-0067 | E31: TUBO 1X2X1.5MM HN | F31: UND | G31: 12600 | H31: =+G31*1.13 -> 14238 | I31: ✓✓
B32: M01-0069 | E32: TUBO 2X2X1.8MM H.N | F32: UND | G32: 10827 | H32: =+G32*1.13 -> 12234.51 | I32: ✓✓
B33: M01-0070 | E33: TUBO 2X4X1.8MM HN | F33: UND | G33: 18873 | H33: =+G33*1.13 -> 21326.49 | I33: ✓✓
B34: M01-0071 | E34: TUBO 2X6X1.8MM H.N. | F34: UND | G34: 16898.72 | H34: =+G34*1.13 -> 19095.554 | I34: ✓✓
B35: M01-0073 | E35: TUBO 3X3X1.8MM H.N. | F35: UND | G35: 12188 | H35: =+G35*1.13 -> 13772.44 | I35: ✓✓
B36: M01-0074 | E36: TUBO 4X6X1.80MM HN | F36: UND | G36: 28236 | H36: =+G36*1.13 -> 31906.68 | I36: ✓✓
B37: M01-0075 | E37: TUBO 1-1/2X1-1/2X1.8MM H.N. | F37: UND | G37: 6646.41 | H37: =+G37*1.13 -> 7510.4433 | I37: ✓✓
B38: M01-0079 | E38: TUBO 1X1X1.5MM H.N | F38: UND | G38: 3946.9 | H38: =+G38*1.13 -> 4459.997 | I38: ✓✓
B39: M01-0096 | E39: TUBO 3X3X1.8MM H.G. | F39: UND | G39: 16219 | H39: =+G39*1.13 -> 18327.47 | I39: ✓✓
B40: M01-0097 | E40: TUBO 2X2X1.8MM H.G | F40: UND | G40: 12108 | H40: =+G40*1.13 -> 13682.04 | I40: ✓✓
... B42: M01-0099 | E42: TUBO 2X6X1.8MM H.G | F42: UND | G42: 37192.76 | H42: =+G42*1.13 -> 42027.819 | I42: ✓✓
A43: MAT01-0025 PILA FIBRA DE VIDRIO 50X63X22 | B43: M01-0104 | E43: TUBO 1 1/2"X1 1/2"X1.5MM HN | F43: UND | G43: 7064.18 | H43: =+G43*1.13 -> 7982.5234 | I43: ✓✓
B44: M01-0105 | E44: PERLING 2X3X2.2MM HG | F44: UND | G44: 9734.51 | H44: =+G44*1.13 -> 10999.996 | I44: ✓✓
B45: M01-0111 | E45: TUBO 1X1X1.8MM HG | F45: UND | G45: 4073.26 | H45: =+G45*1.13 -> 4602.7838 | I45: ✓✓
B46: M01-0121 | E46: TUBO 4X4X1.8MM HG | F46: UND | G46: 19910 | H46: =+G46*1.13 -> 22498.3 | I46: ✓✓
B47: M01-0142 | E47: PERLING 3X2X15MM EN 1.5MM H.G | F47: UND | G47: 6004.9 | H47: =+G47*1.13 -> 6785.537 | I47: ✓✓
B48: M01-0145 | E48: MALLA ELECTROSOLDADA #2 (5.3 MM) | F48: UND | G48: 16603.98 | H48: =+G48*1.13 -> 18762.497 | I48: ✓✓
A49: MAT01-0053 CACHERA FREGADERO MONOCOMANDO KORAL | B49: M01-0146 | E49: VARILLA DEFORME #2 | F49: UND | G49: 504.25 | H49: =+G49*1.13 -> 569.8025
B50: M01-0147 | C50: 01 | E50: VARILLA DEFORME #3 | F50: UND | G50: 1190 | H50: =+G50*1.13 -> 1344.7 | I50: ✓✓
B51: M01-0147 | C51: 02 | E51: VARILLA DEFORME #3 | F51: UND | G51: 1308.23 | H51: =+G51*1.13 -> 1478.2999 | I51: ✓✓
B52: M01-0148 | C52: 01 | E52: VARILLA DEFORME #4 | F52: UND | G52: 2120 | H52: =+G52*1.13 -> 2395.6 | I52: ✓✓
B53: M01-0148 | C53: 02 | E53: VARILLA DEFORME #4 | F53: UND | G53: 2311.83 | H53: =+G53*1.13 -> 2612.3679 | I53: ✓✓
B54: M01-0149 | E54: VARILLA DEFORME #5 | F54: UND | G54: 3436.85 | H54: =+G54*1.13 -> 3883.6405 | I54: ✓✓
B55: M01-0153 | E55: VARILLA LISA #5 | F55: UND | G55: 5022 | H55: =+G55*1.13 -> 5674.86 | I55: ✓✓
B56: M02-0002 | E56: REJILLA P/BAÑO 2" CUADRADA // REJ-10' | F56: UND | G56: 1558.66 | H56: =+G56*1.13 -> 1761.2858 | I56: ✓✓
B57: M02-0008 | E57: TAPA P/INODORO | F57: UND | G57: 21367.52 | H57: =+G57*1.13 -> 24145.298 | I57: ✓✓
B58: M02-0011 | E58: DESAGUE LAVAMANOS PUSH BOTON DE 1-1/4 | F58: UND | G58: 9500 | H58: =+G58*1.13 -> 10735 | I58: ✓✓
B59: M02-0024 | E59: DESAGUE METAL PARA LAVATORIO 11/4 | F59: UND | G59: 1689.26 | H59: =+G59*1.13 -> 1908.8638 | I59: ✓✓
B60: M02-0025 | E60: EMPAQUE CERA | F60: UND | G60: 913.3 | H60: =+G60*1.13 -> 1032.029 | I60: ✓✓
B61: M02-0026 | E61: MANGUERA ABASTO P/INODORO (7/8 A 1/2) | F61: UND | G61: 1364.28 | H61: =+G61*1.13 -> 1541.6364 | I61: ✓✓
B62: M02-0028 | E62: INODORO ONE PIECE SMART ALONGADO (AMERICAN STANDARD) | F62: UND | G62: 46908.77 | H62: =+G62*1.13 -> 53006.91 | I62: ✓✓
B63: M02-0032 | E63: GRIFERIA MONOCONTROL PALMA MEDIA (AMERICAN STANDARD) | F63: UND | G63: 36217.83 | H63: =+G63*1.13 -> 40926.148 | I63: ✓✓
B64: M02-0035 | E64: GRIFERIA LAV.CROMA METAL 4" PALANCA CROMO P/LAV MILANO | F64: UND | G64: 21723 | H64: =+G64*1.13 -> 24546.99 | I64: ✓✓
B65: M02-0036 | E65: GRIFERIA DUCHA BREZZA MONO S/LAVAPIES EZ4015551 SSB | F65: UND | G65: 29253 | H65: =+G65*1.13 -> 33055.89 | I65: ✓✓
... B74: M03-0006 | E74: PATA REDONDA 90CM | F74: UND | G74: 6602.5 | H74: =+G74*1.13 -> 7460.825 | I74: ✓✓
B75: M03-0010 | E75: RODAPIE ALUMI INOX 150-300-ROD2 AL | F75: M | G75: =7498.09/3.6 -> 2082.8028 | H75: =+G75*1.13 -> 2353.5671 | I75: ✓✓
B76: M03-0014 | E76: SOPORTE LATERAL NIQUEL 3H+3TR | F76: UND | G76: 202.56 | H76: =+G76*1.13 -> 228.8928 | I76: ✓✓
A77: MAT02-0043 PLATINA EN 4"X 1/4X6M | B77: M03-0015 | E77: SOPORTE P/ESTANTE TRANS 5MM SP-1-PL-HU | F77: UND | G77: 18.89 | H77: =+G77*1.13 -> 21.3457
B78: M03-0016 | E78: TAPA TORNILLO (100) | F78: UND | G78: 3100 | H78: =+G78*1.13 -> 3503 | I78: ✓✓
B79: M03-0017 | E79: TAPETA 22X0.45MM | F79: M | G79: 80.5736 | H79: =+G79*1.13 -> 91.048168 | I79: ✓✓
B80: M03-0019 | E80: TUBO OVAL P/CLOSET 3 MT | F80: UND | G80: 3184.53 | H80: =+G80*1.13 -> 3598.5189 | I80: ✓✓
A81: MAT02-0063 TUBO 2X3X6MM HN | B81: M03-0021 | E81: DESAGUE-REJILLA P/FREGADERO PLATZ 8523 | F81: UND | G81: 2846.02 | H81: =+G81*1.13 -> 3216.0026 | I81: ✓✓
B82: M03-0022 | E82: BISAGRA RECTA SLOW MOTION CLIP ON | F82: UND | G82: 431.31 | H82: =+G82*1.13 -> 487.3803 | I82: ✓✓
B83: M03-0023 | E83: FREGADERO 1 TANQUE 58X45X20 | F83: UND | G83: 35480.19 | H83: =+G83*1.13 -> 40092.615 | I83: ✓✓
B84: M03-0024 | E84: FREGADERO 2 TANQUES 84X48X20 | F84: UND | G84: 67958 | H84: =+G84*1.13 -> 76792.54 | I84: ✓✓
B85: M03-0025 | E85: GRIFERIA FREGADERO SIERPE (AMERICAN STANDARD) | F85: UND | G85: 27283.85 | H85: =+G85*1.13 -> 30830.75 | I85: ✓✓
B86: M03-0030 | E86: RIEL SUPERI ACL-RSU09 3MTRS | F86: UND | G86: 9536.83 | H86: =+G86*1.13 -> 10776.618 | I86: ✓✓
B87: M03-0031 | E87: RIEL TELESC SLOW MOTION LA 350M RS-C45GA-350 (14") | F87: UND | G87: 2451.92 | H87: =+G87*1.13 -> 2770.6696 | I87: ✓✓
B88: M03-0033 | E88: RIEL TELESCOPICO SLOW MOTION LA 450M RS-A45DT (18") | F88: UND | G88: 2930.33 | H88: =+G88*1.13 -> 3311.2729 | I88: ✓✓
B89: M03-0036 | E89: TIRADERA CILINDRICA CC:12.8CM | F89: UND | G89: 763.51 | H89: =+G89*1.13 -> 862.7663 | I89: ✓✓
A90: MAT02-0140 PLATINA H.N. DE 4 PULGADAS EN 6M | B90: M04-0001 | E90: AISLANTE SONIDO R11 LANA MINERAL VIDRIO 1,22X15,24 | F90: ROLLO | G90: 16550 | H90: =+G90*1.13 -> 18701.5
B91: M04-0003 | E91: LAMINA ESTEREOFON 2" 1.22X2.44 | F91: UND | G91: 4875.86 | H91: =+G91*1.13 -> 5509.7218 | I91: ✓✓
B92: M04-0010 | E92: TABLATEK TABLILLA JS 11MM 1229X2438MM A11 D76 | F92: UND | G92: 22892 | H92: =+G92*1.13 -> 25867.96 | I92: ✓✓
B93: M04-0014 | E93: CINTA JUNTAS PAPEL 2 X 250 | F93: UND | G93: 1046.07 | H93: =+G93*1.13 -> 1182.0591 | I93: ✓✓
B94: M04-0015 | E94: CINTA MALLA ADHESIVA P/GYP (45M) | F94: ROLLO | G94: 1307.75 | H94: =+G94*1.13 -> 1477.7575 | I94: ✓✓
B95: M04-0016 | E95: GYPSUM DENSGLASS 12MM | F95: UND | G95: 15886.73 | H95: =+G95*1.13 -> 17952.005 | I95: ✓✓
B96: M04-0017 | E96: GYPSUM MR VERDE 12MM | F96: UND | G96: 7419.19 | H96: =+G96*1.13 -> 8383.6847 | I96: ✓✓
B97: M04-0018 | E97: GYPSUM REGULAR 12MM | F97: UND | G97: 5649.56 | H97: =+G97*1.13 -> 6384.0028 | I97: ✓✓
B98: M04-0030 | E98: PASTA P/GYPSUM | F98: CUBETA | G98: 15292.04 | H98: =+G98*1.13 -> 17280.005 | I98: ✓✓
B99: M04-0031 | E99: SACO PASTA RAPIDA 45 | F99: SACO | G99: 6714 | H99: =+G99*1.13 -> 7586.82 | I99: ✓✓
B100: M04-0033 | E100: ANGULAR CHANNEL 1X3" 0.36MM 3.05M | F100: UND | G100: 470 | H100: =+G100*1.13 -> 531.1 | I100: ✓✓
B101: M04-0034 | E101: CANAL U 1 1/2X16X4.88 CAL #20 | F101: UND | G101: 1740 | H101: =+G101*1.13 -> 1966.2 | I101: ✓✓
B102: M04-0035 | E102: FURRING CALIBRE 0.36X 3.66 CM | F102: UND | G102: 1090 | H102: =+G102*1.13 -> 1231.7 | I102: ✓✓
... B121: M05-0014 | E121: GAZA P/VARILLA COPPERWELD USA UL | F121: UND | G121: 825.82 | H121: =+G121*1.13 -> 933.1766 | I121: ✓✓
A122: MAT04-0047 MAXIEMPASTE LISO 25KG | B122: M05-0015 | E122: TAPA CIEGA PARA CAJA OCTAGONAL | F122: UND | G122: 138.07 | H122: =+G122*1.13 -> 156.0191
B123: M05-0016 | E123: TAPA CIEGA BLANCA 2X4 | F123: UND | G123: 404.42 | H123: =+G123*1.13 -> 456.9946 | I123: ✓✓
B124: M05-0017 | E124: TAPE ELECTRICO BLANCO EATON | F124: UND | G124: 714.58 | H124: =+G124*1.13 -> 807.4754 | I124: ✓✓
B125: M05-0018 | E125: TAPE ELECTRICO VERDE EATON | F125: UND | G125: 705.54 | H125: =+G125*1.13 -> 797.2602 | I125: ✓✓
B126: M05-0019 | E126: TAPE NEGRO SUPER 33+3M 19MM | F126: UND | G126: 2239.65 | H126: =+G126*1.13 -> 2530.8045 | I126: ✓✓
B127: M05-0021 | E127: VARILLA COOPERWELL 5/8 3M | F127: UND | G127: 9372 | H127: =+G127*1.13 -> 10590.36 | I127: ✓✓
...

Sheet HORAS MANO DE OBRA
A1: Obra | B1: SubTareaObra | C1: Cantidad | D1: Horas | E1: IDObra | F1: IDSubTareaObra | G1: IDEncargado
A2: VN-I.13 | B2: Sello Losa | C2: =+'1_OG y 2_ACA'!D253 -> 48.12 | D2: =+Detallado!F35+Detallado!F36 -> 9 | E2: 336 | F2: 1 | G2: 839 | H2: ✓✓
A3: =+$A$2 -> VN-I.13 | B3: Losa Flotante (Formaleta trazo) | C3: =+'1_OG y 2_ACA'!D275 -> 48.12 | D3: =+Detallado!F19+Detallado!F20+Detallado!F26+Detallado!F27+Detallado!F50+Detallado!F51 -> 131 | E3: =+$E$2 -> 336 | F3: 2 | G3: 839 | H3: ✓✓
A4: =+$A$2 -> VN-I.13 | B4: Acero Losa | C4: =+'1_OG y 2_ACA'!G311 -> 1289.111 | D4: =+Detallado!F48+Detallado!F49 -> 276 | E4: =+$E$2 -> 336 | F4: 3 | G4: 839 | H4: ✓✓
A5: =+$A$2 -> VN-I.13 | B5: Colado de Losa | C5: =+'1_OG y 2_ACA'!D277 -> 10.1052 | D5: =+Detallado!F52+Detallado!F53 -> 40 | E5: =+$E$2 -> 336 | F5: 4 | G5: 839 | H5: ✓✓
A6: =+$A$2 -> VN-I.13 | B6: Muros y Entrepiso (Formaleta, Concreto) | C6: =+'1_OG y 2_ACA'!D491+'1_OG y 2_ACA'!D677 -> 37.925725 | D6: =+Detallado!F66+Detallado!F67+Detallado!F78+Detallado!F79+Detallado!F80+Detallado!F81+Detallado!F99+Detallado!F100+Detallado!F109+Detallado!F110+Detallado!F111+Detallado!F112 -> 638 | E6: =+$E$2 -> 336 | F6: 5 | G6: 839 | H6: ✓✓
A7: =+$A$2 -> VN-I.13 | B7: Acero Muros y Entrepiso | C7: =+'1_OG y 2_ACA'!H420+'1_OG y 2_ACA'!G443+'1_OG y 2_ACA'!H609+'1_OG y 2_ACA'!G628 -> 2386.9731 | D7: =+Detallado!F64+Detallado!F65+Detallado!F97+Detallado!F98 -> 482 | E7: =+$E$2 -> 336 | F7: 6 | G7: 839 | H7: ✓✓
A8: =+$A$2 -> VN-I.13 | B8: Mampostería | C8: 0 | D8: 0 | E8: =+$E$2 -> 336 | F8: 7 | G8: 839 | H8: N/A
A9: =+$A$2 -> VN-I.13 | B9: Desencofre | C9: =+'1_OG y 2_ACA'!D521+'1_OG y 2_ACA'!D706 -> 595.44 | D9: =+Detallado!F82+Detallado!F113 -> 92.5 | E9: =+$E$2 -> 336 | F9: 8 | G9: 839 | H9: ✓✓
A10: =+$A$2 -> VN-I.13 | B10: Resane | C10: =+C9 -> 595.44 | D10: =+Detallado!F83+Detallado!F114 -> 92.5 | E10: =+$E$2 -> 336 | F10: 9 | G10: 839 | H10: ✓✓
A11: =+$A$2 -> VN-I.13 | B11: Estructura Techo Casa | C11: =+'1_OG y 2_ACA'!E781 -> 684.19724 | D11: =+Detallado!F140+Detallado!F141 -> 349 | E11: =+$E$2 -> 336 | F11: 10 | G11: 839 | H11: ✓✓
A12: =+$A$2 -> VN-I.13 | B12: Estructura Interna y Monitor | C12: 0 | D12: 0 | E12: =+$E$2 -> 336 | F12: 11 | G12: 839 | H12: N/A
A13: =+$A$2 -> VN-I.13 | B13: Cubierta Techo Casa | C13: =+'1_OG y 2_ACA'!D848 -> 44.8 | D13: =+Detallado!F173+Detallado!F174 -> 156 | E13: =+$E$2 -> 336 | F13: 12 | G13: 839 | H13: ✓✓
A14: =+$A$2 -> VN-I.13 | B14: Estructura Techo Cochera y Terraza | C14: =+'1_OG y 2_ACA'!E834 -> 266.09616 | D14: =+Detallado!F164+Detallado!F165 -> 136 | E14: =+$E$2 -> 336 | F14: 13 | G14: 839 | H14: ✓✓
A15: =+$A$2 -> VN-I.13 | B15: Cubierta Techo Cochera y Terraza | C15: =+'1_OG y 2_ACA'!D888 -> 0 | D15: =+Detallado!F185+Detallado!F186 -> 0 | E15: =+$E$2 -> 336 | F15: 14 | G15: 839 | H15: ✓✓
A16: =+$A$2 -> VN-I.13 | B16: Barandas, Pasamanos y Portones | C16: =+'1_OG y 2_ACA'!F971 -> 110.96553 | D16: =+Detallado!F227+Detallado!F228 -> 85 | E16: =+$E$2 -> 336 | F16: 15 | G16: 839 | H16: N/A
A17: =+$A$2 -> VN-I.13 | B17: Gradas Metálicas | C17: =+'1_OG y 2_ACA'!F924 -> 0 | D17: =+Detallado!F209+Detallado!F210 -> 0 | E17: =+$E$2 -> 336 | F17: 16 | G17: 839 | H17: N/A
A18: =+$A$2 -> VN-I.13 | B18: Tapias Prefabricadas | C18: =+'1_OG y 2_ACA'!D1239 -> 8.5 | D18: =+Detallado!F308+Detallado!F309+Detallado!F310+Detallado!F311 -> 56 | E18: =+$E$2 -> 336 | F18: 19 | G18: 839 | H18: ✓✓
A19: =+$A$2 -> VN-I.13 | B19: Losas Cochera y Terrazas | C19: =+'1_OG y 2_ACA'!D1190 -> 39.3 | D19: =+Detallado!F291+Detallado!F292+Detallado!F293+Detallado!F294+Detallado!F295+Detallado!F296+Detallado!F297+Detallado!F298 -> 235 | E19: =+$E$2 -> 336 | F19: 20 | G19: 839 | H19: ✓✓
A20: =+$A$2 -> VN-I.13 | B20: Gradas Concreto | C20: =+'1_OG y 2_ACA'!D1061 -> 2.95068 | D20: =+Detallado!F261+Detallado!F262+Detallado!F263+Detallado!F264+Detallado!F265+Detallado!F266+Detallado!F267+Detallado!F268 -> 210 | E20: =+$E$2 -> 336 | F20: 18 | G20: 839 | H20: N/A
A21: =+$A$2 -> VN-I.13 | B21: Aceras | C21: =+'1_OG y 2_ACA'!D1262 -> 12.24 | D21: =+Detallado!F318+Detallado!F319 -> 15 | E21: =+$E$2 -> 336 | F21: 21 | G21: 839 | H21: ✓✓
A22: =+$A$2 -> VN-I.13 | B22: Columnas | C22: =+'1_OG y 2_ACA'!D1174 -> 0.7259 | D22: =+Detallado!F274+Detallado!F275+Detallado!F276+Detallado!F277+Detallado!F278+Detallado!F279+Detallado!F280+Detallado!F281 -> 59 | E22: =+$E$2 -> 336 | F22: 22 | G22: 839 | H22: ✓✓
A23: =+$A$2 -> VN-I.13 | B23: Colado Gradas Metálicas | C23: =+'1_OG y 2_ACA'!D934 -> 0 | D23: =+Detallado!F211+Detallado!F212 -> 0 | E23: =+$E$2 -> 336 | F23: 23 | G23: 839 | H23: N/A
A24: =+$A$2 -> VN-I.13 | B24: Geocelda | C24: =+'1_OG y 2_ACA'!D1263 -> 7.2 | D24: =+Detallado!F320+Detallado!F321 -> 47 | E24: =+$E$2 -> 336 | F24: 24 | G24: 839 | H24: ✓✓
A25: =+$A$2 -> VN-I.13 | B25: Liviano Interiores | C25: =+'1_OG y 2_ACA'!D1366 -> 41.2 | D25: =+Detallado!F389+Detallado!F390+Detallado!F391+Detallado!F392 -> 115 | E25: =+$E$2 -> 336 | F25: 25 | G25: 839 | H25: ✓✓
A26: =+$A$2 -> VN-I.13 | B26: Liviano Exteriores | C26: =+'1_OG y 2_ACA'!D1299+'1_OG y 2_ACA'!D1341 -> 42.85 | D26: =+Detallado!F357+Detallado!F358 -> 73 | E26: =+$E$2 -> 336 | F26: 26 | G26: 839 | H26: ✓✓
A27: =+$A$2 -> VN-I.13 | B27: Tablilla PVC | C27: =+'1_OG y 2_ACA'!D1318 -> 9.7 | D27: =+Detallado!F359+Detallado!F360 -> 21 | E27: =+$E$2 -> 336 | F27: 27 | G27: 839 | H27: ✓✓
A28: =+$A$2 -> VN-I.13 | B28: Hojalatería Botaguas | C28: =+'1_OG y 2_ACA'!D1001 -> 42.8 | D28: =+Detallado!F242+Detallado!F244 -> 107 | E28: =+$E$2 -> 336 | F28: 28 | G28: 840 | H28: ✓✓
A29: =+$A$2 -> VN-I.13 | B29: Hojalatería Canoas | C29: =+'1_OG y 2_ACA'!D1006 -> 14.1 | D29: =+Detallado!F243+Detallado!F245 -> 107 | E29: =+$E$2 -> 336 | F29: 29 | G29: 840 | H29: ✓✓
A30: =+$A$2 -> VN-I.13 | B30: Enchapes Casa | C30: =+'1_OG y 2_ACA'!D1530+'1_OG y 2_ACA'!D1531 -> 119 | D30: =+Detallado!F422+Detallado!F423+Detallado!F426+Detallado!F427 -> 236 | E30: =+$E$2 -> 336 | F30: 30 | G30: 840 | H30: ✓✓
A31: =+$A$2 -> VN-I.13 | B31: Tablatek | C31: =+'1_OG y 2_ACA'!D1550 -> 2.6 | D31: =+Detallado!F424+Detallado!F425 -> 6 | E31: =+$E$2 -> 336 | F31: 31 | G31: 840 | H31: ✓✓
A32: =+$A$2 -> VN-I.13 | B32: Muro Seco | C32: =+'1_OG y 2_ACA'!D1453 -> 474.2825 | D32: =+Detallado!F397+Detallado!F398 -> 392 | E32: =+$E$2 -> 336 | F32: 32 | G32: 840 | H32: ✓✓
A33: =+$A$2 -> VN-I.13 | B33: Empaste Cementicio | C33: =+'1_OG y 2_ACA'!D1465 -> 225.0125 | D33: =+Detallado!F404+Detallado!F405 -> 102 | E33: =+$E$2 -> 336 | F33: 33 | G33: 840 | H33: ✓✓
A34: =+$A$2 -> VN-I.13 | B34: Eléctrico Losa | C34: 0 | D34: 0 | E34: =+$E$2 -> 336 | F34: 34 | G34: 843 | H34: SUCONTRATO
A35: =+$A$2 -> VN-I.13 | B35: Eléctrico Muros | C35: 0 | D35: 0 | E35: =+$E$2 -> 336 | F35: 35 | G35: 843 | H35: SUCONTRATO
A36: =+$A$2 -> VN-I.13 | B36: Eléctrico Iluminación | C36: 0 | D36: 0 | E36: =+$E$2 -> 336 | F36: 36 | G36: 843 | H36: SUCONTRATO
A37: =+$A$2 -> VN-I.13 | B37: Centro de Carga y Columna | C37: 0 | D37: 0 | E37: =+$E$2 -> 336 | F37: 37 | G37: 843 | H37: SUCONTRATO
A38: =+$A$2 -> VN-I.13 | B38: Plaquearía e Iluminación | C38: 0 | D38: 0 | E38: =+$E$2 -> 336 | F38: 38 | G38: 843 | H38: SUCONTRATO
A39: =+$A$2 -> VN-I.13 | B39: Fontanería Losa | C39: =+'3.2_MEC'!D19+'3.2_MEC'!D20+'3.2_MEC'!D21 -> 61.9 | D39: =+Detallado!F839+Detallado!F840+Detallado!F841+Detallado!F842+Detallado!F856+Detallado!F857+Detallado!F858+Detallado!F859 -> 60 | E39: =+$E$2 -> 336 | F39: 39 | G39: 839 | H39: ✓✓
A40: =+$A$2 -> VN-I.13 | B40: Fontanería Muros | C40: =+'3.2_MEC'!D108+'3.2_MEC'!D109+'3.2_MEC'!D110+'3.2_MEC'!D122+'3.2_MEC'!D123+'3.2_MEC'!D124 -> 0 | D40: =+Detallado!F871+Detallado!F872+Detallado!F873+Detallado!F874+Detallado!F887+Detallado!F888+Detallado!F889+Detallado!F890+Detallado!F909+Detallado!F910+Detallado!F941+Detallado!F942+Detallado!F948+Detallado!F949 -> 65 | E40: =+$E$2 -> 336 | F40: 40 | G40: 839 | H40: ✓✓
A41: =+$A$2 -> VN-I.13 | B41: Cajas y Tuberías Mecánicas | C41: =+'3.2_MEC'!D176+'3.2_MEC'!D177 -> 33.9 | D41: =+Detallado!F928+Detallado!F929 -> 70 | E41: =+$E$2 -> 336 | F41: 41 | G41: 839 | H41: ✓✓
A42: =+$A$2 -> VN-I.13 | B42: Bajantes | C42: =+'1_OG y 2_ACA'!D1028 -> 12 | D42: =+Detallado!F251+Detallado!F252 -> 62 | E42: =+$E$2 -> 336 | F42: 42 | G42: 839 | H42: ✓✓
A43: =+$A$2 -> VN-I.13 | B43: Sello Pintura | C43: =+'1_OG y 2_ACA'!D1567 -> 307.4125 | D43: =+ROUNDUP('1_OG y 2_ACA'!F1592,0) -> 78 | E43: =+$E$2 -> 336 | F43: 43 | G43: 840 | H43: ✓✓
A44: =+$A$2 -> VN-I.13 | B44: Pintura Externa | C44: =+'1_OG y 2_ACA'!D1569+'1_OG y 2_ACA'!D1571 -> 25.5 | D44: =+ROUNDUP('1_OG y 2_ACA'!F1600,0) -> 10 | E44: =+$E$2 -> 336 | F44: 44 | G44: 840 | H44: ✓✓
A45: =+$A$2 -> VN-I.13 | B45: Grietas y Resane | C45: =+C43 -> 307.4125 | D45: =+ROUNDUP('1_OG y 2_ACA'!F1604,0)-2 -> 95 | E45: =+$E$2 -> 336 | F45: 45 | G45: 840 | H45: ✓✓
A46: =+$A$2 -> VN-I.13 | B46: Pintura Interna | C46: =+C45 -> 307.4125 | D46: =+ROUNDUP('1_OG y 2_ACA'!F1596,0) -> 116 | E46: =+$E$2 -> 336 | F46: 46 | G46: 840 | H46: ✓✓
A47: =+$A$2 -> VN-I.13 | B47: Impermeabilizante | C47: =+'1_OG y 2_ACA'!D1613 -> 55.7 | D47: =+Detallado!F460+Detallado!F461 -> 44 | E47: =+$E$2 -> 336 | F47: 47 | G47: 840 | H47: N/A
A48: =+$A$2 -> VN-I.13 | B48: Ventanería | C48: 0 | D48: 0 | E48: =+$E$2 -> 336 | F48: 48 | G48: 840 | H48: SUCONTRATO
A49: =+$A$2 -> VN-I.13 | B49: Fabricación Muebles | C49: =+'1_OG y 2_ACA'!I1703 -> 0 | D49: =+Detallado!F509+Detallado!F510 -> 100 | E49: =+$E$2 -> 336 | F49: 49 | G49: 842 | H49: ✓✓
A50: =+$A$2 -> VN-I.13 | B50: Instalación Muebles y Puertas | C50: ='1_OG y 2_ACA'!D1749 -> 10 | D50: =+Detallado!F523+Detallado!F524 -> 123 | E50: =+$E$2 -> 336 | F50: 50 | G50: 842 | H50: ✓✓
A51: =+$A$2 -> VN-I.13 | B51: Losa Sanitaria | C51: =+Detallado!F527+Detallado!F530+Detallado!F541 -> 7 | D51: =+Detallado!F544+Detallado!F545 -> 19 | E51: =+$E$2 -> 336 | F51: 51 | G51: 840 | H51: ✓✓
A52: =+$A$2 -> VN-I.13 | B52: Griferías | C52: =+Detallado!F546+Detallado!F547-2 -> 9 | D52: =+Detallado!F546+Detallado!F547-4 -> 7 | E52: =+$E$2 -> 336 | F52: 52 | G52: 840 | H52: ✓✓
A53: =+$A$2 -> VN-I.13 | B53: Pilas y llaves de chorro | C53: =+Detallado!F538 -> 1 | D53: =+Detallado!F546+Detallado!F547-7 -> 4 | E53: =+$E$2 -> 336 | F53: 53 | G53: 840 | H53: ✓✓
A54: =+$A$2 -> VN-I.13 | B54: Zacate Geocelda y Detalles | C54: =+'1_OG y 2_ACA'!D1821 -> 36.34 | D54: =+Detallado!F555+Detallado!F556 -> 58 | E54: =+$E$2 -> 336 | F54: 54 | G54: 840 | H54: ✓✓
A55: =+$A$2 -> VN-I.13 | B55: Limpieza General | C55: 1 | D55: =+Detallado!F463+Detallado!F464 -> 120 | E55: =+$E$2 -> 336 | F55: 55 | G55: 840 | H55: ✓✓
D57: =SUM(D2:D56) -> 5299 | E57: =+Detallado!F963 -> 5299 | F57: =+E57-D57 -> 0

Sheet ELEC
B3: Modelo | C3: Ikaria / Techo
C4: Insumo | D4: Codigo | F4: 1 | G4: 2 | H4: 3 | I4: 4 | J4: 5 | K4: 6 | L4: 7 | M4: 8 | N4: 9 | O4: 10 | P4: 11 | Q4: 12 | R4: 13 | S4: 14 | T4: 15 | U4: 16 | V4: 17 | W4: 18 | X4: 19 | Y4: 20 | Z4: 21 | AA4: 22 | AB4: 23 | AC4: 24 | AD4: 25 | AE4: 26 | AF4: 27 | AG4: 28 | AH4: 29 | AI4: 30 | AJ4: 31 | AK4: 32 | AL4: 33 | AM4: 34 | AN4: 35 | AO4: 36 | AP4: 37 | AQ4: 38 | AR4: 39 | AS4: 40 | AT4: 41 | AU4: 42 | AV4: 43 | AW4: 44 | AX4: 45 | AY4: 46 | AZ4: 47 | BA4: 48 | BB4: 49 | BC4: 50 | BD4: 51 | BE4: 52 | BF4: 53 | BG4: 54 | BH4: 55 | BI4: 56 | BJ4: 57 | BK4: 58 | BL4: 59 | BM4: 60 | BN4: 61 | BO4: 62 | BP4: 63 | BQ4: 64 | BR4: 65 | BS4: 66 | BT4: 67 | BU4: 68 | BV4: 69 | BW4: 70 | BX4: 71 | BY4: 72 | BZ4: 73 | CA4: 74 | CB4: 75 | CC4: 76 | CD4: 77 | CE4: 78 | CF4: 79 | CG4: 80 | CH4: 81 | CI4: 82 | CJ4: 83 | CK4: 84 | CL4: 85 | CM4: 86 | CN4: 87 | CO4: 88 | CP4: 89 | CQ4: 90 | CR4: 91 | CS4: 92 | CT4: 93 | CU4: 94 | CV4: 95 | CW4: 96 | CX4: 97 | CY4: 98 | CZ4: 99 | DA4: 100
B5: ACOMETIDA, LOSA | E5: Modelos | F5: Ikaria / Techo | G5: Ikaria Especial / Techo | H5: Ikaria / Azotea | I5: Milo / Azotea | J5: Milo / Techo | K5: Milo 1,1 / Techo | L5: Neo Tripoli / Techo | M5: Neo Tripoli / Azotea | N5: Santorini / Azotea | O5: Santorini 4D / Azotea | P5: Santorini DA / Azotea | Q5: Skyros / Techo | R5: Skyros / Azotea | S5: Tebas / Techo | T5: Tebas / Azotea | U5: Zante / Techo | V5: Zante / Azotea | W5: Zante Crece / Techo | X5: Zante Crece / Azotea | Y5: Zante Of / Techo | Z5: Zante Of / Azotea | AA5: Zante Mod. / Azotea | AB5: Stella / Techo | AC5: Stella / Azotea | AD5: Stella 1DA / Techo | AE5: Stella 1DA-1DA / Azotea | AF5: Stella L 1DA / Azotea | AG5: Stella L 1DA-1DA / Azotea | AH5: Stella L 1DA-2DA.1 / Azotea | AI5: Stella L 1DA-2DA.2 / Azotea | AJ5: Stella L 2DA / Techo | AK5: Stella L 2DA / Azotea | AL5: Stellita / Azotea | AM5: Stella L 2DA Amp / Azotea | AN5: Stella L 1DA Amp / Azotea | AO5: Zante DA / Azotea | AP5: Stella L 3DA / Azotea | AQ5: Kora / Azotea | AR5: Fiora /Azotea | AS5: Caspe / Azotea | AT5: Toledo / Techo | AU5: Avila / Techo | AV5: Gyro / Azotea | AW5: 0 | AX5: 0 | AY5: 0 | AZ5: 0 | BA5: 0 | BB5: 0 | BC5: 0 | BD5: 0 | BE5: 0 | BF5: 0 | BG5: 0 | BH5: 0 | BI5: 0 | BJ5: 0 | BK5: 0 | BL5: 0 | BM5: 0 | BN5: 0 | BO5: 0 | BP5: 0 | BQ5: 0 | BR5: 0 | BS5: 0 | BT5: 0 | BU5: 0 | BV5: 0 | BW5: 0 | BX5: 0 | BY5: 0 | BZ5: 0 | CA5: 0 | CB5: 0 | CC5: 0 | CD5: 0 | CE5: 0 | CF5: 0 | CG5: 0 | CH5: 0 | CI5: 0 | CJ5: 0 | CK5: 0 | CL5: 0 | CM5: 0 | CN5: 0 | CO5: 0 | CP5: 0 | CQ5: 0 | CR5: 0 | CS5: 0 | CT5: 0 | CU5: 0 | CV5: 0 | CW5: 0 | CX5: 0
B6: 1 | C6: Curva 38mm 1 1/2" | D6: M05-0362 | F6: 1 | G6: 1 | H6: 1 | I6: 1 | J6: 1 | K6: 1 | L6: 1 | M6: 1 | N6: 1 | O6: 1 | P6: 1 | Q6: 1 | R6: 1 | S6: 1 | T6: 1 | U6: 1 | V6: 1 | W6: 1 | X6: 1 | Y6: 1 | Z6: 1 | AA6: 1 | AB6: 1 | AC6: 1 | AD6: 1 | AE6: 1 | AF6: 1 | AG6: 1 | AH6: 1 | AI6: 1 | AJ6: 1 | AK6: 1 | AL6: 1 | AM6: 1 | AN6: 1 | AO6: 1 | AP6: 1 | AQ6: 1 | AR6: 0 | AS6: 0 | AT6: 0 | AU6: 0 | AV6: 0 | AW6: 0 | AX6: 0 | AY6: 0 | AZ6: 0 | BA6: 0 | BB6: 0 | BC6: 0 | BD6: 0 | BE6: 0 | BF6: 0 | BG6: 0 | BH6: 0 | BI6: 0 | BJ6: 0 | BK6: 0 | BL6: 0 | BM6: 0 | BN6: 0
B7: 2 | C7: Curva 25mm 1" | D7: M05-0366 | F7: 3 | G7: 3 | H7: 3 | I7: 3 | J7: 3 | K7: 3 | L7: 3 | M7: 3 | N7: 3 | O7: 3 | P7: 3 | Q7: 3 | R7: 3 | S7: 3 | T7: 3 | U7: 3 | V7: 3 | W7: 3 | X7: 3 | Y7: 3 | Z7: 3 | AA7: 3 | AB7: 3 | AC7: 3 | AD7: 3 | AE7: 3 | AF7: 3 | AG7: 3 | AH7: 3 | AI7: 3 | AJ7: 3 | AK7: 3 | AL7: 3 | AM7: 3 | AN7: 3 | AO7: 3 | AP7: 3 | AQ7: 3 | AR7: 0 | AS7: 0 | AT7: 0 | AU7: 0 | AV7: 0 | AW7: 0 | AX7: 0 | AY7: 0 | AZ7: 0 | BA7: 0 | BB7: 0 | BC7: 0 | BD7: 0 | BE7: 0 | BF7: 0 | BG7: 0 | BH7: 0 | BI7: 0 | BJ7: 0 | BK7: 0 | BL7: 0 | BM7: 0 | BN7: 0
B8: 3 | C8: Curva 13mm 1/2" | D8: M05-0361 | F8: 50 | G8: 50 | H8: 50 | I8: 37 | J8: 37 | K8: 37 | L8: 50 | M8: 50 | N8: 55 | O8: 55 | P8: 55 | Q8: 45 | R8: 45 | S8: 50 | T8: 50 | U8: 45 | V8: 45 | W8: 45 | X8: 45 | Y8: 45 | Z8: 45 | AA8: 50 | AB8: 40 | AC8: 40 | AD8: 40 | AE8: 40 | AF8: 40 | AG8: 40 | AH8: 40 | AI8: 40 | AJ8: 40 | AK8: 40 | AL8: 0 | AM8: 40 | AN8: 40 | AO8: 50 | AP8: 43 | AQ8: 45 | AR8: 0 | AS8: 0 | AT8: 0 | AU8: 0 | AV8: 0 | AW8: 0 | AX8: 0 | AY8: 0 | AZ8: 0 | BA8: 0 | BB8: 0 | BC8: 0 | BD8: 0 | BE8: 0 | BF8: 0 | BG8: 0 | BH8: 0 | BI8: 0 | BJ8: 0 | BK8: 0 | BL8: 0 | BM8: 0 | BN8: 0
B9: 4 | C9: Curva 19mm 3/4" | D9: M05-0367 | F9: 17 | G9: 17 | H9: 17 | I9: 10 | J9: 10 | K9: 10 | L9: 17 | M9: 17 | N9: 15 | O9: 15 | P9: 15 | Q9: 14 | R9: 14 | S9: 20 | T9: 20 | U9: 15 | V9: 15 | W9: 15 | X9: 15 | Y9: 15 | Z9: 15 | AA9: 18 | AB9: 14 | AC9: 14 | AD9: 14 | AE9: 14 | AF9: 14 | AG9: 14 | AH9: 14 | AI9: 15 | AJ9: 14 | AK9: 14 | AL9: 0 | AM9: 14 | AN9: 14 | AO9: 18 | AP9: 8 | AQ9: 15 | AR9: 0 | AS9: 0 | AT9: 0 | AU9: 0 | AV9: 0 | AW9: 0 | AX9: 0 | AY9: 0 | AZ9: 0 | BA9: 0 | BB9: 0 | BC9: 0 | BD9: 0 | BE9: 0 | BF9: 0 | BG9: 0 | BH9: 0 | BI9: 0 | BJ9: 0 | BK9: 0 | BL9: 0 | BM9: 0 | BN9: 0
B10: 5 | C10: Tubo 38mm 1 1/2" | D10: M05-0368 | F10: 4 | G10: 4 | H10: 4 | I10: 4 | J10: 4 | K10: 4 | L10: 4 | M10: 4 | N10: 4 | O10: 4 | P10: 4 | Q10: 4 | R10: 4 | S10: 4 | T10: 4 | U10: 4 | V10: 4 | W10: 4 | X10: 4 | Y10: 4 | Z10: 4 | AA10: 4 | AB10: 4 | AC10: 4 | AD10: 4 | AE10: 4 | AF10: 4 | AG10: 4 | AH10: 4 | AI10: 4 | AJ10: 4 | AK10: 4 | AL10: 4 | AM10: 4 | AN10: 4 | AO10: 4 | AP10: 4 | AQ10: 4 | AR10: 0 | AS10: 0 | AT10: 0 | AU10: 0 | AV10: 0 | AW10: 0 | AX10: 0 | AY10: 0 | AZ10: 0 | BA10: 0 | BB10: 0 | BC10: 0 | BD10: 0 | BE10: 0 | BF10: 0 | BG10: 0 | BH10: 0 | BI10: 0 | BJ10: 0 | BK10: 0 | BL10: 0 | BM10: 0 | BN10: 0
B11: 6 | C11: Tubo 25mm 1" | D11: M05-0369 | F11: 7 | G11: 7 | H11: 7 | I11: 7 | J11: 7 | K11: 7 | L11: 7 | M11: 7 | N11: 7 | O11: 7 | P11: 7 | Q11: 7 | R11: 7 | S11: 7 | T11: 7 | U11: 7 | V11: 7 | W11: 7 | X11: 7 | Y11: 7 | Z11: 7 | AA11: 7 | AB11: 7 | AC11: 7 | AD11: 7 | AE11: 7 | AF11: 7 | AG11: 7 | AH11: 7 | AI11: 7 | AJ11: 7 | AK11: 7 | AL11: 7 | AM11: 7 | AN11: 7 | AO11: 7 | AP11: 7 | AQ11: 7 | AR11: 0 | AS11: 0 | AT11: 0 | AU11: 0 | AV11: 0 | AW11: 0 | AX11: 0 | AY11: 0 | AZ11: 0 | BA11: 0 | BB11: 0 | BC11: 0 | BD11: 0 | BE11: 0 | BF11: 0 | BG11: 0 | BH11: 0 | BI11: 0 | BJ11: 0 | BK11: 0 | BL11: 0 | BM11: 0 | BN11: 0
B12: 7 | C12: Tubo 13mm 1/2" | D12: M05-0370 | F12: 50 | G12: 50 | H12: 50 | I12: 40 | J12: 40 | K12: 40 | L12: 50 | M12: 50 | N12: 50 | O12: 50 | P12: 50 | Q12: 45 | R12: 45 | S12: 50 | T12: 50 | U12: 45 | V12: 45 | W12: 45 | X12: 45 | Y12: 45 | Z12: 45 | AA12: 45 | AB12: 40 | AC12: 40 | AD12: 40 | AE12: 40 | AF12: 40 | AG12: 40 | AH12: 40 | AI12: 40 | AJ12: 40 | AK12: 40 | AL12: 0 | AM12: 40 | AN12: 40 | AO12: 45 | AP12: 50 | AQ12: 45 | AR12: 0 | AS12: 0 | AT12: 0 | AU12: 0 | AV12: 0 | AW12: 0 | AX12: 0 | AY12: 0 | AZ12: 0 | BA12: 0 | BB12: 0 | BC12: 0 | BD12: 0 | BE12: 0 | BF12: 0 | BG12: 0 | BH12: 0 | BI12: 0 | BJ12: 0 | BK12: 0 | BL12: 0 | BM12: 0 | BN12: 0
B13: 8 | C13: Tubo 19mm 3/4" | D13: M05-0371 | F13: 25 | G13: 25 | H13: 25 | I13: 21 | J13: 21 | K13: 21 | L13: 25 | M13: 25 | N13: 25 | O13: 25 | P13: 25 | Q13: 17 | R13: 17 | S13: 20 | T13: 20 | U13: 25 | V13: 25 | W13: 25 | X13: 25 | Y13: 25 | Z13: 25 | AA13: 25 | AB13: 22 | AC13: 22 | AD13: 22 | AE13: 22 | AF13: 22 | AG13: 22 | AH13: 22 | AI13: 22 | AJ13: 22 | AK13: 22 | AL13: 0 | AM13: 22 | AN13: 22 | AO13: 25 | AP13: 17 | AQ13: 25 | AR13: 0 | AS13: 0 | AT13: 0 | AU13: 0 | AV13: 0 | AW13: 0 | AX13: 0 | AY13: 0 | AZ13: 0 | BA13: 0 | BB13: 0 | BC13: 0 | BD13: 0 | BE13: 0 | BF13: 0 | BG13: 0 | BH13: 0 | BI13: 0 | BJ13: 0 | BK13: 0 | BL13: 0 | BM13: 0 | BN13: 0
B14: 9 | C14: Union 38mm 1 1/2" | D14: M05-0372 | F14: 3 | G14: 3 | H14: 3 | I14: 3 | J14: 3 | K14: 3 | L14: 3 | M14: 3 | N14: 3 | O14: 3 | P14: 3 | Q14: 3 | R14: 3 | S14: 3 | T14: 3 | U14: 3 | V14: 3 | W14: 3 | X14: 3 | Y14: 3 | Z14: 3 | AA14: 3 | AB14: 3 | AC14: 3 | AD14: 3 | AE14: 3 | AF14: 3 | AG14: 3 | AH14: 3 | AI14: 3 | AJ14: 3 | AK14: 3 | AL14: 3 | AM14: 3 | AN14: 3 | AO14: 3 | AP14: 3 | AQ14: 3 | AR14: 0 | AS14: 0 | AT14: 0 | AU14: 0 | AV14: 0 | AW14: 0 | AX14: 0 | AY14: 0 | AZ14: 0 | BA14: 0 | BB14: 0 | BC14: 0 | BD14: 0 | BE14: 0 | BF14: 0 | BG14: 0 | BH14: 0 | BI14: 0 | BJ14: 0 | BK14: 0 | BL14: 0 | BM14: 0 | BN14: 0
B15: 10 | C15: Union 25mm 1" | D15: M05-0373 | F15: 3 | G15: 3 | H15: 3 | I15: 3 | J15: 3 | K15: 3 | L15: 3 | M15: 3 | N15: 3 | O15: 3 | P15: 3 | Q15: 3 | R15: 3 | S15: 3 | T15: 3 | U15: 3 | V15: 3 | W15: 3 | X15: 3 | Y15: 3 | Z15: 3 | AA15: 3 | AB15: 3 | AC15: 3 | AD15: 3 | AE15: 3 | AF15: 3 | AG15: 3 | AH15: 3 | AI15: 3 | AJ15: 3 | AK15: 3 | AL15: 3 | AM15: 3 | AN15: 3 | AO15: 3 | AP15: 3 | AQ15: 3 | AR15: 0 | AS15: 0 | AT15: 0 | AU15: 0 | AV15: 0 | AW15: 0 | AX15: 0 | AY15: 0 | AZ15: 0 | BA15: 0 | BB15: 0 | BC15: 0 | BD15: 0 | BE15: 0 | BF15: 0 | BG15: 0 | BH15: 0 | BI15: 0 | BJ15: 0 | BK15: 0 | BL15: 0 | BM15: 0 | BN15: 0
B16: 11 | C16: Union 13mm 1/2" | D16: M05-0374 | F16: 20 | G16: 20 | H16: 20 | I16: 15 | J16: 15 | K16: 15 | L16: 20 | M16: 20 | N16: 20 | O16: 20 | P16: 20 | Q16: 20 | R16: 20 | S16: 20 | T16: 20 | U16: 18 | V16: 18 | W16: 18 | X16: 18 | Y16: 18 | Z16: 18 | AA16: 18 | AB16: 15 | AC16: 15 | AD16: 15 | AE16: 15 | AF16: 15 | AG16: 15 | AH16: 15 | AI16: 15 | AJ16: 15 | AK16: 15 | AL16: 15 | AM16: 15 | AN16: 15 | AO16: 18 | AP16: 10 | AQ16: 18 | AR16: 0 | AS16: 0 | AT16: 0 | AU16: 0 | AV16: 0 | AW16: 0 | AX16: 0 | AY16: 0 | AZ16: 0 | BA16: 0 | BB16: 0 | BC16: 0 | BD16: 0 | BE16: 0 | BF16: 0 | BG16: 0 | BH16: 0 | BI16: 0 | BJ16: 0 | BK16: 0 | BL16: 0 | BM16: 0 | BN16: 0
B17: 12 | C17: Union 19mm 3/4" | D17: M05-0375 | F17: 12 | G17: 12 | H17: 12 | I17: 8 | J17: 8 | K17: 8 | L17: 12 | M17: 12 | N17: 12 | O17: 12 | P17: 12 | Q17: 12 | R17: 12 | S17: 12 | T17: 12 | U17: 15 | V17: 15 | W17: 15 | X17: 15 | Y17: 15 | Z17: 15 | AA17: 15 | AB17: 10 | AC17: 10 | AD17: 10 | AE17: 10 | AF17: 10 | AG17: 10 | AH17: 10 | AI17: 10 | AJ17: 10 | AK17: 10 | AL17: 10 | AM17: 10 | AN17: 10 | AO17: 15 | AP17: 7 | AQ17: 15 | AR17: 0 | AS17: 0 | AT17: 0 | AU17: 0 | AV17: 0 | AW17: 0 | AX17: 0 | AY17: 0 | AZ17: 0 | BA17: 0 | BB17: 0 | BC17: 0 | BD17: 0 | BE17: 0 | BF17: 0 | BG17: 0 | BH17: 0 | BI17: 0 | BJ17: 0 | BK17: 0 | BL17: 0 | BM17: 0 | BN17: 0
... B25: 20 | C25: Cilindro de gas | D25: M06-0197 | F25: 1 | G25: 1 | H25: 1 | I25: 1 | J25: 1 | K25: 1 | L25: 1 | M25: 1 | N25: 1 | O25: 1 | P25: 1 | Q25: 1 | R25: 1 | S25: 1 | T25: 1 | U25: 1 | V25: 1 | W25: 1 | X25: 1 | Y25: 1 | Z25: 1 | AA25: 1 | AB25: 1 | AC25: 1 | AD25: 1 | AE25: 1 | AF25: 1 | AG25: 1 | AH25: 1 | AI25: 1 | AJ25: 1 | AK25: 1 | AL25: 1 | AM25: 1 | AN25: 1 | AO25: 1 | AP25: 1 | AQ25: 1 | AR25: 0 | AS25: 0 | AT25: 0 | AU25: 0 | AV25: 0 | AW25: 0 | AX25: 0 | AY25: 0 | AZ25: 0 | BA25: 0 | BB25: 0 | BC25: 0 | BD25: 0 | BE25: 0 | BF25: 0 | BG25: 0 | BH25: 0 | BI25: 0 | BJ25: 0 | BK25: 0 | BL25: 0 | BM25: 0 | BN25: 0
B26: 21 | C26: 0 | D26: 0 | F26: 0 | G26: 0 | H26: 0 | I26: 0 | J26: 0 | K26: 0 | L26: 0 | M26: 0 | N26: 0 | O26: 0 | P26: 0 | Q26: 0 | R26: 0 | S26: 0 | T26: 0 | U26: 0 | V26: 0 | W26: 0 | X26: 0 | Y26: 0 | Z26: 0 | AA26: 0 | AB26: 0 | AC26: 0 | AD26: 0 | AE26: 0 | AF26: 0 | AG26: 0 | AH26: 0 | AI26: 0 | AJ26: 0 | AK26: 0 | AL26: 0 | AM26: 0 | AN26: 0 | AO26: 0 | AP26: 0 | AQ26: 0 | AR26: 0 | AS26: 0 | AT26: 0 | AU26: 0 | AV26: 0 | AW26: 0 | AX26: 0 | AY26: 0 | AZ26: 0 | BA26: 0 | BB26: 0 | BC26: 0 | BD26: 0 | BE26: 0 | BF26: 0 | BG26: 0 | BH26: 0 | BI26: 0 | BJ26: 0 | BK26: 0 | BL26: 0 | BM26: 0 | BN26: 0
B27: 22 | C27: 0 | D27: 0 | F27: 0 | G27: 0 | H27: 0 | I27: 0 | J27: 0 | L27: 0 | M27: 0 | N27: 0 | O27: 0 | P27: 0 | Q27: 0 | R27: 0 | S27: 0 | T27: 0 | U27: 0 | V27: 0 | W27: 0 | X27: 0 | Y27: 0 | Z27: 0 | AA27: 0 | AB27: 0 | AC27: 0 | AD27: 0 | AE27: 0 | AF27: 0 | AG27: 0 | AH27: 0 | AI27: 0 | AJ27: 0 | AK27: 0 | AL27: 0 | AM27: 0 | AN27: 0 | AO27: 0 | AP27: 0 | AQ27: 0 | AR27: 0 | AS27: 0 | AT27: 0 | AU27: 0 | AV27: 0 | AW27: 0 | AX27: 0 | AY27: 0 | AZ27: 0 | BA27: 0 | BB27: 0 | BC27: 0 | BD27: 0 | BE27: 0 | BF27: 0 | BG27: 0 | BH27: 0 | BI27: 0 | BJ27: 0 | BK27: 0 | BL27: 0 | BM27: 0 | BN27: 0
B28: 23 | C28: 0 | D28: 0 | F28: 0 | G28: 0 | H28: 0 | I28: 0 | J28: 0 | K28: 0 | L28: 0 | M28: 0 | N28: 0 | O28: 0 | P28: 0 | Q28: 0 | R28: 0 | S28: 0 | T28: 0 | U28: 0 | V28: 0 | W28: 0 | X28: 0 | Y28: 0 | Z28: 0 | AA28: 0 | AB28: 0 | AC28: 0 | AD28: 0 | AE28: 0 | AF28: 0 | AG28: 0 | AH28: 0 | AI28: 0 | AJ28: 0 | AK28: 0 | AL28: 0 | AM28: 0 | AN28: 0 | AO28: 0 | AP28: 0 | AQ28: 0 | AR28: 0 | AS28: 0 | AT28: 0 | AU28: 0 | AV28: 0 | AW28: 0 | AX28: 0 | AY28: 0 | AZ28: 0 | BA28: 0 | BB28: 0 | BC28: 0 | BD28: 0 | BE28: 0 | BF28: 0 | BG28: 0 | BH28: 0 | BI28: 0 | BJ28: 0 | BK28: 0 | BL28: 0 | BM28: 0 | BN28: 0
B29: 24 | C29: 0 | D29: 0 | F29: 0 | G29: 0 | H29: 0 | I29: 0 | J29: 0 | K29: 0 | L29: 0 | M29: 0 | N29: 0 | O29: 0 | P29: 0 | Q29: 0 | R29: 0 | S29: 0 | T29: 0 | U29: 0 | V29: 0 | W29: 0 | X29: 0 | Y29: 0 | Z29: 0 | AA29: 0 | AB29: 0 | AC29: 0 | AD29: 0 | AE29: 0 | AF29: 0 | AG29: 0 | AH29: 0 | AI29: 0 | AJ29: 0 | AK29: 0 | AL29: 0 | AM29: 0 | AN29: 0 | AO29: 0 | AP29: 0 | AQ29: 0 | AR29: 0 | AS29: 0 | AT29: 0 | AU29: 0 | AV29: 0 | AW29: 0 | AX29: 0 | AY29: 0 | AZ29: 0 | BA29: 0 | BB29: 0 | BC29: 0 | BD29: 0 | BE29: 0 | BF29: 0 | BG29: 0 | BH29: 0 | BI29: 0 | BJ29: 0 | BK29: 0 | BL29: 0 | BM29: 0 | BN29: 0
B30: 25 | C30: 0 | D30: 0 | F30: 0 | G30: 0 | H30: 0 | I30: 0 | J30: 0 | K30: 0 | L30: 0 | M30: 0 | N30: 0 | O30: 0 | P30: 0 | Q30: 0 | R30: 0 | S30: 0 | T30: 0 | U30: 0 | V30: 0 | W30: 0 | X30: 0 | Y30: 0 | Z30: 0 | AA30: 0 | AB30: 0 | AC30: 0 | AD30: 0 | AE30: 0 | AF30: 0 | AG30: 0 | AH30: 0 | AI30: 0 | AJ30: 0 | AK30: 0 | AL30: 0 | AM30: 0 | AN30: 0 | AO30: 0 | AP30: 0 | AQ30: 0 | AR30: 0 | AS30: 0 | AT30: 0 | AU30: 0 | AV30: 0 | AW30: 0 | AX30: 0 | AY30: 0 | AZ30: 0 | BA30: 0 | BB30: 0 | BC30: 0 | BD30: 0 | BE30: 0 | BF30: 0 | BG30: 0 | BH30: 0 | BI30: 0 | BJ30: 0 | BK30: 0 | BL30: 0 | BM30: 0 | BN30: 0
B31: MURO N1
B32: 1 | C32: Union 38mm 1 1/2" | D32: M05-0372 | F32: 0 | G32: 0 | H32: 0 | I32: 0 | J32: 0 | K32: 0 | L32: 0 | M32: 0 | N32: 0 | O32: 0 | P32: 0 | Q32: 0 | R32: 0 | S32: 0 | T32: 0 | U32: 0 | V32: 0 | W32: 0 | X32: 0 | Y32: 0 | Z32: 0 | AA32: 0 | AB32: 0 | AC32: 0 | AD32: 0 | AE32: 0 | AF32: 0 | AG32: 0 | AH32: 0 | AI32: 0 | AJ32: 0 | AK32: 0 | AL32: 0 | AM32: 0 | AN32: 0 | AO32: 0 | AP32: 0 | AQ32: 0 | AR32: 0 | AS32: 0 | AT32: 0 | AU32: 0 | AV32: 0 | AW32: 0 | AX32: 0 | AY32: 0 | AZ32: 0 | BA32: 0 | BB32: 0 | BC32: 0 | BD32: 0 | BE32: 0 | BF32: 0 | BG32: 0 | BH32: 0 | BI32: 0 | BJ32: 0 | BK32: 0 | BL32: 0 | BM32: 0 | BN32: 0
B33: 2 | C33: Union 25mm 1" | D33: M05-0373 | F33: 0 | G33: 0 | H33: 0 | I33: 0 | J33: 0 | K33: 0 | L33: 0 | M33: 0 | N33: 0 | O33: 0 | P33: 0 | Q33: 0 | R33: 0 | S33: 0 | T33: 0 | U33: 0 | V33: 0 | W33: 0 | X33: 0 | Y33: 0 | Z33: 0 | AA33: 0 | AB33: 0 | AC33: 0 | AD33: 0 | AE33: 0 | AF33: 0 | AG33: 0 | AH33: 0 | AI33: 0 | AJ33: 0 | AK33: 0 | AL33: 0 | AM33: 0 | AN33: 0 | AO33: 0 | AP33: 0 | AQ33: 0 | AR33: 0 | AS33: 0 | AT33: 0 | AU33: 0 | AV33: 0 | AW33: 0 | AX33: 0 | AY33: 0 | AZ33: 0 | BA33: 0 | BB33: 0 | BC33: 0 | BD33: 0 | BE33: 0 | BF33: 0 | BG33: 0 | BH33: 0 | BI33: 0 | BJ33: 0 | BK33: 0 | BL33: 0 | BM33: 0 | BN33: 0
B34: 3 | C34: Union 13mm 1/2" | D34: M05-0374 | F34: 10 | G34: 10 | H34: 10 | I34: 10 | J34: 10 | K34: 10 | L34: 10 | M34: 10 | N34: 10 | O34: 10 | P34: 10 | Q34: 10 | R34: 10 | S34: 10 | T34: 10 | U34: 10 | V34: 10 | W34: 10 | X34: 10 | Y34: 10 | Z34: 10 | AA34: 10 | AB34: 10 | AC34: 10 | AD34: 10 | AE34: 10 | AF34: 10 | AG34: 10 | AH34: 10 | AI34: 10 | AJ34: 10 | AK34: 10 | AL34: 10 | AM34: 10 | AN34: 10 | AO34: 10 | AP34: 10 | AQ34: 10 | AR34: 0 | AS34: 0 | AT34: 0 | AU34: 0 | AV34: 0 | AW34: 0 | AX34: 0 | AY34: 0 | AZ34: 0 | BA34: 0 | BB34: 0 | BC34: 0 | BD34: 0 | BE34: 0 | BF34: 0 | BG34: 0 | BH34: 0 | BI34: 0 | BJ34: 0 | BK34: 0 | BL34: 0 | BM34: 0 | BN34: 0
B35: 4 | C35: Union 19mm 3/4" | D35: M05-0375 | F35: 6 | G35: 6 | H35: 6 | I35: 6 | J35: 6 | K35: 6 | L35: 6 | M35: 6 | N35: 6 | O35: 6 | P35: 6 | Q35: 6 | R35: 6 | S35: 6 | T35: 6 | U35: 6 | V35: 6 | W35: 6 | X35: 6 | Y35: 6 | Z35: 6 | AA35: 6 | AB35: 6 | AC35: 6 | AD35: 6 | AE35: 6 | AF35: 6 | AG35: 6 | AH35: 6 | AI35: 6 | AJ35: 6 | AK35: 6 | AL35: 6 | AM35: 6 | AN35: 6 | AO35: 6 | AP35: 6 | AQ35: 6 | AR35: 0 | AS35: 0 | AT35: 0 | AU35: 0 | AV35: 0 | AW35: 0 | AX35: 0 | AY35: 0 | AZ35: 0 | BA35: 0 | BB35: 0 | BC35: 0 | BD35: 0 | BE35: 0 | BF35: 0 | BG35: 0 | BH35: 0 | BI35: 0 | BJ35: 0 | BK35: 0 | BL35: 0 | BM35: 0 | BN35: 0
B36: 5 | C36: Spray | D36: M11-0067 | F36: 1 | G36: 1 | H36: 1 | I36: 1 | J36: 1 | K36: 1 | L36: 1 | M36: 1 | N36: 1 | O36: 1 | P36: 1 | Q36: 1 | R36: 1 | S36: 1 | T36: 1 | U36: 1 | V36: 1 | W36: 1 | X36: 1 | Y36: 1 | Z36: 1 | AA36: 1 | AB36: 1 | AC36: 1 | AD36: 1 | AE36: 1 | AF36: 1 | AG36: 1 | AH36: 1 | AI36: 1 | AJ36: 1 | AK36: 1 | AL36: 1 | AM36: 1 | AN36: 1 | AO36: 1 | AP36: 1 | AQ36: 1 | AR36: 0 | AS36: 0 | AT36: 0 | AU36: 0 | AV36: 0 | AW36: 0 | AX36: 0 | AY36: 0 | AZ36: 0 | BA36: 0 | BB36: 0 | BC36: 0 | BD36: 0 | BE36: 0 | BF36: 0 | BG36: 0 | BH36: 0 | BI36: 0 | BJ36: 0 | BK36: 0 | BL36: 0 | BM36: 0 | BN36: 0
B37: 6 | C37: Cinta empaque | D37: M06-0175 | F37: 2 | G37: 2 | H37: 2 | I37: 2 | J37: 2 | K37: 2 | L37: 2 | M37: 2 | N37: 4 | O37: 4 | P37: 4 | Q37: 2 | R37: 2 | S37: 2 | T37: 2 | U37: 2 | V37: 2 | W37: 2 | X37: 2 | Y37: 2 | Z37: 2 | AA37: 2 | AB37: 2 | AC37: 2 | AD37: 2 | AE37: 2 | AF37: 2 | AG37: 2 | AH37: 2 | AI37: 2 | AJ37: 2 | AK37: 2 | AL37: 2 | AM37: 2 | AN37: 2 | AO37: 2 | AP37: 2 | AQ37: 2 | AR37: 0 | AS37: 0 | AT37: 0 | AU37: 0 | AV37: 0 | AW37: 0 | AX37: 0 | AY37: 0 | AZ37: 0 | BA37: 0 | BB37: 0 | BC37: 0 | BD37: 0 | BE37: 0 | BF37: 0 | BG37: 0 | BH37: 0 | BI37: 0 | BJ37: 0 | BK37: 0 | BL37: 0 | BM37: 0 | BN37: 0
B38: 7 | C38: Pegamento | D38: M06-0013 | F38: 2 | G38: 2 | H38: 2 | I38: 2 | J38: 2 | K38: 2 | L38: 2 | M38: 2 | N38: 2 | O38: 2 | P38: 2 | Q38: 2 | R38: 2 | S38: 2 | T38: 2 | U38: 2 | V38: 2 | W38: 2 | X38: 2 | Y38: 2 | Z38: 2 | AA38: 2 | AB38: 2 | AC38: 2 | AD38: 2 | AE38: 2 | AF38: 2 | AG38: 2 | AH38: 2 | AI38: 2 | AJ38: 2 | AK38: 2 | AL38: 2 | AM38: 2 | AN38: 2 | AO38: 2 | AP38: 2 | AQ38: 2 | AR38: 0 | AS38: 0 | AT38: 0 | AU38: 0 | AV38: 0 | AW38: 0 | AX38: 0 | AY38: 0 | AZ38: 0 | BA38: 0 | BB38: 0 | BC38: 0 | BD38: 0 | BE38: 0 | BF38: 0 | BG38: 0 | BH38: 0 | BI38: 0 | BJ38: 0 | BK38: 0 | BL38: 0 | BM38: 0 | BN38: 0
B39: 8 | C39: Cegueta | D39: M06-0210 | F39: 1 | G39: 1 | H39: 1 | I39: 1 | J39: 1 | K39: 1 | L39: 1 | M39: 1 | N39: 1 | O39: 1 | P39: 1 | Q39: 1 | R39: 1 | S39: 1 | T39: 1 | U39: 1 | V39: 1 | W39: 1 | X39: 1 | Y39: 1 | Z39: 1 | AA39: 1 | AB39: 1 | AC39: 1 | AD39: 1 | AE39: 1 | AF39: 1 | AG39: 1 | AH39: 1 | AI39: 1 | AJ39: 1 | AK39: 1 | AL39: 1 | AM39: 1 | AN39: 1 | AO39: 1 | AP39: 1 | AQ39: 1 | AR39: 0 | AS39: 0 | AT39: 0 | AU39: 0 | AV39: 0 | AW39: 0 | AX39: 0 | AY39: 0 | AZ39: 0 | BA39: 0 | BB39: 0 | BC39: 0 | BD39: 0 | BE39: 0 | BF39: 0 | BG39: 0 | BH39: 0 | BI39: 0 | BJ39: 0 | BK39: 0 | BL39: 0 | BM39: 0 | BN39: 0
B40: 9 | C40: Lamina de estereofon | D40: M04-0003 | F40: 0.5 | G40: 0.5 | H40: 0.5 | I40: 0.5 | J40: 0.5 | K40: 0.5 | L40: 0.5 | M40: 0.5 | N40: 0.5 | O40: 0.5 | P40: 0.5 | Q40: 0.5 | R40: 0.5 | S40: 0.5 | T40: 0.5 | U40: 0.5 | V40: 0.5 | W40: 0.5 | X40: 0.5 | Y40: 0.5 | Z40: 0.5 | AA40: 0.5 | AB40: 0.5 | AC40: 0.5 | AD40: 0.5 | AE40: 0.5 | AF40: 0.5 | AG40: 0.5 | AH40: 0.5 | AI40: 0.5 | AJ40: 0.5 | AK40: 0.5 | AL40: 0.5 | AM40: 0.5 | AN40: 0.5 | AO40: 0.5 | AP40: 0.5 | AQ40: 0.5 | AR40: 0 | AS40: 0 | AT40: 0 | AU40: 0 | AV40: 0 | AW40: 0 | AX40: 0 | AY40: 0 | AZ40: 0 | BA40: 0 | BB40: 0 | BC40: 0 | BD40: 0 | BE40: 0 | BF40: 0 | BG40: 0 | BH40: 0 | BI40: 0 | BJ40: 0 | BK40: 0 | BL40: 0 | BM40: 0 | BN40: 0
B41: 10 | C41: Cilindro de gas | D41: M06-0197 | F41: 2 | G41: 2 | H41: 2 | I41: 2 | J41: 2 | K41: 2 | L41: 2 | M41: 2 | N41: 2 | O41: 2 | P41: 2 | Q41: 2 | R41: 2 | S41: 2 | T41: 2 | U41: 2 | V41: 2 | W41: 2 | X41: 2 | Y41: 2 | Z41: 2 | AA41: 2 | AB41: 2 | AC41: 2 | AD41: 2 | AE41: 2 | AF41: 2 | AG41: 2 | AH41: 2 | AI41: 2 | AJ41: 2 | AK41: 2 | AL41: 2 | AM41: 2 | AN41: 2 | AO41: 2 | AP41: 2 | AQ41: 2 | AR41: 0 | AS41: 0 | AT41: 0 | AU41: 0 | AV41: 0 | AW41: 0 | AX41: 0 | AY41: 0 | AZ41: 0 | BA41: 0 | BB41: 0 | BC41: 0 | BD41: 0 | BE41: 0 | BF41: 0 | BG41: 0 | BH41: 0 | BI41: 0 | BJ41: 0 | BK41: 0 | BL41: 0 | BM41: 0 | BN41: 0
B42: 11 | C42: Caja cuadrada 4x4 doble 1 | D42: M05-0388 | F42: 1 | G42: 1 | H42: 1 | I42: 1 | J42: 1 | K42: 1 | L42: 1 | M42: 1 | N42: 1 | O42: 1 | P42: 1 | Q42: 1 | R42: 1 | S42: 1 | T42: 1 | U42: 1 | V42: 1 | W42: 1 | X42: 1 | Y42: 1 | Z42: 1 | AA42: 1 | AB42: 1 | AC42: 1 | AD42: 1 | AE42: 1 | AF42: 1 | AG42: 1 | AH42: 1 | AI42: 1 | AJ42: 1 | AK42: 1 | AL42: 1 | AM42: 1 | AN42: 1 | AO42: 1 | AP42: 1 | AQ42: 1 | AR42: 0 | AS42: 0 | AT42: 0 | AU42: 0 | AV42: 0 | AW42: 0 | AX42: 0 | AY42: 0 | AZ42: 0 | BA42: 0 | BB42: 0 | BC42: 0 | BD42: 0 | BE42: 0 | BF42: 0 | BG42: 0 | BH42: 0 | BI42: 0 | BJ42: 0 | BK42: 0 | BL42: 0 | BM42: 0 | BN42: 0
B43: 12 | C43: Caja cuadrada 4x4 doble 1/2 | D43: M05-0385 | F43: 3 | G43: 3 | H43: 3 | I43: 3 | J43: 3 | K43: 3 | L43: 3 | M43: 3 | N43: 3 | O43: 3 | P43: 3 | Q43: 3 | R43: 3 | S43: 3 | T43: 3 | U43: 3 | V43: 3 | W43: 3 | X43: 3 | Y43: 3 | Z43: 3 | AA43: 3 | AB43: 3 | AC43: 3 | AD43: 3 | AE43: 3 | AF43: 3 | AG43: 3 | AH43: 3 | AI43: 3 | AJ43: 3 | AK43: 3 | AL43: 3 | AM43: 3 | AN43: 3 | AO43: 3 | AP43: 3 | AQ43: 3 | AR43: 0 | AS43: 0 | AT43: 0 | AU43: 0 | AV43: 0 | AW43: 0 | AX43: 0 | AY43: 0 | AZ43: 0 | BA43: 0 | BB43: 0 | BC43: 0 | BD43: 0 | BE43: 0 | BF43: 0 | BG43: 0 | BH43: 0 | BI43: 0 | BJ43: 0 | BK43: 0 | BL43: 0 | BM43: 0 | BN43: 0
B44: 13 | C44: Caja rectangular salida 1/2 | D44: M05-0390 | F44: 40 | G44: 40 | H44: 40 | I44: 35 | J44: 35 | K44: 28 | L44: 43 | M44: 43 | N44: 25 | O44: 25 | P44: 25 | Q44: 36 | R44: 36 | S44: 45 | T44: 45 | U44: 24 | V44: 24 | W44: 24 | X44: 24 | Y44: 24 | Z44: 24 | AA44: 24 | AB44: 22 | AC44: 22 | AD44: 22 | AE44: 22 | AF44: 22 | AG44: 22 | AH44: 22 | AI44: 22 | AJ44: 22 | AK44: 22 | AL44: 22 | AM44: 22 | AN44: 22 | AO44: 24 | AP44: 22 | AQ44: 29 | AR44: 0 | AS44: 0 | AT44: 0 | AU44: 0 | AV44: 0 | AW44: 0 | AX44: 0 | AY44: 0 | AZ44: 0 | BA44: 0 | BB44: 0 | BC44: 0 | BD44: 0 | BE44: 0 | BF44: 0 | BG44: 0 | BH44: 0 | BI44: 0 | BJ44: 0 | BK44: 0 | BL44: 0 | BM44: 0 | BN44: 0
B45: 14 | C45: Caja rectangular salida 3/4 | D45: 0 | F45: 0 | G45: 0 | H45: 0 | I45: 0 | J45: 0 | K45: 0 | L45: 0 | M45: 0 | N45: 0 | O45: 0 | P45: 0 | Q45: 0 | R45: 0 | S45: 0 | T45: 0 | U45: 0 | V45: 0 | W45: 0 | X45: 0 | Y45: 0 | Z45: 0 | AA45: 0 | AB45: 0 | AC45: 0 | AD45: 0 | AE45: 0 | AF45: 0 | AG45: 0 | AH45: 0 | AI45: 0 | AJ45: 0 | AK45: 0 | AL45: 0 | AM45: 0 | AN45: 0 | AO45: 0 | AP45: 0 | AQ45: 0 | AR45: 0 | AS45: 0 | AT45: 0 | AU45: 0 | AV45: 0 | AW45: 0 | AX45: 0 | AY45: 0 | AZ45: 0 | BA45: 0 | BB45: 0 | BC45: 0 | BD45: 0 | BE45: 0 | BF45: 0 | BG45: 0 | BH45: 0 | BI45: 0 | BJ45: 0 | BK45: 0 | BL45: 0 | BM45: 0 | BN45: 0
B46: 15 | C46: Conector 1 1/2" UL | D46: M05-0363 | F46: 0 | G46: 0 | H46: 0 | I46: 0 | J46: 0 | K46: 0 | L46: 0 | M46: 0 | N46: 0 | O46: 0 | P46: 0 | Q46: 0 | R46: 0 | S46: 0 | T46: 0 | U46: 0 | V46: 0 | W46: 0 | X46: 0 | Y46: 0 | Z46: 0 | AA46: 0 | AB46: 0 | AC46: 0 | AD46: 0 | AE46: 0 | AF46: 0 | AG46: 0 | AH46: 0 | AI46: 0 | AJ46: 0 | AK46: 0 | AL46: 0 | AM46: 0 | AN46: 0 | AO46: 0 | AP46: 0 | AQ46: 0 | AR46: 0 | AS46: 0 | AT46: 0 | AU46: 0 | AV46: 0 | AW46: 0 | AX46: 0 | AY46: 0 | AZ46: 0 | BA46: 0 | BB46: 0 | BC46: 0 | BD46: 0 | BE46: 0 | BF46: 0 | BG46: 0 | BH46: 0 | BI46: 0 | BJ46: 0 | BK46: 0 | BL46: 0 | BM46: 0 | BN46: 0
B47: 16 | C47: Conector 1" UL | D47: M05-0364 | F47: 1 | G47: 1 | H47: 1 | I47: 1 | J47: 1 | K47: 1 | L47: 1 | M47: 1 | N47: 1 | O47: 1 | P47: 1 | Q47: 1 | R47: 1 | S47: 1 | T47: 1 | U47: 1 | V47: 1 | W47: 1 | X47: 1 | Y47: 1 | Z47: 1 | AA47: 1 | AB47: 1 | AC47: 1 | AD47: 1 | AE47: 1 | AF47: 1 | AG47: 1 | AH47: 1 | AI47: 1 | AJ47: 1 | AK47: 1 | AL47: 1 | AM47: 1 | AN47: 1 | AO47: 1 | AP47: 1 | AQ47: 0 | AR47: 0 | AS47: 0 | AT47: 0 | AU47: 0 | AV47: 0 | AW47: 0 | AX47: 0 | AY47: 0 | AZ47: 0 | BA47: 0 | BB47: 0 | BC47: 0 | BD47: 0 | BE47: 0 | BF47: 0 | BG47: 0 | BH47: 0 | BI47: 0 | BJ47: 0 | BK47: 0 | BL47: 0 | BM47: 0 | BN47: 0
B48: 17 | C48: Conector de 1/2" UL | D48: M05-0476 | F48: 60 | G48: 60 | H48: 60 | I48: 50 | J48: 50 | K48: 40 | L48: 60 | M48: 60 | N48: 40 | O48: 40 | P48: 40 | Q48: 50 | R48: 50 | S48: 60 | T48: 60 | U48: 30 | V48: 30 | W48: 30 | X48: 30 | Y48: 30 | Z48: 30 | AA48: 30 | AB48: 30 | AC48: 30 | AD48: 30 | AE48: 30 | AF48: 30 | AG48: 30 | AH48: 30 | AI48: 30 | AJ48: 30 | AK48: 30 | AL48: 30 | AM48: 30 | AN48: 30 | AO48: 30 | AP48: 30 | AQ48: 0 | AR48: 0 | AS48: 0 | AT48: 0 | AU48: 0 | AV48: 0 | AW48: 0 | AX48: 0 | AY48: 0 | AZ48: 0 | BA48: 0 | BB48: 0 | BC48: 0 | BD48: 0 | BE48: 0 | BF48: 0 | BG48: 0 | BH48: 0 | BI48: 0 | BJ48: 0 | BK48: 0 | BL48: 0 | BM48: 0 | BN48: 0
B49: 18 | C49: Conector 3/4" UL | D49: M05-0477 | F49: 15 | G49: 15 | H49: 15 | I49: 15 | J49: 15 | K49: 12 | L49: 15 | M49: 15 | N49: 10 | O49: 10 | P49: 10 | Q49: 12 | R49: 12 | S49: 15 | T49: 15 | U49: 8 | V49: 8 | W49: 8 | X49: 8 | Y49: 8 | Z49: 8 | AA49: 8 | AB49: 5 | AC49: 5 | AD49: 5 | AE49: 5 | AF49: 5 | AG49: 5 | AH49: 5 | AI49: 5 | AJ49: 5 | AK49: 5 | AL49: 5 | AM49: 5 | AN49: 5 | AO49: 8 | AP49: 5 | AQ49: 0 | AR49: 0 | AS49: 0 | AT49: 0 | AU49: 0 | AV49: 0 | AW49: 0 | AX49: 0 | AY49: 0 | AZ49: 0 | BA49: 0 | BB49: 0 | BC49: 0 | BD49: 0 | BE49: 0 | BF49: 0 | BG49: 0 | BH49: 0 | BI49: 0 | BJ49: 0 | BK49: 0 | BL49: 0 | BM49: 0 | BN49: 0
B50: 19 | C50: Tubo 13mm 1/2" | D50: M05-0405 | F50: 5 | G50: 5 | H50: 5 | I50: 5 | J50: 5 | K50: 5 | L50: 5 | M50: 5 | N50: 5 | O50: 5 | P50: 5 | Q50: 5 | R50: 5 | S50: 5 | T50: 5 | U50: 5 | V50: 5 | W50: 5 | X50: 5 | Y50: 5 | Z50: 5 | AA50: 5 | AB50: 5 | AC50: 5 | AD50: 5 | AE50: 5 | AF50: 5 | AG50: 5 | AH50: 5 | AI50: 5 | AJ50: 5 | AK50: 5 | AL50: 5 | AM50: 5 | AN50: 5 | AO50: 5 | AP50: 5 | AQ50: 0 | AR50: 0 | AS50: 0 | AT50: 0 | AU50: 0 | AV50: 0 | AW50: 0 | AX50: 0 | AY50: 0 | AZ50: 0 | BA50: 0 | BB50: 0 | BC50: 0 | BD50: 0 | BE50: 0 | BF50: 0 | BG50: 0 | BH50: 0 | BI50: 0 | BJ50: 0 | BK50: 0 | BL50: 0 | BM50: 0 | BN50: 0
B51: 20 | C51: Aro de repello 1 Gang | D51: M05-0386 | F51: 2 | G51: 2 | H51: 2 | I51: 2 | J51: 2 | K51: 2 | L51: 2 | M51: 2 | N51: 2 | O51: 2 | P51: 2 | Q51: 2 | R51: 2 | S51: 2 | T51: 2 | U51: 2 | V51: 2 | W51: 2 | X51: 2 | Y51: 2 | Z51: 2 | AA51: 2 | AB51: 2 | AC51: 2 | AD51: 2 | AE51: 2 | AF51: 2 | AG51: 2 | AH51: 2 | AI51: 2 | AJ51: 2 | AK51: 2 | AL51: 2 | AM51: 2 | AN51: 2 | AO51: 2 | AP51: 2 | AQ51: 0 | AR51: 0 | AS51: 0 | AT51: 0 | AU51: 0 | AV51: 0 | AW51: 0 | AX51: 0 | AY51: 0 | AZ51: 0 | BA51: 0 | BB51: 0 | BC51: 0 | BD51: 0 | BE51: 0 | BF51: 0 | BG51: 0 | BH51: 0 | BI51: 0 | BJ51: 0 | BK51: 0 | BL51: 0 | BM51: 0 | BN51: 0
B52: 21 | C52: Varilla #3 G40 | D52: M01-0147 | F52: 3 | G52: 3 | H52: 3 | I52: 3 | J52: 3 | K52: 3 | L52: 3 | M52: 3 | N52: 3 | O52: 3 | P52: 3 | Q52: 3 | R52: 3 | S52: 3 | T52: 3 | U52: 3 | V52: 3 | W52: 3 | X52: 3 | Y52: 3 | Z52: 3 | AA52: 3 | AB52: 3 | AC52: 3 | AD52: 3 | AE52: 3 | AF52: 3 | AG52: 3 | AH52: 3 | AI52: 3 | AJ52: 3 | AK52: 3 | AL52: 3 | AM52: 3 | AN52: 3 | AO52: 3 | AP52: 3 | AQ52: 0 | AR52: 0 | AS52: 0 | AT52: 0 | AU52: 0 | AV52: 0 | AW52: 0 | AX52: 0 | AY52: 0 | AZ52: 0 | BA52: 0 | BB52: 0 | BC52: 0 | BD52: 0 | BE52: 0 | BF52: 0 | BG52: 0 | BH52: 0 | BI52: 0 | BJ52: 0 | BK52: 0 | BL52: 0 | BM52: 0 | BN52: 0
B53: 22 | C53: Tubo 19mm 3/4" | D53: M05-0371 | F53: 2 | G53: 2 | H53: 2 | I53: 2 | J53: 2 | K53: 2 | L53: 2 | M53: 2 | N53: 2 | O53: 2 | P53: 2 | Q53: 2 | R53: 2 | S53: 2 | T53: 2 | U53: 2 | V53: 2 | W53: 2 | X53: 2 | Y53: 2 | Z53: 2 | AA53: 2 | AB53: 2 | AC53: 2 | AD53: 2 | AE53: 2 | AF53: 2 | AG53: 2 | AH53: 2 | AI53: 2 | AJ53: 2 | AK53: 2 | AL53: 2 | AM53: 2 | AN53: 2 | AO53: 2 | AP53: 2 | AQ53: 0 | AR53: 0 | AS53: 0 | AT53: 0 | AU53: 0 | AV53: 0 | AW53: 0 | AX53: 0 | AY53: 0 | AZ53: 0 | BA53: 0 | BB53: 0 | BC53: 0 | BD53: 0 | BE53: 0 | BF53: 0 | BG53: 0 | BH53: 0 | BI53: 0 | BJ53: 0 | BK53: 0 | BL53: 0 | BM53: 0 | BN53: 0
B54: 23 | C54: 0 | D54: M05-0362 | F54: 0 | G54: 0 | H54: 0 | I54: 0 | J54: 0 | K54: 0 | L54: 0 | M54: 0 | N54: 1 | O54: 0 | P54: 0 | Q54: 0 | R54: 0 | S54: 0 | T54: 0 | U54: 0 | V54: 0 | W54: 0 | X54: 0 | Y54: 0 | Z54: 0 | AA54: 0 | AB54: 0 | AC54: 0 | AD54: 0 | AE54: 0 | AF54: 0 | AG54: 0 | AH54: 0 | AI54: 0 | AJ54: 0 | AK54: 0 | AL54: 0 | AM54: 0 | AN54: 0 | AO54: 0 | AP54: 0 | AQ54: 0 | AR54: 0 | AS54: 0 | AT54: 0 | AU54: 0 | AV54: 0 | AW54: 0 | AX54: 0 | AY54: 0 | AZ54: 0 | BA54: 0 | BB54: 0 | BC54: 0 | BD54: 0 | BE54: 0 | BF54: 0 | BG54: 0 | BH54: 0 | BI54: 0 | BJ54: 0 | BK54: 0 | BL54: 0 | BM54: 0 | BN54: 0
B55: 24 | C55: 0 | D55: 0 | F55: 0 | G55: 0 | H55: 0 | I55: 0 | J55: 0 | K55: 0 | L55: 0 | M55: 0 | N55: 0 | O55: 0 | P55: 0 | Q55: 0 | R55: 0 | S55: 0 | T55: 0 | U55: 0 | V55: 0 | W55: 0 | X55: 0 | Y55: 0 | Z55: 0 | AA55: 0 | AB55: 0 | AC55: 0 | AD55: 0 | AE55: 0 | AF55: 0 | AG55: 0 | AH55: 0 | AI55: 0 | AJ55: 0 | AK55: 0 | AL55: 0 | AM55: 0 | AN55: 0 | AO55: 0 | AP55: 0 | AQ55: 0 | AR55: 0 | AS55: 0 | AT55: 0 | AU55: 0 | AV55: 0 | AW55: 0 | AX55: 0 | AY55: 0 | AZ55: 0 | BA55: 0 | BB55: 0 | BC55: 0 | BD55: 0 | BE55: 0 | BF55: 0 | BG55: 0 | BH55: 0 | BI55: 0 | BJ55: 0 | BK55: 0 | BL55: 0 | BM55: 0 | BN55: 0
B56: 25 | C56: 0 | D56: 0 | F56: 0 | G56: 0 | H56: 0 | I56: 0 | J56: 0 | K56: 0 | L56: 0 | M56: 0 | N56: 0 | O56: 0 | P56: 0 | Q56: 0 | R56: 0 | S56: 0 | T56: 0 | U56: 0 | V56: 0 | W56: 0 | X56: 0 | Y56: 0 | Z56: 0 | AA56: 0 | AB56: 0 | AC56: 0 | AD56: 0 | AE56: 0 | AF56: 0 | AG56: 0 | AH56: 0 | AI56: 0 | AJ56: 0 | AK56: 0 | AL56: 0 | AM56: 0 | AN56: 0 | AO56: 0 | AP56: 0 | AQ56: 0 | AR56: 0 | AS56: 0 | AT56: 0 | AU56: 0 | AV56: 0 | AW56: 0 | AX56: 0 | AY56: 0 | AZ56: 0 | BA56: 0 | BB56: 0 | BC56: 0 | BD56: 0 | BE56: 0 | BF56: 0 | BG56: 0 | BH56: 0 | BI56: 0 | BJ56: 0 | BK56: 0 | BL56: 0 | BM56: 0 | BN56: 0
B57: ENTREPISO (TUBERIAS Y CAJAS)
B58: 1 | C58: Curva 38mm 1 1/2" | D58: M05-0362 | F58: 0 | G58: 0 | H58: 0 | I58: 0 | J58: 0 | K58: 0 | L58: 0 | M58: 0 | N58: 0 | O58: 0 | P58: 0 | Q58: 0 | R58: 0 | S58: 0 | T58: 0 | U58: 0 | V58: 0 | W58: 0 | X58: 0 | Y58: 0 | Z58: 0 | AA58: 0 | AB58: 0 | AC58: 0 | AD58: 0 | AE58: 0 | AF58: 0 | AG58: 0 | AH58: 0 | AI58: 0 | AJ58: 0 | AK58: 0 | AL58: 0 | AM58: 0 | AN58: 0 | AO58: 0 | AP58: 0 | AQ58: 0 | AR58: 0 | AS58: 0 | AT58: 0 | AU58: 0 | AV58: 0 | AW58: 0 | AX58: 0 | AY58: 0 | AZ58: 0 | BA58: 0 | BB58: 0 | BC58: 0 | BD58: 0 | BE58: 0 | BF58: 0 | BG58: 0 | BH58: 0 | BI58: 0 | BJ58: 0 | BK58: 0 | BL58: 0 | BM58: 0 | BN58: 0
B59: 2 | C59: Curva 25mm 1" | D59: M05-0366 | F59: 0 | G59: 0 | H59: 0 | I59: 0 | J59: 0 | K59: 0 | L59: 0 | M59: 0 | N59: 0 | O59: 0 | P59: 0 | Q59: 0 | R59: 0 | S59: 0 | T59: 0 | U59: 0 | V59: 0 | W59: 0 | X59: 0 | Y59: 0 | Z59: 0 | AA59: 0 | AB59: 0 | AC59: 0 | AD59: 0 | AE59: 0 | AF59: 0 | AG59: 0 | AH59: 0 | AI59: 0 | AJ59: 0 | AK59: 0 | AL59: 0 | AM59: 0 | AN59: 0 | AO59: 0 | AP59: 0 | AQ59: 0 | AR59: 0 | AS59: 0 | AT59: 0 | AU59: 0 | AV59: 0 | AW59: 0 | AX59: 0 | AY59: 0 | AZ59: 0 | BA59: 0 | BB59: 0 | BC59: 0 | BD59: 0 | BE59: 0 | BF59: 0 | BG59: 0 | BH59: 0 | BI59: 0 | BJ59: 0 | BK59: 0 | BL59: 0 | BM59: 0 | BN59: 0
B60: 3 | C60: Curva 13mm 1/2" | D60: M05-0361 | F60: 0 | G60: 0 | H60: 0 | I60: 0 | J60: 0 | K60: 0 | L60: 0 | M60: 0 | N60: 45 | O60: 45 | P60: 45 | Q60: 0 | R60: 0 | S60: 0 | T60: 0 | U60: 45 | V60: 45 | W60: 45 | X60: 45 | Y60: 45 | Z60: 45 | AA60: 45 | AB60: 35 | AC60: 35 | AD60: 35 | AE60: 35 | AF60: 35 | AG60: 35 | AH60: 35 | AI60: 35 | AJ60: 35 | AK60: 35 | AL60: 35 | AM60: 35 | AN60: 35 | AO60: 45 | AP60: 0 | AQ60: 0 | AR60: 0 | AS60: 0 | AT60: 0 | AU60: 0 | AV60: 0 | AW60: 0 | AX60: 0 | AY60: 0 | AZ60: 0 | BA60: 0 | BB60: 0 | BC60: 0 | BD60: 0 | BE60: 0 | BF60: 0 | BG60: 0 | BH60: 0 | BI60: 0 | BJ60: 0 | BK60: 0 | BL60: 0 | BM60: 0 | BN60: 0
B61: 4 | C61: Curva 19mm 3/4" | D61: M05-0367 | F61: 0 | G61: 0 | H61: 0 | I61: 0 | J61: 0 | K61: 0 | L61: 0 | M61: 0 | N61: 15 | O61: 15 | P61: 15 | Q61: 0 | R61: 0 | S61: 0 | T61: 0 | U61: 15 | V61: 15 | W61: 15 | X61: 15 | Y61: 15 | Z61: 15 | AA61: 15 | AB61: 9 | AC61: 9 | AD61: 9 | AE61: 9 | AF61: 9 | AG61: 9 | AH61: 9 | AI61: 9 | AJ61: 9 | AK61: 9 | AL61: 0 | AM61: 9 | AN61: 9 | AO61: 15 | AP61: 0 | AQ61: 0 | AR61: 0 | AS61: 0 | AT61: 0 | AU61: 0 | AV61: 0 | AW61: 0 | AX61: 0 | AY61: 0 | AZ61: 0 | BA61: 0 | BB61: 0 | BC61: 0 | BD61: 0 | BE61: 0 | BF61: 0 | BG61: 0 | BH61: 0 | BI61: 0 | BJ61: 0 | BK61: 0 | BL61: 0 | BM61: 0 | BN61: 0
B62: 5 | C62: Tubo 38mm 1 1/2" | D62: M05-0368 | F62: 0 | G62: 0 | H62: 0 | I62: 0 | J62: 0 | K62: 0 | L62: 0 | M62: 0 | N62: 0 | O62: 0 | P62: 0 | Q62: 0 | R62: 0 | S62: 0 | T62: 0 | U62: 0 | V62: 0 | W62: 0 | X62: 0 | Y62: 0 | Z62: 0 | AA62: 0 | AB62: 0 | AC62: 0 | AD62: 0 | AE62: 0 | AF62: 0 | AG62: 0 | AH62: 0 | AI62: 0 | AJ62: 0 | AK62: 0 | AL62: 0 | AM62: 0 | AN62: 0 | AO62: 0 | AP62: 0 | AQ62: 0 | AR62: 0 | AS62: 0 | AT62: 0 | AU62: 0 | AV62: 0 | AW62: 0 | AX62: 0 | AY62: 0 | AZ62: 0 | BA62: 0 | BB62: 0 | BC62: 0 | BD62: 0 | BE62: 0 | BF62: 0 | BG62: 0 | BH62: 0 | BI62: 0 | BJ62: 0 | BK62: 0 | BL62: 0 | BM62: 0 | BN62: 0
B63: 6 | C63: Tubo 25mm 1" | D63: M05-0369 | F63: 0 | G63: 0 | H63: 0 | I63: 0 | J63: 0 | K63: 0 | L63: 0 | M63: 0 | N63: 0 | O63: 0 | P63: 0 | Q63: 0 | R63: 0 | S63: 0 | T63: 0 | U63: 0 | V63: 0 | W63: 0 | X63: 0 | Y63: 0 | Z63: 0 | AA63: 0 | AB63: 0 | AC63: 0 | AD63: 0 | AE63: 0 | AF63: 0 | AG63: 0 | AH63: 0 | AI63: 0 | AJ63: 0 | AK63: 0 | AL63: 0 | AM63: 0 | AN63: 0 | AO63: 0 | AP63: 0 | AQ63: 0 | AR63: 0 | AS63: 0 | AT63: 0 | AU63: 0 | AV63: 0 | AW63: 0 | AX63: 0 | AY63: 0 | AZ63: 0 | BA63: 0 | BB63: 0 | BC63: 0 | BD63: 0 | BE63: 0 | BF63: 0 | BG63: 0 | BH63: 0 | BI63: 0 | BJ63: 0 | BK63: 0 | BL63: 0 | BM63: 0 | BN63: 0
B64: 7 | C64: Tubo 13mm 1/2" | D64: M05-0370 | F64: 0 | G64: 0 | H64: 0 | I64: 0 | J64: 0 | K64: 0 | L64: 0 | M64: 0 | N64: 45 | O64: 45 | P64: 45 | Q64: 0 | R64: 0 | S64: 0 | T64: 0 | U64: 45 | V64: 45 | W64: 45 | X64: 45 | Y64: 45 | Z64: 45 | AA64: 45 | AB64: 35 | AC64: 35 | AD64: 35 | AE64: 35 | AF64: 35 | AG64: 35 | AH64: 35 | AI64: 35 | AJ64: 35 | AK64: 35 | AL64: 35 | AM64: 35 | AN64: 35 | AO64: 40 | AP64: 35 | AQ64: 0 | AR64: 0 | AS64: 0 | AT64: 0 | AU64: 0 | AV64: 0 | AW64: 0 | AX64: 0 | AY64: 0 | AZ64: 0 | BA64: 0 | BB64: 0 | BC64: 0 | BD64: 0 | BE64: 0 | BF64: 0 | BG64: 0 | BH64: 0 | BI64: 0 | BJ64: 0 | BK64: 0 | BL64: 0 | BM64: 0 | BN64: 0
B65: 8 | C65: Tubo 19mm 3/4" | D65: M05-0371 | F65: 0 | G65: 0 | H65: 0 | I65: 0 | J65: 0 | K65: 0 | L65: 0 | M65: 0 | N65: 12 | O65: 12 | P65: 12 | Q65: 0 | R65: 0 | S65: 0 | T65: 0 | U65: 12 | V65: 12 | W65: 12 | X65: 12 | Y65: 12 | Z65: 12 | AA65: 12 | AB65: 10 | AC65: 10 | AD65: 10 | AE65: 10 | AF65: 10 | AG65: 10 | AH65: 10 | AI65: 10 | AJ65: 10 | AK65: 10 | AL65: 0 | AM65: 10 | AN65: 10 | AO65: 12 | AP65: 0 | AQ65: 0 | AR65: 0 | AS65: 0 | AT65: 0 | AU65: 0 | AV65: 0 | AW65: 0 | AX65: 0 | AY65: 0 | AZ65: 0 | BA65: 0 | BB65: 0 | BC65: 0 | BD65: 0 | BE65: 0 | BF65: 0 | BG65: 0 | BH65: 0 | BI65: 0 | BJ65: 0 | BK65: 0 | BL65: 0 | BM65: 0 | BN65: 0
B66: 9 | C66: Union 38mm 1 1/2" | D66: M05-0372 | F66: 0 | G66: 0 | H66: 0 | I66: 0 | J66: 0 | K66: 0 | L66: 0 | M66: 0 | N66: 0 | O66: 0 | P66: 0 | Q66: 0 | R66: 0 | S66: 0 | T66: 0 | U66: 0 | V66: 0 | W66: 0 | X66: 0 | Y66: 0 | Z66: 0 | AA66: 0 | AB66: 0 | AC66: 0 | AD66: 0 | AE66: 0 | AF66: 0 | AG66: 0 | AH66: 0 | AI66: 0 | AJ66: 0 | AK66: 0 | AL66: 0 | AM66: 0 | AN66: 0 | AO66: 0 | AP66: 0 | AQ66: 0 | AR66: 0 | AS66: 0 | AT66: 0 | AU66: 0 | AV66: 0 | AW66: 0 | AX66: 0 | AY66: 0 | AZ66: 0 | BA66: 0 | BB66: 0 | BC66: 0 | BD66: 0 | BE66: 0 | BF66: 0 | BG66: 0 | BH66: 0 | BI66: 0 | BJ66: 0 | BK66: 0 | BL66: 0 | BM66: 0 | BN66: 0
B67: 10 | C67: Union 25mm 1" | D67: M05-0373 | F67: 0 | G67: 0 | H67: 0 | I67: 0 | J67: 0 | K67: 0 | L67: 0 | M67: 0 | N67: 0 | O67: 0 | P67: 0 | Q67: 0 | R67: 0 | S67: 0 | T67: 0 | U67: 0 | V67: 0 | W67: 0 | X67: 0 | Y67: 0 | Z67: 0 | AA67: 0 | AB67: 0 | AC67: 0 | AD67: 0 | AE67: 0 | AF67: 0 | AG67: 0 | AH67: 0 | AI67: 0 | AJ67: 0 | AK67: 0 | AL67: 0 | AM67: 0 | AN67: 0 | AO67: 0 | AP67: 0 | AQ67: 0 | AR67: 0 | AS67: 0 | AT67: 0 | AU67: 0 | AV67: 0 | AW67: 0 | AX67: 0 | AY67: 0 | AZ67: 0 | BA67: 0 | BB67: 0 | BC67: 0 | BD67: 0 | BE67: 0 | BF67: 0 | BG67: 0 | BH67: 0 | BI67: 0 | BJ67: 0 | BK67: 0 | BL67: 0 | BM67: 0 | BN67: 0
B68: 11 | C68: Union 13mm 1/2" | D68: M05-0374 | F68: 0 | G68: 0 | H68: 0 | I68: 0 | J68: 0 | K68: 0 | L68: 0 | M68: 0 | N68: 15 | O68: 15 | P68: 15 | Q68: 0 | R68: 0 | S68: 0 | T68: 0 | U68: 15 | V68: 15 | W68: 15 | X68: 15 | Y68: 15 | Z68: 15 | AA68: 15 | AB68: 15 | AC68: 15 | AD68: 15 | AE68: 15 | AF68: 15 | AG68: 15 | AH68: 15 | AI68: 15 | AJ68: 15 | AK68: 15 | AL68: 0 | AM68: 15 | AN68: 15 | AO68: 15 | AP68: 0 | AQ68: 0 | AR68: 0 | AS68: 0 | AT68: 0 | AU68: 0 | AV68: 0 | AW68: 0 | AX68: 0 | AY68: 0 | AZ68: 0 | BA68: 0 | BB68: 0 | BC68: 0 | BD68: 0 | BE68: 0 | BF68: 0 | BG68: 0 | BH68: 0 | BI68: 0 | BJ68: 0 | BK68: 0 | BL68: 0 | BM68: 0 | BN68: 0
